Workbook

Sheet README
A1: monday.com Operating Plan, Q3 2026-Q4 2027 (Phase 3b) - DRAFT FOR OWNER REVIEW, NOT FROZEN
A3: Management question | B3: If growth decelerates faster than guided after the July 2026 restructuring, how should management adjust hiring and operating spend to protect margin and cash generation without damaging long-term growth?
A4: Information cutoff | B4: October 28, 2026. Inputs: monday_sourcebook.xlsx (Row IDs), monday_analysis.xlsx (cells), locked Q3 call monday_q3_call.xlsx (release q3-2026-call-locked; cells), monday_driver_audit.xlsx (evidence). None is modified.
A5: Labels | B5: Sourced = blue copy with Row ID/reference; Derived = black formula; Assumed = orange on light-orange fill (Assumptions sheet and Management_Response elasticities). Column B of every model table states the label of the row.
A6: Base is not guidance | B6: Base is a BEAT-ADJUSTED central estimate, not guidance: FY2026 Base revenue and non-GAAP operating income sit above the top of the guided ranges (see Scenarios, As guided). Adjusted FCF is held at the guide midpoint on the guide basis.
A7: Cash questions (resolved) | B7: Adjusted FCF as defined by the company has no severance add-back; the FY2026 FCF outlook excludes restructuring (6-K Jul 22, 2026). The plan deducts severance once, separately (no double count), and shows reported-basis FCF as a memo. The H1 2026 cash bridge (Cash_Bridge) explains the earlier -$67M: mostly a transfer into marketable securities. Ending cash is labeled BEFORE UNMODELED ITEMS (new buybacks, M&A beyond run-rate, FX) and is not a headline figure.
A8: Cases | B8: Base = central estimate (Q3 2026 = locked call MID). Downside = faster deceleration (2.6 vs 1.3 pp/yr) with opex DOLLARS held at Base before any response. Sensitivity = Base with Q3 2026 at the locked call LOW. Management response is modeled on the Downside.
A9: Not modeled as separate drivers | B9: Restructuring SAVINGS: no savings amount, exit timing or headcount base is disclosed, so savings are expressed only through the opex-ratio assumptions (P4-P6) and the locked Q3 call. INTEREST INCOME: financial income, net ($17.3M in H1 2026 per the interim MD&A) is received through operating cash flow, so it is already inside adjusted FCF and the guide-anchored conversion (P7); it is not added again.
A10: Headcount | B10: No implied-headcount memo (ruling 4). Hiring decisions are stated in dollars. Fact: 3,155 employees at Dec 31, 2025 (AN-0051) and a ~20% workforce reduction announced July 22, 2026; no quarterly path is modeled.
A11: Status | B11: DRAFT. Not frozen, tagged or released. Review gates are reported in Checks.
A12: Sheets | B12: README, Definitions, Historical_Drivers, Cash_Bridge, Assumptions, Revenue_Build, Opex, PnL, Cash_FCF, Scenarios, Management_Response, Recommendation, Backtest, Trigger_History, Method_Changes, Checks, Scorecard.

Sheet Definitions
A1: Definitions (company definitions per source-book Definitions sheet; plan conventions)
A3: Non-GAAP operating income | B3: GAAP operating income excluding SBC, restructuring (from Q2 2026) and the 2024 foundation contribution (company definition). Plan: gross profit (non-GAAP) - R&D - S&M - G&A (non-GAAP).
A4: Adjusted FCF | B4: Company definition (verbatim in Cash_Bridge): OCF - PP&E - capitalized software + HQ build-out add-back; no add-back for restructuring or severance. Guide basis = excluding restructuring (6-K Jul 22, 2026). Reported basis = guide basis less severance paid. Plan: Q3/Q4 2026 tied to the FY2026 guide (low confidence); 2027 = op. income x annual conversion (P7).
A5: Breakeven revenue loss | B5: FY2027 revenue loss at which the gross profit lost (loss x Downside gross margin) equals the operating income a lever saves. One-year view only.
A6: Forecast band | B6: Base quarterly revenue x (1 +/- backtest error at that horizon). Horizons 5-6 (Q3-Q4 2027) are beyond the tested horizon; the h4 error is used as a floor.
A7: False alarm (trigger history) | B7: A trigger firing after which YoY revenue growth over the next 4 quarters slowed no faster than the Base pace (4 x P1 Base).
A8: Sequential growth | B8: Quarter revenue / prior quarter revenue - 1.
A9: Annual deceleration (P1) | B9: Reduction, in percentage points, of a quarter's sequential growth vs the same quarter one year earlier.
A10: NDR | B10: Company definition (source book); measurement basis not disclosed. INDICATOR ONLY in this plan.
A11: Cash + marketable securities | B11: Balance-sheet cash and cash equivalents plus marketable securities; restricted cash excluded.
A12: Sign convention | B12: Expenses positive in opex lines and subtracted in operating income; cash outflows negative in Cash_FCF (severance, buybacks).
A13: Growth cost (elasticity) | B13: ASSUMED annualized revenue lost per $1 of quarterly spend cut, starting the following quarter and cumulative. Not observable in public data.

Sheet Historical_Drivers
A1: Historical drivers (Sourced copies from monday_sourcebook.xlsx; Row ID row beneath each value row)
A2: USD thousands unless stated. Blue = Sourced; grey row below = source-book Row IDs.
A4: Metric | B4: Label | C4: Q1 2023 | D4: Q2 2023 | E4: Q3 2023 | F4: Q4 2023 | G4: Q1 2024 | H4: Q2 2024 | I4: Q3 2024 | J4: Q4 2024 | K4: Q1 2025 | L4: Q2 2025 | M4: Q3 2025 | N4: Q4 2025 | O4: Q1 2026 | P4: Q2 2026
A6: Revenue | B6: Sourced | C6: 162256 | D6: 175679 | E6: 189190 | F6: 202570 | G6: 216913 | H6: 236106 | I6: 251000 | J6: 267976 | K6: 282250 | L6: 299014 | M6: 316855 | N6: 333878 | O6: 351265 | P6: 364621
A7: Row ID | B7: Row ID | C7: QA-0015 | D7: QA-0016 | E7: QA-0018 | F7: QA-0020 | G7: QA-0022 | H7: QA-0023 | I7: QA-0025 | J7: QA-0027 | K7: QA-0029 | L7: QA-0030 | M7: QA-0032 | N7: QA-0034 | O7: QA-0036 | P7: QA-0037
A8: Gross profit (non-GAAP) | B8: Sourced | C8: 146719 | D8: 158008 | E8: 168866 | F8: 181764 | G8: 194703 | H8: 214215 | I8: 226909 | J8: 239080 | K8: 254579 | L8: 270113 | M8: 284031 | N8: 298736 | O8: 314190 | P8: 324222
A9: Row ID | B9: Row ID | C9: QA-0489 | D9: QA-0490 | E9: QA-0492 | F9: QA-0494 | G9: QA-0496 | H9: QA-0497 | I9: QA-0499 | J9: QA-0501 | K9: QA-0503 | L9: QA-0504 | M9: QA-0506 | N9: QA-0508 | O9: QA-0510 | P9: QA-0511
A10: R&D (non-GAAP) | B10: Sourced | C10: 28519 | D10: 27908 | E10: 28051 | F10: 33285 | G10: 34797 | H10: 36878 | I10: 42973 | J10: 48066 | K10: 53844 | L10: 59233 | M10: 57772 | N10: 67700 | O10: 78413 | P10: 83003
A11: Row ID | B11: Row ID | C11: QA-0565 | D11: QA-0566 | E11: QA-0568 | F11: QA-0570 | G11: QA-0572 | H11: QA-0573 | I11: QA-0575 | J11: QA-0577 | K11: QA-0579 | L11: QA-0580 | M11: QA-0582 | N11: QA-0584 | O11: QA-0586 | P11: QA-0587
A12: S&M (non-GAAP) | B12: Sourced | C12: 102652 | D12: 98831 | E12: 101504 | F12: 110020 | G12: 120806 | H12: 120738 | I12: 130339 | J12: 127791 | K12: 135882 | L12: 139223 | M12: 151804 | N12: 159858 | O12: 158181 | P12: 149444
A13: Row ID | B13: Row ID | C13: QA-0603 | D13: QA-0604 | E13: QA-0606 | F13: QA-0608 | G13: QA-0610 | H13: QA-0611 | I13: QA-0613 | J13: QA-0615 | K13: QA-0617 | L13: QA-0618 | M13: QA-0620 | N13: QA-0622 | O13: QA-0624 | P13: QA-0625
A14: G&A (non-GAAP) | B14: Sourced | C14: 15841 | D14: 14652 | E14: 15234 | F14: 17259 | G14: 17579 | H14: 18182 | I14: 21417 | J14: 22958 | K14: 24099 | L14: 26563 | M14: 26971 | N14: 29247 | O14: 28559 | P14: 30665
A15: Row ID | B15: Row ID | C15: QA-0641 | D15: QA-0642 | E15: QA-0644 | F15: QA-0646 | G15: QA-0648 | H15: QA-0649 | I15: QA-0651 | J15: QA-0653 | K15: QA-0655 | L15: QA-0656 | M15: QA-0658 | N15: QA-0660 | O15: QA-0662 | P15: QA-0663
A16: Operating income (non-GAAP) | B16: Sourced | C16: -293 | D16: 16617 | E16: 24077 | F16: 21200 | G16: 21521 | H16: 38417 | I16: 32180 | J16: 40265 | K16: 40754 | L16: 45094 | M16: 47484 | N16: 41931 | O16: 49037 | P16: 61110
A17: Row ID | B17: Row ID | C17: QA-0679 | D17: QA-0680 | E17: QA-0682 | F17: QA-0684 | G17: QA-0686 | H17: QA-0687 | I17: QA-0689 | J17: QA-0691 | K17: QA-0693 | L17: QA-0694 | M17: QA-0696 | N17: QA-0698 | O17: QA-0700 | P17: QA-0701
A18: Operating income (GAAP) | B18: Sourced | C18: -22752 | D18: -12167 | E18: -2521 | F18: -1145 | G18: -5022 | H18: 1794 | I18: -27402 | J18: 9596 | K18: 9796 | L18: -11551 | M18: -2378 | N18: 2385 | O18: 19754 | P18: -1544
A19: Row ID | B19: Row ID | C19: QA-0321 | D19: QA-0322 | E19: QA-0324 | F19: QA-0326 | G19: QA-0328 | H19: QA-0329 | I19: QA-0331 | J19: QA-0333 | K19: QA-0335 | L19: QA-0336 | M19: QA-0338 | N19: QA-0340 | O19: QA-0342 | P19: QA-0343
A20: SBC total | B20: Sourced | C20: 22459 | D20: 28784 | E20: 26598 | F20: 22345 | G20: 26543 | H20: 36623 | I20: 35374 | J20: 30669 | K20: 30958 | L20: 56645 | M20: 49862 | N20: 39546 | O20: 29283 | P20: 41218
A21: Row ID | B21: Row ID | C21: QA-0847 | D21: QA-0848 | E21: QA-0850 | F21: QA-0852 | G21: QA-0854 | H21: QA-0855 | I21: QA-0857 | J21: QA-0859 | K21: QA-0861 | L21: QA-0862 | M21: QA-0864 | N21: QA-0866 | O21: QA-0868 | P21: QA-0869
A22: Restructuring charges (GAAP line) | B22: Sourced | C22: Not disclosed | D22: Not disclosed | E22: Not disclosed | F22: Not disclosed | G22: Not disclosed | H22: Not disclosed | I22: Not disclosed | J22: Not disclosed | K22: Not disclosed | L22: Not disclosed | M22: Not disclosed | N22: Not disclosed | O22: Not disclosed | P22: 21436
A23: Row ID | B23: Row ID | P23: QA-0267
A24: Adjusted FCF / FCF | B24: Sourced | C24: 38682 | D24: 45932 | E24: 64890 | F24: 55441 | G24: 89894 | H24: 50821 | I24: 82412 | J24: 72703 | K24: 109532 | L24: 64093 | M24: 92301 | N24: 56734 | O24: 102778 | P24: 52344
A25: Row ID | B25: Row ID | C25: QA-1081 | D25: QA-1082 | E25: QA-1084 | F25: QA-1086 | G25: QA-1088 | H25: QA-1089 | I25: QA-1091 | J25: QA-1093 | K25: QA-1095 | L25: QA-1096 | M25: QA-1098 | N25: QA-1100 | O25: QA-1102 | P25: QA-1103
A26: Cash and cash equivalents | B26: Sourced | C26: 935565 | D26: 989377 | E26: 1054270 | F26: 1116128 | G26: 1224544 | H26: 1290242 | I26: 1337155 | J26: 1411602 | K26: 1527605 | L26: 1590515 | M26: 1527246 | N26: 1503149 | O26: 997135 | P26: 853402
A27: Row ID | B27: Row ID | C27: QA-1220 | D27: QA-1221 | E27: QA-1222 | F27: QA-1223 | G27: QA-1224 | H27: QA-1225 | I27: QA-1226 | J27: QA-1227 | K27: QA-1228 | L27: QA-1229 | M27: QA-1230 | N27: QA-1231 | O27: QA-1232 | P27: QA-1233
A28: Marketable securities | B28: Sourced | C28: Not disclosed | D28: Not disclosed | E28: Not disclosed | F28: Not disclosed | G28: Not disclosed | H28: Not disclosed | I28: 50667 | J28: 50004 | K28: 60730 | L28: 60102 | M28: 211740 | N28: 162308 | O28: 215141 | P28: 219353
A29: Row ID | B29: Row ID | I29: QA-1237 | J29: QA-1238 | K29: QA-1239 | L29: QA-1240 | M29: QA-1241 | N29: QA-1242 | O29: QA-1243 | P29: QA-1244
A30: NDR all customers | B30: Sourced | F30: 1.1 | G30: 1.1 | H30: 1.1 | I30: 1.11 | J30: 1.12 | K30: 1.12 | L30: 1.11 | M30: 1.11 | N30: 1.1 | O30: 1.1 | P30: 1.09
A31: Row ID | B31: Row ID | F31: QA-1310 | G31: QA-1311 | H31: QA-1312 | I31: QA-1313 | J31: QA-1314 | K31: QA-1315 | L31: QA-1316 | M31: QA-1317 | N31: QA-1318 | O31: QA-1319 | P31: QA-1320
A32: Customers >$50k ARR | B32: Sourced | C32: 1683 | D32: 1892 | E32: 2077 | F32: 2295 | G32: 2491 | H32: 2713 | I32: 2907 | J32: 3201 | K32: 3444 | L32: 3702 | M32: 3993 | N32: 4281 | O32: 4547 | P32: 4834
A33: Row ID | B33: Row ID | C33: QA-1413 | D33: QA-1414 | E33: QA-1415 | F33: QA-1416 | G33: QA-1417 | H33: QA-1418 | I33: QA-1419 | J33: QA-1420 | K33: QA-1421 | L33: QA-1422 | M33: QA-1423 | N33: QA-1424 | O33: QA-1425 | P33: QA-1426
A34: Derived history
A35: Revenue sequential growth | B35: Derived | D35: =D6/C6-1 -> 0.082727295 | E35: =E6/D6-1 -> 0.076907314 | F35: =F6/E6-1 -> 0.070722554 | G35: =G6/F6-1 -> 0.070805154 | H35: =H6/G6-1 -> 0.088482479 | I35: =I6/H6-1 -> 0.063081836 | J35: =J6/I6-1 -> 0.067633466 | K35: =K6/J6-1 -> 0.053265964 | ... P35: =P6/O6-1 -> 0.038022576
A36: Gross margin (non-GAAP) | B36: Derived | C36: =C8/C6 -> 0.90424391 | D36: =D8/D6 -> 0.89941313 | E36: =E8/E6 -> 0.8925736 | F36: =F8/F6 -> 0.89728983 | G36: =G8/G6 -> 0.89760872 | H36: =H8/H6 -> 0.90728317 | I36: =I8/I6 -> 0.90401992 | J36: =J8/J6 -> 0.89216945 | ... P36: =P8/P6 -> 0.88920276
A37: Operating margin (non-GAAP) | B37: Derived | C37: =C16/C6 -> -0.0018057884 | D37: =D16/D6 -> 0.094587287 | E37: =E16/E6 -> 0.1272636 | F37: =F16/F6 -> 0.10465518 | G37: =G16/G6 -> 0.099214893 | H37: =H16/H6 -> 0.16271082 | I37: =I16/I6 -> 0.12820717 | J37: =J16/J6 -> 0.15025599 | ... P37: =P16/P6 -> 0.16759868
A38: Cash + marketable securities | B38: Derived | C38: =IF(ISNUMBER(C28),C26+C28,"n/a") -> n/a | D38: =IF(ISNUMBER(D28),D26+D28,"n/a") -> n/a | E38: =IF(ISNUMBER(E28),E26+E28,"n/a") -> n/a | F38: =IF(ISNUMBER(F28),F26+F28,"n/a") -> n/a | G38: =IF(ISNUMBER(G28),G26+G28,"n/a") -> n/a | H38: =IF(ISNUMBER(H28),H26+H28,"n/a") -> n/a | I38: =IF(ISNUMBER(I28),I26+I28,"n/a") -> 1387822 | J38: =IF(ISNUMBER(J28),J26+J28,"n/a") -> 1461606 | ... P38: =IF(ISNUMBER(P28),P26+P28,"n/a") -> 1072755
A40: Point inputs (Sourced)
A41: Input | B41: Label | C41: Value | D41: Reference | E41: Unit
A42: FY 2026 Adjusted free cash flow guidance low | B42: Sourced | C42: 280 | D42: GH-0098:low | E42: USD m
A43: FY 2026 Adjusted free cash flow guidance high | B43: Sourced | C43: 290 | D43: GH-0098:high | E43: USD m
A44: FY 2026 Non-GAAP operating income (loss) guidance low | B44: Sourced | C44: 230 | D44: GH-0099:low | E44: USD m
A45: FY 2026 Non-GAAP operating income (loss) guidance high | B45: Sourced | C45: 234 | D45: GH-0099:high | E45: USD m
A46: FY 2026 Revenue guidance low | B46: Sourced | C46: 1466 | D46: GH-0100:low | E46: USD m
A47: FY 2026 Revenue guidance high | B47: Sourced | C47: 1474 | D47: GH-0100:high | E47: USD m
A48: Q3 2026 Non-GAAP operating income (loss) guidance low | B48: Sourced | C48: 57 | D48: GH-0101:low | E48: USD m
A49: Q3 2026 Non-GAAP operating income (loss) guidance high | B49: Sourced | C49: 59 | D49: GH-0101:high | E49: USD m
A50: Q3 2026 Revenue guidance low | B50: Sourced | C50: 368 | D50: GH-0102:low | E50: USD m
A51: Q3 2026 Revenue guidance high | B51: Sourced | C51: 370 | D51: GH-0102:high | E51: USD m
A52: Locked Q3 call: revenue MID (USD m) | B52: Sourced | C52: 378.38246 | D52: monday_q3_call.xlsx Revenue!D55 | E52: as stated
A53: Locked Q3 call: revenue LOW (USD m) | B53: Sourced | C53: 374.47107 | D53: monday_q3_call.xlsx Revenue!C55 | E53: as stated
... A67: Employees, Dec 31, 2025 (fact; ~20% reduction announced July 22, 2026; no quarterly path) | B67: Sourced | C67: 3155 | D67: AN-0051 | E67: employees
A68: Mean Q3 share of H2 adjusted FCF, 2023-2025 | B68: Derived | C68: =AVERAGE(Historical_Drivers!$E$24/(Historical_Drivers!$E$24+Historical_Drivers!$F$24),Historical_Drivers!$I$24/(Historical_Drivers!$I$24+Historical_Drivers!$J$24),Historical_Drivers!$M$24/(Historical_Drivers!$M$24+Historical_Drivers!$N$24)) -> 0.56329433
A69: H2 2026 adjusted FCF implied by FY guide midpoint (USD m) | B69: Derived | C69: =(Historical_Drivers!$C$42+Historical_Drivers!$C$43)/2-Historical_Drivers!$C$59/1000 -> 129.878
A70: FY2025 revenue (USD m) = sum of 2025 quarters | B70: Derived | C70: =(Historical_Drivers!$K$6+Historical_Drivers!$L$6+Historical_Drivers!$M$6+Historical_Drivers!$N$6)/1000 -> 1231.997
A71: FY2025 non-GAAP operating income (USD m) | B71: Derived | C71: =(Historical_Drivers!$K$16+Historical_Drivers!$L$16+Historical_Drivers!$M$16+Historical_Drivers!$N$16)/1000 -> 175.263

Sheet Cash_Bridge
A1: Cash questions resolved from primary sources: adjusted FCF definition, severance treatment, H1 2026 cash bridge
A2: USD thousands unless stated. Quotes are verbatim from SEC filings (Source IDs as in the source book Sources sheet).
A4: A. Quotes
A5: ER-2026Q2 (6-K Ex. 99.1, Aug 10, 2026), Non-GAAP Financial Measures | B5: "adjusted free cash flow, which is defined as free cash flow plus costs associated with the build-out of our corporate headquarters, and adjusted free cash flow margin. Certain of these non-GAAP financial measures exclude share-based compensation and restructuring costs."
A6: H1MDA-2026 (6-K Ex. 99.3) and 20F-FY2025 Item 5 | B6: "We define adjusted free cash flow as net cash provided by operating activities, less cash used for purchases of property and equipment and capitalized software development costs, plus costs associated with the build-out [and expansion] of our corporate headquarters."
A7: 6K-20260722-RESTR (6-K, Jul 22, 2026) | B7: "Full-year 2026 projections for Non-GAAP Operating Margin and Adjusted Free Cash Flow Margin continue to incorporate an estimated adverse foreign currency exchange impact of approximately 100 to 200 basis points and exclude any estimated restructuring charges from the Plan."
A8: 6K-20260722-RESTR | B8: "...approximately $30 - $35 million of future net charges related to severance payments, employee benefits, and related costs..."
A9: H1MDA-2026 | B9: "...the related severance and employee costs are expected to be recognized in subsequent periods as employees are notified." "...a portion of up to approximately $5 million potentially recognized in the first quarter of 2027..."
A11: B. Reconciliation of net cash provided by operating activities to adjusted free cash flow (ER-2026Q2)
A12: Line | B12: Q2 2026 | C12: Row ID | D12: 6M 2026 | E12: Row ID | F12: Label
A13: Net cash provided by operating activities | B13: 55354 | C13: QA-0965 | D13: 160041 | E13: QA-0966 | F13: Sourced
A14: Purchase of property and equipment | B14: -3790 | C14: QA-1003 | D14: -6237 | E14: QA-1004 | F14: Sourced
A15: Capitalized software development costs | B15: -1106 | C15: QA-1041 | D15: -1590 | E15: QA-1042 | F15: Sourced
A16: Purchase of PP&E related to build-out of corporate headquarters (add-back) | B16: 1886 | C16: QA-1065 | D16: 2908 | E16: QA-1066 | F16: Sourced
A17: Line for restructuring / severance payments in the reconciliation | B17: NONE | D17: NONE | F17: Sourced (absence)
A18: Adjusted free cash flow (Derived = sum of lines above) | B18: =SUM(B13:B16) -> 52344 | D18: =SUM(D13:D16) -> 155122 | F18: Derived
A19: Adjusted free cash flow as reported | B19: 52344 | C19: QA-1103 | D19: 155122 | E19: QA-1104 | F19: Sourced
A21: C. Answer
A22: (1) The company definition of adjusted FCF does NOT exclude restructuring or severance payments: severance is paid through operating cash flow and the reconciliation has no add-back for it (only the HQ build-out). Reported adjusted FCF in H2 2026 will therefore be reduced by severance paid.
A23: (2) The FY2026 adjusted FCF outlook EXCLUDES restructuring: the Jul 22, 2026 6-K states the FY2026 adjusted FCF margin projection excludes any estimated restructuring charges from the Plan; the Aug 10 dollar guide ($280-290M, margin 19%-20%) is the same margin and does not restate a change.
A24: (3) Decision: the plan ties guide-basis adjusted FCF to the guide and deducts severance cash ONCE, as a separate line. This is NOT a double count. Reported-basis adjusted FCF (guide basis less severance) is shown as a memo line in Cash_FCF. Residual uncertainty: the Aug 10 release does not repeat the exclusion wording, and up to ~$5M of charges may fall in Q1 2027.
A26: D. Bridge of cash + marketable securities, Dec 31, 2025 -> Jun 30, 2026 (USD k)
A27: Item | B27: H1 2026 | C27: Reference | D27: Note | E27: Class | F27: Label
A28: Opening cash + marketable securities, Dec 31, 2025 | B28: =Historical_Drivers!$N$38 -> 1665457 | C28: Historical_Drivers (QA-1231 + QA-1242) | E28: balance | F28: Derived
A29: Adjusted free cash flow | B29: =Historical_Drivers!$C$59 -> 155122 | C29: QA-1104 | D29: Includes interest income (financial income, net $17.3M H1 2026 per H1MDA-2026 is inside operating cash flow) and FX effects on operating items | E29: FCF | F29: Derived (link)
A30: Less: HQ build-out add-back (cash was spent) | B30: =-D16 -> -2908 | C30: QA-1066 | D30: One-off renovation of vacated Israel office | E30: other: one-off | F30: Derived (link)
A31: Share repurchases | B31: -734971 | C31: QA-1202 | D31: $870M authorization fully used | E31: buyback | F31: Sourced
A32: Acquisition of a business operation (OneAI) | B32: -13200 | C32: H1FS-2026 cash flow statement (6-K Ex. 99.2, acc. 0001178913-26-003971) | D32: Not in source book; primary source | E32: other: one-off | F32: Sourced
A33: Purchase of securities of privately held companies (monday ventures) | B33: -6000 | C33: H1FS-2026 cash flow statement (6-K Ex. 99.2, acc. 0001178913-26-003971) | D33: $50M corporate venture fund | E33: other: recurring | F33: Sourced
A34: Investment in affiliated company (monday ventures) | B34: -4332 | C34: H1FS-2026 cash flow statement (6-K Ex. 99.2, acc. 0001178913-26-003971) | E34: other: recurring | F34: Sourced
A35: Proceeds from exercise of share options and ESPP | B35: 15369 | C35: H1FS-2026 cash flow statement (6-K Ex. 99.2, acc. 0001178913-26-003971) | E35: other: recurring | F35: Sourced
A36: Repayment of tax advance relating to exercises of share options and RSUs, net (taxes on equity awards) | B36: -1829 | C36: H1FS-2026 cash flow statement (6-K Ex. 99.2, acc. 0001178913-26-003971) | E36: other: recurring | F36: Sourced
A37: Accretion of discount on marketable securities (non-cash increase in securities) | B37: 1693 | C37: H1FS-2026 cash flow statement (6-K Ex. 99.2, acc. 0001178913-26-003971) | D37: Deducted in operating cash flow; adds to securities balance | E37: other: recurring | F37: Sourced
A38: Effect of exchange rates on cash (separate line) | B38: 0 | C38: H1FS-2026 cash flow statement (6-K Ex. 99.2, acc. 0001178913-26-003971) | D38: No separate FX line in the statement; FX is inside operating items | E38: FX | F38: Sourced
A39: Fair-value changes and other (Derived residual) | B39: =B40-B28-SUM(B29:B38) -> -1646 | C39: balance less items | E39: other: residual | F39: Derived
A40: Closing cash + marketable securities, Jun 30, 2026 | B40: =Historical_Drivers!$P$38 -> 1072755 | C40: Historical_Drivers (QA-1233 + QA-1244) | E40: balance | F40: Derived
A42: Total other cash flows H1 2026 (all items except FCF and buybacks) | B42: =SUM(B30:B39)-B31 -> -12853 | F42: Derived
A43: Run-rate per quarter (USD m) -> Assumptions P12 | B43: =B42/2/1000 -> -6.4265 | F43: Derived
A44: Sensitivity: run-rate excluding one-offs (OneAI, HQ) (USD m / quarter) | B44: =(B42-B32-B30)/2/1000 -> 1.6275 | F44: Derived
A46: E. Why the analysis workbook showed about -$67M (cash and equivalents only)
A47: Purchase of marketable securities | B47: -112915 | C47: H1FS-2026 cash flow statement (6-K Ex. 99.2, acc. 0001178913-26-003971) | D47: Transfer from cash into securities: no change in cash + securities | E47: transfer | F47: Sourced
A48: Maturities of marketable securities | B48: 55917 | C48: H1FS-2026 cash flow statement (6-K Ex. 99.2, acc. 0001178913-26-003971) | E48: transfer | F48: Sourced
A49: Explained: net securities purchases + OneAI + ventures + options + tax advances | B49: =B47+B48+B32+B33+B34+B35+B36 -> -66990 | F49: Derived
A50: Analysis workbook residual (monday_analysis.xlsx Cash_Conversion!H53) | B50: -66990 | C50: monday_analysis.xlsx Cash_Conversion!H53 | F50: Sourced
A51: Conclusion: about -$57M of the -$67M was a transfer into marketable securities (still liquidity). In cash + securities terms, H1 2026 other flows were only about -$12.9M (-$6.4M/quarter); the earlier "-$34M/quarter" estimate was wrong.
A53: F. Cash flow statement totals (for internal checks)
A54: Net cash used in investing activities | B54: -88357 | C54: H1FS-2026 cash flow statement (6-K Ex. 99.2, acc. 0001178913-26-003971) | E54: total | F54: Sourced
A55: Net cash used in financing activities | B55: -721431 | C55: H1FS-2026 cash flow statement (6-K Ex. 99.2, acc. 0001178913-26-003971) | E55: total | F55: Sourced
A56: Purchase of property and equipment (investing) | B56: =D14 -> -6237 | C56: QA-1004 | E56: total | F56: Derived (link)
A57: Capitalized software development costs (investing) | B57: =D15 -> -1590 | C57: QA-1042 | E57: total | F57: Derived (link)
A58: Net cash provided by operating activities | B58: =D13 -> 160041 | C58: QA-0966 | E58: total | F58: Derived (link)

Sheet Assumptions
A1: Assumptions (owner-approved rulings of Oct 28, 2026; orange = Assumed, black = Derived)
A2: Each parameter: Base and Downside value, current level, forecast path, rationale, evidence IDs, sensitivity.
A4: ID | B4: Parameter | C4: Base | D4: Downside | E4: Unit | F4: Current level | G4: Forecast path | H4: Rationale | I4: Evidence IDs | J4: Sensitivity | K4: Label
A5: P1 | B5: Annual deceleration of same-quarter sequential revenue growth | C5: 1.3 | D5: 2.6 | E5: pp / year | F5: Avg QoQ fell ~1.6 pp 2024->2025 and ~1.1 pp H1 2025->H1 2026 | G5: 2027 quarter seq growth = same quarter 2026 seq - P1 | H5: Method B (ruling 1); Downside = faster deceleration (ruling 2). | I5: Historical_Drivers revenue rows; monday_driver_audit.xlsx Revenue_Backtest | J5: Downside (+1.3 pp/yr) lowers FY2027 revenue by $79.7M and op. income by $79.0M (opex dollars held). | K5: Assumed
A6: P2 | B6: Q4 2026 sequential revenue growth | C6: =((Historical_Drivers!$C$46+Historical_Drivers!$C$47)/2*1000-Historical_Drivers!$C$58-(Historical_Drivers!$C$50+Historical_Drivers!$C$51)/2*1000)/((Historical_Drivers!$C$50+Historical_Drivers!$C$51)/2*1000)-1 -> 0.043669377 | D6: =C6-(D5-C5)/100 -> 0.030669377 | E6: % | F6: Q2 2026 seq 3.8%; Q3 2026 call seq ~3.8% | G6: Base: guidance-implied Q4/Q3 step; Downside: Base - (P1 Downside - P1 Base) | H6: FY guide covers Q4 implicitly (FY mid - H1 actual - Q3 guide mid). | I6: GH-0100, GH-0102, QA H1 2026 revenue | J6: +/-0.5 pp = about +/-$1.9M Q4 2026 revenue and about +/-$8.5M FY2027 revenue (Q4 is the 2027 base). | K6: Derived
A7: P3 | B7: Non-GAAP gross margin change per quarter | C7: -0.1 | D7: -0.25 | E7: pp / quarter | F7: Q2 2026 88.9% | G7: Q3 2026 = Q2 + Base step (both cases, so Q3 matches the call); later quarters + case step | H7: Company expects a modest mid-term decline from AI compute (FY2025 20-F). | I7: Historical_Drivers GP rows; source-book Definitions | J7: Downside step (-0.25 vs -0.10 pp/q) lowers FY2027 op. income by $8.5M (rate effect in Scenarios bridge). | K7: Assumed
A8: P4 | B8: R&D % of revenue: 2027 change vs Q3 2026 (Base only; Downside holds Base dollars) | C8: -0.5 | E8: pp | F8: Q2 2026 22.8% | G8: Q3 2026 from the locked call; Q4 2026 held; 2027 = Q3 + P4 | H8: Restructuring (~20% workforce) net of continued hiring in strategic areas. | I8: Historical_Drivers R&D rows; audit Proposed_Assumptions | J8: each 1 pp = about $17.1M of FY2027 op. income. | K8: Assumed
A9: P5 | B9: S&M % of revenue: 2027 change vs Q3 2026 (Base only) | C9: -0.5 | E9: pp | F9: Q2 2026 41.0% (post-commission-change basis) | G9: as P4 | H9: Ratios use only post-2025 commission-change quarters. | I9: Historical_Drivers S&M rows (2025-2026); AN-0348..AN-0350 | J9: each 1 pp = about $17.1M of FY2027 op. income. | K9: Assumed
A10: P6 | B10: G&A % of revenue: 2027 change vs Q3 2026 (Base only) | C10: -0.2 | E10: pp | F10: Q2 2026 8.4% | G10: as P4 | H10: Stable 8.1%-8.9%. | I10: Historical_Drivers G&A rows | J10: each 1 pp = about $17.1M of FY2027 op. income. | K10: Assumed
A11: P7 | B11: 2027 adjusted FCF / non-GAAP operating income (annual conversion) | C11: 1.23 | D11: 1 | E11: x | F11: FY2026 guide-implied 285/232 = 1.23x; Q2 2026 0.86x | G11: 2027 FCF = 2027 op. income x P7, phased by 2023-2025 quarterly shares | H11: Ruling 3: anchored to the FY2026 guide; historical 2-4x ratios no longer representative. | I11: GH-0098, GH-0099; analysis Cash_Conversion!C41:F41 | J11: FY2027 Base FCF range: $404.0M at 1.23x, $371.4M at 1.13x, $328.5M at 1.00x (Cash_FCF). | K11: Assumed
A12: P8 | B12: Severance cash, H2 2026 (split evenly Q3/Q4), outside adjusted FCF | C12: 32.5 | D12: 35 | E12: USD m | F12: ~$30-35M severance-related estimate (6-K Jul 22, 2026) | G12: -P8/2 in Q3 and Q4 2026 | H12: UNRESOLVED whether the FY FCF guide includes it; modeled as a separate cash item (adjusted FCF tied to the guide is assumed to exclude it). | I12: Annual restructuring rows (6K-20260722-RESTR) | J12: Guide excludes restructuring (6-K Jul 22, 2026): severance is deducted once; +/-$2.5M changes 2026 cash by -/+$2.5M. | K12: Assumed
A13: P9 | B13: SBC % of revenue (GAAP bridge) | C13: 0.105 | D13: 0.105 | E13: share | F13: Q2 2026 11.3% | G13: flat | H13: Recent quarters ~8%-12%. | I13: Historical_Drivers SBC rows | J13: +/-1 pp = about +/-$17.1M FY2027 GAAP op. income (no non-GAAP or cash effect). | K13: Assumed
A14: P10 | B14: Restructuring charges (GAAP, net), H2 2026, split evenly Q3/Q4 | C14: 50 | D14: 50 | E14: USD m | F14: Plan estimate ~$45-55M net (incl. ~$15M SBC credit) | G14: Q3, Q4 2026 = P10/2; 2027 = 0 | H14: Midpoint of the disclosed range; excluded from non-GAAP. | I14: Annual restructuring rows (6K-20260722-RESTR) | J14: +/-$5M changes FY2026 GAAP op. income by -/+$5M (no non-GAAP effect; cash portion is P8). | K14: Assumed
A15: P11 | B15: Share repurchases per quarter | C15: 0 | D15: 0 | E15: USD m | F15: $870M authorization fully used by Q2 2026 | G15: none | H15: FLAG: no new program disclosed. | I15: QA repurchase rows (ER-2026Q2) | J15: A new program reduces cash one-for-one. | K15: Assumed
A16: P12 | B16: Other cash flows per quarter (acquisitions, venture investments, option proceeds, tax advances, securities accretion / fair value) | C16: =Cash_Bridge!$B$43 -> -6.4265 | D16: =Cash_Bridge!$B$43 -> -6.4265 | E16: USD m | F16: H1 2026: -$12.9M in total (Cash_Bridge) | G16: H1 2026 quarterly run-rate held flat Q3 2026-Q4 2027 | H16: ASSUMED persistence of the H1 2026 run-rate from the primary-source cash bridge. Interest income is NOT separate: it is inside operating cash flow and therefore inside adjusted FCF. | I16: H1FS-2026 cash flow statement; QA-1202, QA-1231..1233, QA-1242..1244; Cash_Bridge | J16: Excluding one-offs (OneAI, HQ) the run-rate is $1.6M/quarter instead of $-6.4M: about $48.3M more cash by end 2027. | K16: Derived (Assumed persistence)
A17: P13 | B17: NDR indicator (NOT a driver): change per quarter after Q3 2026 | C17: -0.25 | D17: =(D18-Historical_Drivers!$C$56)*100/5 -> -0.7 | E17: pp / quarter | F17: Q2 2026 109%; locked Q3 call MID 108.5% | G17: Base: Q3 call MID then -0.25 pp/q; Downside: linear to 105% by Q4 2027 | H17: Ruling 1-2: narrative indicator only; never used in any calculation. | I17: QA NDR rows; locked call NDR!D37 | J17: n/a (no model effect) | K17: Assumed
A18: P15 | B18: NDR indicator Downside endpoint, Q4 2027 (NOT a driver) | D18: 1.05 | E18: share | F18: Q2 2026 109% | G18: Downside NDR reaches this level by Q4 2027 | H18: Ruling 2: weakening toward ~105%, documented indicator only. | I18: Owner ruling; QA NDR rows | J18: n/a (no model effect) | K18: Assumed
A19: P14 | B19: Net adds of customers >$50k ARR per quarter (indicator and trigger): Base = last-8 median, Downside = last-8 minimum | C19: =MEDIAN(Trigger_History!$H$20:$H$27) -> 276.5 | D19: =MIN(Trigger_History!$H$20:$H$27) -> 194 | E19: customers | F19: Last-8 median 276.5, min 194 | G19: Q3 call MID then + P14 per quarter | H19: Evidence-supported trigger metric; indicator only. | I19: QA-1405..QA-1426; Trigger_History | J19: n/a (no model effect) | K19: Derived
A20: P16 | B20: Trigger fire-rate tolerance: a trigger firing in more than this share of evaluable quarters is flagged as firing too often | C20: 0.25 | E20: share | F20: n/a | G20: Applied in Trigger_History | H20: A trigger meant to signal a regime change should be rare; one quarter in four is the tolerance. | I20: Trigger_History | J20: At 15% or 35% the flags in Trigger_History change only if a fire rate lies between. | K20: Assumed
B22: Management-response levers (applied to the Downside from the response start quarter L0; see Management_Response)
A23: L0 | B23: Response start quarter in 2027 (1 = Q1 ... 4 = Q4): earliest action consistent with the two-consecutive-quarter trigger rule | C23: 2 | E23: quarter | F23: n/a | G23: Levers active from this quarter through Q4 2027 | H23: T2 (beat) can first fire on Q3+Q4 2026 actuals; Q4 2026 is reported in Feb 2027 (Q1 2027), so savings can start in Q2 2027 at the earliest. T1 cannot fire before Q4 2026+Q1 2027 (reported May 2027), i.e. action from Q3 2027. | I23: Reporting calendar in Sources (Q4 results in February, Q1 in May); Recommendation triggers | J23: Start Q3 2027 instead of Q2: FY2027 saving falls by about one third (3 to 2 active quarters). | K23: Assumed
A24: L1 | B24: Lever 1: cut R&D + G&A dollars vs Downside (slow hiring / opex growth) | C24: 0.05 | E24: share | F24: n/a | G24: From L0 to Q4 2027 | H24: Moderate slowdown equivalent to pausing net hiring growth; size is a choice, not a forecast. | I24: Opex rows | J24: Each 1% = about $5M of full-year 2027 op. income. | K24: Assumed
A25: L2 | B25: Lever 2: cut S&M dollars vs Downside | C25: 0.1 | E25: share | F25: n/a | G25: From L0 to Q4 2027 | H25: Largest discretionary line (advertising, partner commissions). | I25: Opex rows | J25: Each 1% = about $6.5M of 2027 op. income before growth cost. | K25: Assumed
A26: E1 | B26: ILLUSTRATIVE ONLY - growth cost: annualized revenue lost per $1 of quarterly S&M cut (not used for the recommendation; see breakeven) | C26: 0.3 | E26: x | F26: NOT observable in the data | G26: starts the quarter after the cut, cumulative | H26: ASSUMED RANGE 0 / 0.3 / 0.6: the public data cannot prove the growth cost of cutting spend. | I26: none (no evidence exists) | J26: See Management_Response low/mid/high columns. | K26: Assumed
A27: E2 | B27: ILLUSTRATIVE ONLY - growth cost: annualized revenue lost per $1 of quarterly R&D+G&A cut | C27: 0.1 | E27: x | F27: NOT observable in the data | G27: as E1 | H27: ASSUMED RANGE 0 / 0.1 / 0.2; effects of R&D cuts mostly fall beyond 2027. | I27: none (no evidence exists) | J27: See Management_Response. | K27: Assumed

Sheet Revenue_Build
A1: Revenue build (Method B: guidance for the quarters it covers, then sequential-deceleration trend)
A2: USD millions. Q1-Q2 2026 actual; Q3 2026 = locked call; Q4 2026 = guidance-implied step; 2027 = same-quarter 2026 sequential growth less the annual deceleration.
A4: BASE
A5: Line | B5: Label | C5: Q1 2026A | D5: Q2 2026A | E5: Q3 2026 | F5: Q4 2026 | G5: Q1 2027 | H5: Q2 2027 | I5: Q3 2027 | J5: Q4 2027 | K5: FY2026 | L5: FY2027 | M5: Note
A6: Sequential revenue growth | B6: Derived (Assumed P1/P2) | C6: =Historical_Drivers!$O$35 -> 0.052075908 | D6: =Historical_Drivers!$P$35 -> 0.038022576 | E6: =E7/D7-1 -> 0.037741815 | F6: =Assumptions!$C$6 -> 0.043669377 | G6: =C6-Assumptions!$C$5/100 -> 0.039075908 | H6: =D6-Assumptions!$C$5/100 -> 0.025022576 | I6: =E6-Assumptions!$C$5/100 -> 0.024741815 | J6: =F6-Assumptions!$C$5/100 -> 0.030669377
A7: Revenue | B7: Sourced (Q1-Q3) / Derived | C7: =Historical_Drivers!$O$6/1000 -> 351.265 | D7: =Historical_Drivers!$P$6/1000 -> 364.621 | E7: =Historical_Drivers!$C$52 -> 378.38246 | F7: =E7*(1+F6) -> 394.90618 | G7: =F7*(1+G6) -> 410.3375 | H7: =G7*(1+H6) -> 420.6052 | I7: =H7*(1+I6) -> 431.01174 | J7: =I7*(1+J6) -> 444.2306 | K7: =SUM(C7:F7) -> 1489.1746 | L7: =SUM(G7:J7) -> 1706.185 | M7: Q3 2026 = locked call MID
A8: Revenue YoY growth | B8: Derived | C8: =C7*1000/Historical_Drivers!$K$6-1 -> 0.24451727 | D8: =D7*1000/Historical_Drivers!$L$6-1 -> 0.21941113 | E8: =E7*1000/Historical_Drivers!$M$6-1 -> 0.19418175 | F8: =F7*1000/Historical_Drivers!$N$6-1 -> 0.18278588 | G8: =G7/C7-1 -> 0.16817076 | H8: =H7/D7-1 -> 0.15354081 | I8: =I7/E7-1 -> 0.13909017 | J8: =J7/F7-1 -> 0.12490161 | K8: =K7/Historical_Drivers!$C$70-1 -> 0.20874859 | L8: =L7/K7-1 -> 0.14572529
A9: FY2026 revenue minus FY guide midpoint (USD m) | B9: Derived | K9: =K7-(Historical_Drivers!$C$46+Historical_Drivers!$C$47)/2 -> 19.174643
A10: NDR all customers - INDICATOR ONLY (not used in any calculation) | B10: Derived (Assumed P13) | D10: =Historical_Drivers!$P$30 -> 1.09 | E10: =Historical_Drivers!$C$56 -> 1.085 | F10: =E10+Assumptions!$C$17/100 -> 1.0825 | G10: =F10+Assumptions!$C$17/100 -> 1.08 | H10: =G10+Assumptions!$C$17/100 -> 1.0775 | I10: =H10+Assumptions!$C$17/100 -> 1.075 | J10: =I10+Assumptions!$C$17/100 -> 1.0725 | M10: Narrative indicator per ruling 1
A11: Customers >$50k ARR - INDICATOR (trigger metric) | B11: Derived (Assumed P14) | D11: =Historical_Drivers!$P$32 -> 4834 | E11: =Historical_Drivers!$C$57 -> 5110.5 | F11: =E11+Assumptions!$C$19 -> 5387 | G11: =F11+Assumptions!$C$19 -> 5663.5 | H11: =G11+Assumptions!$C$19 -> 5940 | I11: =H11+Assumptions!$C$19 -> 6216.5 | J11: =I11+Assumptions!$C$19 -> 6493
A13: DOWNSIDE (before management response)
A14: Line | B14: Label | C14: Q1 2026A | D14: Q2 2026A | E14: Q3 2026 | F14: Q4 2026 | G14: Q1 2027 | H14: Q2 2027 | I14: Q3 2027 | J14: Q4 2027 | K14: FY2026 | L14: FY2027 | M14: Note
A15: Sequential revenue growth | B15: Derived (Assumed P1/P2) | C15: =Historical_Drivers!$O$35 -> 0.052075908 | D15: =Historical_Drivers!$P$35 -> 0.038022576 | E15: =E16/D16-1 -> 0.037741815 | F15: =Assumptions!$D$6 -> 0.030669377 | G15: =C15-Assumptions!$D$5/100 -> 0.026075908 | H15: =D15-Assumptions!$D$5/100 -> 0.012022576 | I15: =E15-Assumptions!$D$5/100 -> 0.011741815 | J15: =F15-Assumptions!$D$5/100 -> 0.0046693767
A16: Revenue | B16: Sourced (Q1-Q3) / Derived | C16: =Historical_Drivers!$O$6/1000 -> 351.265 | D16: =Historical_Drivers!$P$6/1000 -> 364.621 | E16: =Historical_Drivers!$C$52 -> 378.38246 | F16: =E16*(1+F15) -> 389.98721 | G16: =F16*(1+G15) -> 400.15648 | H16: =G16*(1+H15) -> 404.96739 | I16: =H16*(1+I15) -> 409.72245 | J16: =I16*(1+J15) -> 411.6356 | K16: =SUM(C16:F16) -> 1484.2557 | L16: =SUM(G16:J16) -> 1626.4819 | M16: Q3 2026 = locked call MID
A17: Revenue YoY growth | B17: Derived | C17: =C16*1000/Historical_Drivers!$K$6-1 -> 0.24451727 | D17: =D16*1000/Historical_Drivers!$L$6-1 -> 0.21941113 | E17: =E16*1000/Historical_Drivers!$M$6-1 -> 0.19418175 | F17: =F16*1000/Historical_Drivers!$N$6-1 -> 0.16805304 | G17: =G16/C16-1 -> 0.13918689 | H17: =H16/D16-1 -> 0.11065296 | I17: =I16/E16-1 -> 0.082826219 | J17: =J16/F16-1 -> 0.055510494 | K17: =K16/Historical_Drivers!$C$70-1 -> 0.20475591 | L17: =L16/K16-1 -> 0.095823282
A18: FY2026 revenue minus FY guide midpoint (USD m) | B18: Derived | K18: =K16-(Historical_Drivers!$C$46+Historical_Drivers!$C$47)/2 -> 14.255671
A19: NDR all customers - INDICATOR ONLY (not used in any calculation) | B19: Derived (Assumed P13) | D19: =Historical_Drivers!$P$30 -> 1.09 | E19: =Historical_Drivers!$C$56 -> 1.085 | F19: =E19+Assumptions!$D$17/100 -> 1.078 | G19: =F19+Assumptions!$D$17/100 -> 1.071 | H19: =G19+Assumptions!$D$17/100 -> 1.064 | I19: =H19+Assumptions!$D$17/100 -> 1.057 | J19: =I19+Assumptions!$D$17/100 -> 1.05 | M19: Narrative indicator per ruling 1
A20: Customers >$50k ARR - INDICATOR (trigger metric) | B20: Derived (Assumed P14) | D20: =Historical_Drivers!$P$32 -> 4834 | E20: =Historical_Drivers!$C$57 -> 5110.5 | F20: =E20+Assumptions!$D$19 -> 5304.5 | G20: =F20+Assumptions!$D$19 -> 5498.5 | H20: =G20+Assumptions!$D$19 -> 5692.5 | I20: =H20+Assumptions!$D$19 -> 5886.5 | J20: =I20+Assumptions!$D$19 -> 6080.5
A22: SENSITIVITY: Base with Q3 2026 at the locked call LOW
A23: Line | B23: Label | C23: Q1 2026A | D23: Q2 2026A | E23: Q3 2026 | F23: Q4 2026 | G23: Q1 2027 | H23: Q2 2027 | I23: Q3 2027 | J23: Q4 2027 | K23: FY2026 | L23: FY2027 | M23: Note
A24: Sequential revenue growth | B24: Derived (Assumed P1/P2) | C24: =Historical_Drivers!$O$35 -> 0.052075908 | D24: =Historical_Drivers!$P$35 -> 0.038022576 | E24: =E25/D25-1 -> 0.027014544 | F24: =Assumptions!$C$6 -> 0.043669377 | G24: =C24-Assumptions!$C$5/100 -> 0.039075908 | H24: =D24-Assumptions!$C$5/100 -> 0.025022576 | I24: =E24-Assumptions!$C$5/100 -> 0.014014544 | J24: =F24-Assumptions!$C$5/100 -> 0.030669377
A25: Revenue | B25: Sourced (Q1-Q3) / Derived | C25: =Historical_Drivers!$O$6/1000 -> 351.265 | D25: =Historical_Drivers!$P$6/1000 -> 364.621 | E25: =Historical_Drivers!$C$53 -> 374.47107 | F25: =E25*(1+F24) -> 390.82399 | G25: =F25*(1+G24) -> 406.09579 | H25: =G25*(1+H24) -> 416.25735 | I25: =H25*(1+I24) -> 422.09101 | J25: =I25*(1+J24) -> 435.03628 | K25: =SUM(C25:F25) -> 1481.1811 | L25: =SUM(G25:J25) -> 1679.4804 | M25: Q3 2026 = locked call LOW
A26: Revenue YoY growth | B26: Derived | C26: =C25*1000/Historical_Drivers!$K$6-1 -> 0.24451727 | D26: =D25*1000/Historical_Drivers!$L$6-1 -> 0.21941113 | E26: =E25*1000/Historical_Drivers!$M$6-1 -> 0.18183734 | F26: =F25*1000/Historical_Drivers!$N$6-1 -> 0.17055927 | G26: =G25/C25-1 -> 0.15609523 | H26: =H25/D25-1 -> 0.14161651 | I26: =I25/E25-1 -> 0.12716587 | J26: =J25/F25-1 -> 0.11312583 | K26: =K25/Historical_Drivers!$C$70-1 -> 0.20226028 | L26: =L25/K25-1 -> 0.13387923
A27: FY2026 revenue minus FY guide midpoint (USD m) | B27: Derived | K27: =K25-(Historical_Drivers!$C$46+Historical_Drivers!$C$47)/2 -> 11.181058
A28: NDR all customers - INDICATOR ONLY (not used in any calculation) | B28: Derived (Assumed P13) | D28: =Historical_Drivers!$P$30 -> 1.09 | E28: =Historical_Drivers!$C$56 -> 1.085 | F28: =E28+Assumptions!$C$17/100 -> 1.0825 | G28: =F28+Assumptions!$C$17/100 -> 1.08 | H28: =G28+Assumptions!$C$17/100 -> 1.0775 | I28: =H28+Assumptions!$C$17/100 -> 1.075 | J28: =I28+Assumptions!$C$17/100 -> 1.0725 | M28: Narrative indicator per ruling 1
A29: Customers >$50k ARR - INDICATOR (trigger metric) | B29: Derived (Assumed P14) | D29: =Historical_Drivers!$P$32 -> 4834 | E29: =Historical_Drivers!$C$57 -> 5110.5 | F29: =E29+Assumptions!$C$19 -> 5387 | G29: =F29+Assumptions!$C$19 -> 5663.5 | H29: =G29+Assumptions!$C$19 -> 5940 | I29: =H29+Assumptions!$C$19 -> 6216.5 | J29: =I29+Assumptions!$C$19 -> 6493
A31: FORECAST BAND around Base revenue from backtest errors by horizon (origin = Q2 2026 actual)
A32: Line | B32: Label | C32: Q1 2026A | D32: Q2 2026A | E32: Q3 2026 | F32: Q4 2026 | G32: Q1 2027 | H32: Q2 2027 | I32: Q3 2027 | J32: Q4 2027 | K32: FY2026 | L32: FY2027 | M32: Note
A33: Horizon (quarters ahead of the last actual) | B33: Derived | E33: =COLUMN()-COLUMN($D$1) -> 1 | F33: =COLUMN()-COLUMN($D$1) -> 2 | G33: =COLUMN()-COLUMN($D$1) -> 3 | H33: =COLUMN()-COLUMN($D$1) -> 4 | I33: =COLUMN()-COLUMN($D$1) -> 5 | J33: =COLUMN()-COLUMN($D$1) -> 6
A34: Within tested horizon (1-4)? | B34: Text | E34: tested | F34: tested | G34: tested | H34: tested | I34: BEYOND | J34: BEYOND | M34: Q3 2027 (h5) and Q4 2027 (h6) lie BEYOND the tested horizon: h4 error used as a floor; true band is wider
A35: Backtest mean absolute error used | B35: Derived (link to Backtest) | E35: =Backtest!C75 -> 0.01035725 | F35: =Backtest!C76 -> 0.010650591 | G35: =Backtest!C77 -> 0.02385355 | H35: =Backtest!C78 -> 0.041292045 | I35: =Backtest!C78 -> 0.041292045 | J35: =Backtest!C78 -> 0.041292045
A36: Backtest max absolute error used | B36: Derived (link to Backtest) | E36: =Backtest!E75 -> 0.014664184 | F36: =Backtest!E76 -> 0.032417487 | G36: =Backtest!E77 -> 0.059032954 | H36: =Backtest!E78 -> 0.096390451 | I36: =Backtest!E78 -> 0.096390451 | J36: =Backtest!E78 -> 0.096390451
A37: Memo: backtest bias at that horizon | B37: Derived (link to Backtest) | E37: =Backtest!D75 -> 0.0073551849 | F37: =Backtest!D76 -> 0.0071444617 | G37: =Backtest!D77 -> -0.00056598665 | H37: =Backtest!D78 -> -0.017596508 | I37: =Backtest!D78 -> -0.017596508 | J37: =Backtest!D78 -> -0.017596508
A38: Band low (mean abs. error) | B38: Derived | C38: =Revenue_Build!C7 -> 351.265 | D38: =Revenue_Build!D7 -> 364.621 | E38: =Revenue_Build!E7*(1-E35) -> 374.46346 | F38: =Revenue_Build!F7*(1-F35) -> 390.7002 | G38: =Revenue_Build!G7*(1-G35) -> 400.5495 | H38: =Revenue_Build!H7*(1-H35) -> 403.23755 | I38: =Revenue_Build!I7*(1-I35) -> 413.21438 | J38: =Revenue_Build!J7*(1-J35) -> 425.88741 | K38: =SUM(C38:F38) -> 1481.0497 | L38: =SUM(G38:J38) -> 1642.8888 | M38: FY = sum of quarter bands (errors compound along the path, so they are treated as fully correlated)
A39: Band high (mean abs. error) | B39: Derived | C39: =Revenue_Build!C7 -> 351.265 | D39: =Revenue_Build!D7 -> 364.621 | E39: =Revenue_Build!E7*(1+E35) -> 382.30146 | F39: =Revenue_Build!F7*(1+F35) -> 399.11217 | G39: =Revenue_Build!G7*(1+G35) -> 420.12551 | H39: =Revenue_Build!H7*(1+H35) -> 437.97285 | I39: =Revenue_Build!I7*(1+I35) -> 448.8091 | J39: =Revenue_Build!J7*(1+J35) -> 462.57379 | K39: =SUM(C39:F39) -> 1497.2996 | L39: =SUM(G39:J39) -> 1769.4812 | M39: FY = sum of quarter bands (errors compound along the path, so they are treated as fully correlated)
A40: Band low (max abs. error) | B40: Derived | C40: =Revenue_Build!C7 -> 351.265 | D40: =Revenue_Build!D7 -> 364.621 | E40: =Revenue_Build!E7*(1-E36) -> 372.83379 | F40: =Revenue_Build!F7*(1-F36) -> 382.10432 | G40: =Revenue_Build!G7*(1-G36) -> 386.11407 | H40: =Revenue_Build!H7*(1-H36) -> 380.06288 | I40: =Revenue_Build!I7*(1-I36) -> 389.46632 | J40: =Revenue_Build!J7*(1-J36) -> 401.41101 | K40: =SUM(C40:F40) -> 1470.8241 | L40: =SUM(G40:J40) -> 1557.0543 | M40: FY = sum of quarter bands (errors compound along the path, so they are treated as fully correlated)
A41: Band high (max abs. error) | B41: Derived | C41: =Revenue_Build!C7 -> 351.265 | D41: =Revenue_Build!D7 -> 364.621 | E41: =Revenue_Build!E7*(1+E36) -> 383.93113 | F41: =Revenue_Build!F7*(1+F36) -> 407.70805 | G41: =Revenue_Build!G7*(1+G36) -> 434.56094 | H41: =Revenue_Build!H7*(1+H36) -> 461.14753 | I41: =Revenue_Build!I7*(1+I36) -> 472.55716 | J41: =Revenue_Build!J7*(1+J36) -> 487.05019 | K41: =SUM(C41:F41) -> 1507.5252 | L41: =SUM(G41:J41) -> 1855.3158 | M41: FY = sum of quarter bands (errors compound along the path, so they are treated as fully correlated)
A42: Base - Downside FY2027 revenue gap, % of Base | B42: Derived | L42: =(Revenue_Build!L7-Revenue_Build!L16)/Revenue_Build!L7 -> 0.046714233
A43: Gap / average 4-quarter-ahead backtest miss (x) | B43: Derived | L43: =L42/Backtest!C78 -> 1.1313131 | M43: Below ~1.0x the Downside is within normal 4-quarter forecast error
A45: VARIANT (not used in the plan): BASE with 2027 deceleration applied to a SMOOTHED base (average sequential growth of the last 4 quarters, Q1-Q4 2026)
A46: Line | B46: Label | C46: Q1 2026A | D46: Q2 2026A | E46: Q3 2026 | F46: Q4 2026 | G46: Q1 2027 | H46: Q2 2027 | I46: Q3 2027 | J46: Q4 2027 | K46: FY2026 | L46: FY2027 | M46: Note
A47: Sequential revenue growth (smoothed 2027 rule) | B47: Derived | C47: =Revenue_Build!C6 -> 0.052075908 | D47: =Revenue_Build!D6 -> 0.038022576 | E47: =Revenue_Build!E6 -> 0.037741815 | F47: =Revenue_Build!F6 -> 0.043669377 | G47: =AVERAGE($C47:$F47)-Assumptions!$C$5/100 -> 0.029877419 | H47: =AVERAGE($C47:$F47)-Assumptions!$C$5/100 -> 0.029877419 | I47: =AVERAGE($C47:$F47)-Assumptions!$C$5/100 -> 0.029877419 | J47: =AVERAGE($C47:$F47)-Assumptions!$C$5/100 -> 0.029877419
A48: Revenue (smoothed 2027 rule) | B48: Derived | C48: =Revenue_Build!C7 -> 351.265 | D48: =Revenue_Build!D7 -> 364.621 | E48: =Revenue_Build!E7 -> 378.38246 | F48: =E48*(1+F47) -> 394.90618 | G48: =F48*(1+G47) -> 406.70496 | H48: =G48*(1+H47) -> 418.85626 | I48: =H48*(1+I47) -> 431.3706 | J48: =I48*(1+J47) -> 444.25884 | K48: =SUM(C48:F48) -> 1489.1746 | L48: =SUM(G48:J48) -> 1701.1907
A50: VARIANT (not used in the plan): SENSITIVITY: Base with Q3 2026 at the locked call LOW with 2027 deceleration applied to a SMOOTHED base (average sequential growth of the last 4 quarters, Q1-Q4 2026)
A51: Line | B51: Label | C51: Q1 2026A | D51: Q2 2026A | E51: Q3 2026 | F51: Q4 2026 | G51: Q1 2027 | H51: Q2 2027 | I51: Q3 2027 | J51: Q4 2027 | K51: FY2026 | L51: FY2027 | M51: Note
A52: Sequential revenue growth (smoothed 2027 rule) | B52: Derived | C52: =Revenue_Build!C24 -> 0.052075908 | D52: =Revenue_Build!D24 -> 0.038022576 | E52: =Revenue_Build!E24 -> 0.027014544 | F52: =Revenue_Build!F24 -> 0.043669377 | G52: =AVERAGE($C52:$F52)-Assumptions!$C$5/100 -> 0.027195601 | H52: =AVERAGE($C52:$F52)-Assumptions!$C$5/100 -> 0.027195601 | I52: =AVERAGE($C52:$F52)-Assumptions!$C$5/100 -> 0.027195601 | J52: =AVERAGE($C52:$F52)-Assumptions!$C$5/100 -> 0.027195601
A53: Revenue (smoothed 2027 rule) | B53: Derived | C53: =Revenue_Build!C25 -> 351.265 | D53: =Revenue_Build!D25 -> 364.621 | E53: =Revenue_Build!E25 -> 374.47107 | F53: =E53*(1+F52) -> 390.82399 | G53: =F53*(1+G52) -> 401.45268 | H53: =G53*(1+H52) -> 412.37043 | I53: =H53*(1+I52) -> 423.58509 | J53: =I53*(1+J52) -> 435.10474 | K53: =SUM(C53:F53) -> 1481.1811 | L53: =SUM(G53:J53) -> 1672.5129

Sheet Opex
A1: Non-GAAP gross margin and operating expenses
A2: USD millions. Base ratios; Downside holds Base opex DOLLARS (before any management response).
A4: BASE
A5: Line | B5: Label | C5: Q1 2026A | D5: Q2 2026A | E5: Q3 2026 | F5: Q4 2026 | G5: Q1 2027 | H5: Q2 2027 | I5: Q3 2027 | J5: Q4 2027 | K5: FY2026 | L5: FY2027 | M5: Note
A6: Gross margin (non-GAAP) | B6: Derived (Assumed P3) | C6: =Historical_Drivers!$O$36 -> 0.89445291 | D6: =Historical_Drivers!$P$36 -> 0.88920276 | E6: =D6+Assumptions!$C$7/100 -> 0.88820276 | F6: =E6+Assumptions!$C$7/100 -> 0.88720276 | G6: =F6+Assumptions!$C$7/100 -> 0.88620276 | H6: =G6+Assumptions!$C$7/100 -> 0.88520276 | I6: =H6+Assumptions!$C$7/100 -> 0.88420276 | J6: =I6+Assumptions!$C$7/100 -> 0.88320276
A7: Gross profit (non-GAAP) | B7: Sourced / Derived | C7: =Historical_Drivers!$O$8/1000 -> 314.19 | D7: =Historical_Drivers!$P$8/1000 -> 324.222 | E7: =Revenue_Build!E7*E6 -> 336.08034 | F7: =Revenue_Build!F7*F6 -> 350.36186 | G7: =Revenue_Build!G7*G6 -> 363.64223 | H7: =Revenue_Build!H7*H6 -> 372.32089 | I7: =Revenue_Build!I7*I6 -> 381.10177 | J7: =Revenue_Build!J7*J6 -> 392.34569 | K7: =SUM(C7:F7) -> 1324.8542 | L7: =SUM(G7:J7) -> 1509.4106
A8: Q3 2026 total opex implied by the locked call (GP - call op. income) | B8: Derived | E8: =E7-Historical_Drivers!$C$54 -> 266.44334
A9: R&D % of revenue (non-GAAP) | B9: Derived (Assumed P4-P6) | C9: =C10/Revenue_Build!C7 -> 0.22323032 | D9: =D10/Revenue_Build!D7 -> 0.22764185 | E9: =E10/Revenue_Build!E7 -> 0.22214013 | F9: =E9 -> 0.22214013 | G9: =$E9+Assumptions!$C$8/100 -> 0.21714013 | H9: =$E9+Assumptions!$C$8/100 -> 0.21714013 | I9: =$E9+Assumptions!$C$8/100 -> 0.21714013 | J9: =$E9+Assumptions!$C$8/100 -> 0.21714013 | K9: =K10/Revenue_Build!K7 -> 0.22374437 | L9: =L10/Revenue_Build!L7 -> 0.21714013
A10: R&D (non-GAAP) | B10: Sourced / Derived | C10: =Historical_Drivers!$O$10/1000 -> 78.413 | D10: =Historical_Drivers!$P$10/1000 -> 83.003 | E10: =E8*Historical_Drivers!$P$10/(Historical_Drivers!$P$10+Historical_Drivers!$P$12+Historical_Drivers!$P$14) -> 84.053927 | F10: =F9*Revenue_Build!F7 -> 87.72451 | G10: =G9*Revenue_Build!G7 -> 89.100737 | H10: =H9*Revenue_Build!H7 -> 91.330267 | I10: =I9*Revenue_Build!I7 -> 93.589944 | J10: =J9*Revenue_Build!J7 -> 96.460289 | K10: =SUM(C10:F10) -> 333.19444 | L10: =SUM(G10:J10) -> 370.48124
A11: S&M % of revenue (non-GAAP) | B11: Derived (Assumed P4-P6) | C11: =C12/Revenue_Build!C7 -> 0.45031814 | D11: =D12/Revenue_Build!D7 -> 0.4098612 | E11: =E12/Revenue_Build!E7 -> 0.39995553 | F11: =E11 -> 0.39995553 | G11: =$E11+Assumptions!$C$9/100 -> 0.39495553 | H11: =$E11+Assumptions!$C$9/100 -> 0.39495553 | I11: =$E11+Assumptions!$C$9/100 -> 0.39495553 | J11: =$E11+Assumptions!$C$9/100 -> 0.39495553 | K11: =K12/Revenue_Build!K7 -> 0.41426039 | L11: =L12/Revenue_Build!L7 -> 0.39495553
A12: S&M (non-GAAP) | B12: Sourced / Derived | C12: =Historical_Drivers!$O$12/1000 -> 158.181 | D12: =Historical_Drivers!$P$12/1000 -> 149.444 | E12: =E8*Historical_Drivers!$P$12/(Historical_Drivers!$P$10+Historical_Drivers!$P$12+Historical_Drivers!$P$14) -> 151.33616 | F12: =F11*Revenue_Build!F7 -> 157.94491 | G12: =G11*Revenue_Build!G7 -> 162.06507 | H12: =H11*Revenue_Build!H7 -> 166.12035 | I12: =I11*Revenue_Build!I7 -> 170.23047 | J12: =J11*Revenue_Build!J7 -> 175.45133 | K12: =SUM(C12:F12) -> 616.90607 | L12: =SUM(G12:J12) -> 673.86722
A13: G&A % of revenue (non-GAAP) | B13: Derived (Assumed P4-P6) | C13: =C14/Revenue_Build!C7 -> 0.08130329 | D13: =D14/Revenue_Build!D7 -> 0.084101025 | E13: =E14/Revenue_Build!E7 -> 0.082068443 | F13: =E13 -> 0.082068443 | G13: =$E13+Assumptions!$C$10/100 -> 0.080068443 | H13: =$E13+Assumptions!$C$10/100 -> 0.080068443 | I13: =$E13+Assumptions!$C$10/100 -> 0.080068443 | J13: =$E13+Assumptions!$C$10/100 -> 0.080068443 | K13: =K14/Revenue_Build!K7 -> 0.082385633 | L13: =L14/Revenue_Build!L7 -> 0.080068443
A14: G&A (non-GAAP) | B14: Sourced / Derived | C14: =Historical_Drivers!$O$14/1000 -> 28.559 | D14: =Historical_Drivers!$P$14/1000 -> 30.665 | E14: =E8*Historical_Drivers!$P$14/(Historical_Drivers!$P$10+Historical_Drivers!$P$12+Historical_Drivers!$P$14) -> 31.053259 | F14: =F13*Revenue_Build!F7 -> 32.409336 | G14: =G13*Revenue_Build!G7 -> 32.855085 | H14: =H13*Revenue_Build!H7 -> 33.677204 | I14: =I13*Revenue_Build!I7 -> 34.510439 | J14: =J13*Revenue_Build!J7 -> 35.568853 | K14: =SUM(C14:F14) -> 122.68659 | L14: =SUM(G14:J14) -> 136.61158
A15: Total operating expenses (non-GAAP) | B15: Derived | C15: =C10+C12+C14 -> 265.153 | D15: =D10+D12+D14 -> 263.112 | E15: =E10+E12+E14 -> 266.44334 | F15: =F10+F12+F14 -> 278.07876 | G15: =G10+G12+G14 -> 284.02089 | H15: =H10+H12+H14 -> 291.12782 | I15: =I10+I12+I14 -> 298.33085 | J15: =J10+J12+J14 -> 307.48048 | ... L15: =L10+L12+L14 -> 1180.96
A16: Operating income (non-GAAP) | B16: Derived | C16: =C7-C15 -> 49.037 | D16: =D7-D15 -> 61.11 | E16: =E7-E15 -> 69.637 | F16: =F7-F15 -> 72.283098 | G16: =G7-G15 -> 79.621338 | H16: =H7-H15 -> 81.193064 | I16: =I7-I15 -> 82.770916 | J16: =J7-J15 -> 84.865218 | ... L16: =L7-L15 -> 328.45054
A17: Operating margin (non-GAAP) | B17: Derived | C17: =C16/Revenue_Build!C7 -> 0.13960116 | D17: =D16/Revenue_Build!D7 -> 0.16759868 | E17: =E16/Revenue_Build!E7 -> 0.18403866 | F17: =F16/Revenue_Build!F7 -> 0.18303866 | G17: =G16/Revenue_Build!G7 -> 0.19403866 | H17: =H16/Revenue_Build!H7 -> 0.19303866 | I17: =I16/Revenue_Build!I7 -> 0.19203866 | J17: =J16/Revenue_Build!J7 -> 0.19103866 | ... L17: =L16/Revenue_Build!L7 -> 0.19250581
A19: DOWNSIDE (before management response)
A20: Line | B20: Label | C20: Q1 2026A | D20: Q2 2026A | E20: Q3 2026 | F20: Q4 2026 | G20: Q1 2027 | H20: Q2 2027 | I20: Q3 2027 | J20: Q4 2027 | K20: FY2026 | L20: FY2027 | M20: Note
A21: Gross margin (non-GAAP) | B21: Derived (Assumed P3) | C21: =Historical_Drivers!$O$36 -> 0.89445291 | D21: =Historical_Drivers!$P$36 -> 0.88920276 | E21: =D21+Assumptions!$C$7/100 -> 0.88820276 | F21: =E21+Assumptions!$D$7/100 -> 0.88570276 | G21: =F21+Assumptions!$D$7/100 -> 0.88320276 | H21: =G21+Assumptions!$D$7/100 -> 0.88070276 | I21: =H21+Assumptions!$D$7/100 -> 0.87820276 | J21: =I21+Assumptions!$D$7/100 -> 0.87570276
A22: Gross profit (non-GAAP) | B22: Sourced / Derived | C22: =Historical_Drivers!$O$8/1000 -> 314.19 | D22: =Historical_Drivers!$P$8/1000 -> 324.222 | E22: =Revenue_Build!E16*E21 -> 336.08034 | F22: =Revenue_Build!F16*F21 -> 345.41275 | G22: =Revenue_Build!G16*G21 -> 353.41931 | H22: =Revenue_Build!H16*H21 -> 356.6559 | I22: =Revenue_Build!I16*I21 -> 359.81938 | J22: =Revenue_Build!J16*J21 -> 360.47043 | K22: =SUM(C22:F22) -> 1319.9051 | L22: =SUM(G22:J22) -> 1430.365
A23: Q3 2026 total opex implied by the locked call (GP - call op. income) | B23: Derived | E23: =E22-Historical_Drivers!$C$54 -> 266.44334
A24: R&D % of revenue (non-GAAP) | B24: Derived | C24: =C25/Revenue_Build!C16 -> 0.22323032 | D24: =D25/Revenue_Build!D16 -> 0.22764185 | E24: =E25/Revenue_Build!E16 -> 0.22214013 | F24: =F25/Revenue_Build!F16 -> 0.22494202 | G24: =G25/Revenue_Build!G16 -> 0.22266473 | H24: =H25/Revenue_Build!H16 -> 0.22552499 | I24: =I25/Revenue_Build!I16 -> 0.22842279 | J24: =J25/Revenue_Build!J16 -> 0.23433418 | ... L24: =L25/Revenue_Build!L16 -> 0.22778073
A25: R&D (non-GAAP) | B25: Sourced / Derived | C25: =Historical_Drivers!$O$10/1000 -> 78.413 | D25: =Historical_Drivers!$P$10/1000 -> 83.003 | E25: =Opex!E10 -> 84.053927 | F25: =Opex!F10 -> 87.72451 | G25: =Opex!G10 -> 89.100737 | H25: =Opex!H10 -> 91.330267 | I25: =Opex!I10 -> 93.589944 | J25: =Opex!J10 -> 96.460289 | K25: =SUM(C25:F25) -> 333.19444 | L25: =SUM(G25:J25) -> 370.48124
A26: S&M % of revenue (non-GAAP) | B26: Derived | C26: =C27/Revenue_Build!C16 -> 0.45031814 | D26: =D27/Revenue_Build!D16 -> 0.4098612 | E26: =E27/Revenue_Build!E16 -> 0.39995553 | F26: =F27/Revenue_Build!F16 -> 0.40500024 | G26: =G27/Revenue_Build!G16 -> 0.40500423 | H26: =H27/Revenue_Build!H16 -> 0.41020673 | I26: =I27/Revenue_Build!I16 -> 0.41547753 | J26: =J27/Revenue_Build!J16 -> 0.42622974 | ... L26: =L27/Revenue_Build!L16 -> 0.41430969
A27: S&M (non-GAAP) | B27: Sourced / Derived | C27: =Historical_Drivers!$O$12/1000 -> 158.181 | D27: =Historical_Drivers!$P$12/1000 -> 149.444 | E27: =Opex!E12 -> 151.33616 | F27: =Opex!F12 -> 157.94491 | G27: =Opex!G12 -> 162.06507 | H27: =Opex!H12 -> 166.12035 | I27: =Opex!I12 -> 170.23047 | J27: =Opex!J12 -> 175.45133 | K27: =SUM(C27:F27) -> 616.90607 | L27: =SUM(G27:J27) -> 673.86722
A28: G&A % of revenue (non-GAAP) | B28: Derived | C28: =C29/Revenue_Build!C16 -> 0.08130329 | D28: =D29/Revenue_Build!D16 -> 0.084101025 | E28: =E29/Revenue_Build!E16 -> 0.082068443 | F28: =F29/Revenue_Build!F16 -> 0.083103586 | G28: =G29/Revenue_Build!G16 -> 0.082105592 | H28: =H29/Revenue_Build!H16 -> 0.083160285 | I28: =I29/Revenue_Build!I16 -> 0.084228822 | J28: =J29/Revenue_Build!J16 -> 0.086408593 | ... L28: =L29/Revenue_Build!L16 -> 0.083992068
A29: G&A (non-GAAP) | B29: Sourced / Derived | C29: =Historical_Drivers!$O$14/1000 -> 28.559 | D29: =Historical_Drivers!$P$14/1000 -> 30.665 | E29: =Opex!E14 -> 31.053259 | F29: =Opex!F14 -> 32.409336 | G29: =Opex!G14 -> 32.855085 | H29: =Opex!H14 -> 33.677204 | I29: =Opex!I14 -> 34.510439 | J29: =Opex!J14 -> 35.568853 | K29: =SUM(C29:F29) -> 122.68659 | L29: =SUM(G29:J29) -> 136.61158
A30: Total operating expenses (non-GAAP) | B30: Derived | C30: =C25+C27+C29 -> 265.153 | D30: =D25+D27+D29 -> 263.112 | E30: =E25+E27+E29 -> 266.44334 | F30: =F25+F27+F29 -> 278.07876 | G30: =G25+G27+G29 -> 284.02089 | H30: =H25+H27+H29 -> 291.12782 | I30: =I25+I27+I29 -> 298.33085 | J30: =J25+J27+J29 -> 307.48048 | ... L30: =L25+L27+L29 -> 1180.96
A31: Operating income (non-GAAP) | B31: Derived | C31: =C22-C30 -> 49.037 | D31: =D22-D30 -> 61.11 | E31: =E22-E30 -> 69.637 | F31: =F22-F30 -> 67.333992 | G31: =G22-G30 -> 69.398422 | H31: =H22-H30 -> 65.52808 | I31: =I22-I30 -> 61.48853 | J31: =J22-J30 -> 52.989952 | ... L31: =L22-L30 -> 249.40498
A32: Operating margin (non-GAAP) | B32: Derived | C32: =C31/Revenue_Build!C16 -> 0.13960116 | D32: =D31/Revenue_Build!D16 -> 0.16759868 | E32: =E31/Revenue_Build!E16 -> 0.18403866 | F32: =F31/Revenue_Build!F16 -> 0.17265692 | G32: =G31/Revenue_Build!G16 -> 0.17342821 | H32: =H31/Revenue_Build!H16 -> 0.16181075 | I32: =I31/Revenue_Build!I16 -> 0.15007362 | J32: =J31/Revenue_Build!J16 -> 0.12873025 | ... L32: =L31/Revenue_Build!L16 -> 0.15334015
A34: SENSITIVITY: Base with Q3 2026 at the locked call LOW
A35: Line | B35: Label | C35: Q1 2026A | D35: Q2 2026A | E35: Q3 2026 | F35: Q4 2026 | G35: Q1 2027 | H35: Q2 2027 | I35: Q3 2027 | J35: Q4 2027 | K35: FY2026 | L35: FY2027 | M35: Note
A36: Gross margin (non-GAAP) | B36: Derived (Assumed P3) | C36: =Historical_Drivers!$O$36 -> 0.89445291 | D36: =Historical_Drivers!$P$36 -> 0.88920276 | E36: =D36+Assumptions!$C$7/100 -> 0.88820276 | F36: =E36+Assumptions!$C$7/100 -> 0.88720276 | G36: =F36+Assumptions!$C$7/100 -> 0.88620276 | H36: =G36+Assumptions!$C$7/100 -> 0.88520276 | I36: =H36+Assumptions!$C$7/100 -> 0.88420276 | J36: =I36+Assumptions!$C$7/100 -> 0.88320276
A37: Gross profit (non-GAAP) | B37: Sourced / Derived | C37: =Historical_Drivers!$O$8/1000 -> 314.19 | D37: =Historical_Drivers!$P$8/1000 -> 324.222 | E37: =Revenue_Build!E25*E36 -> 332.60624 | F37: =Revenue_Build!F25*F36 -> 346.74012 | G37: =Revenue_Build!G25*G36 -> 359.88321 | H37: =Revenue_Build!H25*H36 -> 368.47216 | I37: =Revenue_Build!I25*I36 -> 373.21404 | J37: =Revenue_Build!J25*J36 -> 384.22524 | K37: =SUM(C37:F37) -> 1317.7584 | L37: =SUM(G37:J37) -> 1485.7946
A38: Q3 2026 total opex implied by the locked call (GP - call op. income) | B38: Derived | E38: =E37-Historical_Drivers!$C$55 -> 269.67524
A39: R&D % of revenue (non-GAAP) | B39: Derived | C39: =C40/Revenue_Build!C25 -> 0.22323032 | D39: =D40/Revenue_Build!D25 -> 0.22764185 | E39: =E40/Revenue_Build!E25 -> 0.22718305 | F39: =Opex!F9 -> 0.22214013 | G39: =Opex!G9 -> 0.21714013 | H39: =Opex!H9 -> 0.21714013 | I39: =Opex!I9 -> 0.21714013 | J39: =Opex!J9 -> 0.21714013 | K39: =K40/Revenue_Build!K25 -> 0.22502797 | L39: =L40/Revenue_Build!L25 -> 0.21714013
A40: R&D (non-GAAP) | B40: Sourced / Derived | C40: =Historical_Drivers!$O$10/1000 -> 78.413 | D40: =Historical_Drivers!$P$10/1000 -> 83.003 | E40: =E38*Historical_Drivers!$P$10/(Historical_Drivers!$P$10+Historical_Drivers!$P$12+Historical_Drivers!$P$14) -> 85.073481 | F40: =F39*Revenue_Build!F25 -> 86.81769 | G40: =G39*Revenue_Build!G25 -> 88.179691 | H40: =H39*Revenue_Build!H25 -> 90.386174 | I40: =I39*Revenue_Build!I25 -> 91.652895 | J40: =J39*Revenue_Build!J25 -> 94.463833 | K40: =SUM(C40:F40) -> 333.30717 | L40: =SUM(G40:J40) -> 364.68259
A41: S&M % of revenue (non-GAAP) | B41: Derived | C41: =C42/Revenue_Build!C25 -> 0.45031814 | D41: =D42/Revenue_Build!D25 -> 0.4098612 | E41: =E42/Revenue_Build!E25 -> 0.40903515 | F41: =Opex!F11 -> 0.39995553 | G41: =Opex!G11 -> 0.39495553 | H41: =Opex!H11 -> 0.39495553 | I41: =Opex!I11 -> 0.39495553 | J41: =Opex!J11 -> 0.39495553 | K41: =K42/Revenue_Build!K25 -> 0.41663309 | L41: =L42/Revenue_Build!L25 -> 0.39495553
A42: S&M (non-GAAP) | B42: Sourced / Derived | C42: =Historical_Drivers!$O$12/1000 -> 158.181 | D42: =Historical_Drivers!$P$12/1000 -> 149.444 | E42: =E38*Historical_Drivers!$P$12/(Historical_Drivers!$P$10+Historical_Drivers!$P$12+Historical_Drivers!$P$14) -> 153.17183 | F42: =F41*Revenue_Build!F25 -> 156.31222 | G42: =G41*Revenue_Build!G25 -> 160.38978 | H42: =H41*Revenue_Build!H25 -> 164.40314 | I42: =I41*Revenue_Build!I25 -> 166.70718 | J42: =J41*Revenue_Build!J25 -> 171.81998 | K42: =SUM(C42:F42) -> 617.10905 | L42: =SUM(G42:J42) -> 663.32009
A43: G&A % of revenue (non-GAAP) | B43: Derived | C43: =C44/Revenue_Build!C25 -> 0.08130329 | D43: =D44/Revenue_Build!D25 -> 0.084101025 | E43: =E44/Revenue_Build!E25 -> 0.083931525 | F43: =Opex!F13 -> 0.082068443 | G43: =Opex!G13 -> 0.080068443 | H43: =Opex!H13 -> 0.080068443 | I43: =Opex!I13 -> 0.080068443 | J43: =Opex!J13 -> 0.080068443 | K43: =K44/Revenue_Build!K25 -> 0.082858367 | L43: =L44/Revenue_Build!L25 -> 0.080068443
A44: G&A (non-GAAP) | B44: Sourced / Derived | C44: =Historical_Drivers!$O$14/1000 -> 28.559 | D44: =Historical_Drivers!$P$14/1000 -> 30.665 | E44: =E38*Historical_Drivers!$P$14/(Historical_Drivers!$P$10+Historical_Drivers!$P$12+Historical_Drivers!$P$14) -> 31.429928 | F44: =F43*Revenue_Build!F25 -> 32.074316 | G44: =G43*Revenue_Build!G25 -> 32.515458 | H44: =H43*Revenue_Build!H25 -> 33.329078 | I44: =I43*Revenue_Build!I25 -> 33.79617 | J44: =J43*Revenue_Build!J25 -> 34.832677 | K44: =SUM(C44:F44) -> 122.72824 | L44: =SUM(G44:J44) -> 134.47338
A45: Total operating expenses (non-GAAP) | B45: Derived | C45: =C40+C42+C44 -> 265.153 | D45: =D40+D42+D44 -> 263.112 | E45: =E40+E42+E44 -> 269.67524 | F45: =F40+F42+F44 -> 275.20422 | G45: =G40+G42+G44 -> 281.08493 | H45: =H40+H42+H44 -> 288.1184 | I45: =I40+I42+I44 -> 292.15625 | J45: =J40+J42+J44 -> 301.11649 | ... L45: =L40+L42+L44 -> 1162.4761
A46: Operating income (non-GAAP) | B46: Derived | C46: =C37-C45 -> 49.037 | D46: =D37-D45 -> 61.11 | E46: =E37-E45 -> 62.931 | F46: =F37-F45 -> 71.535898 | G46: =G37-G45 -> 78.798282 | H46: =H37-H45 -> 80.353761 | I46: =I37-I45 -> 81.057791 | J46: =J37-J45 -> 83.108747 | ... L46: =L37-L45 -> 323.31858
A47: Operating margin (non-GAAP) | B47: Derived | C47: =C46/Revenue_Build!C25 -> 0.13960116 | D47: =D46/Revenue_Build!D25 -> 0.16759868 | E47: =E46/Revenue_Build!E25 -> 0.16805304 | F47: =F46/Revenue_Build!F25 -> 0.18303866 | G47: =G46/Revenue_Build!G25 -> 0.19403866 | H47: =H46/Revenue_Build!H25 -> 0.19303866 | I47: =I46/Revenue_Build!I25 -> 0.19203866 | J47: =J46/Revenue_Build!J25 -> 0.19103866 | ... L47: =L46/Revenue_Build!L25 -> 0.19251107

Sheet PnL
A1: P&L: non-GAAP with GAAP bridge (SBC, restructuring)
A2: USD millions.
A4: BASE
A5: Line | B5: Label | C5: Q1 2026A | D5: Q2 2026A | E5: Q3 2026 | F5: Q4 2026 | G5: Q1 2027 | H5: Q2 2027 | I5: Q3 2027 | J5: Q4 2027 | K5: FY2026 | L5: FY2027 | M5: Note
A6: Revenue | B6: Derived (link) | C6: =Revenue_Build!C7 -> 351.265 | D6: =Revenue_Build!D7 -> 364.621 | E6: =Revenue_Build!E7 -> 378.38246 | F6: =Revenue_Build!F7 -> 394.90618 | G6: =Revenue_Build!G7 -> 410.3375 | H6: =Revenue_Build!H7 -> 420.6052 | I6: =Revenue_Build!I7 -> 431.01174 | J6: =Revenue_Build!J7 -> 444.2306 | ... L6: =Revenue_Build!L7 -> 1706.185
A7: Gross profit (non-GAAP) | B7: Derived (link) | C7: =Opex!C7 -> 314.19 | D7: =Opex!D7 -> 324.222 | E7: =Opex!E7 -> 336.08034 | F7: =Opex!F7 -> 350.36186 | G7: =Opex!G7 -> 363.64223 | H7: =Opex!H7 -> 372.32089 | I7: =Opex!I7 -> 381.10177 | J7: =Opex!J7 -> 392.34569 | ... L7: =Opex!L7 -> 1509.4106
A8: R&D (non-GAAP) | B8: Derived (link) | C8: =Opex!C10 -> 78.413 | D8: =Opex!D10 -> 83.003 | E8: =Opex!E10 -> 84.053927 | F8: =Opex!F10 -> 87.72451 | G8: =Opex!G10 -> 89.100737 | H8: =Opex!H10 -> 91.330267 | I8: =Opex!I10 -> 93.589944 | J8: =Opex!J10 -> 96.460289 | ... L8: =Opex!L10 -> 370.48124
A9: S&M (non-GAAP) | B9: Derived (link) | C9: =Opex!C12 -> 158.181 | D9: =Opex!D12 -> 149.444 | E9: =Opex!E12 -> 151.33616 | F9: =Opex!F12 -> 157.94491 | G9: =Opex!G12 -> 162.06507 | H9: =Opex!H12 -> 166.12035 | I9: =Opex!I12 -> 170.23047 | J9: =Opex!J12 -> 175.45133 | ... L9: =Opex!L12 -> 673.86722
A10: G&A (non-GAAP) | B10: Derived (link) | C10: =Opex!C14 -> 28.559 | D10: =Opex!D14 -> 30.665 | E10: =Opex!E14 -> 31.053259 | F10: =Opex!F14 -> 32.409336 | G10: =Opex!G14 -> 32.855085 | H10: =Opex!H14 -> 33.677204 | I10: =Opex!I14 -> 34.510439 | J10: =Opex!J14 -> 35.568853 | ... L10: =Opex!L14 -> 136.61158
A11: Operating income (non-GAAP) | B11: Derived (link) | C11: =Opex!C16 -> 49.037 | D11: =Opex!D16 -> 61.11 | E11: =Opex!E16 -> 69.637 | F11: =Opex!F16 -> 72.283098 | G11: =Opex!G16 -> 79.621338 | H11: =Opex!H16 -> 81.193064 | I11: =Opex!I16 -> 82.770916 | J11: =Opex!J16 -> 84.865218 | ... L11: =Opex!L16 -> 328.45054
A12: Operating margin (non-GAAP) | B12: Derived | C12: =C11/C6 -> 0.13960116 | D12: =D11/D6 -> 0.16759868 | E12: =E11/E6 -> 0.18403866 | F12: =F11/F6 -> 0.18303866 | G12: =G11/G6 -> 0.19403866 | H12: =H11/H6 -> 0.19303866 | I12: =I11/I6 -> 0.19203866 | J12: =J11/J6 -> 0.19103866 | ... L12: =L11/L6 -> 0.19250581
A13: Less: share-based compensation | B13: Sourced / Derived (Assumed P9) | C13: =Historical_Drivers!$O$20/1000 -> 29.283 | D13: =Historical_Drivers!$P$20/1000 -> 41.218 | E13: =Assumptions!$C$13*E6 -> 39.730158 | F13: =Assumptions!$C$13*F6 -> 41.465149 | G13: =Assumptions!$C$13*G6 -> 43.085438 | H13: =Assumptions!$C$13*H6 -> 44.163546 | I13: =Assumptions!$C$13*I6 -> 45.256233 | J13: =Assumptions!$C$13*J6 -> 46.644213 | K13: =SUM(C13:F13) -> 151.69631 | L13: =SUM(G13:J13) -> 179.14943
A14: Less: restructuring charges (GAAP) | B14: Sourced / Derived (Assumed P10) | C14: =(Historical_Drivers!$C$60-Historical_Drivers!$P$22)/1000 -> 0 | D14: =Historical_Drivers!$P$22/1000 -> 21.436 | E14: =Assumptions!$C$14/2 -> 25 | F14: =Assumptions!$C$14/2 -> 25 | G14: =0*1 -> 0 | H14: =0*1 -> 0 | I14: =0*1 -> 0 | J14: =0*1 -> 0 | K14: =SUM(C14:F14) -> 71.436 | L14: =SUM(G14:J14) -> 0 | M14: Q1 2026 = H1 less Q2 (Derived; line first reported Q2 2026); Q2 2026: Israel office impairment; H2 2026: plan estimate midpoint
A15: Operating income (GAAP) | B15: Derived | C15: =C11-C13-C14 -> 19.754 | D15: =D11-D13-D14 -> -1.544 | E15: =E11-E13-E14 -> 4.9068419 | F15: =F11-F13-F14 -> 5.8179488 | G15: =G11-G13-G14 -> 36.535901 | H15: =H11-H13-H14 -> 37.029518 | I15: =I11-I13-I14 -> 37.514684 | J15: =J11-J13-J14 -> 38.221005 | ... L15: =L11-L13-L14 -> 149.30111
A16: Operating margin (GAAP) | B16: Derived | C16: =C15/C6 -> 0.056236744 | D16: =D15/D6 -> -0.0042345339 | E16: =E15/E6 -> 0.012967942 | F16: =F15/F6 -> 0.014732483 | G16: =G15/G6 -> 0.089038658 | H16: =H15/H6 -> 0.088038658 | I16: =I15/I6 -> 0.087038658 | J16: =J15/J6 -> 0.086038658 | ... L16: =L15/L6 -> 0.087505812
A17: Check: bridge vs reported GAAP op. income (Q1-Q2 2026 actual) | B17: Derived | C17: =C15-Historical_Drivers!$O$18/1000 -> 0 | D17: =D15-Historical_Drivers!$P$18/1000 -> -4.6629367e-14 | M17: Should be 0
A19: DOWNSIDE (before management response)
A20: Line | B20: Label | C20: Q1 2026A | D20: Q2 2026A | E20: Q3 2026 | F20: Q4 2026 | G20: Q1 2027 | H20: Q2 2027 | I20: Q3 2027 | J20: Q4 2027 | K20: FY2026 | L20: FY2027 | M20: Note
A21: Revenue | B21: Derived (link) | C21: =Revenue_Build!C16 -> 351.265 | D21: =Revenue_Build!D16 -> 364.621 | E21: =Revenue_Build!E16 -> 378.38246 | F21: =Revenue_Build!F16 -> 389.98721 | G21: =Revenue_Build!G16 -> 400.15648 | H21: =Revenue_Build!H16 -> 404.96739 | I21: =Revenue_Build!I16 -> 409.72245 | J21: =Revenue_Build!J16 -> 411.6356 | ... L21: =Revenue_Build!L16 -> 1626.4819
A22: Gross profit (non-GAAP) | B22: Derived (link) | C22: =Opex!C22 -> 314.19 | D22: =Opex!D22 -> 324.222 | E22: =Opex!E22 -> 336.08034 | F22: =Opex!F22 -> 345.41275 | G22: =Opex!G22 -> 353.41931 | H22: =Opex!H22 -> 356.6559 | I22: =Opex!I22 -> 359.81938 | J22: =Opex!J22 -> 360.47043 | ... L22: =Opex!L22 -> 1430.365
A23: R&D (non-GAAP) | B23: Derived (link) | C23: =Opex!C25 -> 78.413 | D23: =Opex!D25 -> 83.003 | E23: =Opex!E25 -> 84.053927 | F23: =Opex!F25 -> 87.72451 | G23: =Opex!G25 -> 89.100737 | H23: =Opex!H25 -> 91.330267 | I23: =Opex!I25 -> 93.589944 | J23: =Opex!J25 -> 96.460289 | ... L23: =Opex!L25 -> 370.48124
A24: S&M (non-GAAP) | B24: Derived (link) | C24: =Opex!C27 -> 158.181 | D24: =Opex!D27 -> 149.444 | E24: =Opex!E27 -> 151.33616 | F24: =Opex!F27 -> 157.94491 | G24: =Opex!G27 -> 162.06507 | H24: =Opex!H27 -> 166.12035 | I24: =Opex!I27 -> 170.23047 | J24: =Opex!J27 -> 175.45133 | ... L24: =Opex!L27 -> 673.86722
A25: G&A (non-GAAP) | B25: Derived (link) | C25: =Opex!C29 -> 28.559 | D25: =Opex!D29 -> 30.665 | E25: =Opex!E29 -> 31.053259 | F25: =Opex!F29 -> 32.409336 | G25: =Opex!G29 -> 32.855085 | H25: =Opex!H29 -> 33.677204 | I25: =Opex!I29 -> 34.510439 | J25: =Opex!J29 -> 35.568853 | ... L25: =Opex!L29 -> 136.61158
A26: Operating income (non-GAAP) | B26: Derived (link) | C26: =Opex!C31 -> 49.037 | D26: =Opex!D31 -> 61.11 | E26: =Opex!E31 -> 69.637 | F26: =Opex!F31 -> 67.333992 | G26: =Opex!G31 -> 69.398422 | H26: =Opex!H31 -> 65.52808 | I26: =Opex!I31 -> 61.48853 | J26: =Opex!J31 -> 52.989952 | ... L26: =Opex!L31 -> 249.40498
A27: Operating margin (non-GAAP) | B27: Derived | C27: =C26/C21 -> 0.13960116 | D27: =D26/D21 -> 0.16759868 | E27: =E26/E21 -> 0.18403866 | F27: =F26/F21 -> 0.17265692 | G27: =G26/G21 -> 0.17342821 | H27: =H26/H21 -> 0.16181075 | I27: =I26/I21 -> 0.15007362 | J27: =J26/J21 -> 0.12873025 | ... L27: =L26/L21 -> 0.15334015
A28: Less: share-based compensation | B28: Sourced / Derived (Assumed P9) | C28: =Historical_Drivers!$O$20/1000 -> 29.283 | D28: =Historical_Drivers!$P$20/1000 -> 41.218 | E28: =Assumptions!$D$13*E21 -> 39.730158 | F28: =Assumptions!$D$13*F21 -> 40.948657 | G28: =Assumptions!$D$13*G21 -> 42.016431 | H28: =Assumptions!$D$13*H21 -> 42.521576 | I28: =Assumptions!$D$13*I21 -> 43.020857 | J28: =Assumptions!$D$13*J21 -> 43.221737 | K28: =SUM(C28:F28) -> 151.17982 | L28: =SUM(G28:J28) -> 170.7806
A29: Less: restructuring charges (GAAP) | B29: Sourced / Derived (Assumed P10) | C29: =(Historical_Drivers!$C$60-Historical_Drivers!$P$22)/1000 -> 0 | D29: =Historical_Drivers!$P$22/1000 -> 21.436 | E29: =Assumptions!$D$14/2 -> 25 | F29: =Assumptions!$D$14/2 -> 25 | G29: =0*1 -> 0 | H29: =0*1 -> 0 | I29: =0*1 -> 0 | J29: =0*1 -> 0 | K29: =SUM(C29:F29) -> 71.436 | L29: =SUM(G29:J29) -> 0 | M29: Q1 2026 = H1 less Q2 (Derived; line first reported Q2 2026); Q2 2026: Israel office impairment; H2 2026: plan estimate midpoint
A30: Operating income (GAAP) | B30: Derived | C30: =C26-C28-C29 -> 19.754 | D30: =D26-D28-D29 -> -1.544 | E30: =E26-E28-E29 -> 4.9068419 | F30: =F26-F28-F29 -> 1.3853346 | G30: =G26-G28-G29 -> 27.381991 | H30: =H26-H28-H29 -> 23.006503 | I30: =I26-I28-I29 -> 18.467673 | J30: =J26-J28-J29 -> 9.7682147 | ... L30: =L26-L28-L29 -> 78.624382
A31: Operating margin (GAAP) | B31: Derived | C31: =C30/C21 -> 0.056236744 | D31: =D30/D21 -> -0.0042345339 | E31: =E30/E21 -> 0.012967942 | F31: =F30/F21 -> 0.0035522564 | G31: =G30/G21 -> 0.068428208 | H31: =H30/H21 -> 0.056810754 | I31: =I30/I21 -> 0.045073619 | J31: =J30/J21 -> 0.023730248 | ... L31: =L30/L21 -> 0.048340151
A32: Check: bridge vs reported GAAP op. income (Q1-Q2 2026 actual) | B32: Derived | C32: =C30-Historical_Drivers!$O$18/1000 -> 0 | D32: =D30-Historical_Drivers!$P$18/1000 -> -4.6629367e-14 | M32: Should be 0
A34: SENSITIVITY: Base with Q3 2026 at the locked call LOW
A35: Line | B35: Label | C35: Q1 2026A | D35: Q2 2026A | E35: Q3 2026 | F35: Q4 2026 | G35: Q1 2027 | H35: Q2 2027 | I35: Q3 2027 | J35: Q4 2027 | K35: FY2026 | L35: FY2027 | M35: Note
A36: Revenue | B36: Derived (link) | C36: =Revenue_Build!C25 -> 351.265 | D36: =Revenue_Build!D25 -> 364.621 | E36: =Revenue_Build!E25 -> 374.47107 | F36: =Revenue_Build!F25 -> 390.82399 | G36: =Revenue_Build!G25 -> 406.09579 | H36: =Revenue_Build!H25 -> 416.25735 | I36: =Revenue_Build!I25 -> 422.09101 | J36: =Revenue_Build!J25 -> 435.03628 | ... L36: =Revenue_Build!L25 -> 1679.4804
A37: Gross profit (non-GAAP) | B37: Derived (link) | C37: =Opex!C37 -> 314.19 | D37: =Opex!D37 -> 324.222 | E37: =Opex!E37 -> 332.60624 | F37: =Opex!F37 -> 346.74012 | G37: =Opex!G37 -> 359.88321 | H37: =Opex!H37 -> 368.47216 | I37: =Opex!I37 -> 373.21404 | J37: =Opex!J37 -> 384.22524 | ... L37: =Opex!L37 -> 1485.7946
A38: R&D (non-GAAP) | B38: Derived (link) | C38: =Opex!C40 -> 78.413 | D38: =Opex!D40 -> 83.003 | E38: =Opex!E40 -> 85.073481 | F38: =Opex!F40 -> 86.81769 | G38: =Opex!G40 -> 88.179691 | H38: =Opex!H40 -> 90.386174 | I38: =Opex!I40 -> 91.652895 | J38: =Opex!J40 -> 94.463833 | ... L38: =Opex!L40 -> 364.68259
A39: S&M (non-GAAP) | B39: Derived (link) | C39: =Opex!C42 -> 158.181 | D39: =Opex!D42 -> 149.444 | E39: =Opex!E42 -> 153.17183 | F39: =Opex!F42 -> 156.31222 | G39: =Opex!G42 -> 160.38978 | H39: =Opex!H42 -> 164.40314 | I39: =Opex!I42 -> 166.70718 | J39: =Opex!J42 -> 171.81998 | ... L39: =Opex!L42 -> 663.32009
A40: G&A (non-GAAP) | B40: Derived (link) | C40: =Opex!C44 -> 28.559 | D40: =Opex!D44 -> 30.665 | E40: =Opex!E44 -> 31.429928 | F40: =Opex!F44 -> 32.074316 | G40: =Opex!G44 -> 32.515458 | H40: =Opex!H44 -> 33.329078 | I40: =Opex!I44 -> 33.79617 | J40: =Opex!J44 -> 34.832677 | ... L40: =Opex!L44 -> 134.47338
A41: Operating income (non-GAAP) | B41: Derived (link) | C41: =Opex!C46 -> 49.037 | D41: =Opex!D46 -> 61.11 | E41: =Opex!E46 -> 62.931 | F41: =Opex!F46 -> 71.535898 | G41: =Opex!G46 -> 78.798282 | H41: =Opex!H46 -> 80.353761 | I41: =Opex!I46 -> 81.057791 | J41: =Opex!J46 -> 83.108747 | ... L41: =Opex!L46 -> 323.31858
A42: Operating margin (non-GAAP) | B42: Derived | C42: =C41/C36 -> 0.13960116 | D42: =D41/D36 -> 0.16759868 | E42: =E41/E36 -> 0.16805304 | F42: =F41/F36 -> 0.18303866 | G42: =G41/G36 -> 0.19403866 | H42: =H41/H36 -> 0.19303866 | I42: =I41/I36 -> 0.19203866 | J42: =J41/J36 -> 0.19103866 | ... L42: =L41/L36 -> 0.19251107
A43: Less: share-based compensation | B43: Sourced / Derived (Assumed P9) | C43: =Historical_Drivers!$O$20/1000 -> 29.283 | D43: =Historical_Drivers!$P$20/1000 -> 41.218 | E43: =Assumptions!$C$13*E36 -> 39.319462 | F43: =Assumptions!$C$13*F36 -> 41.036519 | G43: =Assumptions!$C$13*G36 -> 42.640058 | H43: =Assumptions!$C$13*H36 -> 43.707022 | I43: =Assumptions!$C$13*I36 -> 44.319556 | J43: =Assumptions!$C$13*J36 -> 45.678809 | K43: =SUM(C43:F43) -> 150.85698 | L43: =SUM(G43:J43) -> 176.34545
A44: Less: restructuring charges (GAAP) | B44: Sourced / Derived (Assumed P10) | C44: =(Historical_Drivers!$C$60-Historical_Drivers!$P$22)/1000 -> 0 | D44: =Historical_Drivers!$P$22/1000 -> 21.436 | E44: =Assumptions!$C$14/2 -> 25 | F44: =Assumptions!$C$14/2 -> 25 | G44: =0*1 -> 0 | H44: =0*1 -> 0 | I44: =0*1 -> 0 | J44: =0*1 -> 0 | K44: =SUM(C44:F44) -> 71.436 | L44: =SUM(G44:J44) -> 0 | M44: Q1 2026 = H1 less Q2 (Derived; line first reported Q2 2026); Q2 2026: Israel office impairment; H2 2026: plan estimate midpoint
A45: Operating income (GAAP) | B45: Derived | C45: =C41-C43-C44 -> 19.754 | D45: =D41-D43-D44 -> -1.544 | E45: =E41-E43-E44 -> -1.3884623 | F45: =F41-F43-F44 -> 5.4993797 | G45: =G41-G43-G44 -> 36.158224 | H45: =H41-H43-H44 -> 36.646739 | I45: =I41-I43-I44 -> 36.738235 | J45: =J41-J43-J44 -> 37.429938 | ... L45: =L41-L43-L44 -> 146.97314
A46: Operating margin (GAAP) | B46: Derived | C46: =C45/C36 -> 0.056236744 | D46: =D45/D36 -> -0.0042345339 | E46: =E45/E36 -> -0.003707796 | F46: =F45/F36 -> 0.014071244 | G46: =G45/G36 -> 0.089038658 | H46: =H45/H36 -> 0.088038658 | I46: =I45/I36 -> 0.087038658 | J46: =J45/J36 -> 0.086038658 | ... L46: =L45/L36 -> 0.087511074
A47: Check: bridge vs reported GAAP op. income (Q1-Q2 2026 actual) | B47: Derived | C47: =C45-Historical_Drivers!$O$18/1000 -> 0 | D47: =D45-Historical_Drivers!$P$18/1000 -> -4.6629367e-14 | M47: Should be 0

Sheet Cash_FCF
A1: Adjusted free cash flow and cash
A2: USD millions. Q3/Q4 2026 adjusted FCF = LOW CONFIDENCE, tied to the FY2026 guide; severance cash shown separately (UNRESOLVED whether the guide includes it).
A4: BASE
A5: Line | B5: Label | C5: Q1 2026A | D5: Q2 2026A | E5: Q3 2026 | F5: Q4 2026 | G5: Q1 2027 | H5: Q2 2027 | I5: Q3 2027 | J5: Q4 2027 | K5: FY2026 | L5: FY2027 | M5: Note
A6: Operating income (non-GAAP) | B6: Derived (link) | C6: =Opex!C16 -> 49.037 | D6: =Opex!D16 -> 61.11 | E6: =Opex!E16 -> 69.637 | F6: =Opex!F16 -> 72.283098 | G6: =Opex!G16 -> 79.621338 | H6: =Opex!H16 -> 81.193064 | I6: =Opex!I16 -> 82.770916 | J6: =Opex!J16 -> 84.865218 | ... L6: =Opex!L16 -> 328.45054
A7: Adjusted FCF, guide basis (excludes restructuring/severance cash) | B7: Sourced / Derived (Assumed P7) | C7: =Historical_Drivers!$O$24/1000 -> 102.778 | D7: =Historical_Drivers!$P$24/1000 -> 52.344 | E7: =Historical_Drivers!$C$69*Historical_Drivers!$C$68*E6/Opex!E16 -> 73.159541 | F7: =Historical_Drivers!$C$69*(1-Historical_Drivers!$C$68)*F6/Opex!F16 -> 56.718459 | G7: =L6*Assumptions!$C$11*Historical_Drivers!$C$61/(Historical_Drivers!$C$61+Historical_Drivers!$C$62+Historical_Drivers!$C$63+Historical_Drivers!$C$64) -> 112.05175 | H7: =L6*Assumptions!$C$11*Historical_Drivers!$C$62/(Historical_Drivers!$C$61+Historical_Drivers!$C$62+Historical_Drivers!$C$63+Historical_Drivers!$C$64) -> 80.064819 | I7: =L6*Assumptions!$C$11*Historical_Drivers!$C$63/(Historical_Drivers!$C$61+Historical_Drivers!$C$62+Historical_Drivers!$C$63+Historical_Drivers!$C$64) -> 118.67506 | J7: =L6*Assumptions!$C$11*Historical_Drivers!$C$64/(Historical_Drivers!$C$61+Historical_Drivers!$C$62+Historical_Drivers!$C$63+Historical_Drivers!$C$64) -> 93.202532 | K7: =SUM(C7:F7) -> 285 | L7: =SUM(G7:J7) -> 403.99416 | M7: Q3-Q4 2026 LOW CONFIDENCE (FY guide less H1, split by 2023-2025 Q3 share; scaled by op. income vs Base). Guide excludes restructuring (6-K Jul 22, 2026).
A8: Confidence flag | B8: Text | E8: LOW CONF. | F8: LOW CONF.
A9: Adjusted FCF / non-GAAP operating income | B9: Derived | C9: =C7/C6 -> 2.0959276 | D9: =D7/D6 -> 0.85655376 | E9: =E7/E6 -> 1.0505843 | F9: =F7/F6 -> 0.78467111 | G9: =G7/G6 -> 1.407308 | H9: =H7/H6 -> 0.98610417 | I9: =I7/I6 -> 1.4337773 | J9: =J7/J6 -> 1.0982418 | ... L9: =L7/L6 -> 1.23
A10: Severance cash (outflow; excluded from the FY FCF guide, included in reported adjusted FCF) | B10: Derived (Assumed P8) | E10: =-Assumptions!$C$12/2 -> -16.25 | F10: =-Assumptions!$C$12/2 -> -16.25 | G10: =0*1 -> 0 | H10: =0*1 -> 0 | I10: =0*1 -> 0 | J10: =0*1 -> 0 | K10: =SUM(C10:F10) -> -32.5 | L10: =SUM(G10:J10) -> 0 | M10: Counted once: not double-counted (Cash_Bridge)
A11: Memo: adjusted FCF, reported basis (company definition has no severance add-back) | B11: Derived | C11: =C7 -> 102.778 | D11: =D7 -> 52.344 | E11: =E7+E10 -> 56.909541 | F11: =F7+F10 -> 40.468459 | G11: =G7+G10 -> 112.05175 | H11: =H7+H10 -> 80.064819 | I11: =I7+I10 -> 118.67506 | J11: =J7+J10 -> 93.202532 | K11: =SUM(C11:F11) -> 252.5 | L11: =SUM(G11:J11) -> 403.99416 | M11: What the company will report = guide basis less severance paid
A12: Share repurchases (outflow) | B12: Derived (Assumed P11) | E12: =-Assumptions!$C$15 -> 0 | F12: =-Assumptions!$C$15 -> 0 | G12: =-Assumptions!$C$15 -> 0 | H12: =-Assumptions!$C$15 -> 0 | I12: =-Assumptions!$C$15 -> 0 | J12: =-Assumptions!$C$15 -> 0 | K12: =SUM(C12:F12) -> 0 | L12: =SUM(G12:J12) -> 0 | M12: FLAG: authorization exhausted; none assumed
A13: Other cash flows (H1 2026 run-rate from Cash_Bridge) | B13: Derived (Assumed P12) | E13: =Assumptions!$C$16 -> -6.4265 | F13: =Assumptions!$C$16 -> -6.4265 | G13: =Assumptions!$C$16 -> -6.4265 | H13: =Assumptions!$C$16 -> -6.4265 | I13: =Assumptions!$C$16 -> -6.4265 | J13: =Assumptions!$C$16 -> -6.4265 | K13: =SUM(C13:F13) -> -12.853 | L13: =SUM(G13:J13) -> -25.706
A14: Net change in cash + marketable securities (forecast quarters) | B14: Derived | E14: =E7+E10+E12+E13 -> 50.483041 | F14: =F7+F10+F12+F13 -> 34.041959 | G14: =G7+G10+G12+G13 -> 105.62525 | H14: =H7+H10+H12+H13 -> 73.638319 | I14: =I7+I10+I12+I13 -> 112.24856 | J14: =J7+J10+J12+J13 -> 86.776032
A15: Ending cash + marketable securities BEFORE UNMODELED ITEMS (new buybacks, M&A beyond run-rate, FX) | B15: Sourced (Q1-Q2) / Derived | C15: =Historical_Drivers!$O$38/1000 -> 1212.276 | D15: =Historical_Drivers!$P$38/1000 -> 1072.755 | E15: =D15+E14 -> 1123.238 | F15: =E15+F14 -> 1157.28 | G15: =F15+G14 -> 1262.9053 | H15: =G15+H14 -> 1336.5436 | I15: =H15+I14 -> 1448.7921 | J15: =I15+J14 -> 1535.5682 | K15: =F15 -> 1157.28 | L15: =J15 -> 1535.5682 | M15: FY columns = year-end balance; not a headline figure
A16: FY2026 adjusted FCF minus FY guide midpoint | B16: Derived | K16: =K7-(Historical_Drivers!$C$42+Historical_Drivers!$C$43)/2 -> 0
A18: DOWNSIDE (before management response)
A19: Line | B19: Label | C19: Q1 2026A | D19: Q2 2026A | E19: Q3 2026 | F19: Q4 2026 | G19: Q1 2027 | H19: Q2 2027 | I19: Q3 2027 | J19: Q4 2027 | K19: FY2026 | L19: FY2027 | M19: Note
A20: Operating income (non-GAAP) | B20: Derived (link) | C20: =Opex!C31 -> 49.037 | D20: =Opex!D31 -> 61.11 | E20: =Opex!E31 -> 69.637 | F20: =Opex!F31 -> 67.333992 | G20: =Opex!G31 -> 69.398422 | H20: =Opex!H31 -> 65.52808 | I20: =Opex!I31 -> 61.48853 | J20: =Opex!J31 -> 52.989952 | ... L20: =Opex!L31 -> 249.40498
A21: Adjusted FCF, guide basis (excludes restructuring/severance cash) | B21: Sourced / Derived (Assumed P7) | C21: =Historical_Drivers!$O$24/1000 -> 102.778 | D21: =Historical_Drivers!$P$24/1000 -> 52.344 | E21: =Historical_Drivers!$C$69*Historical_Drivers!$C$68*E20/Opex!E16 -> 73.159541 | F21: =Historical_Drivers!$C$69*(1-Historical_Drivers!$C$68)*F20/Opex!F16 -> 52.835038 | G21: =L20*Assumptions!$D$11*Historical_Drivers!$C$61/(Historical_Drivers!$C$61+Historical_Drivers!$C$62+Historical_Drivers!$C$63+Historical_Drivers!$C$64) -> 69.174923 | H21: =L20*Assumptions!$D$11*Historical_Drivers!$C$62/(Historical_Drivers!$C$61+Historical_Drivers!$C$62+Historical_Drivers!$C$63+Historical_Drivers!$C$64) -> 49.427856 | I21: =L20*Assumptions!$D$11*Historical_Drivers!$C$63/(Historical_Drivers!$C$61+Historical_Drivers!$C$62+Historical_Drivers!$C$63+Historical_Drivers!$C$64) -> 73.263809 | J21: =L20*Assumptions!$D$11*Historical_Drivers!$C$64/(Historical_Drivers!$C$61+Historical_Drivers!$C$62+Historical_Drivers!$C$63+Historical_Drivers!$C$64) -> 57.538396 | K21: =SUM(C21:F21) -> 281.11658 | L21: =SUM(G21:J21) -> 249.40498 | M21: Q3-Q4 2026 LOW CONFIDENCE (FY guide less H1, split by 2023-2025 Q3 share; scaled by op. income vs Base). Guide excludes restructuring (6-K Jul 22, 2026).
A22: Confidence flag | B22: Text | E22: LOW CONF. | F22: LOW CONF.
A23: Adjusted FCF / non-GAAP operating income | B23: Derived | C23: =C21/C20 -> 2.0959276 | D23: =D21/D20 -> 0.85655376 | E23: =E21/E20 -> 1.0505843 | F23: =F21/F20 -> 0.78467111 | G23: =G21/G20 -> 0.99677948 | H23: =H21/H20 -> 0.75430038 | I23: =I21/I20 -> 1.1915037 | J23: =J21/J20 -> 1.085836 | ... L23: =L21/L20 -> 1
A24: Severance cash (outflow; excluded from the FY FCF guide, included in reported adjusted FCF) | B24: Derived (Assumed P8) | E24: =-Assumptions!$D$12/2 -> -17.5 | F24: =-Assumptions!$D$12/2 -> -17.5 | G24: =0*1 -> 0 | H24: =0*1 -> 0 | I24: =0*1 -> 0 | J24: =0*1 -> 0 | K24: =SUM(C24:F24) -> -35 | L24: =SUM(G24:J24) -> 0 | M24: Counted once: not double-counted (Cash_Bridge)
A25: Memo: adjusted FCF, reported basis (company definition has no severance add-back) | B25: Derived | C25: =C21 -> 102.778 | D25: =D21 -> 52.344 | E25: =E21+E24 -> 55.659541 | F25: =F21+F24 -> 35.335038 | G25: =G21+G24 -> 69.174923 | H25: =H21+H24 -> 49.427856 | I25: =I21+I24 -> 73.263809 | J25: =J21+J24 -> 57.538396 | K25: =SUM(C25:F25) -> 246.11658 | L25: =SUM(G25:J25) -> 249.40498 | M25: What the company will report = guide basis less severance paid
A26: Share repurchases (outflow) | B26: Derived (Assumed P11) | E26: =-Assumptions!$D$15 -> 0 | F26: =-Assumptions!$D$15 -> 0 | G26: =-Assumptions!$D$15 -> 0 | H26: =-Assumptions!$D$15 -> 0 | I26: =-Assumptions!$D$15 -> 0 | J26: =-Assumptions!$D$15 -> 0 | K26: =SUM(C26:F26) -> 0 | L26: =SUM(G26:J26) -> 0 | M26: FLAG: authorization exhausted; none assumed
A27: Other cash flows (H1 2026 run-rate from Cash_Bridge) | B27: Derived (Assumed P12) | E27: =Assumptions!$D$16 -> -6.4265 | F27: =Assumptions!$D$16 -> -6.4265 | G27: =Assumptions!$D$16 -> -6.4265 | H27: =Assumptions!$D$16 -> -6.4265 | I27: =Assumptions!$D$16 -> -6.4265 | J27: =Assumptions!$D$16 -> -6.4265 | K27: =SUM(C27:F27) -> -12.853 | L27: =SUM(G27:J27) -> -25.706
A28: Net change in cash + marketable securities (forecast quarters) | B28: Derived | E28: =E21+E24+E26+E27 -> 49.233041 | F28: =F21+F24+F26+F27 -> 28.908538 | G28: =G21+G24+G26+G27 -> 62.748423 | H28: =H21+H24+H26+H27 -> 43.001356 | I28: =I21+I24+I26+I27 -> 66.837309 | J28: =J21+J24+J26+J27 -> 51.111896
A29: Ending cash + marketable securities BEFORE UNMODELED ITEMS (new buybacks, M&A beyond run-rate, FX) | B29: Sourced (Q1-Q2) / Derived | C29: =Historical_Drivers!$O$38/1000 -> 1212.276 | D29: =Historical_Drivers!$P$38/1000 -> 1072.755 | E29: =D29+E28 -> 1121.988 | F29: =E29+F28 -> 1150.8966 | G29: =F29+G28 -> 1213.645 | H29: =G29+H28 -> 1256.6464 | I29: =H29+I28 -> 1323.4837 | J29: =I29+J28 -> 1374.5956 | K29: =F29 -> 1150.8966 | L29: =J29 -> 1374.5956 | M29: FY columns = year-end balance; not a headline figure
A30: FY2026 adjusted FCF minus FY guide midpoint | B30: Derived | K30: =K21-(Historical_Drivers!$C$42+Historical_Drivers!$C$43)/2 -> -3.8834208
A32: SENSITIVITY: Base with Q3 2026 at the locked call LOW
A33: Line | B33: Label | C33: Q1 2026A | D33: Q2 2026A | E33: Q3 2026 | F33: Q4 2026 | G33: Q1 2027 | H33: Q2 2027 | I33: Q3 2027 | J33: Q4 2027 | K33: FY2026 | L33: FY2027 | M33: Note
A34: Operating income (non-GAAP) | B34: Derived (link) | C34: =Opex!C46 -> 49.037 | D34: =Opex!D46 -> 61.11 | E34: =Opex!E46 -> 62.931 | F34: =Opex!F46 -> 71.535898 | G34: =Opex!G46 -> 78.798282 | H34: =Opex!H46 -> 80.353761 | I34: =Opex!I46 -> 81.057791 | J34: =Opex!J46 -> 83.108747 | ... L34: =Opex!L46 -> 323.31858
A35: Adjusted FCF, guide basis (excludes restructuring/severance cash) | B35: Sourced / Derived (Assumed P7) | C35: =Historical_Drivers!$O$24/1000 -> 102.778 | D35: =Historical_Drivers!$P$24/1000 -> 52.344 | E35: =Historical_Drivers!$C$69*Historical_Drivers!$C$68*E34/Opex!E16 -> 66.114322 | F35: =Historical_Drivers!$C$69*(1-Historical_Drivers!$C$68)*F34/Opex!F16 -> 56.132153 | G35: =L34*Assumptions!$C$11*Historical_Drivers!$C$61/(Historical_Drivers!$C$61+Historical_Drivers!$C$62+Historical_Drivers!$C$63+Historical_Drivers!$C$64) -> 110.30097 | H35: =L34*Assumptions!$C$11*Historical_Drivers!$C$62/(Historical_Drivers!$C$61+Historical_Drivers!$C$62+Historical_Drivers!$C$63+Historical_Drivers!$C$64) -> 78.813827 | I35: =L34*Assumptions!$C$11*Historical_Drivers!$C$63/(Historical_Drivers!$C$61+Historical_Drivers!$C$62+Historical_Drivers!$C$63+Historical_Drivers!$C$64) -> 116.82079 | J35: =L34*Assumptions!$C$11*Historical_Drivers!$C$64/(Historical_Drivers!$C$61+Historical_Drivers!$C$62+Historical_Drivers!$C$63+Historical_Drivers!$C$64) -> 91.746266 | K35: =SUM(C35:F35) -> 277.36848 | L35: =SUM(G35:J35) -> 397.68186 | M35: Q3-Q4 2026 LOW CONFIDENCE (FY guide less H1, split by 2023-2025 Q3 share; scaled by op. income vs Base). Guide excludes restructuring (6-K Jul 22, 2026).
A36: Confidence flag | B36: Text | E36: LOW CONF. | F36: LOW CONF.
A37: Adjusted FCF / non-GAAP operating income | B37: Derived | C37: =C35/C34 -> 2.0959276 | D37: =D35/D34 -> 0.85655376 | E37: =E35/E34 -> 1.0505843 | F37: =F35/F34 -> 0.78467111 | G37: =G35/G34 -> 1.399789 | H37: =H35/H34 -> 0.98083557 | I37: =I35/I34 -> 1.4412037 | J37: =J35/J34 -> 1.1039303 | ... L37: =L35/L34 -> 1.23
A38: Severance cash (outflow; excluded from the FY FCF guide, included in reported adjusted FCF) | B38: Derived (Assumed P8) | E38: =-Assumptions!$C$12/2 -> -16.25 | F38: =-Assumptions!$C$12/2 -> -16.25 | G38: =0*1 -> 0 | H38: =0*1 -> 0 | I38: =0*1 -> 0 | J38: =0*1 -> 0 | K38: =SUM(C38:F38) -> -32.5 | L38: =SUM(G38:J38) -> 0 | M38: Counted once: not double-counted (Cash_Bridge)
A39: Memo: adjusted FCF, reported basis (company definition has no severance add-back) | B39: Derived | C39: =C35 -> 102.778 | D39: =D35 -> 52.344 | E39: =E35+E38 -> 49.864322 | F39: =F35+F38 -> 39.882153 | G39: =G35+G38 -> 110.30097 | H39: =H35+H38 -> 78.813827 | I39: =I35+I38 -> 116.82079 | J39: =J35+J38 -> 91.746266 | K39: =SUM(C39:F39) -> 244.86848 | L39: =SUM(G39:J39) -> 397.68186 | M39: What the company will report = guide basis less severance paid
A40: Share repurchases (outflow) | B40: Derived (Assumed P11) | E40: =-Assumptions!$C$15 -> 0 | F40: =-Assumptions!$C$15 -> 0 | G40: =-Assumptions!$C$15 -> 0 | H40: =-Assumptions!$C$15 -> 0 | I40: =-Assumptions!$C$15 -> 0 | J40: =-Assumptions!$C$15 -> 0 | K40: =SUM(C40:F40) -> 0 | L40: =SUM(G40:J40) -> 0 | M40: FLAG: authorization exhausted; none assumed
A41: Other cash flows (H1 2026 run-rate from Cash_Bridge) | B41: Derived (Assumed P12) | E41: =Assumptions!$C$16 -> -6.4265 | F41: =Assumptions!$C$16 -> -6.4265 | G41: =Assumptions!$C$16 -> -6.4265 | H41: =Assumptions!$C$16 -> -6.4265 | I41: =Assumptions!$C$16 -> -6.4265 | J41: =Assumptions!$C$16 -> -6.4265 | K41: =SUM(C41:F41) -> -12.853 | L41: =SUM(G41:J41) -> -25.706
A42: Net change in cash + marketable securities (forecast quarters) | B42: Derived | E42: =E35+E38+E40+E41 -> 43.437822 | F42: =F35+F38+F40+F41 -> 33.455653 | G42: =G35+G38+G40+G41 -> 103.87447 | H42: =H35+H38+H40+H41 -> 72.387327 | I42: =I35+I38+I40+I41 -> 110.39429 | J42: =J35+J38+J40+J41 -> 85.319766
A43: Ending cash + marketable securities BEFORE UNMODELED ITEMS (new buybacks, M&A beyond run-rate, FX) | B43: Sourced (Q1-Q2) / Derived | C43: =Historical_Drivers!$O$38/1000 -> 1212.276 | D43: =Historical_Drivers!$P$38/1000 -> 1072.755 | E43: =D43+E42 -> 1116.1928 | F43: =E43+F42 -> 1149.6485 | G43: =F43+G42 -> 1253.5229 | H43: =G43+H42 -> 1325.9103 | I43: =H43+I42 -> 1436.3046 | J43: =I43+J42 -> 1521.6243 | K43: =F43 -> 1149.6485 | L43: =J43 -> 1521.6243 | M43: FY columns = year-end balance; not a headline figure
A44: FY2026 adjusted FCF minus FY guide midpoint | B44: Derived | K44: =K35-(Historical_Drivers!$C$42+Historical_Drivers!$C$43)/2 -> -7.6315246
A47: FCF CONVERSION BY YEAR (adjusted FCF / non-GAAP operating income)
A48: Year / case | B48: Label | C48: Adj. FCF (USD m) | D48: Non-GAAP op. income (USD m) | E48: Conversion | F48: Note
A49: FY2023 actual | B49: Derived (sum of quarters) | C49: =(Historical_Drivers!$C$24+Historical_Drivers!$D$24+Historical_Drivers!$E$24+Historical_Drivers!$F$24)/1000 -> 204.945 | D49: =(Historical_Drivers!$C$16+Historical_Drivers!$D$16+Historical_Drivers!$E$16+Historical_Drivers!$F$16)/1000 -> 61.601 | E49: =C49/D49 -> 3.3269752
A50: FY2024 actual | B50: Derived (sum of quarters) | C50: =(Historical_Drivers!$G$24+Historical_Drivers!$H$24+Historical_Drivers!$I$24+Historical_Drivers!$J$24)/1000 -> 295.83 | D50: =(Historical_Drivers!$G$16+Historical_Drivers!$H$16+Historical_Drivers!$I$16+Historical_Drivers!$J$16)/1000 -> 132.383 | E50: =C50/D50 -> 2.2346525
A51: FY2025 actual | B51: Derived (sum of quarters) | C51: =(Historical_Drivers!$K$24+Historical_Drivers!$L$24+Historical_Drivers!$M$24+Historical_Drivers!$N$24)/1000 -> 322.66 | D51: =(Historical_Drivers!$K$16+Historical_Drivers!$L$16+Historical_Drivers!$M$16+Historical_Drivers!$N$16)/1000 -> 175.263 | E51: =C51/D51 -> 1.8410047
A52: FY2026 Base | B52: Derived | C52: =Cash_FCF!K7 -> 285 | D52: =Cash_FCF!K6 -> 252.0671 | E52: =C52/D52 -> 1.1306513 | F52: FCF held at the guide midpoint; op. income beat-adjusted
A53: FY2027 Base | B53: Derived | C53: =Cash_FCF!L7 -> 403.99416 | D53: =Cash_FCF!L6 -> 328.45054 | E53: =C53/D53 -> 1.23 | F53: P7 Base
A54: FY2027 Downside | B54: Derived | C54: =Cash_FCF!L21 -> 249.40498 | D54: =Cash_FCF!L20 -> 249.40498 | E54: =C54/D54 -> 1 | F54: P7 Downside
A55: Memo: FY2026 guide midpoints (FCF / op. income) | B55: Derived | C55: =(Historical_Drivers!$C$42+Historical_Drivers!$C$43)/2 -> 285 | D55: =(Historical_Drivers!$C$44+Historical_Drivers!$C$45)/2 -> 232 | E55: =C55/D55 -> 1.2284483
A56: Conversion fell from 3.33x (FY2023) to 2.23x and 1.84x as operating income grew faster than cash flow; in 2026 interest income also fell after the $735M buyback (financial income $17.3M in H1 2026 vs $31.7M in H1 2025). FY2026 Base is 1.13x because FCF is held at the guide midpoint ($285.0M) while operating income is beat-adjusted to $252.1M (guide midpoint $232.0M; guide ratio 1.23x). Applying 1.23x in FY2027 assumes the 2026 operating-income beat starts converting to cash at the guide ratio in 2027; holding the FY2026 Base ratio instead gives $371.4M. Present FY2027 Base FCF as a range: $328.5M-$404.0M.
A58: FY2027 BASE ADJUSTED FCF AS A RANGE (same Base op. income, three conversions)
A59: Conversion basis | B59: Label | C59: Conversion | D59: FY2027 adj. FCF (USD m) | E59: vs Base plan (USD m) | F59: Note
A60: High: FY2026 guide ratio (P7 Base) | B60: Derived | C60: =Assumptions!$C$11 -> 1.23 | D60: =C60*Cash_FCF!L6 -> 403.99416 | E60: =D60-Cash_FCF!L7 -> 0 | F60: plan value
A61: Mid: FY2026 Base ratio | B61: Derived | C61: =E52 -> 1.1306513 | D61: =C61*Cash_FCF!L6 -> 371.36304 | E61: =D61-Cash_FCF!L7 -> -32.631124 | F61: guide FCF on beat-adjusted op. income
A62: Low: Downside ratio (P7 Downside) | B62: Derived | C62: =Assumptions!$D$11 -> 1 | D62: =C62*Cash_FCF!L6 -> 328.45054 | E62: =D62-Cash_FCF!L7 -> -75.543623

Sheet Scenarios
A1: Scenarios: Base vs Downside (before response) vs Q3-LOW sensitivity, with bridges
A2: USD millions. All values are links / formulas.
A4: Metric | B4: Base FY2026 | C4: Base FY2027 | D4: Downside FY2026 | E4: Downside FY2027 | F4: Q3-LOW FY2026 | G4: Q3-LOW FY2027 | H4: Label
A5: Revenue | B5: =Revenue_Build!K7 -> 1489.1746 | C5: =Revenue_Build!L7 -> 1706.185 | D5: =Revenue_Build!K16 -> 1484.2557 | E5: =Revenue_Build!L16 -> 1626.4819 | F5: =Revenue_Build!K25 -> 1481.1811 | G5: =Revenue_Build!L25 -> 1679.4804 | H5: Derived (links)
A6: Revenue YoY growth | B6: =Revenue_Build!K8 -> 0.20874859 | C6: =Revenue_Build!L8 -> 0.14572529 | D6: =Revenue_Build!K17 -> 0.20475591 | E6: =Revenue_Build!L17 -> 0.095823282 | F6: =Revenue_Build!K26 -> 0.20226028 | G6: =Revenue_Build!L26 -> 0.13387923 | H6: Derived (links)
A7: Operating income (non-GAAP) | B7: =Opex!K16 -> 252.0671 | C7: =Opex!L16 -> 328.45054 | D7: =Opex!K31 -> 247.11799 | E7: =Opex!L31 -> 249.40498 | F7: =Opex!K46 -> 244.6139 | G7: =Opex!L46 -> 323.31858 | H7: Derived (links)
A8: Operating margin (non-GAAP) | B8: =Opex!K17 -> 0.16926631 | C8: =Opex!L17 -> 0.19250581 | D8: =Opex!K32 -> 0.16649287 | E8: =Opex!L32 -> 0.15334015 | F8: =Opex!K47 -> 0.16514787 | G8: =Opex!L47 -> 0.19251107 | H8: Derived (links)
A9: Operating income (GAAP) | B9: =PnL!K15 -> 28.934791 | C9: =PnL!L15 -> 149.30111 | D9: =PnL!K30 -> 24.502176 | E9: =PnL!L30 -> 78.624382 | F9: =PnL!K45 -> 22.320917 | G9: =PnL!L45 -> 146.97314 | H9: Derived (links)
A10: Adjusted FCF, guide basis (excl. severance) | B10: =Cash_FCF!K7 -> 285 | C10: =Cash_FCF!L7 -> 403.99416 | D10: =Cash_FCF!K21 -> 281.11658 | E10: =Cash_FCF!L21 -> 249.40498 | F10: =Cash_FCF!K35 -> 277.36848 | G10: =Cash_FCF!L35 -> 397.68186 | H10: Derived (links)
A11: Adjusted FCF, reported basis (incl. severance) | B11: =Cash_FCF!K11 -> 252.5 | C11: =Cash_FCF!L11 -> 403.99416 | D11: =Cash_FCF!K25 -> 246.11658 | E11: =Cash_FCF!L25 -> 249.40498 | F11: =Cash_FCF!K39 -> 244.86848 | G11: =Cash_FCF!L39 -> 397.68186 | H11: Derived (links)
A12: Memo: ending cash + securities, before unmodeled items (not a headline) | B12: =Cash_FCF!K15 -> 1157.28 | C12: =Cash_FCF!L15 -> 1535.5682 | D12: =Cash_FCF!K29 -> 1150.8966 | E12: =Cash_FCF!L29 -> 1374.5956 | F12: =Cash_FCF!K43 -> 1149.6485 | G12: =Cash_FCF!L43 -> 1521.6243 | H12: Derived (links)
A14: Bridge: Base -> Downside FY2027 non-GAAP operating income
A15: Component | B15: USD m | C15: Label | D15: Formula note
A16: Base FY2027 operating income | B16: =Opex!L16 -> 328.45054 | C16: Derived
A17: Revenue volume effect (lower revenue x Base gross margin) | B17: =(Revenue_Build!L16-Revenue_Build!L7)*Opex!L7/Revenue_Build!L7 -> -70.510957 | C17: Derived | D17: dRev x GM Base
A18: Gross margin rate effect | B18: =Revenue_Build!L16*(Opex!L22/Revenue_Build!L16-Opex!L7/Revenue_Build!L7) -> -8.5345956 | C18: Derived | D18: Rev Downside x dGM
A19: Operating expense effect (dollars held at Base) | B19: =-(Opex!L30-Opex!L15) -> 0 | C19: Derived | D19: should be 0
A20: Downside FY2027 operating income | B20: =B16+B17+B18+B19 -> 249.40498 | C20: Derived | D20: start + components
A21: Bridge check: end - Downside op. income (should be 0) | B21: =B20-Opex!L31 -> 0 | C21: Derived
A23: Bridge: Base -> Downside FY2027 adjusted FCF
A24: Base FY2027 adjusted FCF | B24: =Cash_FCF!L7 -> 403.99416 | C24: Derived
A25: Lower operating income x Base conversion | B25: =(Opex!L31-Opex!L16)*Assumptions!$C$11 -> -97.22603 | C25: Derived
A26: Lower conversion x Downside operating income | B26: =Opex!L31*(Assumptions!$D$11-Assumptions!$C$11) -> -57.363146 | C26: Derived
A27: Downside FY2027 adjusted FCF | B27: =B24+B25+B26 -> 249.40498 | C27: Derived
A28: FCF bridge check (should be 0) | B28: =B27-Cash_FCF!L21 -> 0 | C28: Derived
A30: Q3 2026 at the call LOW: effect on 2027 vs Base (ruling 5)
A31: FY2027 revenue (Q3-LOW minus Base) | B31: =Revenue_Build!L25-Revenue_Build!L7 -> -26.704614 | C31: Derived
A32: FY2027 non-GAAP operating income (Q3-LOW minus Base) | B32: =Opex!L46-Opex!L16 -> -5.1319553 | C32: Derived
A33: FY2027 adjusted FCF (Q3-LOW minus Base) | B33: =Cash_FCF!L35-Cash_FCF!L7 -> -6.312305 | C33: Derived
A34: Cash + securities, end 2027 (Q3-LOW minus Base) | B34: =Cash_FCF!L43-Cash_FCF!L15 -> -13.94383 | C34: Derived
A35: FY2027 operating margin (Q3-LOW minus Base, pp) | B35: =(Opex!L47-Opex!L17)*100 -> 0.0005262456 | C35: Derived
A37: AS GUIDED vs Base, FY2026 (Base is a beat-adjusted central estimate, NOT guidance)
A38: Metric (USD m) | B38: Guide low | C38: Guide mid | D38: Guide high | E38: Base FY2026 | F38: Base - guide mid | G38: Base - guide high (gap above top) | H38: Label
A39: Revenue | B39: =Historical_Drivers!$C$46 -> 1466 | C39: =(B39+D39)/2 -> 1470 | D39: =Historical_Drivers!$C$47 -> 1474 | E39: =Revenue_Build!K7 -> 1489.1746 | F39: =E39-C39 -> 19.174643 | G39: =E39-D39 -> 15.174643 | H39: Derived (links)
A40: Non-GAAP operating income | B40: =Historical_Drivers!$C$44 -> 230 | C40: =(B40+D40)/2 -> 232 | D40: =Historical_Drivers!$C$45 -> 234 | E40: =Opex!K16 -> 252.0671 | F40: =E40-C40 -> 20.067098 | G40: =E40-D40 -> 18.067098 | H40: Derived (links)
A41: Adjusted FCF, guide basis | B41: =Historical_Drivers!$C$42 -> 280 | C41: =(B41+D41)/2 -> 285 | D41: =Historical_Drivers!$C$43 -> 290 | E41: =Cash_FCF!K7 -> 285 | F41: =E41-C41 -> 0 | G41: =E41-D41 -> -5 | H41: Derived (links)
A42: Adjusted FCF, reported basis (incl. severance) | B42: =Historical_Drivers!$C$42 -> 280 | C42: =(B42+D42)/2 -> 285 | D42: =Historical_Drivers!$C$43 -> 290 | E42: =Cash_FCF!K11 -> 252.5 | F42: =E42-C42 -> -32.5 | G42: =E42-D42 -> -37.5 | H42: Derived (links)
A44: Q3 2026 at call LOW: FY2027 revenue effect split into level shift and same-quarter rule effect (item 5)
A45: Component (USD m) | B45: Plan rule (same-quarter) | C45: Smoothed variant | D45: Label | E45: Note
A46: Base FY2027 revenue | B46: =Revenue_Build!L7 -> 1706.185 | C46: =Revenue_Build!L48 -> 1701.1907 | D46: Derived | E46: smoothed variant changes Base too
A47: Q3-LOW FY2027 revenue | B47: =Revenue_Build!L25 -> 1679.4804 | C47: =Revenue_Build!L53 -> 1672.5129 | D47: Derived
A48: Total effect | B48: =B47-B46 -> -26.704614 | C48: =C47-C46 -> -28.677718 | D48: Derived
A49: Level shift (all later quarters scaled by LOW/MID) | B49: =B46*(Historical_Drivers!$C$53/Historical_Drivers!$C$52-1) -> -17.637055 | C49: =C46*(Historical_Drivers!$C$53/Historical_Drivers!$C$52-1) -> -17.585428 | D49: Derived | E49: what the effect would be if later growth were unchanged
A50: Effect of the deceleration rule (total - level) | B50: =B48-B49 -> -9.0675592 | C50: =C48-C49 -> -11.09229 | D50: Derived | E50: weak Q3 2026 growth carried into Q3 2027

Sheet Management_Response
A1: Management response on the Downside: Lever 1 (slow hiring / R&D+G&A growth) and Lever 2 (reduce S&M), from the response start quarter
A2: USD millions. Decision basis = BREAKEVEN revenue loss. Growth-cost elasticities appear only as labeled ILLUSTRATIVE cases: the data cannot prove the growth cost of cutting spend.
A4: Response start quarter in 2027 (Assumptions L0; 1 = Q1 ... 4 = Q4) | B4: Derived (Assumed L0) | C4: =Assumptions!$C$23 -> 2
A6: Line | B6: Label | C6: Q1 2026A | D6: Q2 2026A | E6: Q3 2026 | F6: Q4 2026 | G6: Q1 2027 | H6: Q2 2027 | I6: Q3 2027 | J6: Q4 2027 | K6: FY2026 | L6: FY2027 | M6: Note
A7: Quarter index within 2027 | B7: Derived | G7: =COLUMN()-COLUMN($F$1) -> 1 | H7: =COLUMN()-COLUMN($F$1) -> 2 | I7: =COLUMN()-COLUMN($F$1) -> 3 | J7: =COLUMN()-COLUMN($F$1) -> 4
A8: Lever active (1 = yes) | B8: Derived | G8: =IF(G7>=$C$4,1,0) -> 0 | H8: =IF(H7>=$C$4,1,0) -> 1 | I8: =IF(I7>=$C$4,1,0) -> 1 | J8: =IF(J7>=$C$4,1,0) -> 1
A9: Lever 1 saving: R&D + G&A dollars x L1 (active quarters) | B9: Derived (Assumed L1) | G9: =(Opex!G25+Opex!G29)*Assumptions!$C$24*G8 -> 0 | H9: =(Opex!H25+Opex!H29)*Assumptions!$C$24*H8 -> 6.2503735 | I9: =(Opex!I25+Opex!I29)*Assumptions!$C$24*I8 -> 6.4050191 | J9: =(Opex!J25+Opex!J29)*Assumptions!$C$24*J8 -> 6.6014571 | L9: =SUM(G9:J9) -> 19.25685
A10: Lever 2 saving: S&M dollars x L2 (active quarters) | B10: Derived (Assumed L2) | G10: =Opex!G27*Assumptions!$C$25*G8 -> 0 | H10: =Opex!H27*Assumptions!$C$25*H8 -> 16.612035 | I10: =Opex!I27*Assumptions!$C$25*I8 -> 17.023047 | J10: =Opex!J27*Assumptions!$C$25*J8 -> 17.545133 | L10: =SUM(G10:J10) -> 51.180216
A11: Total saving (Lever 1 + Lever 2) | B11: Derived | G11: =G9+G10 -> 0 | H11: =H9+H10 -> 22.862409 | I11: =I9+I10 -> 23.428066 | J11: =J9+J10 -> 24.14659 | L11: =L9+L10 -> 70.437065
A13: BREAKEVEN: FY2027 revenue loss that would wipe out the FY2027 operating income saved (lost revenue x Downside gross margin = saving)
A14: Measure | B14: Label | C14: Lever 1 | D14: Lever 2 | E14: Both
A15: FY2027 operating income saved (USD m) | B15: Derived | C15: =L9 -> 19.25685 | D15: =L10 -> 51.180216 | E15: =L11 -> 70.437065
A16: Downside FY2027 non-GAAP gross margin | B16: Derived | C16: =Opex!L22/Revenue_Build!L16 -> 0.87942264 | D16: =Opex!L22/Revenue_Build!L16 -> 0.87942264 | E16: =Opex!L22/Revenue_Build!L16 -> 0.87942264
A17: Breakeven FY2027 revenue loss (USD m) | B17: Derived | C17: =C15/C16 -> 21.89715 | D17: =D15/D16 -> 58.197519 | E17: =E15/E16 -> 80.094669
A18: Breakeven as % of Downside FY2027 revenue | B18: Derived | C18: =C17/Revenue_Build!L16 -> 0.013462892 | D18: =D17/Revenue_Build!L16 -> 0.035781227 | E18: =E17/Revenue_Build!L16 -> 0.049244119
A19: Breakeven as points of FY2027 YoY growth | B19: Derived | C19: =C17/Revenue_Build!K16*100 -> 1.475295 | D19: =D17/Revenue_Build!K16*100 -> 3.9209902 | E19: =E17/Revenue_Build!K16*100 -> 5.3962852
A20: Quarters with lever active in FY2027 | B20: Derived | C20: =SUM(G8:J8) -> 3 | D20: =SUM(G8:J8) -> 3 | E20: =SUM(G8:J8) -> 3
A21: Reading: a lever pays in FY2027 only if it costs less revenue than the breakeven. The breakeven is a ONE-YEAR view: revenue lost from lower customer acquisition recurs and compounds after 2027, while the saving can be reversed, so a lever near its breakeven destroys value over several years.
A23: ILLUSTRATIVE ONLY (Assumed elasticities with NO evidence; not the decision basis): annualized revenue lost per $1 of quarterly cut, from the next quarter, cumulative
A24: Case | B24: Label | C24: S&M elasticity | D24: R&D+G&A elasticity
A25: Low (no growth cost) | B25: Assumed (illustrative) | C25: 0 | D25: 0
A26: Mid | B26: Assumed (illustrative) | C26: =Assumptions!$C$26 -> 0.3 | D26: =Assumptions!$C$27 -> 0.1
A27: High | B27: Assumed (illustrative) | C27: 0.6 | D27: 0.2
A29: Line | B29: Label | C29: Q1 2026A | D29: Q2 2026A | E29: Q3 2026 | F29: Q4 2026 | G29: Q1 2027 | H29: Q2 2027 | I29: Q3 2027 | J29: Q4 2027 | K29: FY2026 | L29: FY2027 | M29: Note
A30: Downside AFTER response - ILLUSTRATIVE growth-cost case: Low
A31: Revenue foregone (ILLUSTRATIVE growth cost) | B31: Derived (Assumed illustrative elasticity) | G31: =0*1 -> 0 | H31: =G31+($C$25*G10+$D$25*G9)/4 -> 0 | I31: =H31+($C$25*H10+$D$25*H9)/4 -> 0 | J31: =I31+($C$25*I10+$D$25*I9)/4 -> 0 | L31: =SUM(G31:J31) -> 0
A32: Revenue | B32: Derived | G32: =Revenue_Build!G16-G31 -> 400.15648 | H32: =Revenue_Build!H16-H31 -> 404.96739 | I32: =Revenue_Build!I16-I31 -> 409.72245 | J32: =Revenue_Build!J16-J31 -> 411.6356 | L32: =SUM(G32:J32) -> 1626.4819
A33: Gross profit (Downside gross margin) | B33: Derived | G33: =G32*Opex!G21 -> 353.41931 | H33: =H32*Opex!H21 -> 356.6559 | I33: =I32*Opex!I21 -> 359.81938 | J33: =J32*Opex!J21 -> 360.47043 | L33: =SUM(G33:J33) -> 1430.365
A34: Operating expenses after levers | B34: Derived | G34: =Opex!G30-G11 -> 284.02089 | H34: =Opex!H30-H11 -> 268.26541 | I34: =Opex!I30-I11 -> 274.90279 | J34: =Opex!J30-J11 -> 283.33388 | L34: =SUM(G34:J34) -> 1110.523
A35: Operating income (non-GAAP) | B35: Derived | G35: =G33-G34 -> 69.398422 | H35: =H33-H34 -> 88.390488 | I35: =I33-I34 -> 84.916597 | J35: =J33-J34 -> 77.136543 | L35: =L33-L34 -> 319.84205
A36: Operating margin (non-GAAP) | B36: Derived | G36: =G35/G32 -> 0.17342821 | H36: =H35/H32 -> 0.21826569 | I36: =I35/I32 -> 0.20725395 | J36: =J35/J32 -> 0.18739036 | L36: =L35/L32 -> 0.19664654
A37: Adjusted FCF (Downside conversion P7) | B37: Derived | G37: =$L35*Assumptions!$D$11*Historical_Drivers!$C$61/(Historical_Drivers!$C$61+Historical_Drivers!$C$62+Historical_Drivers!$C$63+Historical_Drivers!$C$64) -> 88.711335 | H37: =$L35*Assumptions!$D$11*Historical_Drivers!$C$62/(Historical_Drivers!$C$61+Historical_Drivers!$C$62+Historical_Drivers!$C$63+Historical_Drivers!$C$64) -> 63.387292 | I37: =$L35*Assumptions!$D$11*Historical_Drivers!$C$63/(Historical_Drivers!$C$61+Historical_Drivers!$C$62+Historical_Drivers!$C$63+Historical_Drivers!$C$64) -> 93.955007 | J37: =$L35*Assumptions!$D$11*Historical_Drivers!$C$64/(Historical_Drivers!$C$61+Historical_Drivers!$C$62+Historical_Drivers!$C$63+Historical_Drivers!$C$64) -> 73.788415 | L37: =SUM(G37:J37) -> 319.84205
A38: Ending cash + securities, end 2027 (before unmodeled items) | B38: Derived | L38: =Cash_FCF!F29+L37+Cash_FCF!L26+Cash_FCF!L27 -> 1445.0326
A40: Downside AFTER response - ILLUSTRATIVE growth-cost case: Mid
A41: Revenue foregone (ILLUSTRATIVE growth cost) | B41: Derived (Assumed illustrative elasticity) | G41: =0*1 -> 0 | H41: =G41+($C$26*G10+$D$26*G9)/4 -> 0 | I41: =H41+($C$26*H10+$D$26*H9)/4 -> 1.402162 | J41: =I41+($C$26*I10+$D$26*I9)/4 -> 2.839016 | L41: =SUM(G41:J41) -> 4.241178
A42: Revenue | B42: Derived | G42: =Revenue_Build!G16-G41 -> 400.15648 | H42: =Revenue_Build!H16-H41 -> 404.96739 | I42: =Revenue_Build!I16-I41 -> 408.32028 | J42: =Revenue_Build!J16-J41 -> 408.79658 | L42: =SUM(G42:J42) -> 1622.2407
A43: Gross profit (Downside gross margin) | B43: Derived | G43: =G42*Opex!G21 -> 353.41931 | H43: =H42*Opex!H21 -> 356.6559 | I43: =I42*Opex!I21 -> 358.588 | J43: =J42*Opex!J21 -> 357.98429 | L43: =SUM(G43:J43) -> 1426.6475
A44: Operating expenses after levers | B44: Derived | G44: =Opex!G30-G11 -> 284.02089 | H44: =Opex!H30-H11 -> 268.26541 | I44: =Opex!I30-I11 -> 274.90279 | J44: =Opex!J30-J11 -> 283.33388 | L44: =SUM(G44:J44) -> 1110.523
A45: Operating income (non-GAAP) | B45: Derived | G45: =G43-G44 -> 69.398422 | H45: =H43-H44 -> 88.390488 | I45: =I43-I44 -> 83.685214 | J45: =J43-J44 -> 74.650409 | L45: =L43-L44 -> 316.12453
A46: Operating margin (non-GAAP) | B46: Derived | G46: =G45/G42 -> 0.17342821 | H46: =H45/H42 -> 0.21826569 | I46: =I45/I42 -> 0.20494993 | J46: =J45/J42 -> 0.18261016 | L46: =L45/L42 -> 0.19486906
A47: Adjusted FCF (Downside conversion P7) | B47: Derived | G47: =$L45*Assumptions!$D$11*Historical_Drivers!$C$61/(Historical_Drivers!$C$61+Historical_Drivers!$C$62+Historical_Drivers!$C$63+Historical_Drivers!$C$64) -> 87.680245 | H47: =$L45*Assumptions!$D$11*Historical_Drivers!$C$62/(Historical_Drivers!$C$61+Historical_Drivers!$C$62+Historical_Drivers!$C$63+Historical_Drivers!$C$64) -> 62.650543 | I47: =$L45*Assumptions!$D$11*Historical_Drivers!$C$63/(Historical_Drivers!$C$61+Historical_Drivers!$C$62+Historical_Drivers!$C$63+Historical_Drivers!$C$64) -> 92.86297 | J47: =$L45*Assumptions!$D$11*Historical_Drivers!$C$64/(Historical_Drivers!$C$61+Historical_Drivers!$C$62+Historical_Drivers!$C$63+Historical_Drivers!$C$64) -> 72.930774 | L47: =SUM(G47:J47) -> 316.12453
A48: Ending cash + securities, end 2027 (before unmodeled items) | B48: Derived | L48: =Cash_FCF!F29+L47+Cash_FCF!L26+Cash_FCF!L27 -> 1441.3151
A50: Downside AFTER response - ILLUSTRATIVE growth-cost case: High
A51: Revenue foregone (ILLUSTRATIVE growth cost) | B51: Derived (Assumed illustrative elasticity) | G51: =0*1 -> 0 | H51: =G51+($C$27*G10+$D$27*G9)/4 -> 0 | I51: =H51+($C$27*H10+$D$27*H9)/4 -> 2.804324 | J51: =I51+($C$27*I10+$D$27*I9)/4 -> 5.678032 | L51: =SUM(G51:J51) -> 8.4823559
A52: Revenue | B52: Derived | G52: =Revenue_Build!G16-G51 -> 400.15648 | H52: =Revenue_Build!H16-H51 -> 404.96739 | I52: =Revenue_Build!I16-I51 -> 406.91812 | J52: =Revenue_Build!J16-J51 -> 405.95756 | L52: =SUM(G52:J52) -> 1617.9996
A53: Gross profit (Downside gross margin) | B53: Derived | G53: =G52*Opex!G21 -> 353.41931 | H53: =H52*Opex!H21 -> 356.6559 | I53: =I52*Opex!I21 -> 357.35662 | J53: =J52*Opex!J21 -> 355.49816 | L53: =SUM(G53:J53) -> 1422.93
A54: Operating expenses after levers | B54: Derived | G54: =Opex!G30-G11 -> 284.02089 | H54: =Opex!H30-H11 -> 268.26541 | I54: =Opex!I30-I11 -> 274.90279 | J54: =Opex!J30-J11 -> 283.33388 | L54: =SUM(G54:J54) -> 1110.523
A55: Operating income (non-GAAP) | B55: Derived | G55: =G53-G54 -> 69.398422 | H55: =H53-H54 -> 88.390488 | I55: =I53-I54 -> 82.453831 | J55: =J53-J54 -> 72.164274 | L55: =L53-L54 -> 312.40702
A56: Operating margin (non-GAAP) | B56: Derived | G56: =G55/G52 -> 0.17342821 | H56: =H55/H52 -> 0.21826569 | I56: =I55/I52 -> 0.20263003 | J56: =J55/J52 -> 0.1777631 | L56: =L55/L52 -> 0.19308226
A57: Adjusted FCF (Downside conversion P7) | B57: Derived | G57: =$L55*Assumptions!$D$11*Historical_Drivers!$C$61/(Historical_Drivers!$C$61+Historical_Drivers!$C$62+Historical_Drivers!$C$63+Historical_Drivers!$C$64) -> 86.649156 | H57: =$L55*Assumptions!$D$11*Historical_Drivers!$C$62/(Historical_Drivers!$C$61+Historical_Drivers!$C$62+Historical_Drivers!$C$63+Historical_Drivers!$C$64) -> 61.913794 | I57: =$L55*Assumptions!$D$11*Historical_Drivers!$C$63/(Historical_Drivers!$C$61+Historical_Drivers!$C$62+Historical_Drivers!$C$63+Historical_Drivers!$C$64) -> 91.770933 | J57: =$L55*Assumptions!$D$11*Historical_Drivers!$C$64/(Historical_Drivers!$C$61+Historical_Drivers!$C$62+Historical_Drivers!$C$63+Historical_Drivers!$C$64) -> 72.073133 | L57: =SUM(G57:J57) -> 312.40702
A58: Ending cash + securities, end 2027 (before unmodeled items) | B58: Derived | L58: =Cash_FCF!F29+L57+Cash_FCF!L26+Cash_FCF!L27 -> 1437.5976
A60: RESULT vs Downside before response (FY2027), levers from the start quarter
A61: Measure | B61: Label | C61: Low (no growth cost) | D61: Mid (illustrative) | E61: High (illustrative)
A62: Operating income preserved (USD m) | B62: Derived | C62: =Management_Response!L35-Opex!L31 -> 70.437065 | D62: =Management_Response!L45-Opex!L31 -> 66.719549 | E62: =Management_Response!L55-Opex!L31 -> 63.002032
A63: Operating margin preserved (pp) | B63: Derived | C63: =(Management_Response!L36-Opex!L32)*100 -> 4.3306393 | D63: =(Management_Response!L46-Opex!L32)*100 -> 4.1528911 | E63: =(Management_Response!L56-Opex!L32)*100 -> 3.9742111
A64: Cash preserved by end 2027 (USD m) | B64: Derived | C64: =Management_Response!L38-Cash_FCF!L29 -> 70.437065 | D64: =Management_Response!L48-Cash_FCF!L29 -> 66.719549 | E64: =Management_Response!L58-Cash_FCF!L29 -> 63.002032
A65: ILLUSTRATIVE FY2027 revenue lost (USD m) | B65: Derived | C65: =Management_Response!L31 -> 0 | D65: =Management_Response!L41 -> 4.241178 | E65: =Management_Response!L51 -> 8.4823559
A66: ILLUSTRATIVE revenue lost / breakeven (both levers) | B66: Derived | C66: =Management_Response!L31/$E$17 -> 0 | D66: =Management_Response!L41/$E$17 -> 0.052952063 | E66: =Management_Response!L51/$E$17 -> 0.10590413
A67: FY2027 operating margin after response | B67: Derived | C67: =Management_Response!L36 -> 0.19664654 | D67: =Management_Response!L46 -> 0.19486906 | E67: =Management_Response!L56 -> 0.19308226
A68: Memo: Base FY2027 operating margin | B68: Derived | C68: =Opex!L17 -> 0.19250581 | D68: =Opex!L17 -> 0.19250581 | E68: =Opex!L17 -> 0.19250581
A69: Memo: Downside FY2027 margin before response | B69: Derived | C69: =Opex!L32 -> 0.15334015 | D69: =Opex!L32 -> 0.15334015 | E69: =Opex!L32 -> 0.15334015

Sheet Recommendation
A1: Recommendation: trigger metrics and actions (derived from model outputs; not a forecast)
A2: Thresholds and effects link to model cells. Lever decisions use the BREAKEVEN revenue loss; the growth cost of cutting spend is not provable from the data.
A4: Trigger metric | B4: Label | C4: Q4 2026 | D4: Q1 2027 | E4: Q2 2027 | F4: Q3 2027 | G4: Q4 2027 | H4: Rule | I4: Evidence
A5: T1 threshold: sequential revenue growth on the Downside path | B5: Derived (link) | C5: =Revenue_Build!F15 -> 0.030669377 | D5: =Revenue_Build!G15 -> 0.026075908 | E5: =Revenue_Build!H15 -> 0.012022576 | F5: =Revenue_Build!I15 -> 0.011741815 | G5: =Revenue_Build!J15 -> 0.0046693767 | H5: TRIGGER if actual sequential growth is at or below the Downside path for two consecutive quarters. | I5: Revenue_Build Downside seq row; Trigger_History T1
A6: Memo: Base path sequential growth | B6: Derived (link) | C6: =Revenue_Build!F6 -> 0.043669377 | D6: =Revenue_Build!G6 -> 0.039075908 | E6: =Revenue_Build!H6 -> 0.025022576 | F6: =Revenue_Build!I6 -> 0.024741815 | G6: =Revenue_Build!J6 -> 0.030669377
A7: T2 threshold: revenue beat vs guidance midpoint | B7: Derived (link) | C7: =Trigger_History!$E$36 -> 0.014826748 | H7: TRIGGER if the beat vs the guidance midpoint is below the last-8 minimum for two consecutive quarters. | I7: Trigger_History derivation (= analysis Guidance_Accuracy!I68)
A8: T3 threshold: quarterly net adds of customers >$50k ARR | B8: Derived (link) | C8: =Assumptions!$D$19 -> 194 | H8: TRIGGER if net adds are at or below the last-8 minimum for two consecutive quarters. | I8: Trigger_History derivation
A10: Trigger history, last 20 quarters (Trigger_History)
A11: Trigger | B11: Label | C11: Evaluable | D11: Fires | E11: Fire rate | F11: Confirmed | G11: False alarms | H11: Not evaluable / fires last 8 | I11: Flag
A12: T1 | B12: Derived (link) | C12: =Trigger_History!B31 -> 16 | D12: =Trigger_History!C31 -> 5 | E12: =Trigger_History!D31 -> 0.3125 | F12: =Trigger_History!E31 -> 5 | G12: =Trigger_History!F31 -> 0 | H12: =Trigger_History!G31&" / "&Trigger_History!H31 -> 0 / 0 | I12: =Trigger_History!I31 -> FIRES TOO OFTEN
A13: T2 | B13: Derived (link) | C13: =Trigger_History!B32 -> 19 | D13: =Trigger_History!C32 -> 0 | E13: =Trigger_History!D32 -> 0 | F13: =Trigger_History!E32 -> 0 | G13: =Trigger_History!F32 -> 0 | H13: =Trigger_History!G32&" / "&Trigger_History!H32 -> 0 / 0 | I13: =Trigger_History!I32 -> NEVER FIRED: untested
A14: T3 | B14: Derived (link) | C14: =Trigger_History!B33 -> 20 | D14: =Trigger_History!C33 -> 4 | E14: =Trigger_History!D33 -> 0.2 | F14: =Trigger_History!E33 -> 2 | G14: =Trigger_History!F33 -> 0 | H14: =Trigger_History!G33&" / "&Trigger_History!H33 -> 2 / 0 | I14: =Trigger_History!I33 -> OK
A16: Actions (applied to the Downside from the response start quarter)
A17: Action | B17: Label | C17: Start quarter (2027) | D17: FY2027 op. income saved (USD m) | E17: Breakeven revenue loss (USD m) | F17: Breakeven % of revenue | G17: Breakeven growth pts | H17: When | I17: Condition
A18: Lever 1: hold R&D+G&A dollars below plan | B18: Derived (link) | C18: =Management_Response!$C$4 -> 2 | D18: =Management_Response!C15 -> 19.25685 | E18: =Management_Response!C17 -> 21.89715 | F18: =Management_Response!C18 -> 0.013462892 | G18: =Management_Response!C19 -> 1.475295 | H18: On T1 or T2 (two consecutive quarters) | I18: Act if the expected revenue cost is below the breakeven
A19: Lever 2: reduce S&M dollars | B19: Derived (link) | C19: =Management_Response!$C$4 -> 2 | D19: =Management_Response!D15 -> 51.180216 | E19: =Management_Response!D17 -> 58.197519 | F19: =Management_Response!D18 -> 0.035781227 | G19: =Management_Response!D19 -> 3.9209902 | H19: CONDITIONAL: only if T3 also fires | I19: Not automatic: a one-year view ignores multi-year effects of cutting customer acquisition spend
A20: Both levers | B20: Derived (link) | C20: =Management_Response!$C$4 -> 2 | D20: =Management_Response!E15 -> 70.437065 | E20: =Management_Response!E17 -> 80.094669 | F20: =Management_Response!E18 -> 0.049244119 | G20: =Management_Response!E19 -> 5.3962852 | H20: T1/T2 plus T3 | I20: As above
A22: Recommendation (text derived from the cells above)
A23: 1. HOLD the Base plan; do not act on the forecast alone. Base FY2027 revenue $1,706.2M, non-GAAP margin 19.3%. The Downside (faster deceleration, opex dollars unchanged) gives $1,626.5M and 15.3%, falling to 12.9% in Q4 2027. The Base-Downside revenue gap (4.7% of Base) is only 1.13x the average 4-quarter-ahead backtest miss, so the two cases cannot be told apart in advance: act on the triggers.
A24: 2. TRIGGERS (two consecutive quarters each; NDR is NOT a trigger): T1 sequential growth at or below the Downside path (3.07%, 2.61%, 1.20%, 1.17%, 0.47% for Q4 2026-Q4 2027; Base 4.37%, 3.91%, 2.50%, 2.47%, 3.07%); T2 beat vs guidance midpoint below 1.48%; T3 net adds of customers >$50k at or below 194. History (last 20 quarters): T1 5 fires, all 2022-2023 and all confirmed, none in the last 8; T2 never fired (untested); T3 4 fires, all 2021-2022. Compare actuals on the guide basis: reported FY2026 adjusted FCF will include severance ($252.5M vs guide low $280.0M) and is not a miss if all severance is paid in 2026.
A25: 3. ACTIONS from Q2 2027 at the earliest (T2 can first fire on Q3+Q4 2026 results, reported February 2027). Lever 1 on T1 or T2: hold R&D+G&A 5% below plan, saving $19.3M in FY2027; it pays only if it costs less than $21.9M of FY2027 revenue (1.3%, 1.5 growth points). Lever 2 (S&M 10% below plan) saves $51.2M, breakeven $58.2M (3.6%, 3.9 points).
A26: 4. Lever 2 is CONDITIONAL, not automatic: use it only if T3 also fires. The breakeven is a one-year view and ignores the multi-year effect of cutting customer acquisition spend: revenue lost from customers not acquired recurs and compounds after 2027, while the saving can be reversed. The data cannot prove the growth cost; the illustrative mid case ($4.2M of FY2027 revenue) is 5% of the two-lever breakeven, but it rests on an assumed elasticity.
A27: 5. Q3 2026 at the call LOW lowers FY2027 revenue by $26.7M: $17.6M level shift and $9.1M from carrying weak Q3 growth into Q3 2027 under the same-quarter rule. With a smoothed base the effect is $28.7M ($11.1M rule effect). Not a trigger by itself.

Sheet Backtest
A1: Revenue backtest by horizon (1-4 quarters ahead): Method B (guidance-anchored first step, then same-quarter sequential trend less estimated deceleration) vs pure trend
A2: Targets: Q3 2024-Q2 2026 (8 per horizon). Deceleration at origin t = mean QoQ of quarters t-7..t-4 minus mean QoQ of t-3..t (data available at t). Only data available at the origin is used.
A4: Quarter | B4: Revenue (USD m) | C4: Row ID | D4: Guide low | E4: Guide high | F4: GH Row ID | G4: QoQ growth | H4: Guide midpoint | I4: % beat
A5: Q1 2021 | B5: 58.972 | C5: QA-0001
A6: Q2 2021 | B6: 70.615 | C6: QA-0002 | G6: =B6/B5-1 -> 0.19743268
A7: Q3 2021 | B7: 83.018 | C7: QA-0004 | D7: 74 | E7: 75 | F7: GH-0004 | G7: =B7/B6-1 -> 0.17564257 | H7: =(D7+E7)/2 -> 74.5 | I7: =B7/H7-1 -> 0.11433557
A8: Q4 2021 | B8: 95.545 | C8: QA-0006 | D8: 87 | E8: 88 | F8: GH-0008 | G8: =B8/B7-1 -> 0.15089499 | H8: =(D8+E8)/2 -> 87.5 | I8: =B8/H8-1 -> 0.091942857
A9: Q1 2022 | B9: 108.497 | C9: QA-0008 | D9: 100 | E9: 102 | F9: GH-0012 | G9: =B9/B8-1 -> 0.13555916 | H9: =(D9+E9)/2 -> 101 | I9: =B9/H9-1 -> 0.074227723
A10: Q2 2022 | B10: 123.718 | C10: QA-0009 | D10: 117 | E10: 119 | F10: GH-0016 | G10: =B10/B9-1 -> 0.14028959 | H10: =(D10+E10)/2 -> 118 | I10: =B10/H10-1 -> 0.048457627
A11: Q3 2022 | B11: 136.893 | C11: QA-0011 | D11: 130 | E11: 131 | F11: GH-0020 | G11: =B11/B10-1 -> 0.10649218 | H11: =(D11+E11)/2 -> 130.5 | I11: =B11/H11-1 -> 0.048988506
A12: Q4 2022 | B12: 149.921 | C12: QA-0013 | D12: 140 | E12: 142 | F12: GH-0024 | G12: =B12/B11-1 -> 0.09516922 | H12: =(D12+E12)/2 -> 141 | I12: =B12/H12-1 -> 0.063269504
A13: Q1 2023 | B13: 162.256 | C13: QA-0015 | D13: 154 | E13: 156 | F13: GH-0028 | G13: =B13/B12-1 -> 0.082276666 | H13: =(D13+E13)/2 -> 155 | I13: =B13/H13-1 -> 0.046812903
A14: Q2 2023 | B14: 175.679 | C14: QA-0016 | D14: 168 | E14: 170 | F14: GH-0032 | G14: =B14/B13-1 -> 0.082727295 | H14: =(D14+E14)/2 -> 169 | I14: =B14/H14-1 -> 0.03952071
A15: Q3 2023 | B15: 189.19 | C15: QA-0018 | D15: 181 | E15: 183 | F15: GH-0036 | G15: =B15/B14-1 -> 0.076907314 | H15: =(D15+E15)/2 -> 182 | I15: =B15/H15-1 -> 0.039505495
A16: Q4 2023 | B16: 202.57 | C16: QA-0020 | D16: 196 | E16: 198 | F16: GH-0040 | G16: =B16/B15-1 -> 0.070722554 | H16: =(D16+E16)/2 -> 197 | I16: =B16/H16-1 -> 0.028274112
A17: Q1 2024 | B17: 216.913 | C17: QA-0022 | D17: 207 | E17: 211 | F17: GH-0046 | G17: =B17/B16-1 -> 0.070805154 | H17: =(D17+E17)/2 -> 209 | I17: =B17/H17-1 -> 0.037861244
A18: Q2 2024 | B18: 236.106 | C18: QA-0023 | D18: 226 | E18: 230 | F18: GH-0052 | G18: =B18/B17-1 -> 0.088482479 | H18: =(D18+E18)/2 -> 228 | I18: =B18/H18-1 -> 0.035552632
... A26: Q2 2026 | B26: 364.621 | C26: QA-0037 | D26: 354 | E26: 356 | F26: GH-0094 | G26: =B26/B25-1 -> 0.038022576 | H26: =(D26+E26)/2 -> 355 | I26: =B26/H26-1 -> 0.027101408
A29: Horizon 1 quarter(s) ahead
A30: Target | B30: Origin | C30: Decel. d_t | D30: B step 1 | E30: Trend step 1 | F30: Actual | G30: B error % | H30: Trend error %
A31: Q3 2024 | B31: Q2 2024 | C31: =AVERAGE(G11:G14)-AVERAGE(G15:G18) -> 0.014936966 | D31: =H19*(1+MEDIAN(I11:I18)) -> 254.68071 | E31: =B18*(1+G15-$C31) -> 250.73757 | F31: =B19 -> 251 | G31: =D31/F31-1 -> 0.014664184 | H31: =E31/F31-1 -> -0.0010455339
A32: Q4 2024 | B32: Q3 2024 | C32: =AVERAGE(G12:G15)-AVERAGE(G16:G19) -> 0.010997118 | D32: =H20*(1+MEDIAN(I12:I19)) -> 271.09636 | E32: =B19*(1+G16-$C32) -> 265.99108 | F32: =B20 -> 267.976 | G32: =D32/F32-1 -> 0.011644175 | H32: =E32/F32-1 -> -0.0074070645
A33: Q1 2025 | B33: Q4 2024 | C33: =AVERAGE(G13:G16)-AVERAGE(G17:G20) -> 0.0056577234 | D33: =H21*(1+MEDIAN(I13:I20)) -> 285.09441 | E33: =B20*(1+G17-$C33) -> 285.43395 | F33: =B21 -> 282.25 | G33: =D33/F33-1 -> 0.010077619 | H33: =E33/F33-1 -> 0.011280595
A34: Q2 2025 | B34: Q1 2025 | C34: =AVERAGE(G14:G17)-AVERAGE(G18:G21) -> 0.0071746428 | D34: =H22*(1+MEDIAN(I14:I21)) -> 302.35062 | E34: =B21*(1+G18-$C34) -> 305.19914 | F34: =B22 -> 299.014 | G34: =D34/F34-1 -> 0.011158735 | H34: =E34/F34-1 -> 0.020685108
A35: Q3 2025 | B35: Q2 2025 | C35: =AVERAGE(G15:G18)-AVERAGE(G19:G22) -> 0.01588552 | D35: =H23*(1+MEDIAN(I15:I22)) -> 320.58032 | E35: =B22*(1+G19-$C35) -> 313.12636 | F35: =B23 -> 316.855 | G35: =D35/F35-1 -> 0.011757191 | H35: =E35/F35-1 -> -0.011767656
A36: Q4 2025 | B36: Q3 2025 | C36: =AVERAGE(G16:G19)-AVERAGE(G20:G23) -> 0.013283084 | D36: =H24*(1+MEDIAN(I16:I23)) -> 337.73357 | E36: =B23*(1+G20-$C36) -> 334.07619 | F36: =B24 -> 333.878 | G36: =D36/F36-1 -> 0.011547838 | H36: =E36/F36-1 -> 0.00059360102
A37: Q1 2026 | B37: Q4 2025 | C37: =AVERAGE(G17:G20)-AVERAGE(G21:G24) -> 0.015987956 | D37: =H25*(1+MEDIAN(I17:I24)) -> 347.61966 | E37: =B24*(1+G21-$C37) -> 346.32431 | F37: =B25 -> 351.265 | G37: =D37/F37-1 -> -0.010377758 | H37: =E37/F37-1 -> -0.01406543
A38: Q2 2026 | B38: Q1 2026 | C38: =AVERAGE(G18:G21)-AVERAGE(G22:G25) -> 0.011900673 | D38: =H26*(1+MEDIAN(I18:I25)) -> 364.02648 | E38: =B25*(1+G22-$C38) -> 367.9478 | F38: =B26 -> 364.621 | G38: =D38/F38-1 -> -0.0016305034 | H38: =E38/F38-1 -> 0.0091239883
A40: Horizon 2 quarter(s) ahead
A41: Target | B41: Origin | C41: Decel. d_t | D41: B step 1 | E41: B step 2 | F41: Trend step 1 | G41: Trend step 2 | H41: Actual | I41: B error % | J41: Trend error %
A42: Q3 2024 | B42: Q1 2024 | C42: =AVERAGE(G10:G13)-AVERAGE(G14:G17) -> 0.030766336 | D42: =H18*(1+MEDIAN(I10:I17)) -> 237.84203 | E42: =D42*(1+G15-$C42) -> 248.8163 | F42: =B17*(1+G14-$C42) -> 228.18401 | G42: =F42*(1+G15-$C42) -> 238.71264 | H42: =B19 -> 251 | I42: =E42/H42-1 -> -0.0087000169 | J42: =G42/H42-1 -> -0.048953623
A43: Q4 2024 | B43: Q2 2024 | C43: =AVERAGE(G11:G14)-AVERAGE(G15:G18) -> 0.014936966 | D43: =H19*(1+MEDIAN(I11:I18)) -> 254.68071 | E43: =D43*(1+G16-$C43) -> 268.88822 | F43: =B18*(1+G15-$C43) -> 250.73757 | G43: =F43*(1+G16-$C43) -> 264.72511 | H43: =B20 -> 267.976 | I43: =E43/H43-1 -> 0.003404123 | J43: =G43/H43-1 -> -0.012131259
A44: Q1 2025 | B44: Q3 2024 | C44: =AVERAGE(G12:G15)-AVERAGE(G16:G19) -> 0.010997118 | D44: =H20*(1+MEDIAN(I12:I19)) -> 271.09636 | E44: =D44*(1+G17-$C44) -> 287.3101 | F44: =B19*(1+G16-$C44) -> 265.99108 | G44: =F44*(1+G17-$C44) -> 281.89949 | H44: =B21 -> 282.25 | I44: =E44/H44-1 -> 0.017927724 | J44: =G44/H44-1 -> -0.0012418465
A45: Q2 2025 | B45: Q4 2024 | C45: =AVERAGE(G13:G16)-AVERAGE(G17:G20) -> 0.0056577234 | D45: =H21*(1+MEDIAN(I13:I20)) -> 285.09441 | E45: =D45*(1+G18-$C45) -> 308.70728 | F45: =B20*(1+G17-$C45) -> 285.43395 | G45: =F45*(1+G18-$C45) -> 309.07494 | H45: =B22 -> 299.014 | I45: =E45/H45-1 -> 0.032417487 | J45: =G45/H45-1 -> 0.033647069
A46: Q3 2025 | B46: Q1 2025 | C46: =AVERAGE(G14:G17)-AVERAGE(G18:G21) -> 0.0071746428 | D46: =H22*(1+MEDIAN(I14:I21)) -> 302.35062 | E46: =D46*(1+G19-$C46) -> 319.25419 | F46: =B21*(1+G18-$C46) -> 305.19914 | G46: =F46*(1+G19-$C46) -> 322.26196 | H46: =B23 -> 316.855 | I46: =E46/H46-1 -> 0.0075718935 | J46: =G46/H46-1 -> 0.017064474
A47: Q4 2025 | B47: Q2 2025 | C47: =AVERAGE(G15:G18)-AVERAGE(G19:G22) -> 0.01588552 | D47: =H23*(1+MEDIAN(I15:I22)) -> 320.58032 | E47: =D47*(1+G20-$C47) -> 337.1697 | F47: =B22*(1+G19-$C47) -> 313.12636 | G47: =F47*(1+G20-$C47) -> 329.33001 | H47: =B24 -> 333.878 | I47: =E47/H47-1 -> 0.0098589844 | J47: =G47/H47-1 -> -0.013621727
A48: Q1 2026 | B48: Q3 2025 | C48: =AVERAGE(G16:G19)-AVERAGE(G20:G23) -> 0.013283084 | D48: =H24*(1+MEDIAN(I16:I23)) -> 337.73357 | E48: =D48*(1+G21-$C48) -> 351.23713 | F48: =B23*(1+G20-$C48) -> 334.07619 | G48: =F48*(1+G21-$C48) -> 347.43352 | H48: =B25 -> 351.265 | I48: =E48/H48-1 -> -7.9341994e-05 | J48: =G48/H48-1 -> -0.010907666
A49: Q2 2026 | B49: Q4 2025 | C49: =AVERAGE(G17:G20)-AVERAGE(G21:G24) -> 0.015987956 | D49: =H25*(1+MEDIAN(I17:I24)) -> 347.61966 | E49: =D49*(1+G22-$C49) -> 362.7085 | F49: =B24*(1+G21-$C49) -> 346.32431 | G49: =F49*(1+G22-$C49) -> 361.35693 | H49: =B26 -> 364.621 | I49: =E49/H49-1 -> -0.0052451602 | J49: =G49/H49-1 -> -0.0089519578
A51: Horizon 3 quarter(s) ahead
A52: Target | B52: Origin | C52: Decel. d_t | D52: B step 1 | E52: B step 2 | F52: B step 3 | G52: Trend step 1 | H52: Trend step 2 | I52: Trend step 3 | J52: Actual | K52: B error % | L52: Trend error %
A53: Q3 2024 | B53: Q4 2023 | C53: =AVERAGE(G9:G12)-AVERAGE(G13:G16) -> 0.041219082 | D53: =H17*(1+MEDIAN(I9:I16)) -> 218.95577 | E53: =D53*(1+G14-$C53) -> 228.04423 | F53: =E53*(1+G15-$C53) -> 236.18273 | G53: =B16*(1+G13-$C53) -> 210.88703 | H53: =G53*(1+G14-$C53) -> 219.64058 | I53: =H53*(1+G15-$C53) -> 227.47916 | J53: =B19 -> 251 | K53: =F53/J53-1 -> -0.059032954 | L53: =I53/J53-1 -> -0.093708516
A54: Q4 2024 | B54: Q1 2024 | C54: =AVERAGE(G10:G13)-AVERAGE(G14:G17) -> 0.030766336 | D54: =H18*(1+MEDIAN(I10:I17)) -> 237.84203 | E54: =D54*(1+G15-$C54) -> 248.8163 | F54: =E54*(1+G16-$C54) -> 258.75805 | G54: =B17*(1+G14-$C54) -> 228.18401 | H54: =G54*(1+G15-$C54) -> 238.71264 | I54: =H54*(1+G16-$C54) -> 248.25069 | J54: =B20 -> 267.976 | K54: =F54/J54-1 -> -0.034398402 | L54: =I54/J54-1 -> -0.073608477
A55: Q1 2025 | B55: Q2 2024 | C55: =AVERAGE(G11:G14)-AVERAGE(G15:G18) -> 0.014936966 | D55: =H19*(1+MEDIAN(I11:I18)) -> 254.68071 | E55: =D55*(1+G16-$C55) -> 268.88822 | F55: =E55*(1+G17-$C55) -> 283.91052 | G55: =B18*(1+G15-$C55) -> 250.73757 | H55: =G55*(1+G16-$C55) -> 264.72511 | I55: =H55*(1+G17-$C55) -> 279.51483 | J55: =B21 -> 282.25 | K55: =F55/J55-1 -> 0.0058831569 | L55: =I55/J55-1 -> -0.0096906067
A56: Q2 2025 | B56: Q3 2024 | C56: =AVERAGE(G12:G15)-AVERAGE(G16:G19) -> 0.010997118 | D56: =H20*(1+MEDIAN(I12:I19)) -> 271.09636 | E56: =D56*(1+G17-$C56) -> 287.3101 | F56: =E56*(1+G18-$C56) -> 309.57243 | G56: =B19*(1+G16-$C56) -> 265.99108 | H56: =G56*(1+G17-$C56) -> 281.89949 | I56: =H56*(1+G18-$C56) -> 303.74257 | J56: =B22 -> 299.014 | K56: =F56/J56-1 -> 0.035310812 | L56: =I56/J56-1 -> 0.015813883
A57: Q3 2025 | B57: Q4 2024 | C57: =AVERAGE(G13:G16)-AVERAGE(G17:G20) -> 0.0056577234 | D57: =H21*(1+MEDIAN(I13:I20)) -> 285.09441 | E57: =D57*(1+G18-$C57) -> 308.70728 | F57: =E57*(1+G19-$C57) -> 326.43452 | G57: =B20*(1+G17-$C57) -> 285.43395 | H57: =G57*(1+G18-$C57) -> 309.07494 | I57: =H57*(1+G19-$C57) -> 326.8233 | J57: =B23 -> 316.855 | K57: =F57/J57-1 -> 0.030233149 | L57: =I57/J57-1 -> 0.031460129
A58: Q4 2025 | B58: Q1 2025 | C58: =AVERAGE(G14:G17)-AVERAGE(G18:G21) -> 0.0071746428 | D58: =H22*(1+MEDIAN(I14:I21)) -> 302.35062 | E58: =D58*(1+G19-$C58) -> 319.25419 | F58: =E58*(1+G20-$C58) -> 338.55593 | G58: =B21*(1+G18-$C58) -> 305.19914 | H58: =G58*(1+G19-$C58) -> 322.26196 | I58: =H58*(1+G20-$C58) -> 341.74554 | J58: =B24 -> 333.878 | K58: =F58/J58-1 -> 0.014010882 | L58: =I58/J58-1 -> 0.023564125
A59: Q1 2026 | B59: Q2 2025 | C59: =AVERAGE(G15:G18)-AVERAGE(G19:G22) -> 0.01588552 | D59: =H23*(1+MEDIAN(I15:I22)) -> 320.58032 | E59: =D59*(1+G20-$C59) -> 337.1697 | F59: =E59*(1+G21-$C59) -> 349.77325 | G59: =B22*(1+G19-$C59) -> 313.12636 | H59: =G59*(1+G20-$C59) -> 329.33001 | I59: =H59*(1+G21-$C59) -> 341.64051 | J59: =B25 -> 351.265 | K59: =F59/J59-1 -> -0.0042467909 | L59: =I59/J59-1 -> -0.027399522
A60: Q2 2026 | B60: Q3 2025 | C60: =AVERAGE(G16:G19)-AVERAGE(G20:G23) -> 0.013283084 | D60: =H24*(1+MEDIAN(I16:I23)) -> 337.73357 | E60: =D60*(1+G21-$C60) -> 351.23713 | F60: =E60*(1+G22-$C60) -> 367.43305 | G60: =B23*(1+G20-$C60) -> 334.07619 | H60: =G60*(1+G21-$C60) -> 347.43352 | I60: =H60*(1+G22-$C60) -> 363.45405 | J60: =B26 -> 364.621 | K60: =F60/J60-1 -> 0.0077122542 | L60: =I60/J60-1 -> -0.0032004468
A62: Horizon 4 quarter(s) ahead
A63: Target | B63: Origin | C63: Decel. d_t | D63: B step 1 | E63: B step 2 | F63: B step 3 | G63: B step 4 | H63: Trend step 1 | I63: Trend step 2 | J63: Trend step 3 | K63: Trend step 4 | L63: Actual | M63: B error % | N63: Trend error %
A64: Q3 2024 | B64: Q3 2023 | C64: =AVERAGE(G8:G11)-AVERAGE(G12:G15) -> 0.049038857 | D64: =H16*(1+MEDIAN(I8:I15)) -> 206.59844 | E64: =D64*(1+G13-$C64) -> 213.46532 | F64: =E64*(1+G14-$C64) -> 220.65664 | G64: =F64*(1+G15-$C64) -> 226.806 | H64: =B15*(1+G12-$C64) -> 197.9174 | I64: =H64*(1+G13-$C64) -> 204.49574 | J64: =I64*(1+G14-$C64) -> 211.38489 | K64: =J64*(1+G15-$C64) -> 217.27586 | L64: =B19 -> 251 | M64: =G64/L64-1 -> -0.096390451 | N64: =K64/L64-1 -> -0.13435914
A65: Q4 2024 | B65: Q4 2023 | C65: =AVERAGE(G9:G12)-AVERAGE(G13:G16) -> 0.041219082 | D65: =H17*(1+MEDIAN(I9:I16)) -> 218.95577 | E65: =D65*(1+G14-$C65) -> 228.04423 | F65: =E65*(1+G15-$C65) -> 236.18273 | G65: =F65*(1+G16-$C65) -> 243.15094 | H65: =B16*(1+G13-$C65) -> 210.88703 | I65: =H65*(1+G14-$C65) -> 219.64058 | J65: =I65*(1+G15-$C65) -> 227.47916 | K65: =J65*(1+G16-$C65) -> 234.19059 | L65: =B20 -> 267.976 | M65: =G65/L65-1 -> -0.09263912 | N65: =K65/L65-1 -> -0.12607626
A66: Q1 2025 | B66: Q1 2024 | C66: =AVERAGE(G10:G13)-AVERAGE(G14:G17) -> 0.030766336 | D66: =H18*(1+MEDIAN(I10:I17)) -> 237.84203 | E66: =D66*(1+G15-$C66) -> 248.8163 | F66: =E66*(1+G16-$C66) -> 258.75805 | G66: =F66*(1+G17-$C66) -> 269.11842 | H66: =B17*(1+G14-$C66) -> 228.18401 | I66: =H66*(1+G15-$C66) -> 238.71264 | J66: =I66*(1+G16-$C66) -> 248.25069 | K66: =J66*(1+G17-$C66) -> 258.19036 | L66: =B21 -> 282.25 | M66: =G66/L66-1 -> -0.04652464 | N66: =K66/L66-1 -> -0.085242306
A67: Q2 2025 | B67: Q2 2024 | C67: =AVERAGE(G11:G14)-AVERAGE(G15:G18) -> 0.014936966 | D67: =H19*(1+MEDIAN(I11:I18)) -> 254.68071 | E67: =D67*(1+G16-$C67) -> 268.88822 | F67: =E67*(1+G17-$C67) -> 283.91052 | G67: =F67*(1+G18-$C67) -> 304.79087 | H67: =B18*(1+G15-$C67) -> 250.73757 | I67: =H67*(1+G16-$C67) -> 264.72511 | J67: =I67*(1+G17-$C67) -> 279.51483 | K67: =J67*(1+G18-$C67) -> 300.07189 | L67: =B22 -> 299.014 | M67: =G67/L67-1 -> 0.019319718 | N67: =K67/L67-1 -> 0.00353792
A68: Q3 2025 | B68: Q3 2024 | C68: =AVERAGE(G12:G15)-AVERAGE(G16:G19) -> 0.010997118 | D68: =H20*(1+MEDIAN(I12:I19)) -> 271.09636 | E68: =D68*(1+G17-$C68) -> 287.3101 | F68: =E68*(1+G18-$C68) -> 309.57243 | G68: =F68*(1+G19-$C68) -> 325.69642 | H68: =B19*(1+G16-$C68) -> 265.99108 | I68: =H68*(1+G17-$C68) -> 281.89949 | J68: =I68*(1+G18-$C68) -> 303.74257 | K68: =J68*(1+G19-$C68) -> 319.56292 | L68: =B23 -> 316.855 | M68: =G68/L68-1 -> 0.027903678 | N68: =K68/L68-1 -> 0.00854624
A69: Q4 2025 | B69: Q4 2024 | C69: =AVERAGE(G13:G16)-AVERAGE(G17:G20) -> 0.0056577234 | D69: =H21*(1+MEDIAN(I13:I20)) -> 285.09441 | E69: =D69*(1+G18-$C69) -> 308.70728 | F69: =E69*(1+G19-$C69) -> 326.43452 | G69: =F69*(1+G20-$C69) -> 346.66555 | H69: =B20*(1+G17-$C69) -> 285.43395 | I69: =H69*(1+G18-$C69) -> 309.07494 | J69: =I69*(1+G19-$C69) -> 326.8233 | K69: =J69*(1+G20-$C69) -> 347.07842 | L69: =B24 -> 333.878 | M69: =G69/L69-1 -> 0.038300057 | N69: =K69/L69-1 -> 0.039536645
A70: Q1 2026 | B70: Q1 2025 | C70: =AVERAGE(G14:G17)-AVERAGE(G18:G21) -> 0.0071746428 | D70: =H22*(1+MEDIAN(I14:I21)) -> 302.35062 | E70: =D70*(1+G19-$C70) -> 319.25419 | F70: =E70*(1+G20-$C70) -> 338.55593 | G70: =F70*(1+G21-$C70) -> 354.16042 | H70: =B21*(1+G18-$C70) -> 305.19914 | I70: =H70*(1+G19-$C70) -> 322.26196 | J70: =I70*(1+G20-$C70) -> 341.74554 | K70: =J70*(1+G21-$C70) -> 357.49705 | L70: =B25 -> 351.265 | M70: =G70/L70-1 -> 0.0082428225 | N70: =K70/L70-1 -> 0.017741724
A71: Q2 2026 | B71: Q2 2025 | C71: =AVERAGE(G15:G18)-AVERAGE(G19:G22) -> 0.01588552 | D71: =H23*(1+MEDIAN(I15:I22)) -> 320.58032 | E71: =D71*(1+G20-$C71) -> 337.1697 | F71: =E71*(1+G21-$C71) -> 349.77325 | G71: =F71*(1+G22-$C71) -> 364.99141 | H71: =B22*(1+G19-$C71) -> 313.12636 | I71: =H71*(1+G20-$C71) -> 329.33001 | J71: =I71*(1+G21-$C71) -> 341.64051 | K71: =J71*(1+G22-$C71) -> 356.50482 | L71: =B26 -> 364.621 | M71: =G71/L71-1 -> 0.0010158695 | N71: =K71/L71-1 -> -0.022259226
A73: Summary by horizon (Derived)
A74: Horizon | B74: Test points | C74: B: mean abs. error | D74: B: bias | E74: B: max abs. | F74: Trend: mean abs. error | G74: Trend: bias | H74: Trend: max abs.
A75: 1 | B75: =COUNT(G31:G38) -> 8 | C75: =SUMPRODUCT(ABS(G31:G38))/B75 -> 0.01035725 | D75: =AVERAGE(G31:G38) -> 0.0073551849 | E75: =MAX(MAX(G31:G38),-MIN(G31:G38)) -> 0.014664184 | F75: =SUMPRODUCT(ABS(H31:H38))/B75 -> 0.009496122 | G75: =AVERAGE(H31:H38) -> 0.00092470086 | H75: =MAX(MAX(H31:H38),-MIN(H31:H38)) -> 0.020685108
A76: 2 | B76: =COUNT(I42:I49) -> 8 | C76: =SUMPRODUCT(ABS(I42:I49))/B76 -> 0.010650591 | D76: =AVERAGE(I42:I49) -> 0.0071444617 | E76: =MAX(MAX(I42:I49),-MIN(I42:I49)) -> 0.032417487 | F76: =SUMPRODUCT(ABS(J42:J49))/B76 -> 0.018314953 | G76: =AVERAGE(J42:J49) -> -0.0056370669 | H76: =MAX(MAX(J42:J49),-MIN(J42:J49)) -> 0.048953623
A77: 3 | B77: =COUNT(K53:K60) -> 8 | C77: =SUMPRODUCT(ABS(K53:K60))/B77 -> 0.02385355 | D77: =AVERAGE(K53:K60) -> -0.00056598665 | E77: =MAX(MAX(K53:K60),-MIN(K53:K60)) -> 0.059032954 | F77: =SUMPRODUCT(ABS(L53:L60))/B77 -> 0.034805713 | G77: =AVERAGE(L53:L60) -> -0.017096179 | H77: =MAX(MAX(L53:L60),-MIN(L53:L60)) -> 0.093708516
A78: 4 | B78: =COUNT(M64:M71) -> 8 | C78: =SUMPRODUCT(ABS(M64:M71))/B78 -> 0.041292045 | D78: =AVERAGE(M64:M71) -> -0.017596508 | E78: =MAX(MAX(M64:M71),-MIN(M64:M71)) -> 0.096390451 | F78: =SUMPRODUCT(ABS(N64:N71))/B78 -> 0.054662433 | G78: =AVERAGE(N64:N71) -> -0.0373218 | H78: =MAX(MAX(N64:N71),-MIN(N64:N71)) -> 0.13435914
A80: Accuracy degrades with horizon. Method B mean absolute error: h1 1.04% (bias +0.74%, max 1.47%, n=8); h2 1.07% (bias +0.71%, max 3.24%, n=8); h3 2.39% (bias -0.06%, max 5.90%, n=8); h4 4.13% (bias -1.76%, max 9.64%, n=8). Pure trend: h1 0.95%; h2 1.83%; h3 3.48%; h4 5.47%. Beyond two quarters the bias turns negative (under-forecast) and the worst miss exceeds 5%; Q3-Q4 2027 (h5-h6) are beyond the tested horizon.

Sheet Trigger_History
A1: Trigger history test: how often each Recommendation trigger would have fired, and how many were false alarms
A2: Each trigger fires on the 2nd consecutive quarter its condition holds. Outcome = change in YoY revenue growth over the next 4 quarters: "Confirmed" if growth slowed faster than the Base pace (4 x P1 Base), else "False alarm" (growth recovered to the Base pace or better); "Not evaluable" if 4 later quarters are not yet reported.
A5: Quarter | B5: Revenue (USD m) | C5: Seq. growth | D5: YoY growth | E5: Beat vs guide mid | F5: Customers >$50k | G5: Row ID | H5: Net adds | I5: T1 cond. | J5: T1 fires | K5: T2 cond. | L5: T2 fires | M5: T3 cond. | N5: T3 fires | O5: YoY change next 4q | P5: T1 outcome | Q5: T2 outcome | R5: T3 outcome
A6: Q1 2021 | B6: =Backtest!B5 -> 58.972 | F6: 335 | G6: QA-1405 | P6: =IF(J6=1,IF(ISNUMBER(O6),IF(O6<-4*Assumptions!$C$5/100,"Confirmed","False alarm"),"Not evaluable"),"") | Q6: =IF(L6=1,IF(ISNUMBER(O6),IF(O6<-4*Assumptions!$C$5/100,"Confirmed","False alarm"),"Not evaluable"),"") | R6: =IF(N6=1,IF(ISNUMBER(O6),IF(O6<-4*Assumptions!$C$5/100,"Confirmed","False alarm"),"Not evaluable"),"")
A7: Q2 2021 | B7: =Backtest!B6 -> 70.615 | C7: =B7/B6-1 -> 0.19743268 | F7: 470 | G7: QA-1406 | H7: =F7-F6 -> 135 | M7: =IF(H7<=Assumptions!$D$19,1,0) -> 1 | P7: =IF(J7=1,IF(ISNUMBER(O7),IF(O7<-4*Assumptions!$C$5/100,"Confirmed","False alarm"),"Not evaluable"),"") | Q7: =IF(L7=1,IF(ISNUMBER(O7),IF(O7<-4*Assumptions!$C$5/100,"Confirmed","False alarm"),"Not evaluable"),"") | R7: =IF(N7=1,IF(ISNUMBER(O7),IF(O7<-4*Assumptions!$C$5/100,"Confirmed","False alarm"),"Not evaluable"),"")
A8: Q3 2021 | B8: =Backtest!B7 -> 83.018 | C8: =B8/B7-1 -> 0.17564257 | E8: =Backtest!I7 -> 0.11433557 | F8: 613 | G8: QA-1407 | H8: =F8-F7 -> 143 | K8: =IF(E8<Trigger_History!$E$36,1,0) -> 0 | M8: =IF(H8<=Assumptions!$D$19,1,0) -> 1 | N8: =IF(AND(M8=1,M7=1),1,0) -> 1 | P8: =IF(J8=1,IF(ISNUMBER(O8),IF(O8<-4*Assumptions!$C$5/100,"Confirmed","False alarm"),"Not evaluable"),"") | Q8: =IF(L8=1,IF(ISNUMBER(O8),IF(O8<-4*Assumptions!$C$5/100,"Confirmed","False alarm"),"Not evaluable"),"") | R8: =IF(N8=1,IF(ISNUMBER(O8),IF(O8<-4*Assumptions!$C$5/100,"Confirmed","False alarm"),"Not evaluable"),"") -> Not evaluable
A9: Q4 2021 | B9: =Backtest!B8 -> 95.545 | C9: =B9/B8-1 -> 0.15089499 | E9: =Backtest!I8 -> 0.091942857 | F9: 793 | G9: QA-1408 | H9: =F9-F8 -> 180 | K9: =IF(E9<Trigger_History!$E$36,1,0) -> 0 | L9: =IF(AND(K9=1,K8=1),1,0) -> 0 | M9: =IF(H9<=Assumptions!$D$19,1,0) -> 1 | N9: =IF(AND(M9=1,M8=1),1,0) -> 1 | P9: =IF(J9=1,IF(ISNUMBER(O9),IF(O9<-4*Assumptions!$C$5/100,"Confirmed","False alarm"),"Not evaluable"),"") | Q9: =IF(L9=1,IF(ISNUMBER(O9),IF(O9<-4*Assumptions!$C$5/100,"Confirmed","False alarm"),"Not evaluable"),"") | R9: =IF(N9=1,IF(ISNUMBER(O9),IF(O9<-4*Assumptions!$C$5/100,"Confirmed","False alarm"),"Not evaluable"),"") -> Not evaluable
A10: Q1 2022 | B10: =Backtest!B9 -> 108.497 | C10: =B10/B9-1 -> 0.13555916 | D10: =B10/B6-1 -> 0.83980533 | E10: =Backtest!I9 -> 0.074227723 | F10: 960 | G10: QA-1409 | H10: =F10-F9 -> 167 | K10: =IF(E10<Trigger_History!$E$36,1,0) -> 0 | L10: =IF(AND(K10=1,K9=1),1,0) -> 0 | M10: =IF(H10<=Assumptions!$D$19,1,0) -> 1 | N10: =IF(AND(M10=1,M9=1),1,0) -> 1 | O10: =D14-D10 -> -0.34431698 | P10: =IF(J10=1,IF(ISNUMBER(O10),IF(O10<-4*Assumptions!$C$5/100,"Confirmed","False alarm"),"Not evaluable"),"") | Q10: =IF(L10=1,IF(ISNUMBER(O10),IF(O10<-4*Assumptions!$C$5/100,"Confirmed","False alarm"),"Not evaluable"),"") | R10: =IF(N10=1,IF(ISNUMBER(O10),IF(O10<-4*Assumptions!$C$5/100,"Confirmed","False alarm"),"Not evaluable"),"") -> Confirmed
A11: Q2 2022 | B11: =Backtest!B10 -> 123.718 | C11: =B11/B10-1 -> 0.14028959 | D11: =B11/B7-1 -> 0.75200736 | E11: =Backtest!I10 -> 0.048457627 | F11: 1160 | G11: QA-1410 | H11: =F11-F10 -> 200 | I11: =IF(C11<=C7-Assumptions!$D$5/100,1,0) -> 1 | K11: =IF(E11<Trigger_History!$E$36,1,0) -> 0 | L11: =IF(AND(K11=1,K10=1),1,0) -> 0 | M11: =IF(H11<=Assumptions!$D$19,1,0) -> 0 | N11: =IF(AND(M11=1,M10=1),1,0) -> 0 | O11: =D15-D11 -> -0.33201189 | P11: =IF(J11=1,IF(ISNUMBER(O11),IF(O11<-4*Assumptions!$C$5/100,"Confirmed","False alarm"),"Not evaluable"),"") | Q11: =IF(L11=1,IF(ISNUMBER(O11),IF(O11<-4*Assumptions!$C$5/100,"Confirmed","False alarm"),"Not evaluable"),"") | R11: =IF(N11=1,IF(ISNUMBER(O11),IF(O11<-4*Assumptions!$C$5/100,"Confirmed","False alarm"),"Not evaluable"),"")
A12: Q3 2022 | B12: =Backtest!B11 -> 136.893 | C12: =B12/B11-1 -> 0.10649218 | D12: =B12/B8-1 -> 0.64895565 | E12: =Backtest!I11 -> 0.048988506 | F12: 1323 | G12: QA-1411 | H12: =F12-F11 -> 163 | I12: =IF(C12<=C8-Assumptions!$D$5/100,1,0) -> 1 | J12: =IF(AND(I12=1,I11=1),1,0) -> 1 | K12: =IF(E12<Trigger_History!$E$36,1,0) -> 0 | L12: =IF(AND(K12=1,K11=1),1,0) -> 0 | M12: =IF(H12<=Assumptions!$D$19,1,0) -> 1 | N12: =IF(AND(M12=1,M11=1),1,0) -> 0 | O12: =D16-D12 -> -0.26692735 | P12: =IF(J12=1,IF(ISNUMBER(O12),IF(O12<-4*Assumptions!$C$5/100,"Confirmed","False alarm"),"Not evaluable"),"") -> Confirmed | Q12: =IF(L12=1,IF(ISNUMBER(O12),IF(O12<-4*Assumptions!$C$5/100,"Confirmed","False alarm"),"Not evaluable"),"") | R12: =IF(N12=1,IF(ISNUMBER(O12),IF(O12<-4*Assumptions!$C$5/100,"Confirmed","False alarm"),"Not evaluable"),"")
A13: Q4 2022 | B13: =Backtest!B12 -> 149.921 | C13: =B13/B12-1 -> 0.09516922 | D13: =B13/B9-1 -> 0.56911403 | E13: =Backtest!I12 -> 0.063269504 | F13: 1474 | G13: QA-1412 | H13: =F13-F12 -> 151 | I13: =IF(C13<=C9-Assumptions!$D$5/100,1,0) -> 1 | J13: =IF(AND(I13=1,I12=1),1,0) -> 1 | K13: =IF(E13<Trigger_History!$E$36,1,0) -> 0 | L13: =IF(AND(K13=1,K12=1),1,0) -> 0 | M13: =IF(H13<=Assumptions!$D$19,1,0) -> 1 | N13: =IF(AND(M13=1,M12=1),1,0) -> 1 | O13: =D17-D13 -> -0.21793574 | P13: =IF(J13=1,IF(ISNUMBER(O13),IF(O13<-4*Assumptions!$C$5/100,"Confirmed","False alarm"),"Not evaluable"),"") -> Confirmed | Q13: =IF(L13=1,IF(ISNUMBER(O13),IF(O13<-4*Assumptions!$C$5/100,"Confirmed","False alarm"),"Not evaluable"),"") | R13: =IF(N13=1,IF(ISNUMBER(O13),IF(O13<-4*Assumptions!$C$5/100,"Confirmed","False alarm"),"Not evaluable"),"") -> Confirmed
A14: Q1 2023 | B14: =Backtest!B13 -> 162.256 | C14: =B14/B13-1 -> 0.082276666 | D14: =B14/B10-1 -> 0.49548835 | E14: =Backtest!I13 -> 0.046812903 | F14: 1683 | G14: QA-1413 | H14: =F14-F13 -> 209 | I14: =IF(C14<=C10-Assumptions!$D$5/100,1,0) -> 1 | J14: =IF(AND(I14=1,I13=1),1,0) -> 1 | K14: =IF(E14<Trigger_History!$E$36,1,0) -> 0 | L14: =IF(AND(K14=1,K13=1),1,0) -> 0 | M14: =IF(H14<=Assumptions!$D$19,1,0) -> 0 | N14: =IF(AND(M14=1,M13=1),1,0) -> 0 | O14: =D18-D14 -> -0.15863178 | P14: =IF(J14=1,IF(ISNUMBER(O14),IF(O14<-4*Assumptions!$C$5/100,"Confirmed","False alarm"),"Not evaluable"),"") -> Confirmed | Q14: =IF(L14=1,IF(ISNUMBER(O14),IF(O14<-4*Assumptions!$C$5/100,"Confirmed","False alarm"),"Not evaluable"),"") | R14: =IF(N14=1,IF(ISNUMBER(O14),IF(O14<-4*Assumptions!$C$5/100,"Confirmed","False alarm"),"Not evaluable"),"")
A15: Q2 2023 | B15: =Backtest!B14 -> 175.679 | C15: =B15/B14-1 -> 0.082727295 | D15: =B15/B11-1 -> 0.41999547 | E15: =Backtest!I14 -> 0.03952071 | F15: 1892 | G15: QA-1414 | H15: =F15-F14 -> 209 | I15: =IF(C15<=C11-Assumptions!$D$5/100,1,0) -> 1 | J15: =IF(AND(I15=1,I14=1),1,0) -> 1 | K15: =IF(E15<Trigger_History!$E$36,1,0) -> 0 | L15: =IF(AND(K15=1,K14=1),1,0) -> 0 | M15: =IF(H15<=Assumptions!$D$19,1,0) -> 0 | N15: =IF(AND(M15=1,M14=1),1,0) -> 0 | O15: =D19-D15 -> -0.076032905 | P15: =IF(J15=1,IF(ISNUMBER(O15),IF(O15<-4*Assumptions!$C$5/100,"Confirmed","False alarm"),"Not evaluable"),"") -> Confirmed | Q15: =IF(L15=1,IF(ISNUMBER(O15),IF(O15<-4*Assumptions!$C$5/100,"Confirmed","False alarm"),"Not evaluable"),"") | R15: =IF(N15=1,IF(ISNUMBER(O15),IF(O15<-4*Assumptions!$C$5/100,"Confirmed","False alarm"),"Not evaluable"),"")
A16: Q3 2023 | B16: =Backtest!B15 -> 189.19 | C16: =B16/B15-1 -> 0.076907314 | D16: =B16/B12-1 -> 0.3820283 | E16: =Backtest!I15 -> 0.039505495 | F16: 2077 | G16: QA-1415 | H16: =F16-F15 -> 185 | I16: =IF(C16<=C12-Assumptions!$D$5/100,1,0) -> 1 | J16: =IF(AND(I16=1,I15=1),1,0) -> 1 | K16: =IF(E16<Trigger_History!$E$36,1,0) -> 0 | L16: =IF(AND(K16=1,K15=1),1,0) -> 0 | M16: =IF(H16<=Assumptions!$D$19,1,0) -> 1 | N16: =IF(AND(M16=1,M15=1),1,0) -> 0 | O16: =D20-D16 -> -0.0553197 | P16: =IF(J16=1,IF(ISNUMBER(O16),IF(O16<-4*Assumptions!$C$5/100,"Confirmed","False alarm"),"Not evaluable"),"") -> Confirmed | Q16: =IF(L16=1,IF(ISNUMBER(O16),IF(O16<-4*Assumptions!$C$5/100,"Confirmed","False alarm"),"Not evaluable"),"") | R16: =IF(N16=1,IF(ISNUMBER(O16),IF(O16<-4*Assumptions!$C$5/100,"Confirmed","False alarm"),"Not evaluable"),"")
A17: Q4 2023 | B17: =Backtest!B16 -> 202.57 | C17: =B17/B16-1 -> 0.070722554 | D17: =B17/B13-1 -> 0.35117829 | E17: =Backtest!I16 -> 0.028274112 | F17: 2295 | G17: QA-1416 | H17: =F17-F16 -> 218 | I17: =IF(C17<=C13-Assumptions!$D$5/100,1,0) -> 0 | J17: =IF(AND(I17=1,I16=1),1,0) -> 0 | K17: =IF(E17<Trigger_History!$E$36,1,0) -> 0 | L17: =IF(AND(K17=1,K16=1),1,0) -> 0 | M17: =IF(H17<=Assumptions!$D$19,1,0) -> 0 | N17: =IF(AND(M17=1,M16=1),1,0) -> 0 | O17: =D21-D17 -> -0.028297308 | P17: =IF(J17=1,IF(ISNUMBER(O17),IF(O17<-4*Assumptions!$C$5/100,"Confirmed","False alarm"),"Not evaluable"),"") | Q17: =IF(L17=1,IF(ISNUMBER(O17),IF(O17<-4*Assumptions!$C$5/100,"Confirmed","False alarm"),"Not evaluable"),"") | R17: =IF(N17=1,IF(ISNUMBER(O17),IF(O17<-4*Assumptions!$C$5/100,"Confirmed","False alarm"),"Not evaluable"),"")
A18: Q1 2024 | B18: =Backtest!B17 -> 216.913 | C18: =B18/B17-1 -> 0.070805154 | D18: =B18/B14-1 -> 0.33685657 | E18: =Backtest!I17 -> 0.037861244 | F18: 2491 | G18: QA-1417 | H18: =F18-F17 -> 196 | I18: =IF(C18<=C14-Assumptions!$D$5/100,1,0) -> 0 | J18: =IF(AND(I18=1,I17=1),1,0) -> 0 | K18: =IF(E18<Trigger_History!$E$36,1,0) -> 0 | L18: =IF(AND(K18=1,K17=1),1,0) -> 0 | M18: =IF(H18<=Assumptions!$D$19,1,0) -> 0 | N18: =IF(AND(M18=1,M17=1),1,0) -> 0 | O18: =D22-D18 -> -0.035643644 | P18: =IF(J18=1,IF(ISNUMBER(O18),IF(O18<-4*Assumptions!$C$5/100,"Confirmed","False alarm"),"Not evaluable"),"") | Q18: =IF(L18=1,IF(ISNUMBER(O18),IF(O18<-4*Assumptions!$C$5/100,"Confirmed","False alarm"),"Not evaluable"),"") | R18: =IF(N18=1,IF(ISNUMBER(O18),IF(O18<-4*Assumptions!$C$5/100,"Confirmed","False alarm"),"Not evaluable"),"")
A19: Q2 2024 | B19: =Backtest!B18 -> 236.106 | C19: =B19/B18-1 -> 0.088482479 | D19: =B19/B15-1 -> 0.34396257 | E19: =Backtest!I18 -> 0.035552632 | F19: 2713 | G19: QA-1418 | H19: =F19-F18 -> 222 | I19: =IF(C19<=C15-Assumptions!$D$5/100,1,0) -> 0 | J19: =IF(AND(I19=1,I18=1),1,0) -> 0 | K19: =IF(E19<Trigger_History!$E$36,1,0) -> 0 | L19: =IF(AND(K19=1,K18=1),1,0) -> 0 | M19: =IF(H19<=Assumptions!$D$19,1,0) -> 0 | N19: =IF(AND(M19=1,M18=1),1,0) -> 0 | O19: =D23-D19 -> -0.077522918 | P19: =IF(J19=1,IF(ISNUMBER(O19),IF(O19<-4*Assumptions!$C$5/100,"Confirmed","False alarm"),"Not evaluable"),"") | Q19: =IF(L19=1,IF(ISNUMBER(O19),IF(O19<-4*Assumptions!$C$5/100,"Confirmed","False alarm"),"Not evaluable"),"") | R19: =IF(N19=1,IF(ISNUMBER(O19),IF(O19<-4*Assumptions!$C$5/100,"Confirmed","False alarm"),"Not evaluable"),"")
A20: Q3 2024 | B20: =Backtest!B19 -> 251 | C20: =B20/B19-1 -> 0.063081836 | D20: =B20/B16-1 -> 0.3267086 | E20: =Backtest!I19 -> 0.024489796 | F20: 2907 | G20: QA-1419 | H20: =F20-F19 -> 194 | I20: =IF(C20<=C16-Assumptions!$D$5/100,1,0) -> 0 | J20: =IF(AND(I20=1,I19=1),1,0) -> 0 | K20: =IF(E20<Trigger_History!$E$36,1,0) -> 0 | L20: =IF(AND(K20=1,K19=1),1,0) -> 0 | M20: =IF(H20<=Assumptions!$D$19,1,0) -> 1 | N20: =IF(AND(M20=1,M19=1),1,0) -> 0 | O20: =D24-D20 -> -0.064338082 | P20: =IF(J20=1,IF(ISNUMBER(O20),IF(O20<-4*Assumptions!$C$5/100,"Confirmed","False alarm"),"Not evaluable"),"") | Q20: =IF(L20=1,IF(ISNUMBER(O20),IF(O20<-4*Assumptions!$C$5/100,"Confirmed","False alarm"),"Not evaluable"),"") | R20: =IF(N20=1,IF(ISNUMBER(O20),IF(O20<-4*Assumptions!$C$5/100,"Confirmed","False alarm"),"Not evaluable"),"")
A21: Q4 2024 | B21: =Backtest!B20 -> 267.976 | C21: =B21/B20-1 -> 0.067633466 | D21: =B21/B17-1 -> 0.32288098 | E21: =Backtest!I20 -> 0.026727969 | F21: 3201 | G21: QA-1420 | H21: =F21-F20 -> 294 | I21: =IF(C21<=C17-Assumptions!$D$5/100,1,0) -> 0 | J21: =IF(AND(I21=1,I20=1),1,0) -> 0 | K21: =IF(E21<Trigger_History!$E$36,1,0) -> 0 | L21: =IF(AND(K21=1,K20=1),1,0) -> 0 | M21: =IF(H21<=Assumptions!$D$19,1,0) -> 0 | N21: =IF(AND(M21=1,M20=1),1,0) -> 0 | O21: =D25-D21 -> -0.076955971 | P21: =IF(J21=1,IF(ISNUMBER(O21),IF(O21<-4*Assumptions!$C$5/100,"Confirmed","False alarm"),"Not evaluable"),"") | Q21: =IF(L21=1,IF(ISNUMBER(O21),IF(O21<-4*Assumptions!$C$5/100,"Confirmed","False alarm"),"Not evaluable"),"") | R21: =IF(N21=1,IF(ISNUMBER(O21),IF(O21<-4*Assumptions!$C$5/100,"Confirmed","False alarm"),"Not evaluable"),"")
A22: Q1 2025 | B22: =Backtest!B21 -> 282.25 | C22: =B22/B21-1 -> 0.053265964 | D22: =B22/B18-1 -> 0.30121293 | E22: =Backtest!I21 -> 0.026363636 | F22: 3444 | G22: QA-1421 | H22: =F22-F21 -> 243 | I22: =IF(C22<=C18-Assumptions!$D$5/100,1,0) -> 0 | J22: =IF(AND(I22=1,I21=1),1,0) -> 0 | K22: =IF(E22<Trigger_History!$E$36,1,0) -> 0 | L22: =IF(AND(K22=1,K21=1),1,0) -> 0 | M22: =IF(H22<=Assumptions!$D$19,1,0) -> 0 | N22: =IF(AND(M22=1,M21=1),1,0) -> 0 | O22: =D26-D22 -> -0.056695657 | P22: =IF(J22=1,IF(ISNUMBER(O22),IF(O22<-4*Assumptions!$C$5/100,"Confirmed","False alarm"),"Not evaluable"),"") | Q22: =IF(L22=1,IF(ISNUMBER(O22),IF(O22<-4*Assumptions!$C$5/100,"Confirmed","False alarm"),"Not evaluable"),"") | R22: =IF(N22=1,IF(ISNUMBER(O22),IF(O22<-4*Assumptions!$C$5/100,"Confirmed","False alarm"),"Not evaluable"),"")
A23: Q2 2025 | B23: =Backtest!B22 -> 299.014 | C23: =B23/B22-1 -> 0.059394154 | D23: =B23/B19-1 -> 0.26643965 | E23: =Backtest!I22 -> 0.020525597 | F23: 3702 | G23: QA-1422 | H23: =F23-F22 -> 258 | I23: =IF(C23<=C19-Assumptions!$D$5/100,1,0) -> 1 | J23: =IF(AND(I23=1,I22=1),1,0) -> 0 | K23: =IF(E23<Trigger_History!$E$36,1,0) -> 0 | L23: =IF(AND(K23=1,K22=1),1,0) -> 0 | M23: =IF(H23<=Assumptions!$D$19,1,0) -> 0 | N23: =IF(AND(M23=1,M22=1),1,0) -> 0 | O23: =D27-D23 -> -0.047028519 | P23: =IF(J23=1,IF(ISNUMBER(O23),IF(O23<-4*Assumptions!$C$5/100,"Confirmed","False alarm"),"Not evaluable"),"") | Q23: =IF(L23=1,IF(ISNUMBER(O23),IF(O23<-4*Assumptions!$C$5/100,"Confirmed","False alarm"),"Not evaluable"),"") | R23: =IF(N23=1,IF(ISNUMBER(O23),IF(O23<-4*Assumptions!$C$5/100,"Confirmed","False alarm"),"Not evaluable"),"")
A24: Q3 2025 | B24: =Backtest!B23 -> 316.855 | C24: =B24/B23-1 -> 0.059666103 | D24: =B24/B20-1 -> 0.26237052 | E24: =Backtest!I23 -> 0.015560897 | F24: 3993 | G24: QA-1423 | H24: =F24-F23 -> 291 | I24: =IF(C24<=C20-Assumptions!$D$5/100,1,0) -> 0 | J24: =IF(AND(I24=1,I23=1),1,0) -> 0 | K24: =IF(E24<Trigger_History!$E$36,1,0) -> 0 | L24: =IF(AND(K24=1,K23=1),1,0) -> 0 | M24: =IF(H24<=Assumptions!$D$19,1,0) -> 0 | N24: =IF(AND(M24=1,M23=1),1,0) -> 0 | P24: =IF(J24=1,IF(ISNUMBER(O24),IF(O24<-4*Assumptions!$C$5/100,"Confirmed","False alarm"),"Not evaluable"),"") | Q24: =IF(L24=1,IF(ISNUMBER(O24),IF(O24<-4*Assumptions!$C$5/100,"Confirmed","False alarm"),"Not evaluable"),"") | R24: =IF(N24=1,IF(ISNUMBER(O24),IF(O24<-4*Assumptions!$C$5/100,"Confirmed","False alarm"),"Not evaluable"),"")
A25: Q4 2025 | B25: =Backtest!B24 -> 333.878 | C25: =B25/B24-1 -> 0.05372489 | D25: =B25/B21-1 -> 0.24592501 | E25: =Backtest!I24 -> 0.014826748 | F25: 4281 | G25: QA-1424 | H25: =F25-F24 -> 288 | I25: =IF(C25<=C21-Assumptions!$D$5/100,1,0) -> 0 | J25: =IF(AND(I25=1,I24=1),1,0) -> 0 | K25: =IF(E25<Trigger_History!$E$36,1,0) -> 0 | L25: =IF(AND(K25=1,K24=1),1,0) -> 0 | M25: =IF(H25<=Assumptions!$D$19,1,0) -> 0 | N25: =IF(AND(M25=1,M24=1),1,0) -> 0 | P25: =IF(J25=1,IF(ISNUMBER(O25),IF(O25<-4*Assumptions!$C$5/100,"Confirmed","False alarm"),"Not evaluable"),"") | Q25: =IF(L25=1,IF(ISNUMBER(O25),IF(O25<-4*Assumptions!$C$5/100,"Confirmed","False alarm"),"Not evaluable"),"") | R25: =IF(N25=1,IF(ISNUMBER(O25),IF(O25<-4*Assumptions!$C$5/100,"Confirmed","False alarm"),"Not evaluable"),"")
A26: Q1 2026 | B26: =Backtest!B25 -> 351.265 | C26: =B26/B25-1 -> 0.052075908 | D26: =B26/B22-1 -> 0.24451727 | E26: =Backtest!I25 -> 0.036179941 | F26: 4547 | G26: QA-1425 | H26: =F26-F25 -> 266 | I26: =IF(C26<=C22-Assumptions!$D$5/100,1,0) -> 0 | J26: =IF(AND(I26=1,I25=1),1,0) -> 0 | K26: =IF(E26<Trigger_History!$E$36,1,0) -> 0 | L26: =IF(AND(K26=1,K25=1),1,0) -> 0 | M26: =IF(H26<=Assumptions!$D$19,1,0) -> 0 | N26: =IF(AND(M26=1,M25=1),1,0) -> 0 | P26: =IF(J26=1,IF(ISNUMBER(O26),IF(O26<-4*Assumptions!$C$5/100,"Confirmed","False alarm"),"Not evaluable"),"") | Q26: =IF(L26=1,IF(ISNUMBER(O26),IF(O26<-4*Assumptions!$C$5/100,"Confirmed","False alarm"),"Not evaluable"),"") | R26: =IF(N26=1,IF(ISNUMBER(O26),IF(O26<-4*Assumptions!$C$5/100,"Confirmed","False alarm"),"Not evaluable"),"")
A27: Q2 2026 | B27: =Backtest!B26 -> 364.621 | C27: =B27/B26-1 -> 0.038022576 | D27: =B27/B23-1 -> 0.21941113 | E27: =Backtest!I26 -> 0.027101408 | F27: 4834 | G27: QA-1426 | H27: =F27-F26 -> 287 | I27: =IF(C27<=C23-Assumptions!$D$5/100,1,0) -> 0 | J27: =IF(AND(I27=1,I26=1),1,0) -> 0 | K27: =IF(E27<Trigger_History!$E$36,1,0) -> 0 | L27: =IF(AND(K27=1,K26=1),1,0) -> 0 | M27: =IF(H27<=Assumptions!$D$19,1,0) -> 0 | N27: =IF(AND(M27=1,M26=1),1,0) -> 0 | P27: =IF(J27=1,IF(ISNUMBER(O27),IF(O27<-4*Assumptions!$C$5/100,"Confirmed","False alarm"),"Not evaluable"),"") | Q27: =IF(L27=1,IF(ISNUMBER(O27),IF(O27<-4*Assumptions!$C$5/100,"Confirmed","False alarm"),"Not evaluable"),"") | R27: =IF(N27=1,IF(ISNUMBER(O27),IF(O27<-4*Assumptions!$C$5/100,"Confirmed","False alarm"),"Not evaluable"),"")
A29: Summary: last 20 quarters (Q3 2021 - Q2 2026); fires are counted only where the condition can be computed
A30: Trigger | B30: Evaluable quarters | C30: Fires | D30: Fire rate | E30: Confirmed | F30: False alarms | G30: Not evaluable | H30: Fires, last 8 quarters | I30: Flag
A31: T1 seq. growth <= same quarter last year - P1 Downside | B31: =COUNT(J8:J27) -> 16 | C31: =SUM(J8:J27) -> 5 | D31: =IF(B31>0,C31/B31,0) -> 0.3125 | E31: =COUNTIF(P8:P27,"Confirmed") -> 5 | F31: =COUNTIF(P8:P27,"False alarm") -> 0 | G31: =COUNTIF(P8:P27,"Not evaluable") -> 0 | H31: =SUM(J20:J27) -> 0 | I31: =IF(D31>Assumptions!$C$20,"FIRES TOO OFTEN",IF(C31=0,"NEVER FIRED: untested","OK")) -> FIRES TOO OFTEN
A32: T2 beat < last-8 minimum | B32: =COUNT(L8:L27) -> 19 | C32: =SUM(L8:L27) -> 0 | D32: =IF(B32>0,C32/B32,0) -> 0 | E32: =COUNTIF(Q8:Q27,"Confirmed") -> 0 | F32: =COUNTIF(Q8:Q27,"False alarm") -> 0 | G32: =COUNTIF(Q8:Q27,"Not evaluable") -> 0 | H32: =SUM(L20:L27) -> 0 | I32: =IF(D32>Assumptions!$C$20,"FIRES TOO OFTEN",IF(C32=0,"NEVER FIRED: untested","OK")) -> NEVER FIRED: untested
A33: T3 net adds <= last-8 minimum | B33: =COUNT(N8:N27) -> 20 | C33: =SUM(N8:N27) -> 4 | D33: =IF(B33>0,C33/B33,0) -> 0.2 | E33: =COUNTIF(R8:R27,"Confirmed") -> 2 | F33: =COUNTIF(R8:R27,"False alarm") -> 0 | G33: =COUNTIF(R8:R27,"Not evaluable") -> 2 | H33: =SUM(N20:N27) -> 0 | I33: =IF(D33>Assumptions!$C$20,"FIRES TOO OFTEN",IF(C33=0,"NEVER FIRED: untested","OK")) -> OK
A35: Derivation of thresholds (last 8 quarters)
A36: Revenue beat vs guidance midpoint: MIN | E36: =MIN(E20:E27) -> 0.014826748 | F36: Derived = T2 threshold (1.48%)
A37: Revenue beat vs guidance midpoint: MEDIAN | E37: =MEDIAN(E20:E27) -> 0.025426716 | F37: Derived
A38: Net adds of customers >$50k: MIN | H38: =MIN(H20:H27) -> 194 | I38: Derived = T3 threshold (194) = P14 Downside
A39: Net adds of customers >$50k: MEDIAN | H39: =MEDIAN(H20:H27) -> 276.5 | I39: Derived = P14 Base
A41: T1 fired in 5 of 16 evaluable quarters (31%): all in Q3 2022-Q3 2023, during the post-IPO normalization from ~80% to ~35% YoY growth; 5 confirmed, 0 false alarms, 0 fires in the last 8 quarters. Over the full window it FIRES TOO OFTEN; in the current regime it has not fired. T2 never fired (19 evaluable quarters): the threshold is the last-8 minimum, so it is untested. T3 fired 4 times (20%), all in 2021-2022 when the >$50k customer base was at most a third of today's: 2 confirmed, 2 not evaluable, 0 false alarms, 0 fires in the last 8 quarters. Caveat: an absolute net-adds threshold becomes easier to clear as the base grows; the history contains no slowdown comparable to the Downside in the current regime.

Sheet Method_Changes
A1: Method changes and owner rulings applied (vs PHASE3_DESIGN.md and the Phase 3a audit proposals)
A3: # | B3: Ruling / change | C3: What was applied | D3: Reason | E3: Date
A4: R1 | B4: Revenue method B | C4: Guidance for quarters it covers (Q3 2026 locked call; Q4 2026 via FY guide), then same-quarter sequential growth less annual deceleration. NDR shown only as an indicator. | D4: Backtest: method A biased high in 8/8 quarters. | E4: 2026-10-28
A5: R2 | B5: Downside definition | C5: Deceleration 2.6 pp/yr (Base 1.3); opex dollars held at Base before response; NDR toward 105% shown as an indicator only. | D5: Owner ruling. | E5: 2026-10-28
A6: R3 | B6: FCF | C6: Annual conversion anchored to the FY2026 guide (Base 1.23x, Downside 1.0x); Q3/Q4 2026 LOW CONFIDENCE tied to the FY guide; severance $32.5M (Downside $35M) split evenly Q3/Q4 2026, UNRESOLVED whether in the guide. | D6: Owner ruling. | E6: 2026-10-28
A7: R4 | B7: Headcount | C7: Implied-headcount memo removed; hiring stated in dollars; ~20% reduction recorded as a fact with no quarterly path. | D7: Owner ruling. | E7: 2026-10-28
A8: R5 | B8: Q3 2026 | C8: Base = locked call MID; sensitivity with Q3 at the locked call LOW and its 2027 effect (Scenarios). | D8: Owner ruling. | E8: 2026-10-28
A9: R6 | B9: Restructuring savings and interest income | C9: Not modeled as separate drivers; documented in README. | D9: Owner ruling; no disclosed savings amount; interest income not in source book. | E9: 2026-10-28
A10: R7 | B10: Backtest horizons | C10: Extended to 2-, 3- and 4-quarters ahead (8 test points each). | D10: Owner ruling. | E10: 2026-10-28
A11: D1 | B11: Design decision: Downside Q3 2026 | C11: Downside Q3 2026 = locked call MID (audit had proposed LOW); Downside diverges from Q4 2026. Q3 at LOW is the separate sensitivity (R5). | D11: Keeps the Q3 effect and the deceleration effect separate. | E11: 2026-10-28
A12: D2 | B12: Design decision: Q3 2026 gross margin | C12: Q3 2026 gross margin uses the Base step in all cases so Q3 op. income equals the locked call. | D12: Q3 is locked. | E12: 2026-10-28
A13: D3 | B13: Design decision: GAAP restructuring | C13: H2 2026 GAAP restructuring charges Assumed at $50M net (midpoint of $45-55M), split evenly Q3/Q4. | D13: Needed for the GAAP bridge. | E13: 2026-10-28
A14: C1 | B14: Cash questions (item 1) | C14: Quoted the adjusted FCF definition and reconciliation (no severance add-back) and the Jul 22 6-K exclusion of restructuring from the FY2026 outlook; severance deducted once (not double-counted); reported-basis FCF memo added; H1 2026 cash + securities bridge built from the primary cash flow statement (Cash_Bridge); Other cash flows (P12) now Assumed at the H1 2026 run-rate instead of nil; ending cash labeled before unmodeled items and removed as a headline. | D14: Owner request; resolves the UNRESOLVED flag from the first draft. | E14: 2026-10-29
... A22: C8 | B22: Undisclosed values (item 8) | C22: Marketable securities (and the Q1 2026 restructuring line) show "Not disclosed" instead of blank; liquidity is "n/a" where securities are not disclosed; N() blank-to-zero conversions removed; Q1 2026 restructuring now Derived as H1 less Q2; Checks row added. | D22: Owner request. | E22: 2026-10-29

Sheet Checks
A1: Checks: input tie-outs (source book, analysis, locked call) and internal model checks
A3: Check ID | B3: Type | C3: Cell / item | D3: Reference | E3: Value | F3: Expected | G3: Difference | H3: Status
A4: PL-0001 | B4: Source book QA | C4: Historical_Drivers!C6 | D4: QA-0015 | E4: =Historical_Drivers!C6 -> 162256 | F4: 162256 | G4: =E4-F4 -> 0 | H4: =IF(ABS(G4)<=0.000001,"PASS","FAIL") -> PASS
A5: PL-0002 | B5: Source book QA | C5: Historical_Drivers!D6 | D5: QA-0016 | E5: =Historical_Drivers!D6 -> 175679 | F5: 175679 | G5: =E5-F5 -> 0 | H5: =IF(ABS(G5)<=0.000001,"PASS","FAIL") -> PASS
A6: PL-0003 | B6: Source book QA | C6: Historical_Drivers!E6 | D6: QA-0018 | E6: =Historical_Drivers!E6 -> 189190 | F6: 189190 | G6: =E6-F6 -> 0 | H6: =IF(ABS(G6)<=0.000001,"PASS","FAIL") -> PASS
A7: PL-0004 | B7: Source book QA | C7: Historical_Drivers!F6 | D7: QA-0020 | E7: =Historical_Drivers!F6 -> 202570 | F7: 202570 | G7: =E7-F7 -> 0 | H7: =IF(ABS(G7)<=0.000001,"PASS","FAIL") -> PASS
A8: PL-0005 | B8: Source book QA | C8: Historical_Drivers!G6 | D8: QA-0022 | E8: =Historical_Drivers!G6 -> 216913 | F8: 216913 | G8: =E8-F8 -> 0 | H8: =IF(ABS(G8)<=0.000001,"PASS","FAIL") -> PASS
A9: PL-0006 | B9: Source book QA | C9: Historical_Drivers!H6 | D9: QA-0023 | E9: =Historical_Drivers!H6 -> 236106 | F9: 236106 | G9: =E9-F9 -> 0 | H9: =IF(ABS(G9)<=0.000001,"PASS","FAIL") -> PASS
A10: PL-0007 | B10: Source book QA | C10: Historical_Drivers!I6 | D10: QA-0025 | E10: =Historical_Drivers!I6 -> 251000 | F10: 251000 | G10: =E10-F10 -> 0 | H10: =IF(ABS(G10)<=0.000001,"PASS","FAIL") -> PASS
A11: PL-0008 | B11: Source book QA | C11: Historical_Drivers!J6 | D11: QA-0027 | E11: =Historical_Drivers!J6 -> 267976 | F11: 267976 | G11: =E11-F11 -> 0 | H11: =IF(ABS(G11)<=0.000001,"PASS","FAIL") -> PASS
A12: PL-0009 | B12: Source book QA | C12: Historical_Drivers!K6 | D12: QA-0029 | E12: =Historical_Drivers!K6 -> 282250 | F12: 282250 | G12: =E12-F12 -> 0 | H12: =IF(ABS(G12)<=0.000001,"PASS","FAIL") -> PASS
A13: PL-0010 | B13: Source book QA | C13: Historical_Drivers!L6 | D13: QA-0030 | E13: =Historical_Drivers!L6 -> 299014 | F13: 299014 | G13: =E13-F13 -> 0 | H13: =IF(ABS(G13)<=0.000001,"PASS","FAIL") -> PASS
A14: PL-0011 | B14: Source book QA | C14: Historical_Drivers!M6 | D14: QA-0032 | E14: =Historical_Drivers!M6 -> 316855 | F14: 316855 | G14: =E14-F14 -> 0 | H14: =IF(ABS(G14)<=0.000001,"PASS","FAIL") -> PASS
A15: PL-0012 | B15: Source book QA | C15: Historical_Drivers!N6 | D15: QA-0034 | E15: =Historical_Drivers!N6 -> 333878 | F15: 333878 | G15: =E15-F15 -> 0 | H15: =IF(ABS(G15)<=0.000001,"PASS","FAIL") -> PASS
A16: PL-0013 | B16: Source book QA | C16: Historical_Drivers!O6 | D16: QA-0036 | E16: =Historical_Drivers!O6 -> 351265 | F16: 351265 | G16: =E16-F16 -> 0 | H16: =IF(ABS(G16)<=0.000001,"PASS","FAIL") -> PASS
A17: PL-0014 | B17: Source book QA | C17: Historical_Drivers!P6 | D17: QA-0037 | E17: =Historical_Drivers!P6 -> 364621 | F17: 364621 | G17: =E17-F17 -> 0 | H17: =IF(ABS(G17)<=0.000001,"PASS","FAIL") -> PASS
A18: PL-0015 | B18: Source book QA | C18: Historical_Drivers!C8 | D18: QA-0489 | E18: =Historical_Drivers!C8 -> 146719 | F18: 146719 | G18: =E18-F18 -> 0 | H18: =IF(ABS(G18)<=0.000001,"PASS","FAIL") -> PASS
A19: PL-0016 | B19: Source book QA | C19: Historical_Drivers!D8 | D19: QA-0490 | E19: =Historical_Drivers!D8 -> 158008 | F19: 158008 | G19: =E19-F19 -> 0 | H19: =IF(ABS(G19)<=0.000001,"PASS","FAIL") -> PASS
A20: PL-0017 | B20: Source book QA | C20: Historical_Drivers!E8 | D20: QA-0492 | E20: =Historical_Drivers!E8 -> 168866 | F20: 168866 | G20: =E20-F20 -> 0 | H20: =IF(ABS(G20)<=0.000001,"PASS","FAIL") -> PASS
A21: PL-0018 | B21: Source book QA | C21: Historical_Drivers!F8 | D21: QA-0494 | E21: =Historical_Drivers!F8 -> 181764 | F21: 181764 | G21: =E21-F21 -> 0 | H21: =IF(ABS(G21)<=0.000001,"PASS","FAIL") -> PASS
A22: PL-0019 | B22: Source book QA | C22: Historical_Drivers!G8 | D22: QA-0496 | E22: =Historical_Drivers!G8 -> 194703 | F22: 194703 | G22: =E22-F22 -> 0 | H22: =IF(ABS(G22)<=0.000001,"PASS","FAIL") -> PASS
A23: PL-0020 | B23: Source book QA | C23: Historical_Drivers!H8 | D23: QA-0497 | E23: =Historical_Drivers!H8 -> 214215 | F23: 214215 | G23: =E23-F23 -> 0 | H23: =IF(ABS(G23)<=0.000001,"PASS","FAIL") -> PASS
A24: PL-0021 | B24: Source book QA | C24: Historical_Drivers!I8 | D24: QA-0499 | E24: =Historical_Drivers!I8 -> 226909 | F24: 226909 | G24: =E24-F24 -> 0 | H24: =IF(ABS(G24)<=0.000001,"PASS","FAIL") -> PASS
A25: PL-0022 | B25: Source book QA | C25: Historical_Drivers!J8 | D25: QA-0501 | E25: =Historical_Drivers!J8 -> 239080 | F25: 239080 | G25: =E25-F25 -> 0 | H25: =IF(ABS(G25)<=0.000001,"PASS","FAIL") -> PASS
A26: PL-0023 | B26: Source book QA | C26: Historical_Drivers!K8 | D26: QA-0503 | E26: =Historical_Drivers!K8 -> 254579 | F26: 254579 | G26: =E26-F26 -> 0 | H26: =IF(ABS(G26)<=0.000001,"PASS","FAIL") -> PASS
A27: PL-0024 | B27: Source book QA | C27: Historical_Drivers!L8 | D27: QA-0504 | E27: =Historical_Drivers!L8 -> 270113 | F27: 270113 | G27: =E27-F27 -> 0 | H27: =IF(ABS(G27)<=0.000001,"PASS","FAIL") -> PASS
A28: PL-0025 | B28: Source book QA | C28: Historical_Drivers!M8 | D28: QA-0506 | E28: =Historical_Drivers!M8 -> 284031 | F28: 284031 | G28: =E28-F28 -> 0 | H28: =IF(ABS(G28)<=0.000001,"PASS","FAIL") -> PASS
A29: PL-0026 | B29: Source book QA | C29: Historical_Drivers!N8 | D29: QA-0508 | E29: =Historical_Drivers!N8 -> 298736 | F29: 298736 | G29: =E29-F29 -> 0 | H29: =IF(ABS(G29)<=0.000001,"PASS","FAIL") -> PASS
A30: PL-0027 | B30: Source book QA | C30: Historical_Drivers!O8 | D30: QA-0510 | E30: =Historical_Drivers!O8 -> 314190 | F30: 314190 | G30: =E30-F30 -> 0 | H30: =IF(ABS(G30)<=0.000001,"PASS","FAIL") -> PASS
A31: PL-0028 | B31: Source book QA | C31: Historical_Drivers!P8 | D31: QA-0511 | E31: =Historical_Drivers!P8 -> 324222 | F31: 324222 | G31: =E31-F31 -> 0 | H31: =IF(ABS(G31)<=0.000001,"PASS","FAIL") -> PASS
A32: PL-0029 | B32: Source book QA | C32: Historical_Drivers!C10 | D32: QA-0565 | E32: =Historical_Drivers!C10 -> 28519 | F32: 28519 | G32: =E32-F32 -> 0 | H32: =IF(ABS(G32)<=0.000001,"PASS","FAIL") -> PASS
A33: PL-0030 | B33: Source book QA | C33: Historical_Drivers!D10 | D33: QA-0566 | E33: =Historical_Drivers!D10 -> 27908 | F33: 27908 | G33: =E33-F33 -> 0 | H33: =IF(ABS(G33)<=0.000001,"PASS","FAIL") -> PASS
A34: PL-0031 | B34: Source book QA | C34: Historical_Drivers!E10 | D34: QA-0568 | E34: =Historical_Drivers!E10 -> 28051 | F34: 28051 | G34: =E34-F34 -> 0 | H34: =IF(ABS(G34)<=0.000001,"PASS","FAIL") -> PASS
A35: PL-0032 | B35: Source book QA | C35: Historical_Drivers!F10 | D35: QA-0570 | E35: =Historical_Drivers!F10 -> 33285 | F35: 33285 | G35: =E35-F35 -> 0 | H35: =IF(ABS(G35)<=0.000001,"PASS","FAIL") -> PASS
A36: PL-0033 | B36: Source book QA | C36: Historical_Drivers!G10 | D36: QA-0572 | E36: =Historical_Drivers!G10 -> 34797 | F36: 34797 | G36: =E36-F36 -> 0 | H36: =IF(ABS(G36)<=0.000001,"PASS","FAIL") -> PASS
A37: PL-0034 | B37: Source book QA | C37: Historical_Drivers!H10 | D37: QA-0573 | E37: =Historical_Drivers!H10 -> 36878 | F37: 36878 | G37: =E37-F37 -> 0 | H37: =IF(ABS(G37)<=0.000001,"PASS","FAIL") -> PASS
A38: PL-0035 | B38: Source book QA | C38: Historical_Drivers!I10 | D38: QA-0575 | E38: =Historical_Drivers!I10 -> 42973 | F38: 42973 | G38: =E38-F38 -> 0 | H38: =IF(ABS(G38)<=0.000001,"PASS","FAIL") -> PASS
A39: PL-0036 | B39: Source book QA | C39: Historical_Drivers!J10 | D39: QA-0577 | E39: =Historical_Drivers!J10 -> 48066 | F39: 48066 | G39: =E39-F39 -> 0 | H39: =IF(ABS(G39)<=0.000001,"PASS","FAIL") -> PASS
A40: PL-0037 | B40: Source book QA | C40: Historical_Drivers!K10 | D40: QA-0579 | E40: =Historical_Drivers!K10 -> 53844 | F40: 53844 | G40: =E40-F40 -> 0 | H40: =IF(ABS(G40)<=0.000001,"PASS","FAIL") -> PASS
A41: PL-0038 | B41: Source book QA | C41: Historical_Drivers!L10 | D41: QA-0580 | E41: =Historical_Drivers!L10 -> 59233 | F41: 59233 | G41: =E41-F41 -> 0 | H41: =IF(ABS(G41)<=0.000001,"PASS","FAIL") -> PASS
A42: PL-0039 | B42: Source book QA | C42: Historical_Drivers!M10 | D42: QA-0582 | E42: =Historical_Drivers!M10 -> 57772 | F42: 57772 | G42: =E42-F42 -> 0 | H42: =IF(ABS(G42)<=0.000001,"PASS","FAIL") -> PASS
A43: PL-0040 | B43: Source book QA | C43: Historical_Drivers!N10 | D43: QA-0584 | E43: =Historical_Drivers!N10 -> 67700 | F43: 67700 | G43: =E43-F43 -> 0 | H43: =IF(ABS(G43)<=0.000001,"PASS","FAIL") -> PASS
A44: PL-0041 | B44: Source book QA | C44: Historical_Drivers!O10 | D44: QA-0586 | E44: =Historical_Drivers!O10 -> 78413 | F44: 78413 | G44: =E44-F44 -> 0 | H44: =IF(ABS(G44)<=0.000001,"PASS","FAIL") -> PASS
A45: PL-0042 | B45: Source book QA | C45: Historical_Drivers!P10 | D45: QA-0587 | E45: =Historical_Drivers!P10 -> 83003 | F45: 83003 | G45: =E45-F45 -> 0 | H45: =IF(ABS(G45)<=0.000001,"PASS","FAIL") -> PASS
A46: PL-0043 | B46: Source book QA | C46: Historical_Drivers!C12 | D46: QA-0603 | E46: =Historical_Drivers!C12 -> 102652 | F46: 102652 | G46: =E46-F46 -> 0 | H46: =IF(ABS(G46)<=0.000001,"PASS","FAIL") -> PASS
A47: PL-0044 | B47: Source book QA | C47: Historical_Drivers!D12 | D47: QA-0604 | E47: =Historical_Drivers!D12 -> 98831 | F47: 98831 | G47: =E47-F47 -> 0 | H47: =IF(ABS(G47)<=0.000001,"PASS","FAIL") -> PASS
A48: PL-0045 | B48: Source book QA | C48: Historical_Drivers!E12 | D48: QA-0606 | E48: =Historical_Drivers!E12 -> 101504 | F48: 101504 | G48: =E48-F48 -> 0 | H48: =IF(ABS(G48)<=0.000001,"PASS","FAIL") -> PASS
A49: PL-0046 | B49: Source book QA | C49: Historical_Drivers!F12 | D49: QA-0608 | E49: =Historical_Drivers!F12 -> 110020 | F49: 110020 | G49: =E49-F49 -> 0 | H49: =IF(ABS(G49)<=0.000001,"PASS","FAIL") -> PASS
A50: PL-0047 | B50: Source book QA | C50: Historical_Drivers!G12 | D50: QA-0610 | E50: =Historical_Drivers!G12 -> 120806 | F50: 120806 | G50: =E50-F50 -> 0 | H50: =IF(ABS(G50)<=0.000001,"PASS","FAIL") -> PASS
A51: PL-0048 | B51: Source book QA | C51: Historical_Drivers!H12 | D51: QA-0611 | E51: =Historical_Drivers!H12 -> 120738 | F51: 120738 | G51: =E51-F51 -> 0 | H51: =IF(ABS(G51)<=0.000001,"PASS","FAIL") -> PASS
A52: PL-0049 | B52: Source book QA | C52: Historical_Drivers!I12 | D52: QA-0613 | E52: =Historical_Drivers!I12 -> 130339 | F52: 130339 | G52: =E52-F52 -> 0 | H52: =IF(ABS(G52)<=0.000001,"PASS","FAIL") -> PASS
A53: PL-0050 | B53: Source book QA | C53: Historical_Drivers!J12 | D53: QA-0615 | E53: =Historical_Drivers!J12 -> 127791 | F53: 127791 | G53: =E53-F53 -> 0 | H53: =IF(ABS(G53)<=0.000001,"PASS","FAIL") -> PASS
A54: PL-0051 | B54: Source book QA | C54: Historical_Drivers!K12 | D54: QA-0617 | E54: =Historical_Drivers!K12 -> 135882 | F54: 135882 | G54: =E54-F54 -> 0 | H54: =IF(ABS(G54)<=0.000001,"PASS","FAIL") -> PASS
A55: PL-0052 | B55: Source book QA | C55: Historical_Drivers!L12 | D55: QA-0618 | E55: =Historical_Drivers!L12 -> 139223 | F55: 139223 | G55: =E55-F55 -> 0 | H55: =IF(ABS(G55)<=0.000001,"PASS","FAIL") -> PASS
A56: PL-0053 | B56: Source book QA | C56: Historical_Drivers!M12 | D56: QA-0620 | E56: =Historical_Drivers!M12 -> 151804 | F56: 151804 | G56: =E56-F56 -> 0 | H56: =IF(ABS(G56)<=0.000001,"PASS","FAIL") -> PASS
A57: PL-0054 | B57: Source book QA | C57: Historical_Drivers!N12 | D57: QA-0622 | E57: =Historical_Drivers!N12 -> 159858 | F57: 159858 | G57: =E57-F57 -> 0 | H57: =IF(ABS(G57)<=0.000001,"PASS","FAIL") -> PASS
A58: PL-0055 | B58: Source book QA | C58: Historical_Drivers!O12 | D58: QA-0624 | E58: =Historical_Drivers!O12 -> 158181 | F58: 158181 | G58: =E58-F58 -> 0 | H58: =IF(ABS(G58)<=0.000001,"PASS","FAIL") -> PASS
A59: PL-0056 | B59: Source book QA | C59: Historical_Drivers!P12 | D59: QA-0625 | E59: =Historical_Drivers!P12 -> 149444 | F59: 149444 | G59: =E59-F59 -> 0 | H59: =IF(ABS(G59)<=0.000001,"PASS","FAIL") -> PASS
A60: PL-0057 | B60: Source book QA | C60: Historical_Drivers!C14 | D60: QA-0641 | E60: =Historical_Drivers!C14 -> 15841 | F60: 15841 | G60: =E60-F60 -> 0 | H60: =IF(ABS(G60)<=0.000001,"PASS","FAIL") -> PASS
A61: PL-0058 | B61: Source book QA | C61: Historical_Drivers!D14 | D61: QA-0642 | E61: =Historical_Drivers!D14 -> 14652 | F61: 14652 | G61: =E61-F61 -> 0 | H61: =IF(ABS(G61)<=0.000001,"PASS","FAIL") -> PASS
A62: PL-0059 | B62: Source book QA | C62: Historical_Drivers!E14 | D62: QA-0644 | E62: =Historical_Drivers!E14 -> 15234 | F62: 15234 | G62: =E62-F62 -> 0 | H62: =IF(ABS(G62)<=0.000001,"PASS","FAIL") -> PASS
A63: PL-0060 | B63: Source book QA | C63: Historical_Drivers!F14 | D63: QA-0646 | E63: =Historical_Drivers!F14 -> 17259 | F63: 17259 | G63: =E63-F63 -> 0 | H63: =IF(ABS(G63)<=0.000001,"PASS","FAIL") -> PASS
A64: PL-0061 | B64: Source book QA | C64: Historical_Drivers!G14 | D64: QA-0648 | E64: =Historical_Drivers!G14 -> 17579 | F64: 17579 | G64: =E64-F64 -> 0 | H64: =IF(ABS(G64)<=0.000001,"PASS","FAIL") -> PASS
A65: PL-0062 | B65: Source book QA | C65: Historical_Drivers!H14 | D65: QA-0649 | E65: =Historical_Drivers!H14 -> 18182 | F65: 18182 | G65: =E65-F65 -> 0 | H65: =IF(ABS(G65)<=0.000001,"PASS","FAIL") -> PASS
A66: PL-0063 | B66: Source book QA | C66: Historical_Drivers!I14 | D66: QA-0651 | E66: =Historical_Drivers!I14 -> 21417 | F66: 21417 | G66: =E66-F66 -> 0 | H66: =IF(ABS(G66)<=0.000001,"PASS","FAIL") -> PASS
A67: PL-0064 | B67: Source book QA | C67: Historical_Drivers!J14 | D67: QA-0653 | E67: =Historical_Drivers!J14 -> 22958 | F67: 22958 | G67: =E67-F67 -> 0 | H67: =IF(ABS(G67)<=0.000001,"PASS","FAIL") -> PASS
A68: PL-0065 | B68: Source book QA | C68: Historical_Drivers!K14 | D68: QA-0655 | E68: =Historical_Drivers!K14 -> 24099 | F68: 24099 | G68: =E68-F68 -> 0 | H68: =IF(ABS(G68)<=0.000001,"PASS","FAIL") -> PASS
A69: PL-0066 | B69: Source book QA | C69: Historical_Drivers!L14 | D69: QA-0656 | E69: =Historical_Drivers!L14 -> 26563 | F69: 26563 | G69: =E69-F69 -> 0 | H69: =IF(ABS(G69)<=0.000001,"PASS","FAIL") -> PASS
A70: PL-0067 | B70: Source book QA | C70: Historical_Drivers!M14 | D70: QA-0658 | E70: =Historical_Drivers!M14 -> 26971 | F70: 26971 | G70: =E70-F70 -> 0 | H70: =IF(ABS(G70)<=0.000001,"PASS","FAIL") -> PASS
A71: PL-0068 | B71: Source book QA | C71: Historical_Drivers!N14 | D71: QA-0660 | E71: =Historical_Drivers!N14 -> 29247 | F71: 29247 | G71: =E71-F71 -> 0 | H71: =IF(ABS(G71)<=0.000001,"PASS","FAIL") -> PASS
A72: PL-0069 | B72: Source book QA | C72: Historical_Drivers!O14 | D72: QA-0662 | E72: =Historical_Drivers!O14 -> 28559 | F72: 28559 | G72: =E72-F72 -> 0 | H72: =IF(ABS(G72)<=0.000001,"PASS","FAIL") -> PASS
A73: PL-0070 | B73: Source book QA | C73: Historical_Drivers!P14 | D73: QA-0663 | E73: =Historical_Drivers!P14 -> 30665 | F73: 30665 | G73: =E73-F73 -> 0 | H73: =IF(ABS(G73)<=0.000001,"PASS","FAIL") -> PASS
A74: PL-0071 | B74: Source book QA | C74: Historical_Drivers!C16 | D74: QA-0679 | E74: =Historical_Drivers!C16 -> -293 | F74: -293 | G74: =E74-F74 -> 0 | H74: =IF(ABS(G74)<=0.000001,"PASS","FAIL") -> PASS
A75: PL-0072 | B75: Source book QA | C75: Historical_Drivers!D16 | D75: QA-0680 | E75: =Historical_Drivers!D16 -> 16617 | F75: 16617 | G75: =E75-F75 -> 0 | H75: =IF(ABS(G75)<=0.000001,"PASS","FAIL") -> PASS
A76: PL-0073 | B76: Source book QA | C76: Historical_Drivers!E16 | D76: QA-0682 | E76: =Historical_Drivers!E16 -> 24077 | F76: 24077 | G76: =E76-F76 -> 0 | H76: =IF(ABS(G76)<=0.000001,"PASS","FAIL") -> PASS
A77: PL-0074 | B77: Source book QA | C77: Historical_Drivers!F16 | D77: QA-0684 | E77: =Historical_Drivers!F16 -> 21200 | F77: 21200 | G77: =E77-F77 -> 0 | H77: =IF(ABS(G77)<=0.000001,"PASS","FAIL") -> PASS
A78: PL-0075 | B78: Source book QA | C78: Historical_Drivers!G16 | D78: QA-0686 | E78: =Historical_Drivers!G16 -> 21521 | F78: 21521 | G78: =E78-F78 -> 0 | H78: =IF(ABS(G78)<=0.000001,"PASS","FAIL") -> PASS
A79: PL-0076 | B79: Source book QA | C79: Historical_Drivers!H16 | D79: QA-0687 | E79: =Historical_Drivers!H16 -> 38417 | F79: 38417 | G79: =E79-F79 -> 0 | H79: =IF(ABS(G79)<=0.000001,"PASS","FAIL") -> PASS
A80: PL-0077 | B80: Source book QA | C80: Historical_Drivers!I16 | D80: QA-0689 | E80: =Historical_Drivers!I16 -> 32180 | F80: 32180 | G80: =E80-F80 -> 0 | H80: =IF(ABS(G80)<=0.000001,"PASS","FAIL") -> PASS
A81: PL-0078 | B81: Source book QA | C81: Historical_Drivers!J16 | D81: QA-0691 | E81: =Historical_Drivers!J16 -> 40265 | F81: 40265 | G81: =E81-F81 -> 0 | H81: =IF(ABS(G81)<=0.000001,"PASS","FAIL") -> PASS
A82: PL-0079 | B82: Source book QA | C82: Historical_Drivers!K16 | D82: QA-0693 | E82: =Historical_Drivers!K16 -> 40754 | F82: 40754 | G82: =E82-F82 -> 0 | H82: =IF(ABS(G82)<=0.000001,"PASS","FAIL") -> PASS
A83: PL-0080 | B83: Source book QA | C83: Historical_Drivers!L16 | D83: QA-0694 | E83: =Historical_Drivers!L16 -> 45094 | F83: 45094 | G83: =E83-F83 -> 0 | H83: =IF(ABS(G83)<=0.000001,"PASS","FAIL") -> PASS
A84: PL-0081 | B84: Source book QA | C84: Historical_Drivers!M16 | D84: QA-0696 | E84: =Historical_Drivers!M16 -> 47484 | F84: 47484 | G84: =E84-F84 -> 0 | H84: =IF(ABS(G84)<=0.000001,"PASS","FAIL") -> PASS
A85: PL-0082 | B85: Source book QA | C85: Historical_Drivers!N16 | D85: QA-0698 | E85: =Historical_Drivers!N16 -> 41931 | F85: 41931 | G85: =E85-F85 -> 0 | H85: =IF(ABS(G85)<=0.000001,"PASS","FAIL") -> PASS
A86: PL-0083 | B86: Source book QA | C86: Historical_Drivers!O16 | D86: QA-0700 | E86: =Historical_Drivers!O16 -> 49037 | F86: 49037 | G86: =E86-F86 -> 0 | H86: =IF(ABS(G86)<=0.000001,"PASS","FAIL") -> PASS
A87: PL-0084 | B87: Source book QA | C87: Historical_Drivers!P16 | D87: QA-0701 | E87: =Historical_Drivers!P16 -> 61110 | F87: 61110 | G87: =E87-F87 -> 0 | H87: =IF(ABS(G87)<=0.000001,"PASS","FAIL") -> PASS
A88: PL-0085 | B88: Source book QA | C88: Historical_Drivers!C18 | D88: QA-0321 | E88: =Historical_Drivers!C18 -> -22752 | F88: -22752 | G88: =E88-F88 -> 0 | H88: =IF(ABS(G88)<=0.000001,"PASS","FAIL") -> PASS
A89: PL-0086 | B89: Source book QA | C89: Historical_Drivers!D18 | D89: QA-0322 | E89: =Historical_Drivers!D18 -> -12167 | F89: -12167 | G89: =E89-F89 -> 0 | H89: =IF(ABS(G89)<=0.000001,"PASS","FAIL") -> PASS
A90: PL-0087 | B90: Source book QA | C90: Historical_Drivers!E18 | D90: QA-0324 | E90: =Historical_Drivers!E18 -> -2521 | F90: -2521 | G90: =E90-F90 -> 0 | H90: =IF(ABS(G90)<=0.000001,"PASS","FAIL") -> PASS
A91: PL-0088 | B91: Source book QA | C91: Historical_Drivers!F18 | D91: QA-0326 | E91: =Historical_Drivers!F18 -> -1145 | F91: -1145 | G91: =E91-F91 -> 0 | H91: =IF(ABS(G91)<=0.000001,"PASS","FAIL") -> PASS
A92: PL-0089 | B92: Source book QA | C92: Historical_Drivers!G18 | D92: QA-0328 | E92: =Historical_Drivers!G18 -> -5022 | F92: -5022 | G92: =E92-F92 -> 0 | H92: =IF(ABS(G92)<=0.000001,"PASS","FAIL") -> PASS
A93: PL-0090 | B93: Source book QA | C93: Historical_Drivers!H18 | D93: QA-0329 | E93: =Historical_Drivers!H18 -> 1794 | F93: 1794 | G93: =E93-F93 -> 0 | H93: =IF(ABS(G93)<=0.000001,"PASS","FAIL") -> PASS
A94: PL-0091 | B94: Source book QA | C94: Historical_Drivers!I18 | D94: QA-0331 | E94: =Historical_Drivers!I18 -> -27402 | F94: -27402 | G94: =E94-F94 -> 0 | H94: =IF(ABS(G94)<=0.000001,"PASS","FAIL") -> PASS
A95: PL-0092 | B95: Source book QA | C95: Historical_Drivers!J18 | D95: QA-0333 | E95: =Historical_Drivers!J18 -> 9596 | F95: 9596 | G95: =E95-F95 -> 0 | H95: =IF(ABS(G95)<=0.000001,"PASS","FAIL") -> PASS
A96: PL-0093 | B96: Source book QA | C96: Historical_Drivers!K18 | D96: QA-0335 | E96: =Historical_Drivers!K18 -> 9796 | F96: 9796 | G96: =E96-F96 -> 0 | H96: =IF(ABS(G96)<=0.000001,"PASS","FAIL") -> PASS
A97: PL-0094 | B97: Source book QA | C97: Historical_Drivers!L18 | D97: QA-0336 | E97: =Historical_Drivers!L18 -> -11551 | F97: -11551 | G97: =E97-F97 -> 0 | H97: =IF(ABS(G97)<=0.000001,"PASS","FAIL") -> PASS
A98: PL-0095 | B98: Source book QA | C98: Historical_Drivers!M18 | D98: QA-0338 | E98: =Historical_Drivers!M18 -> -2378 | F98: -2378 | G98: =E98-F98 -> 0 | H98: =IF(ABS(G98)<=0.000001,"PASS","FAIL") -> PASS
A99: PL-0096 | B99: Source book QA | C99: Historical_Drivers!N18 | D99: QA-0340 | E99: =Historical_Drivers!N18 -> 2385 | F99: 2385 | G99: =E99-F99 -> 0 | H99: =IF(ABS(G99)<=0.000001,"PASS","FAIL") -> PASS
A100: PL-0097 | B100: Source book QA | C100: Historical_Drivers!O18 | D100: QA-0342 | E100: =Historical_Drivers!O18 -> 19754 | F100: 19754 | G100: =E100-F100 -> 0 | H100: =IF(ABS(G100)<=0.000001,"PASS","FAIL") -> PASS
A101: PL-0098 | B101: Source book QA | C101: Historical_Drivers!P18 | D101: QA-0343 | E101: =Historical_Drivers!P18 -> -1544 | F101: -1544 | G101: =E101-F101 -> 0 | H101: =IF(ABS(G101)<=0.000001,"PASS","FAIL") -> PASS
...

Sheet Scorecard
A1: Scorecard - Q3 2026 plan vs actual (BLANK; to be completed after November 9, 2026 without changing the plan)
A3: Metric | B3: Unit | C3: Plan (Base) | D3: Actual | E3: Difference | F3: Note | G3: Label
A4: Revenue Q3 2026 | B4: USD m | C4: =Revenue_Build!E7 -> 378.38246 | F4: Equals locked call MID | G4: Derived (link); D:E blank
A5: Non-GAAP operating income Q3 2026 | B5: USD m | C5: =Opex!E16 -> 69.637 | F5: Equals locked call MID | G5: Derived (link); D:E blank
A6: Non-GAAP operating margin Q3 2026 | B6: % | C6: =Opex!E17 -> 0.18403866 | F6: Derived | G6: Derived (link); D:E blank
A7: Adjusted FCF Q3 2026, reported basis | B7: USD m | C7: =Cash_FCF!E11 -> 56.909541 | F7: LOW CONFIDENCE (Q3 FCF was a NO CALL); includes Assumed severance | G7: Derived (link); D:E blank
A8: NDR Q3 2026 (indicator) | B8: % | C8: =Revenue_Build!E10 -> 1.085 | F8: indicator only | G8: Derived (link); D:E blank
A9: Customers >$50k ARR Q3 2026 | B9: count | C9: =Revenue_Build!E11 -> 5110.5 | F9: indicator | G9: Derived (link); D:E blank
A10: Cash + securities, Sep 30, 2026 | B10: USD m | C10: =Cash_FCF!E15 -> 1123.238 | F10: before unmodeled items; after Assumed severance and other flows | G10: Derived (link); D:E blank
