Workbook

Sheet README
A1: monday.com Operating Plan & Rolling Reforecast - Phase 1 Historical Analysis
A3: Purpose | B3: Historical analysis of monday.com built entirely on the Phase 0 source book (monday_sourcebook.xlsx). It measures guidance accuracy, places revenue growth beside disclosed KPIs, describes margin and cash-conversion structure, and computes what current guidance arithmetically implies for H2 2026.
A4: Information cutoff | B4: October 28, 2026 (inherited from the source book; latest underlying filing August 10, 2026).
A5: Source | B5: monday_sourcebook.xlsx only (branch phase0-sourcebook). No new data sources. Every input is a copy of a source-book value with the source-book Row ID (and Source ID) beside it.
A6: Labels | B6: Sourced (copied from source book) = blue font hard-code, Row ID adjacent. Derived = black-font live formula. Assumed = none in Phase 1. The second header row of every table states the label for every cell in that column; "Text / label", "Row ID" and "Source ID" columns are identifiers, not data.
A7: Assumed values | B7: NONE. Presentation conventions (e.g., pairing guidance range ends low-with-low in the H2-implied table, choosing 2022-2025 as the seasonality window) are stated next to the table and are not data assumptions.
A8: What Phase 1 does NOT do | B8: No forecast, no operating plan, no Q3 2026 call, no scenario, no driver model, no assertion that any KPI drives revenue, no smoothing / annualizing / normalizing of any series (the 2025 commission change is shown, not adjusted), no modification of the source book.
A9: Units | B9: USD thousands for actuals (as in the source book); USD millions for guidance; percentages as decimals displayed as %; basis points for FX; counts for customers.
A10: Sheets | B10: Guidance_Accuracy, Growth_Decomposition, Margin_Structure, Cash_Conversion, Deceleration, Findings, Checks.
A11: Checks | B11: Every copied input is re-read from the source book by Row ID and compared (Checks sheet), plus internal arithmetic tie-outs.
A13: Blank source-book values encountered (left blank, not filled)
A15: Structural blanks | B15: YoY growth for 2021 quarters (2020 quarters not in source book); KPI cohorts before their first disclosure (see Growth_Decomposition flags); quarterly FCF guidance outside 2024; revenue FX impact Q3 2024-Q1 2026; commission % for quarters (only annual / half-year disclosed).

Sheet Guidance_Accuracy
A1: Guidance accuracy: next-quarter guidance vs. reported actual
A2: Guidance (USD millions) copied from Guidance_History; actuals (USD thousands) copied from Quarterly_Actuals. Every quarter with a guidance vintage issued in the prior quarter's release is included. Q3 2026 guidance (GH-0101/GH-0102) has no actual yet and is excluded.
A4: Revenue
A5: Quarter | B5: GH Row ID | C5: Source ID | D5: Guidance issued | E5: Guidance metric label | F5: Low (USD m) | G5: High (USD m) | H5: Midpoint (USD m) | I5: Actual (USD k) | J5: Actual Row ID | K5: Actual Source ID | L5: Actual (USD m) | M5: Actual - midpoint (USD m) | N5: % difference vs midpoint | O5: Outcome | P5: Beat top (1/0) | Q5: In range (1/0) | R5: Missed bottom (1/0) | S5: Disclosed FX impact on revenue growth (bps) | T5: FX Row ID | U5: FX Source ID | V5: Disclosed FX impact on non-GAAP op. margin (bps) | W5: FX Row ID | X5: FX Source ID | Y5: FX assumption stated in the guidance (copied text) and notes
A6: Text / label | B6: Source-book Row ID | C6: Source ID | D6: Sourced (copied) | E6: Sourced (copied) | F6: Sourced (copied from source book) | G6: Sourced (copied from source book) | H6: Derived (formula) | I6: Sourced (copied from source book) | J6: Source-book Row ID | K6: Source ID | L6: Derived (formula) | M6: Derived (formula) | N6: Derived (formula) | O6: Derived (formula) | P6: Derived (formula) | Q6: Derived (formula) | R6: Derived (formula) | S6: Sourced (copied from source book) | T6: Source-book Row ID | U6: Source ID | V6: Sourced (copied from source book) | W6: Source-book Row ID | X6: Source ID | Y6: Sourced text / note
A7: Q3 2021 | B7: GH-0004 | C7: ER-2021Q2 | D7: 44425 | E7: Revenue | F7: 74 | G7: 75 | H7: =(F7+G7)/2 -> 74.5 | I7: 83018 | J7: QA-0004 | K7: ER-2021Q3 | L7: =I7/1000 -> 83.018 | M7: =L7-H7 -> 8.518 | N7: =M7/ABS(H7) -> 0.11433557 | O7: =IF(L7>G7,"Beat top",IF(L7>=F7,"In range","Missed bottom")) -> Beat top | P7: =IF(L7>G7,1,0) -> 1 | Q7: =IF(AND(L7>=F7,L7<=G7),1,0) -> 0 | R7: =IF(L7<F7,1,0) -> 0
A8: Q4 2021 | B8: GH-0008 | C8: ER-2021Q3 | D8: 44510 | E8: Revenue | F8: 87 | G8: 88 | H8: =(F8+G8)/2 -> 87.5 | I8: 95545 | J8: QA-0006 | K8: ER-2021Q4 | L8: =I8/1000 -> 95.545 | M8: =L8-H8 -> 8.045 | N8: =M8/ABS(H8) -> 0.091942857 | O8: =IF(L8>G8,"Beat top",IF(L8>=F8,"In range","Missed bottom")) -> Beat top | P8: =IF(L8>G8,1,0) -> 1 | Q8: =IF(AND(L8>=F8,L8<=G8),1,0) -> 0 | R8: =IF(L8<F8,1,0) -> 0
A9: Q1 2022 | B9: GH-0012 | C9: ER-2021Q4 | D9: 44615 | E9: Revenue | F9: 100 | G9: 102 | H9: =(F9+G9)/2 -> 101 | I9: 108497 | J9: QA-0008 | K9: ER-2022Q1 | L9: =I9/1000 -> 108.497 | M9: =L9-H9 -> 7.497 | N9: =M9/ABS(H9) -> 0.074227723 | O9: =IF(L9>G9,"Beat top",IF(L9>=F9,"In range","Missed bottom")) -> Beat top | P9: =IF(L9>G9,1,0) -> 1 | Q9: =IF(AND(L9>=F9,L9<=G9),1,0) -> 0 | R9: =IF(L9<F9,1,0) -> 0 | S9: -100 | T9: QA-1546 | U9: ER-2022Q3
A10: Q2 2022 | B10: GH-0016 | C10: ER-2022Q1 | D10: 44697 | E10: Revenue | F10: 117 | G10: 119 | H10: =(F10+G10)/2 -> 118 | I10: 123718 | J10: QA-0009 | K10: ER-2022Q2 | L10: =I10/1000 -> 123.718 | M10: =L10-H10 -> 5.718 | N10: =M10/ABS(H10) -> 0.048457627 | O10: =IF(L10>G10,"Beat top",IF(L10>=F10,"In range","Missed bottom")) -> Beat top | P10: =IF(L10>G10,1,0) -> 1 | Q10: =IF(AND(L10>=F10,L10<=G10),1,0) -> 0 | R10: =IF(L10<F10,1,0) -> 0 | S10: -200 | T10: QA-1547 | U10: ER-2022Q3
A11: Q3 2022 | B11: GH-0020 | C11: ER-2022Q2 | D11: 44781 | E11: Revenue | F11: 130 | G11: 131 | H11: =(F11+G11)/2 -> 130.5 | I11: 136893 | J11: QA-0011 | K11: ER-2022Q3 | L11: =I11/1000 -> 136.893 | M11: =L11-H11 -> 6.393 | N11: =M11/ABS(H11) -> 0.048988506 | O11: =IF(L11>G11,"Beat top",IF(L11>=F11,"In range","Missed bottom")) -> Beat top | P11: =IF(L11>G11,1,0) -> 1 | Q11: =IF(AND(L11>=F11,L11<=G11),1,0) -> 0 | R11: =IF(L11<F11,1,0) -> 0 | S11: -300 | T11: QA-1548 | U11: ER-2022Q3
A12: Q4 2022 | B12: GH-0024 | C12: ER-2022Q3 | D12: 44879 | E12: Revenue | F12: 140 | G12: 142 | H12: =(F12+G12)/2 -> 141 | I12: 149921 | J12: QA-0013 | K12: ER-2022Q4 | L12: =I12/1000 -> 149.921 | M12: =L12-H12 -> 8.921 | N12: =M12/ABS(H12) -> 0.063269504 | O12: =IF(L12>G12,"Beat top",IF(L12>=F12,"In range","Missed bottom")) -> Beat top | P12: =IF(L12>G12,1,0) -> 1 | Q12: =IF(AND(L12>=F12,L12<=G12),1,0) -> 0 | R12: =IF(L12<F12,1,0) -> 0 | S12: -300 | T12: QA-1549 | U12: ER-2022Q4
A13: Q1 2023 | B13: GH-0028 | C13: ER-2022Q4 | D13: 44970 | E13: Revenue | F13: 154 | G13: 156 | H13: =(F13+G13)/2 -> 155 | I13: 162256 | J13: QA-0015 | K13: ER-2023Q1 | L13: =I13/1000 -> 162.256 | M13: =L13-H13 -> 7.256 | N13: =M13/ABS(H13) -> 0.046812903 | O13: =IF(L13>G13,"Beat top",IF(L13>=F13,"In range","Missed bottom")) -> Beat top | P13: =IF(L13>G13,1,0) -> 1 | Q13: =IF(AND(L13>=F13,L13<=G13),1,0) -> 0 | R13: =IF(L13<F13,1,0) -> 0 | S13: -100 | T13: QA-1551 | U13: ER-2023Q1
A14: Q2 2023 | B14: GH-0032 | C14: ER-2023Q1 | D14: 45061 | E14: Revenue | F14: 168 | G14: 170 | H14: =(F14+G14)/2 -> 169 | I14: 175679 | J14: QA-0016 | K14: ER-2023Q2 | L14: =I14/1000 -> 175.679 | M14: =L14-H14 -> 6.679 | N14: =M14/ABS(H14) -> 0.03952071 | O14: =IF(L14>G14,"Beat top",IF(L14>=F14,"In range","Missed bottom")) -> Beat top | P14: =IF(L14>G14,1,0) -> 1 | Q14: =IF(AND(L14>=F14,L14<=G14),1,0) -> 0 | R14: =IF(L14<F14,1,0) -> 0 | S14: -100 | T14: QA-1552 | U14: ER-2023Q2
A15: Q3 2023 | B15: GH-0036 | C15: ER-2023Q2 | D15: 45152 | E15: Revenue | F15: 181 | G15: 183 | H15: =(F15+G15)/2 -> 182 | I15: 189190 | J15: QA-0018 | K15: ER-2023Q3 | L15: =I15/1000 -> 189.19 | M15: =L15-H15 -> 7.19 | N15: =M15/ABS(H15) -> 0.039505495 | O15: =IF(L15>G15,"Beat top",IF(L15>=F15,"In range","Missed bottom")) -> Beat top | P15: =IF(L15>G15,1,0) -> 1 | Q15: =IF(AND(L15>=F15,L15<=G15),1,0) -> 0 | R15: =IF(L15<F15,1,0) -> 0 | S15: 0 | T15: QA-1553 | U15: ER-2023Q3
A16: Q4 2023 | B16: GH-0040 | C16: ER-2023Q3 | D16: 45243 | E16: Revenue | F16: 196 | G16: 198 | H16: =(F16+G16)/2 -> 197 | I16: 202570 | J16: QA-0020 | K16: ER-2023Q4 | L16: =I16/1000 -> 202.57 | M16: =L16-H16 -> 5.57 | N16: =M16/ABS(H16) -> 0.028274112 | O16: =IF(L16>G16,"Beat top",IF(L16>=F16,"In range","Missed bottom")) -> Beat top | P16: =IF(L16>G16,1,0) -> 1 | Q16: =IF(AND(L16>=F16,L16<=G16),1,0) -> 0 | R16: =IF(L16<F16,1,0) -> 0 | S16: 0 | T16: QA-1554 | U16: ER-2023Q4
A17: Q1 2024 | B17: GH-0046 | C17: ER-2023Q4 | D17: 45334 | E17: Revenue | F17: 207 | G17: 211 | H17: =(F17+G17)/2 -> 209 | I17: 216913 | J17: QA-0022 | K17: ER-2024Q1 | L17: =I17/1000 -> 216.913 | M17: =L17-H17 -> 7.913 | N17: =M17/ABS(H17) -> 0.037861244 | O17: =IF(L17>G17,"Beat top",IF(L17>=F17,"In range","Missed bottom")) -> Beat top | P17: =IF(L17>G17,1,0) -> 1 | Q17: =IF(AND(L17>=F17,L17<=G17),1,0) -> 0 | R17: =IF(L17<F17,1,0) -> 0 | S17: 0 | T17: QA-1556 | U17: ER-2024Q1
A18: Q2 2024 | B18: GH-0052 | C18: ER-2024Q1 | D18: 45427 | E18: Revenue | F18: 226 | G18: 230 | H18: =(F18+G18)/2 -> 228 | I18: 236106 | J18: QA-0023 | K18: ER-2024Q2 | L18: =I18/1000 -> 236.106 | M18: =L18-H18 -> 8.106 | N18: =M18/ABS(H18) -> 0.035552632 | O18: =IF(L18>G18,"Beat top",IF(L18>=F18,"In range","Missed bottom")) -> Beat top | P18: =IF(L18>G18,1,0) -> 1 | Q18: =IF(AND(L18>=F18,L18<=G18),1,0) -> 0 | R18: =IF(L18<F18,1,0) -> 0 | S18: 0 | T18: QA-1557 | U18: ER-2024Q2
A19: Q3 2024 | B19: GH-0058 | C19: ER-2024Q2 | D19: 45516 | E19: Revenue | F19: 243 | G19: 247 | H19: =(F19+G19)/2 -> 245 | I19: 251000 | J19: QA-0025 | K19: ER-2024Q3 | L19: =I19/1000 -> 251 | M19: =L19-H19 -> 6 | N19: =M19/ABS(H19) -> 0.024489796 | O19: =IF(L19>G19,"Beat top",IF(L19>=F19,"In range","Missed bottom")) -> Beat top | P19: =IF(L19>G19,1,0) -> 1 | Q19: =IF(AND(L19>=F19,L19<=G19),1,0) -> 0 | R19: =IF(L19<F19,1,0) -> 0
A20: Q4 2024 | B20: GH-0064 | C20: ER-2024Q3 | D20: 45608 | E20: Revenue | F20: 260 | G20: 262 | H20: =(F20+G20)/2 -> 261 | I20: 267976 | J20: QA-0027 | K20: ER-2024Q4 | L20: =I20/1000 -> 267.976 | M20: =L20-H20 -> 6.976 | N20: =M20/ABS(H20) -> 0.026727969 | O20: =IF(L20>G20,"Beat top",IF(L20>=F20,"In range","Missed bottom")) -> Beat top | P20: =IF(L20>G20,1,0) -> 1 | Q20: =IF(AND(L20>=F20,L20<=G20),1,0) -> 0 | R20: =IF(L20<F20,1,0) -> 0
A21: Q1 2025 | B21: GH-0069 | C21: ER-2024Q4 | D21: 45698 | E21: Revenue | F21: 274 | G21: 276 | H21: =(F21+G21)/2 -> 275 | I21: 282250 | J21: QA-0029 | K21: ER-2025Q1 | L21: =I21/1000 -> 282.25 | M21: =L21-H21 -> 7.25 | N21: =M21/ABS(H21) -> 0.026363636 | O21: =IF(L21>G21,"Beat top",IF(L21>=F21,"In range","Missed bottom")) -> Beat top | P21: =IF(L21>G21,1,0) -> 1 | Q21: =IF(AND(L21>=F21,L21<=G21),1,0) -> 0 | R21: =IF(L21<F21,1,0) -> 0
A22: Q2 2025 | B22: GH-0074 | C22: ER-2025Q1 | D22: 45789 | E22: Revenue | F22: 292 | G22: 294 | H22: =(F22+G22)/2 -> 293 | I22: 299014 | J22: QA-0030 | K22: ER-2025Q2 | L22: =I22/1000 -> 299.014 | M22: =L22-H22 -> 6.014 | N22: =M22/ABS(H22) -> 0.020525597 | O22: =IF(L22>G22,"Beat top",IF(L22>=F22,"In range","Missed bottom")) -> Beat top | P22: =IF(L22>G22,1,0) -> 1 | Q22: =IF(AND(L22>=F22,L22<=G22),1,0) -> 0 | R22: =IF(L22<F22,1,0) -> 0
A23: Q3 2025 | B23: GH-0079 | C23: ER-2025Q2 | D23: 45880 | E23: Revenue | F23: 311 | G23: 313 | H23: =(F23+G23)/2 -> 312 | I23: 316855 | J23: QA-0032 | K23: ER-2025Q3 | L23: =I23/1000 -> 316.855 | M23: =L23-H23 -> 4.855 | N23: =M23/ABS(H23) -> 0.015560897 | O23: =IF(L23>G23,"Beat top",IF(L23>=F23,"In range","Missed bottom")) -> Beat top | P23: =IF(L23>G23,1,0) -> 1 | Q23: =IF(AND(L23>=F23,L23<=G23),1,0) -> 0 | R23: =IF(L23<F23,1,0) -> 0
A24: Q4 2025 | B24: GH-0084 | C24: ER-2025Q3 | D24: 45971 | E24: Revenue | F24: 328 | G24: 330 | H24: =(F24+G24)/2 -> 329 | I24: 333878 | J24: QA-0034 | K24: ER-2025Q4 | L24: =I24/1000 -> 333.878 | M24: =L24-H24 -> 4.878 | N24: =M24/ABS(H24) -> 0.014826748 | O24: =IF(L24>G24,"Beat top",IF(L24>=F24,"In range","Missed bottom")) -> Beat top | P24: =IF(L24>G24,1,0) -> 1 | Q24: =IF(AND(L24>=F24,L24<=G24),1,0) -> 0 | R24: =IF(L24<F24,1,0) -> 0 | V24: -180 | W24: QA-1559 | X24: ER-2025Q4
A25: Q1 2026 | B25: GH-0089 | C25: ER-2025Q4 | D25: 46062 | E25: Revenue | F25: 338 | G25: 340 | H25: =(F25+G25)/2 -> 339 | I25: 351265 | J25: QA-0036 | K25: ER-2026Q1 | L25: =I25/1000 -> 351.265 | M25: =L25-H25 -> 12.265 | N25: =M25/ABS(H25) -> 0.036179941 | O25: =IF(L25>G25,"Beat top",IF(L25>=F25,"In range","Missed bottom")) -> Beat top | P25: =IF(L25>G25,1,0) -> 1 | Q25: =IF(AND(L25>=F25,L25<=G25),1,0) -> 0 | R25: =IF(L25<F25,1,0) -> 0 | V25: -190 | W25: QA-1561 | X25: ER-2026Q1
A26: Q2 2026 | B26: GH-0094 | C26: ER-2026Q1 | D26: 46153 | E26: Revenue | F26: 354 | G26: 356 | H26: =(F26+G26)/2 -> 355 | I26: 364621 | J26: QA-0037 | K26: ER-2026Q2 | L26: =I26/1000 -> 364.621 | M26: =L26-H26 -> 9.621 | N26: =M26/ABS(H26) -> 0.027101408 | O26: =IF(L26>G26,"Beat top",IF(L26>=F26,"In range","Missed bottom")) -> Beat top | P26: =IF(L26>G26,1,0) -> 1 | Q26: =IF(AND(L26>=F26,L26<=G26),1,0) -> 0 | R26: =IF(L26<F26,1,0) -> 0 | S26: 110 | T26: QA-1558 | U26: ER-2026Q2 | V26: -210 | W26: QA-1562 | X26: ER-2026Q2
A29: Non-GAAP operating income
A30: Quarter | B30: GH Row ID | C30: Source ID | D30: Guidance issued | E30: Guidance metric label | F30: Low (USD m) | G30: High (USD m) | H30: Midpoint (USD m) | I30: Actual (USD k) | J30: Actual Row ID | K30: Actual Source ID | L30: Actual (USD m) | M30: Actual - midpoint (USD m) | N30: % difference vs midpoint | O30: Outcome | P30: Beat top (1/0) | Q30: In range (1/0) | R30: Missed bottom (1/0) | S30: Disclosed FX impact on revenue growth (bps) | T30: FX Row ID | U30: FX Source ID | V30: Disclosed FX impact on non-GAAP op. margin (bps) | W30: FX Row ID | X30: FX Source ID | Y30: FX assumption stated in the guidance (copied text) and notes
A31: Text / label | B31: Source-book Row ID | C31: Source ID | D31: Sourced (copied) | E31: Sourced (copied) | F31: Sourced (copied from source book) | G31: Sourced (copied from source book) | H31: Derived (formula) | I31: Sourced (copied from source book) | J31: Source-book Row ID | K31: Source ID | L31: Derived (formula) | M31: Derived (formula) | N31: Derived (formula) | O31: Derived (formula) | P31: Derived (formula) | Q31: Derived (formula) | R31: Derived (formula) | S31: Sourced (copied from source book) | T31: Source-book Row ID | U31: Source ID | V31: Sourced (copied from source book) | W31: Source-book Row ID | X31: Source ID | Y31: Sourced text / note
A32: Q3 2021 | B32: GH-0003 | C32: ER-2021Q2 | D32: 44425 | E32: Non-GAAP operating income (loss) | F32: -26 | G32: -25 | H32: =(F32+G32)/2 -> -25.5 | I32: -9449 | J32: QA-0668 | K32: ER-2021Q3 | L32: =I32/1000 -> -9.449 | M32: =L32-H32 -> 16.051 | N32: =M32/ABS(H32) -> 0.62945098 | O32: =IF(L32>G32,"Beat top",IF(L32>=F32,"In range","Missed bottom")) -> Beat top | P32: =IF(L32>G32,1,0) -> 1 | Q32: =IF(AND(L32>=F32,L32<=G32),1,0) -> 0 | R32: =IF(L32<F32,1,0) -> 0 | Y32: Guided as an operating loss; % difference uses ABS(midpoint).
A33: Q4 2021 | B33: GH-0007 | C33: ER-2021Q3 | D33: 44510 | E33: Non-GAAP operating income (loss) | F33: -23 | G33: -22 | H33: =(F33+G33)/2 -> -22.5 | I33: -9929 | J33: QA-0670 | K33: ER-2021Q4 | L33: =I33/1000 -> -9.929 | M33: =L33-H33 -> 12.571 | N33: =M33/ABS(H33) -> 0.55871111 | O33: =IF(L33>G33,"Beat top",IF(L33>=F33,"In range","Missed bottom")) -> Beat top | P33: =IF(L33>G33,1,0) -> 1 | Q33: =IF(AND(L33>=F33,L33<=G33),1,0) -> 0 | R33: =IF(L33<F33,1,0) -> 0 | Y33: Guided as an operating loss; % difference uses ABS(midpoint).
A34: Q1 2022 | B34: GH-0011 | C34: ER-2021Q4 | D34: 44615 | E34: Non-GAAP operating income (loss) | F34: -47 | G34: -45 | H34: =(F34+G34)/2 -> -46 | I34: -43830 | J34: QA-0672 | K34: ER-2022Q1 | L34: =I34/1000 -> -43.83 | M34: =L34-H34 -> 2.17 | N34: =M34/ABS(H34) -> 0.047173913 | O34: =IF(L34>G34,"Beat top",IF(L34>=F34,"In range","Missed bottom")) -> Beat top | P34: =IF(L34>G34,1,0) -> 1 | Q34: =IF(AND(L34>=F34,L34<=G34),1,0) -> 0 | R34: =IF(L34<F34,1,0) -> 0 | S34: -100 | T34: QA-1546 | U34: ER-2022Q3 | Y34: Guided as an operating loss; % difference uses ABS(midpoint).
A35: Q2 2022 | B35: GH-0015 | C35: ER-2022Q1 | D35: 44697 | E35: Non-GAAP operating income (loss) | F35: -35 | G35: -33 | H35: =(F35+G35)/2 -> -34 | I35: -15358 | J35: QA-0673 | K35: ER-2022Q2 | L35: =I35/1000 -> -15.358 | M35: =L35-H35 -> 18.642 | N35: =M35/ABS(H35) -> 0.54829412 | O35: =IF(L35>G35,"Beat top",IF(L35>=F35,"In range","Missed bottom")) -> Beat top | P35: =IF(L35>G35,1,0) -> 1 | Q35: =IF(AND(L35>=F35,L35<=G35),1,0) -> 0 | R35: =IF(L35<F35,1,0) -> 0 | S35: -200 | T35: QA-1547 | U35: ER-2022Q3 | Y35: Guided as an operating loss; % difference uses ABS(midpoint).
A36: Q3 2022 | B36: GH-0019 | C36: ER-2022Q2 | D36: 44781 | E36: Non-GAAP operating income (loss) | F36: -25 | G36: -24 | H36: =(F36+G36)/2 -> -24.5 | I36: -2185 | J36: QA-0675 | K36: ER-2022Q3 | L36: =I36/1000 -> -2.185 | M36: =L36-H36 -> 22.315 | N36: =M36/ABS(H36) -> 0.91081633 | O36: =IF(L36>G36,"Beat top",IF(L36>=F36,"In range","Missed bottom")) -> Beat top | P36: =IF(L36>G36,1,0) -> 1 | Q36: =IF(AND(L36>=F36,L36<=G36),1,0) -> 0 | R36: =IF(L36<F36,1,0) -> 0 | S36: -300 | T36: QA-1548 | U36: ER-2022Q3 | Y36: Guided as an operating loss; % difference uses ABS(midpoint).
A37: Q4 2022 | B37: GH-0023 | C37: ER-2022Q3 | D37: 44879 | E37: Non-GAAP operating income (loss) | F37: -22 | G37: -20 | H37: =(F37+G37)/2 -> -21 | I37: 14278 | J37: QA-0677 | K37: ER-2022Q4 | L37: =I37/1000 -> 14.278 | M37: =L37-H37 -> 35.278 | N37: =M37/ABS(H37) -> 1.6799048 | O37: =IF(L37>G37,"Beat top",IF(L37>=F37,"In range","Missed bottom")) -> Beat top | P37: =IF(L37>G37,1,0) -> 1 | Q37: =IF(AND(L37>=F37,L37<=G37),1,0) -> 0 | R37: =IF(L37<F37,1,0) -> 0 | S37: -300 | T37: QA-1549 | U37: ER-2022Q4 | Y37: Guided as an operating loss; % difference uses ABS(midpoint).
A38: Q1 2023 | B38: GH-0027 | C38: ER-2022Q4 | D38: 44970 | E38: Non-GAAP operating income (loss) | F38: -19 | G38: -17 | H38: =(F38+G38)/2 -> -18 | I38: -293 | J38: QA-0679 | K38: ER-2023Q1 | L38: =I38/1000 -> -0.293 | M38: =L38-H38 -> 17.707 | N38: =M38/ABS(H38) -> 0.98372222 | O38: =IF(L38>G38,"Beat top",IF(L38>=F38,"In range","Missed bottom")) -> Beat top | P38: =IF(L38>G38,1,0) -> 1 | Q38: =IF(AND(L38>=F38,L38<=G38),1,0) -> 0 | R38: =IF(L38<F38,1,0) -> 0 | S38: -100 | T38: QA-1551 | U38: ER-2023Q1 | Y38: Guided as an operating loss; % difference uses ABS(midpoint).
A39: Q2 2023 | B39: GH-0031 | C39: ER-2023Q1 | D39: 45061 | E39: Non-GAAP operating income (loss) | F39: 2 | G39: 4 | H39: =(F39+G39)/2 -> 3 | I39: 16617 | J39: QA-0680 | K39: ER-2023Q2 | L39: =I39/1000 -> 16.617 | M39: =L39-H39 -> 13.617 | N39: =M39/ABS(H39) -> 4.539 | O39: =IF(L39>G39,"Beat top",IF(L39>=F39,"In range","Missed bottom")) -> Beat top | P39: =IF(L39>G39,1,0) -> 1 | Q39: =IF(AND(L39>=F39,L39<=G39),1,0) -> 0 | R39: =IF(L39<F39,1,0) -> 0 | S39: -100 | T39: QA-1552 | U39: ER-2023Q2
A40: Q3 2023 | B40: GH-0035 | C40: ER-2023Q2 | D40: 45152 | E40: Non-GAAP operating income (loss) | F40: 4 | G40: 6 | H40: =(F40+G40)/2 -> 5 | I40: 24077 | J40: QA-0682 | K40: ER-2023Q3 | L40: =I40/1000 -> 24.077 | M40: =L40-H40 -> 19.077 | N40: =M40/ABS(H40) -> 3.8154 | O40: =IF(L40>G40,"Beat top",IF(L40>=F40,"In range","Missed bottom")) -> Beat top | P40: =IF(L40>G40,1,0) -> 1 | Q40: =IF(AND(L40>=F40,L40<=G40),1,0) -> 0 | R40: =IF(L40<F40,1,0) -> 0 | S40: 0 | T40: QA-1553 | U40: ER-2023Q3
A41: Q4 2023 | B41: GH-0039 | C41: ER-2023Q3 | D41: 45243 | E41: Non-GAAP operating income (loss) | F41: 7 | G41: 9 | H41: =(F41+G41)/2 -> 8 | I41: 21200 | J41: QA-0684 | K41: ER-2023Q4 | L41: =I41/1000 -> 21.2 | M41: =L41-H41 -> 13.2 | N41: =M41/ABS(H41) -> 1.65 | O41: =IF(L41>G41,"Beat top",IF(L41>=F41,"In range","Missed bottom")) -> Beat top | P41: =IF(L41>G41,1,0) -> 1 | Q41: =IF(AND(L41>=F41,L41<=G41),1,0) -> 0 | R41: =IF(L41<F41,1,0) -> 0 | S41: 0 | T41: QA-1554 | U41: ER-2023Q4
A42: Q1 2024 | B42: GH-0045 | C42: ER-2023Q4 | D42: 45334 | E42: Non-GAAP operating income (loss) | F42: 8 | G42: 12 | H42: =(F42+G42)/2 -> 10 | I42: 21521 | J42: QA-0686 | K42: ER-2024Q1 | L42: =I42/1000 -> 21.521 | M42: =L42-H42 -> 11.521 | N42: =M42/ABS(H42) -> 1.1521 | O42: =IF(L42>G42,"Beat top",IF(L42>=F42,"In range","Missed bottom")) -> Beat top | P42: =IF(L42>G42,1,0) -> 1 | Q42: =IF(AND(L42>=F42,L42<=G42),1,0) -> 0 | R42: =IF(L42<F42,1,0) -> 0 | S42: 0 | T42: QA-1556 | U42: ER-2024Q1
A43: Q2 2024 | B43: GH-0051 | C43: ER-2024Q1 | D43: 45427 | E43: Non-GAAP operating income (loss) | F43: 17 | G43: 21 | H43: =(F43+G43)/2 -> 19 | I43: 38417 | J43: QA-0687 | K43: ER-2024Q2 | L43: =I43/1000 -> 38.417 | M43: =L43-H43 -> 19.417 | N43: =M43/ABS(H43) -> 1.0219474 | O43: =IF(L43>G43,"Beat top",IF(L43>=F43,"In range","Missed bottom")) -> Beat top | P43: =IF(L43>G43,1,0) -> 1 | Q43: =IF(AND(L43>=F43,L43<=G43),1,0) -> 0 | R43: =IF(L43<F43,1,0) -> 0 | S43: 0 | T43: QA-1557 | U43: ER-2024Q2
A44: Q3 2024 | B44: GH-0057 | C44: ER-2024Q2 | D44: 45516 | E44: Non-GAAP operating income (loss) | F44: 19 | G44: 23 | H44: =(F44+G44)/2 -> 21 | I44: 32180 | J44: QA-0689 | K44: ER-2024Q3 | L44: =I44/1000 -> 32.18 | M44: =L44-H44 -> 11.18 | N44: =M44/ABS(H44) -> 0.53238095 | O44: =IF(L44>G44,"Beat top",IF(L44>=F44,"In range","Missed bottom")) -> Beat top | P44: =IF(L44>G44,1,0) -> 1 | Q44: =IF(AND(L44>=F44,L44<=G44),1,0) -> 0 | R44: =IF(L44<F44,1,0) -> 0
A45: Q4 2024 | B45: GH-0063 | C45: ER-2024Q3 | D45: 45608 | E45: Non-GAAP operating income (loss) | F45: 29 | G45: 31 | H45: =(F45+G45)/2 -> 30 | I45: 40265 | J45: QA-0691 | K45: ER-2024Q4 | L45: =I45/1000 -> 40.265 | M45: =L45-H45 -> 10.265 | N45: =M45/ABS(H45) -> 0.34216667 | O45: =IF(L45>G45,"Beat top",IF(L45>=F45,"In range","Missed bottom")) -> Beat top | P45: =IF(L45>G45,1,0) -> 1 | Q45: =IF(AND(L45>=F45,L45<=G45),1,0) -> 0 | R45: =IF(L45<F45,1,0) -> 0
A46: Q1 2025 | B46: GH-0068 | C46: ER-2024Q4 | D46: 45698 | E46: Non-GAAP operating income (loss) | F46: 25 | G46: 27 | H46: =(F46+G46)/2 -> 26 | I46: 40754 | J46: QA-0693 | K46: ER-2025Q1 | L46: =I46/1000 -> 40.754 | M46: =L46-H46 -> 14.754 | N46: =M46/ABS(H46) -> 0.56746154 | O46: =IF(L46>G46,"Beat top",IF(L46>=F46,"In range","Missed bottom")) -> Beat top | P46: =IF(L46>G46,1,0) -> 1 | Q46: =IF(AND(L46>=F46,L46<=G46),1,0) -> 0 | R46: =IF(L46<F46,1,0) -> 0
A47: Q2 2025 | B47: GH-0073 | C47: ER-2025Q1 | D47: 45789 | E47: Non-GAAP operating income (loss) | F47: 32 | G47: 34 | H47: =(F47+G47)/2 -> 33 | I47: 45094 | J47: QA-0694 | K47: ER-2025Q2 | L47: =I47/1000 -> 45.094 | M47: =L47-H47 -> 12.094 | N47: =M47/ABS(H47) -> 0.36648485 | O47: =IF(L47>G47,"Beat top",IF(L47>=F47,"In range","Missed bottom")) -> Beat top | P47: =IF(L47>G47,1,0) -> 1 | Q47: =IF(AND(L47>=F47,L47<=G47),1,0) -> 0 | R47: =IF(L47<F47,1,0) -> 0
A48: Q3 2025 | B48: GH-0078 | C48: ER-2025Q2 | D48: 45880 | E48: Non-GAAP operating income (loss) | F48: 34 | G48: 36 | H48: =(F48+G48)/2 -> 35 | I48: 47484 | J48: QA-0696 | K48: ER-2025Q3 | L48: =I48/1000 -> 47.484 | M48: =L48-H48 -> 12.484 | N48: =M48/ABS(H48) -> 0.35668571 | O48: =IF(L48>G48,"Beat top",IF(L48>=F48,"In range","Missed bottom")) -> Beat top | P48: =IF(L48>G48,1,0) -> 1 | Q48: =IF(AND(L48>=F48,L48<=G48),1,0) -> 0 | R48: =IF(L48<F48,1,0) -> 0
A49: Q4 2025 | B49: GH-0083 | C49: ER-2025Q3 | D49: 45971 | E49: Non-GAAP operating income (loss) | F49: 36 | G49: 38 | H49: =(F49+G49)/2 -> 37 | I49: 41931 | J49: QA-0698 | K49: ER-2025Q4 | L49: =I49/1000 -> 41.931 | M49: =L49-H49 -> 4.931 | N49: =M49/ABS(H49) -> 0.13327027 | O49: =IF(L49>G49,"Beat top",IF(L49>=F49,"In range","Missed bottom")) -> Beat top | P49: =IF(L49>G49,1,0) -> 1 | Q49: =IF(AND(L49>=F49,L49<=G49),1,0) -> 0 | R49: =IF(L49<F49,1,0) -> 0 | V49: -180 | W49: QA-1559 | X49: ER-2025Q4 | Y49: FX: from the Q4 2025 release onward the company quantifies FX on non-GAAP operating margin (column V).
A50: Q1 2026 | B50: GH-0088 | C50: ER-2025Q4 | D50: 46062 | E50: Non-GAAP operating income (loss) | F50: 37 | G50: 39 | H50: =(F50+G50)/2 -> 38 | I50: 49037 | J50: QA-0700 | K50: ER-2026Q1 | L50: =I50/1000 -> 49.037 | M50: =L50-H50 -> 11.037 | N50: =M50/ABS(H50) -> 0.29044737 | O50: =IF(L50>G50,"Beat top",IF(L50>=F50,"In range","Missed bottom")) -> Beat top | P50: =IF(L50>G50,1,0) -> 1 | Q50: =IF(AND(L50>=F50,L50<=G50),1,0) -> 0 | R50: =IF(L50<F50,1,0) -> 0 | V50: -190 | W50: QA-1561 | X50: ER-2026Q1 | Y50: Guidance FX assumption: "assuming a negative FX impact of 100 to 200 basis points" FX: from the Q4 2025 release onward the company quantifies FX on non-GAAP operating margin (column V).
A51: Q2 2026 | B51: GH-0093 | C51: ER-2026Q1 | D51: 46153 | E51: Non-GAAP operating income (loss) | F51: 46 | G51: 48 | H51: =(F51+G51)/2 -> 47 | I51: 61110 | J51: QA-0701 | K51: ER-2026Q2 | L51: =I51/1000 -> 61.11 | M51: =L51-H51 -> 14.11 | N51: =M51/ABS(H51) -> 0.30021277 | O51: =IF(L51>G51,"Beat top",IF(L51>=F51,"In range","Missed bottom")) -> Beat top | P51: =IF(L51>G51,1,0) -> 1 | Q51: =IF(AND(L51>=F51,L51<=G51),1,0) -> 0 | R51: =IF(L51<F51,1,0) -> 0 | S51: 110 | T51: QA-1558 | U51: ER-2026Q2 | V51: -210 | W51: QA-1562 | X51: ER-2026Q2 | Y51: Guidance FX assumption: "assuming a negative FX impact of 100 to 200 basis points" FX: from the Q4 2025 release onward the company quantifies FX on non-GAAP operating margin (column V).
A54: Adjusted free cash flow / free cash flow
A55: Quarter | B55: GH Row ID | C55: Source ID | D55: Guidance issued | E55: Guidance metric label | F55: Low (USD m) | G55: High (USD m) | H55: Midpoint (USD m) | I55: Actual (USD k) | J55: Actual Row ID | K55: Actual Source ID | L55: Actual (USD m) | M55: Actual - midpoint (USD m) | N55: % difference vs midpoint | O55: Outcome | P55: Beat top (1/0) | Q55: In range (1/0) | R55: Missed bottom (1/0) | S55: Disclosed FX impact on revenue growth (bps) | T55: FX Row ID | U55: FX Source ID | V55: Disclosed FX impact on non-GAAP op. margin (bps) | W55: FX Row ID | X55: FX Source ID | Y55: FX assumption stated in the guidance (copied text) and notes
A56: Text / label | B56: Source-book Row ID | C56: Source ID | D56: Sourced (copied) | E56: Sourced (copied) | F56: Sourced (copied from source book) | G56: Sourced (copied from source book) | H56: Derived (formula) | I56: Sourced (copied from source book) | J56: Source-book Row ID | K56: Source ID | L56: Derived (formula) | M56: Derived (formula) | N56: Derived (formula) | O56: Derived (formula) | P56: Derived (formula) | Q56: Derived (formula) | R56: Derived (formula) | S56: Sourced (copied from source book) | T56: Source-book Row ID | U56: Source ID | V56: Sourced (copied from source book) | W56: Source-book Row ID | X56: Source ID | Y56: Sourced text / note
A57: Q1 2024 | B57: GH-0044 | C57: ER-2023Q4 | D57: 45334 | E57: Free cash flow | F57: 56 | G57: 60 | H57: =(F57+G57)/2 -> 58 | I57: 89894 | J57: QA-1088 | K57: ER-2024Q1 | L57: =I57/1000 -> 89.894 | M57: =L57-H57 -> 31.894 | N57: =M57/ABS(H57) -> 0.54989655 | O57: =IF(L57>G57,"Beat top",IF(L57>=F57,"In range","Missed bottom")) -> Beat top | P57: =IF(L57>G57,1,0) -> 1 | Q57: =IF(AND(L57>=F57,L57<=G57),1,0) -> 0 | R57: =IF(L57<F57,1,0) -> 0 | S57: 0 | T57: QA-1556 | U57: ER-2024Q1 | Y57: Guided as "free cash flow" (2024); HQ add-back was nil in 2024, so FCF = adjusted FCF for these quarters.
A58: Q2 2024 | B58: GH-0050 | C58: ER-2024Q1 | D58: 45427 | E58: Free cash flow | F58: 47 | G58: 51 | H58: =(F58+G58)/2 -> 49 | I58: 50821 | J58: QA-1089 | K58: ER-2024Q2 | L58: =I58/1000 -> 50.821 | M58: =L58-H58 -> 1.821 | N58: =M58/ABS(H58) -> 0.037163265 | O58: =IF(L58>G58,"Beat top",IF(L58>=F58,"In range","Missed bottom")) -> In range | P58: =IF(L58>G58,1,0) -> 0 | Q58: =IF(AND(L58>=F58,L58<=G58),1,0) -> 1 | R58: =IF(L58<F58,1,0) -> 0 | S58: 0 | T58: QA-1557 | U58: ER-2024Q2 | Y58: Guided as "free cash flow" (2024); HQ add-back was nil in 2024, so FCF = adjusted FCF for these quarters.
A59: Q3 2024 | B59: GH-0056 | C59: ER-2024Q2 | D59: 45516 | E59: Free cash flow | F59: 70 | G59: 74 | H59: =(F59+G59)/2 -> 72 | I59: 82412 | J59: QA-1091 | K59: ER-2024Q3 | L59: =I59/1000 -> 82.412 | M59: =L59-H59 -> 10.412 | N59: =M59/ABS(H59) -> 0.14461111 | O59: =IF(L59>G59,"Beat top",IF(L59>=F59,"In range","Missed bottom")) -> Beat top | P59: =IF(L59>G59,1,0) -> 1 | Q59: =IF(AND(L59>=F59,L59<=G59),1,0) -> 0 | R59: =IF(L59<F59,1,0) -> 0 | Y59: Guided as "free cash flow" (2024); HQ add-back was nil in 2024, so FCF = adjusted FCF for these quarters.
A60: Q4 2024 | B60: GH-0062 | C60: ER-2024Q3 | D60: 45608 | E60: Free cash flow | F60: 63 | G60: 66 | H60: =(F60+G60)/2 -> 64.5 | I60: 72703 | J60: QA-1093 | K60: ER-2024Q4 | L60: =I60/1000 -> 72.703 | M60: =L60-H60 -> 8.203 | N60: =M60/ABS(H60) -> 0.12717829 | O60: =IF(L60>G60,"Beat top",IF(L60>=F60,"In range","Missed bottom")) -> Beat top | P60: =IF(L60>G60,1,0) -> 1 | Q60: =IF(AND(L60>=F60,L60<=G60),1,0) -> 0 | R60: =IF(L60<F60,1,0) -> 0 | Y60: Guided as "free cash flow" (2024); HQ add-back was nil in 2024, so FCF = adjusted FCF for these quarters.
A64: Summary by metric (Derived; formulas over the blocks above)
A65: Metric | B65: Window | C65: Count | D65: Average diff (USD m) | E65: Median diff (USD m) | F65: Average % diff | G65: Median % diff | H65: Std dev of % diff | I65: Min % diff | J65: Max % diff | K65: Beat-top rate | L65: In-range rate | M65: Missed-bottom rate | N65: Quarters covered
A66: Text / label | B66: Text / label | C66: Derived (formula) | D66: Derived (formula) | E66: Derived (formula) | F66: Derived (formula) | G66: Derived (formula) | H66: Derived (formula) | I66: Derived (formula) | J66: Derived (formula) | K66: Derived (formula) | L66: Derived (formula) | M66: Derived (formula) | N66: Derived (formula)
A67: Revenue | B67: All history | C67: =COUNT(L7:L26) -> 20 | D67: =AVERAGE(M7:M26) -> 7.28325 | E67: =MEDIAN(M7:M26) -> 7.22 | F67: =AVERAGE(N7:N26) -> 0.043026244 | G67: =MEDIAN(N7:N26) -> 0.037020593 | H67: =STDEV(N7:N26) -> 0.025658271 | I67: =MIN(N7:N26) -> 0.014826748 | J67: =MAX(N7:N26) -> 0.11433557 | K67: =SUM(P7:P26)/C67 -> 1 | L67: =SUM(Q7:Q26)/C67 -> 0 | M67: =SUM(R7:R26)/C67 -> 0 | N67: =A7&" to "&A26 -> Q3 2021 to Q2 2026
A68: Revenue | B68: Last 8 quarters | C68: =COUNT(L19:L26) -> 8 | D68: =AVERAGE(M19:M26) -> 7.232375 | E68: =MEDIAN(M19:M26) -> 6.495 | F68: =AVERAGE(N19:N26) -> 0.023971999 | G68: =MEDIAN(N19:N26) -> 0.025426716 | H68: =STDEV(N19:N26) -> 0.0069556801 | I68: =MIN(N19:N26) -> 0.014826748 | J68: =MAX(N19:N26) -> 0.036179941 | K68: =SUM(P19:P26)/C68 -> 1 | L68: =SUM(Q19:Q26)/C68 -> 0 | M68: =SUM(R19:R26)/C68 -> 0 | N68: =A19&" to "&A26 -> Q3 2024 to Q2 2026
A69: Non-GAAP operating income | B69: All history | C69: =COUNT(L32:L51) -> 20 | D69: =AVERAGE(M32:M51) -> 14.62105 | E69: =MEDIAN(M32:M51) -> 13.4085 | F69: =AVERAGE(N32:N51) -> 1.0212815 | G69: =MEDIAN(N32:N51) -> 0.56308632 | H69: =STDEV(N32:N51) -> 1.1742991 | I69: =MIN(N32:N51) -> 0.047173913 | J69: =MAX(N32:N51) -> 4.539 | K69: =SUM(P32:P51)/C69 -> 1 | L69: =SUM(Q32:Q51)/C69 -> 0 | M69: =SUM(R32:R51)/C69 -> 0 | N69: =A32&" to "&A51 -> Q3 2021 to Q2 2026
A70: Non-GAAP operating income | B70: Last 8 quarters | C70: =COUNT(L44:L51) -> 8 | D70: =AVERAGE(M44:M51) -> 11.356875 | E70: =MEDIAN(M44:M51) -> 11.637 | F70: =AVERAGE(N44:N51) -> 0.36113877 | G70: =MEDIAN(N44:N51) -> 0.34942619 | H70: =STDEV(N44:N51) -> 0.13780661 | I70: =MIN(N44:N51) -> 0.13327027 | J70: =MAX(N44:N51) -> 0.56746154 | K70: =SUM(P44:P51)/C70 -> 1 | L70: =SUM(Q44:Q51)/C70 -> 0 | M70: =SUM(R44:R51)/C70 -> 0 | N70: =A44&" to "&A51 -> Q3 2024 to Q2 2026
A71: Adjusted free cash flow / free cash flow | B71: All history | C71: =COUNT(L57:L60) -> 4 | D71: =AVERAGE(M57:M60) -> 13.0825 | E71: =MEDIAN(M57:M60) -> 9.3075 | F71: =AVERAGE(N57:N60) -> 0.21471231 | G71: =MEDIAN(N57:N60) -> 0.1358947 | H71: =STDEV(N57:N60) -> 0.22836267 | I71: =MIN(N57:N60) -> 0.037163265 | J71: =MAX(N57:N60) -> 0.54989655 | K71: =SUM(P57:P60)/C71 -> 0.75 | L71: =SUM(Q57:Q60)/C71 -> 0.25 | M71: =SUM(R57:R60)/C71 -> 0 | N71: =A57&" to "&A60 -> Q1 2024 to Q4 2024
A72: Adjusted free cash flow / free cash flow | B72: Last 8 quarters | C72: =COUNT(L57:L60) -> 4 | D72: =AVERAGE(M57:M60) -> 13.0825 | E72: =MEDIAN(M57:M60) -> 9.3075 | F72: =AVERAGE(N57:N60) -> 0.21471231 | G72: =MEDIAN(N57:N60) -> 0.1358947 | H72: =STDEV(N57:N60) -> 0.22836267 | I72: =MIN(N57:N60) -> 0.037163265 | J72: =MAX(N57:N60) -> 0.54989655 | K72: =SUM(P57:P60)/C72 -> 0.75 | L72: =SUM(Q57:Q60)/C72 -> 0.25 | M72: =SUM(R57:R60)/C72 -> 0 | N72: =A57&" to "&A60 -> Q1 2024 to Q4 2024
A74: Notes: % difference = (actual - midpoint) / ABS(midpoint). Free cash flow quarterly guidance was given only for Q1-Q4 2024 (4 quarters), so "Last 8 quarters" equals all history for that metric. Standard deviation is the sample standard deviation (STDEV). Guidance values are rounded to USD millions by the company.
A77: Context: full-year guidance vintages vs. full-year actual (Derived comparison; not part of the quarterly summary)
A78: Fiscal year | B78: GH Row ID | C78: Source ID | D78: Issued with | E78: Metric label | F78: Low (USD m) | G78: High (USD m) | H78: Midpoint (USD m) | I78: FY actual (USD k) | J78: Actual Row ID | K78: Actual Source ID | L78: FY actual (USD m) | M78: Actual - midpoint (USD m) | N78: % difference | O78: Outcome
A79: Text / label | B79: Source-book Row ID | C79: Source ID | D79: Sourced (copied) | E79: Sourced (copied) | F79: Sourced (copied from source book) | G79: Sourced (copied from source book) | H79: Derived (formula) | I79: Sourced (copied from source book) | J79: Source-book Row ID | K79: Source ID | L79: Derived (formula) | M79: Derived (formula) | N79: Derived (formula) | O79: Derived (formula)
A80: FY 2021 | B80: GH-0001 | C80: ER-2021Q2 | D80: Q2 2021 | E80: Non-GAAP operating income (loss) | F80: -93 | G80: -91 | H80: =(F80+G80)/2 -> -92 | I80: -52596 | J80: QA-0671 | K80: ER-2021Q4 | L80: =I80/1000 -> -52.596 | M80: =L80-H80 -> 39.404 | N80: =M80/ABS(H80) -> 0.42830435 | O80: =IF(L80>G80,"Beat top",IF(L80>=F80,"In range","Missed bottom")) -> Beat top
A81: FY 2021 | B81: GH-0002 | C81: ER-2021Q2 | D81: Q2 2021 | E81: Revenue | F81: 280 | G81: 282 | H81: =(F81+G81)/2 -> 281 | I81: 308150 | J81: QA-0007 | K81: ER-2021Q4 | L81: =I81/1000 -> 308.15 | M81: =L81-H81 -> 27.15 | N81: =M81/ABS(H81) -> 0.096619217 | O81: =IF(L81>G81,"Beat top",IF(L81>=F81,"In range","Missed bottom")) -> Beat top
A82: FY 2021 | B82: GH-0005 | C82: ER-2021Q3 | D82: Q3 2021 | E82: Non-GAAP operating income (loss) | F82: -65 | G82: -64 | H82: =(F82+G82)/2 -> -64.5 | I82: -52596 | J82: QA-0671 | K82: ER-2021Q4 | L82: =I82/1000 -> -52.596 | M82: =L82-H82 -> 11.904 | N82: =M82/ABS(H82) -> 0.18455814 | O82: =IF(L82>G82,"Beat top",IF(L82>=F82,"In range","Missed bottom")) -> Beat top
A83: FY 2021 | B83: GH-0006 | C83: ER-2021Q3 | D83: Q3 2021 | E83: Revenue | F83: 300 | G83: 301 | H83: =(F83+G83)/2 -> 300.5 | I83: 308150 | J83: QA-0007 | K83: ER-2021Q4 | L83: =I83/1000 -> 308.15 | M83: =L83-H83 -> 7.65 | N83: =M83/ABS(H83) -> 0.025457571 | O83: =IF(L83>G83,"Beat top",IF(L83>=F83,"In range","Missed bottom")) -> Beat top
A84: FY 2022 | B84: GH-0009 | C84: ER-2021Q4 | D84: Q4 2021 | E84: Non-GAAP operating income (loss) | F84: -147 | G84: -142 | H84: =(F84+G84)/2 -> -144.5 | I84: -47095 | J84: QA-0678 | K84: ER-2022Q4 | L84: =I84/1000 -> -47.095 | M84: =L84-H84 -> 97.405 | N84: =M84/ABS(H84) -> 0.67408304 | O84: =IF(L84>G84,"Beat top",IF(L84>=F84,"In range","Missed bottom")) -> Beat top
A85: FY 2022 | B85: GH-0010 | C85: ER-2021Q4 | D85: Q4 2021 | E85: Revenue | F85: 470 | G85: 475 | H85: =(F85+G85)/2 -> 472.5 | I85: 519029 | J85: QA-0014 | K85: ER-2022Q4 | L85: =I85/1000 -> 519.029 | M85: =L85-H85 -> 46.529 | N85: =M85/ABS(H85) -> 0.098474074 | O85: =IF(L85>G85,"Beat top",IF(L85>=F85,"In range","Missed bottom")) -> Beat top
A86: FY 2022 | B86: GH-0013 | C86: ER-2022Q1 | D86: Q1 2022 | E86: Non-GAAP operating income (loss) | F86: -139 | G86: -135 | H86: =(F86+G86)/2 -> -137 | I86: -47095 | J86: QA-0678 | K86: ER-2022Q4 | L86: =I86/1000 -> -47.095 | M86: =L86-H86 -> 89.905 | N86: =M86/ABS(H86) -> 0.65624088 | O86: =IF(L86>G86,"Beat top",IF(L86>=F86,"In range","Missed bottom")) -> Beat top
A87: FY 2022 | B87: GH-0014 | C87: ER-2022Q1 | D87: Q1 2022 | E87: Revenue | F87: 488 | G87: 492 | H87: =(F87+G87)/2 -> 490 | I87: 519029 | J87: QA-0014 | K87: ER-2022Q4 | L87: =I87/1000 -> 519.029 | M87: =L87-H87 -> 29.029 | N87: =M87/ABS(H87) -> 0.059242857 | O87: =IF(L87>G87,"Beat top",IF(L87>=F87,"In range","Missed bottom")) -> Beat top
A88: FY 2022 | B88: GH-0017 | C88: ER-2022Q2 | D88: Q2 2022 | E88: Non-GAAP operating income (loss) | F88: -112 | G88: -108 | H88: =(F88+G88)/2 -> -110 | I88: -47095 | J88: QA-0678 | K88: ER-2022Q4 | L88: =I88/1000 -> -47.095 | M88: =L88-H88 -> 62.905 | N88: =M88/ABS(H88) -> 0.57186364 | O88: =IF(L88>G88,"Beat top",IF(L88>=F88,"In range","Missed bottom")) -> Beat top
A89: FY 2022 | B89: GH-0018 | C89: ER-2022Q2 | D89: Q2 2022 | E89: Revenue | F89: 498 | G89: 502 | H89: =(F89+G89)/2 -> 500 | I89: 519029 | J89: QA-0014 | K89: ER-2022Q4 | L89: =I89/1000 -> 519.029 | M89: =L89-H89 -> 19.029 | N89: =M89/ABS(H89) -> 0.038058 | O89: =IF(L89>G89,"Beat top",IF(L89>=F89,"In range","Missed bottom")) -> Beat top
A90: FY 2022 | B90: GH-0021 | C90: ER-2022Q3 | D90: Q3 2022 | E90: Non-GAAP operating income (loss) | F90: -83 | G90: -81 | H90: =(F90+G90)/2 -> -82 | I90: -47095 | J90: QA-0678 | K90: ER-2022Q4 | L90: =I90/1000 -> -47.095 | M90: =L90-H90 -> 34.905 | N90: =M90/ABS(H90) -> 0.42567073 | O90: =IF(L90>G90,"Beat top",IF(L90>=F90,"In range","Missed bottom")) -> Beat top
A91: FY 2022 | B91: GH-0022 | C91: ER-2022Q3 | D91: Q3 2022 | E91: Revenue | F91: 509 | G91: 511 | H91: =(F91+G91)/2 -> 510 | I91: 519029 | J91: QA-0014 | K91: ER-2022Q4 | L91: =I91/1000 -> 519.029 | M91: =L91-H91 -> 9.029 | N91: =M91/ABS(H91) -> 0.017703922 | O91: =IF(L91>G91,"Beat top",IF(L91>=F91,"In range","Missed bottom")) -> Beat top
... A123: FY 2025 | B123: GH-0082 | C123: ER-2025Q3 | D123: Q3 2025 | E123: Revenue | F123: 1226 | G123: 1228 | H123: =(F123+G123)/2 -> 1227 | I123: 1231997 | J123: QA-0035 | K123: ER-2025Q4 | L123: =I123/1000 -> 1231.997 | M123: =L123-H123 -> 4.997 | N123: =M123/ABS(H123) -> 0.0040725346 | O123: =IF(L123>G123,"Beat top",IF(L123>=F123,"In range","Missed bottom")) -> Beat top
A126: FY2026 guidance vintages contained in the source book Guidance_History (confirmation list)
A127: GH Row ID | B127: Release date | C127: Issued with | D127: Period covered | E127: Metric | F127: Low | G127: High | H127: Unit | I127: Source ID
A128: Source-book Row ID | B128: Sourced (copied) | C128: Sourced (copied) | D128: Sourced (copied) | E128: Sourced (copied) | F128: Sourced (copied from source book) | G128: Sourced (copied from source book) | H128: Sourced (copied) | I128: Source ID
A129: GH-0085 | B129: 46062 | C129: Q4 2025 | D129: FY 2026 | E129: Adjusted free cash flow | F129: 275 | G129: 290 | H129: USD millions | I129: ER-2025Q4
A130: GH-0086 | B130: 46062 | C130: Q4 2025 | D130: FY 2026 | E130: Non-GAAP operating income (loss) | F130: 165 | G130: 175 | H130: USD millions | I130: ER-2025Q4
A131: GH-0087 | B131: 46062 | C131: Q4 2025 | D131: FY 2026 | E131: Revenue | F131: 1452 | G131: 1462 | H131: USD millions | I131: ER-2025Q4
A132: GH-0088 | B132: 46062 | C132: Q4 2025 | D132: Q1 2026 | E132: Non-GAAP operating income (loss) | F132: 37 | G132: 39 | H132: USD millions | I132: ER-2025Q4
A133: GH-0089 | B133: 46062 | C133: Q4 2025 | D133: Q1 2026 | E133: Revenue | F133: 338 | G133: 340 | H133: USD millions | I133: ER-2025Q4
A134: GH-0090 | B134: 46153 | C134: Q1 2026 | D134: FY 2026 | E134: Adjusted free cash flow | F134: 280 | G134: 290 | H134: USD millions | I134: ER-2026Q1
A135: GH-0091 | B135: 46153 | C135: Q1 2026 | D135: FY 2026 | E135: Non-GAAP operating income (loss) | F135: 185 | G135: 191 | H135: USD millions | I135: ER-2026Q1
A136: GH-0092 | B136: 46153 | C136: Q1 2026 | D136: FY 2026 | E136: Revenue | F136: 1466 | G136: 1474 | H136: USD millions | I136: ER-2026Q1
A137: GH-0093 | B137: 46153 | C137: Q1 2026 | D137: Q2 2026 | E137: Non-GAAP operating income (loss) | F137: 46 | G137: 48 | H137: USD millions | I137: ER-2026Q1
A138: GH-0094 | B138: 46153 | C138: Q1 2026 | D138: Q2 2026 | E138: Revenue | F138: 354 | G138: 356 | H138: USD millions | I138: ER-2026Q1
A139: GH-0095 | B139: 46225 | C139: Interim update (6-K, no results) | D139: FY 2026 | E139: FY 2026 adjusted free cash flow margin (%) | F139: 0.19 | G139: 0.2 | H139: percentage | I139: 6K-20260722-RESTR
A140: GH-0096 | B140: 46225 | C140: Interim update (6-K, no results) | D140: FY 2026 | E140: FY 2026 non-GAAP operating margin (%) | F140: 0.15 | G140: 0.15 | H140: percentage | I140: 6K-20260722-RESTR
... A146: GH-0102 | B146: 46244 | C146: Q2 2026 | D146: Q3 2026 | E146: Revenue | F146: 368 | G146: 370 | H146: USD millions | I146: ER-2026Q2
A148: FY2026 vintages: Feb 9, 2026 (Q4 2025 release), May 11, 2026 (Q1 2026 release), July 22, 2026 (restructuring 6-K: growth/margin percentages only), Aug 10, 2026 (Q2 2026 release). No other FY2026 vintage exists in the source book.

Sheet Growth_Decomposition
A1: Revenue growth alongside disclosed KPIs (descriptive only)
A2: This table places revenue growth next to the KPIs the company discloses. It does not claim that any KPI drives revenue. Blank = not disclosed in the source book for that period.
A4: Quarter | B4: Revenue (USD k) | C4: Row ID | D4: Source ID | E4: Revenue YoY growth | F4: Revenue QoQ growth | G4: NDR - all customers | H4: Row ID | I4: Source ID | J4: NDR - >10 users | K4: Row ID | L4: Source ID | M4: NDR - >$50k ARR | N4: Row ID | O4: Source ID | P4: NDR - >$100k ARR | Q4: Row ID | R4: Source ID | S4: Customers >10 users | T4: Row ID | U4: Source ID | V4: Customers >10 users YoY growth | W4: Customers >$50k ARR | X4: Row ID | Y4: Source ID | Z4: Customers >$50k ARR YoY growth | AA4: Customers >$100k ARR | AB4: Row ID | AC4: Source ID | AD4: Customers >$100k ARR YoY growth | AE4: Customers >$500k ARR | AF4: Row ID | AG4: Source ID | AH4: Customers >$500k ARR YoY growth | AI4: ARR share >10 users | AJ4: Row ID | AK4: Source ID | AL4: ARR share >$50k | AM4: Row ID | AN4: Source ID | AO4: ARR share >$100k | AP4: Row ID | AQ4: Source ID | AR4: ARR share >$500k | AS4: Row ID | AT4: Source ID | AU4: Flags (floors, definition and comparability notes)
A5: Text / label | B5: Sourced (copied from source book) | C5: Source-book Row ID | D5: Source ID | E5: Derived (formula) | F5: Derived (formula) | G5: Sourced (copied from source book) (floor where marked) | H5: Source-book Row ID | I5: Source ID | J5: Sourced (copied from source book) (floor where marked) | K5: Source-book Row ID | L5: Source ID | M5: Sourced (copied from source book) (floor where marked) | N5: Source-book Row ID | O5: Source ID | P5: Sourced (copied from source book) (floor where marked) | Q5: Source-book Row ID | R5: Source ID | S5: Sourced (copied from source book) (floor where marked) | T5: Source-book Row ID | U5: Source ID | V5: Derived (formula) | W5: Sourced (copied from source book) (floor where marked) | X5: Source-book Row ID | Y5: Source ID | Z5: Derived (formula) | AA5: Sourced (copied from source book) (floor where marked) | AB5: Source-book Row ID | AC5: Source ID | AD5: Derived (formula) | AE5: Sourced (copied from source book) (floor where marked) | AF5: Source-book Row ID | AG5: Source ID | AH5: Derived (formula) | AI5: Sourced (copied from source book) (floor where marked) | AJ5: Source-book Row ID | AK5: Source ID | AL5: Sourced (copied from source book) (floor where marked) | AM5: Source-book Row ID | AN5: Source ID | AO5: Sourced (copied from source book) (floor where marked) | AP5: Source-book Row ID | AQ5: Source ID | AR5: Sourced (copied from source book) (floor where marked) | AS5: Source-book Row ID | AT5: Source ID | AU5: Text / label
A6: Q1 2021 | B6: 58972 | C6: QA-0001 | D6: ER-2022Q1 | W6: 335 | X6: QA-1405 | Y6: ER-2022Q1 | AL6: 0.12 | AM6: QA-1492 | AN6: ER-2022Q1 | AU6: YoY revenue growth blank: 2020 quarters are not in the source book (history starts Q1 2021). Customer counts and ARR shares are point-in-time; ARR thresholds are nominal USD.
A7: Q2 2021 | B7: 70615 | C7: QA-0002 | D7: ER-2021Q2 | F7: =IF(OR(B7="",B6=""),"",B7/B6-1) -> 0.19743268 | J7: 1.25 | K7: QA-1353 (floor) | L7: ER-2021Q2 | W7: 470 | X7: QA-1406 | Y7: ER-2021Q2 | AU7: YoY revenue growth blank: 2020 quarters are not in the source book (history starts Q1 2021). NDR - >10 users: floor only (over 125%). >10 users NDR is the only NDR cohort disclosed (cohorts added: all customers Q4 2021, >$50k Q1 2022, >$100k Q4 2023). Customer counts and ARR shares are point-in-time; ARR thresholds are nominal USD.
A8: Q3 2021 | B8: 83018 | C8: QA-0004 | D8: ER-2021Q3 | F8: =IF(OR(B8="",B7=""),"",B8/B7-1) -> 0.17564257 | J8: 1.3 | K8: QA-1354 (floor) | L8: ER-2021Q3 | W8: 613 | X8: QA-1407 | Y8: ER-2021Q3 | AU8: YoY revenue growth blank: 2020 quarters are not in the source book (history starts Q1 2021). NDR - >10 users: floor only (over 130%). Customer counts and ARR shares are point-in-time; ARR thresholds are nominal USD.
A9: Q4 2021 | B9: 95545 | C9: QA-0006 | D9: ER-2021Q4 | F9: =IF(OR(B9="",B8=""),"",B9/B8-1) -> 0.15089499 | G9: 1.2 | H9: QA-1302 (floor) | I9: ER-2021Q4 | J9: 1.35 | K9: QA-1355 (floor) | L9: ER-2021Q4 | W9: 793 | X9: QA-1408 | Y9: ER-2021Q4 | AI9: 0.72 | AJ9: QA-1510 | AK9: ER-2021Q4 | AU9: YoY revenue growth blank: 2020 quarters are not in the source book (history starts Q1 2021). NDR - all customers: floor only (over 120%). NDR - >10 users: floor only (over 135%). Customer counts and ARR shares are point-in-time; ARR thresholds are nominal USD.
A10: Q1 2022 | B10: 108497 | C10: QA-0008 | D10: ER-2022Q1 | E10: =IF(OR(B10="",B6=""),"",B10/B6-1) -> 0.83980533 | F10: =IF(OR(B10="",B9=""),"",B10/B9-1) -> 0.13555916 | G10: 1.25 | H10: QA-1303 (floor) | I10: ER-2022Q1 | J10: 1.35 | K10: QA-1356 (floor) | L10: ER-2022Q1 | M10: 1.5 | N10: QA-1334 (floor) | O10: ER-2022Q1 | V10: =IF(OR(S10="",S6=""),"",S10/S6-1) | W10: 960 | X10: QA-1409 | Y10: ER-2022Q1 | Z10: =IF(OR(W10="",W6=""),"",W10/W6-1) -> 1.8656716 | AD10: =IF(OR(AA10="",AA6=""),"",AA10/AA6-1) | AH10: =IF(OR(AE10="",AE6=""),"",AE10/AE6-1) | AL10: 0.22 | AM10: QA-1493 | AN10: ER-2022Q1 | AU10: NDR - all customers: floor only (over 125%). NDR - >10 users: floor only (over 135%). NDR - >$50k ARR: floor only (over 150%). Customer counts and ARR shares are point-in-time; ARR thresholds are nominal USD.
A11: Q2 2022 | B11: 123718 | C11: QA-0009 | D11: ER-2022Q2 | E11: =IF(OR(B11="",B7=""),"",B11/B7-1) -> 0.75200736 | F11: =IF(OR(B11="",B10=""),"",B11/B10-1) -> 0.14028959 | G11: 1.25 | H11: QA-1304 (floor) | I11: ER-2022Q2 | J11: 1.35 | K11: QA-1357 (floor) | L11: ER-2022Q2 | M11: 1.5 | N11: QA-1335 (floor) | O11: ER-2022Q2 | V11: =IF(OR(S11="",S7=""),"",S11/S7-1) | W11: 1160 | X11: QA-1410 | Y11: ER-2022Q2 | Z11: =IF(OR(W11="",W7=""),"",W11/W7-1) -> 1.4680851 | AD11: =IF(OR(AA11="",AA7=""),"",AA11/AA7-1) | AH11: =IF(OR(AE11="",AE7=""),"",AE11/AE7-1) | AU11: NDR - all customers: floor only (over 125%). NDR - >10 users: floor only (over 135%). NDR - >$50k ARR: floor only (over 150%). Customer counts and ARR shares are point-in-time; ARR thresholds are nominal USD.
A12: Q3 2022 | B12: 136893 | C12: QA-0011 | D12: ER-2022Q3 | E12: =IF(OR(B12="",B8=""),"",B12/B8-1) -> 0.64895565 | F12: =IF(OR(B12="",B11=""),"",B12/B11-1) -> 0.10649218 | G12: 1.2 | H12: QA-1305 (floor) | I12: ER-2022Q3 | J12: 1.35 | K12: QA-1358 (floor) | L12: ER-2022Q3 | M12: 1.45 | N12: QA-1336 (floor) | O12: ER-2022Q3 | V12: =IF(OR(S12="",S8=""),"",S12/S8-1) | W12: 1323 | X12: QA-1411 | Y12: ER-2022Q3 | Z12: =IF(OR(W12="",W8=""),"",W12/W8-1) -> 1.1582382 | AD12: =IF(OR(AA12="",AA8=""),"",AA12/AA8-1) | AH12: =IF(OR(AE12="",AE8=""),"",AE12/AE8-1) | AU12: NDR - all customers: floor only (over 120%). NDR - >10 users: floor only (over 135%). NDR - >$50k ARR: floor only (over 145%). Customer counts and ARR shares are point-in-time; ARR thresholds are nominal USD.
A13: Q4 2022 | B13: 149921 | C13: QA-0013 | D13: ER-2022Q4 | E13: =IF(OR(B13="",B9=""),"",B13/B9-1) -> 0.56911403 | F13: =IF(OR(B13="",B12=""),"",B13/B12-1) -> 0.09516922 | G13: 1.21 | H13: QA-1321 | I13: 20F-FY2024 | J13: 1.3 | K13: QA-1374 | L13: 20F-FY2024 | M13: 1.37 | N13: QA-1352 | O13: 20F-FY2024 | P13: 1.35 | Q13: QA-1333 | R13: 20F-FY2024 | V13: =IF(OR(S13="",S9=""),"",S13/S9-1) | W13: 1474 | X13: QA-1412 | Y13: ER-2022Q4 | Z13: =IF(OR(W13="",W9=""),"",W13/W9-1) -> 0.85876419 | AA13: 527 | AB13: QA-1379 | AC13: ER-2023Q4 | AD13: =IF(OR(AA13="",AA9=""),"",AA13/AA9-1) | AH13: =IF(OR(AE13="",AE9=""),"",AE13/AE9-1) | AU13: NDR - all customers: exact value from 20F-FY2024 later disclosure (release gave a floor). NDR - >10 users: exact value from 20F-FY2024 later disclosure (release gave a floor). NDR - >$50k ARR: exact value from 20F-FY2024 later disclosure (release gave a floor). NDR - >$100k ARR: exact value from 20F-FY2024 later disclosure (release gave a floor). NDR >10 users Q4 2022: release and FY2022/FY2023 20-Fs say "over 130%", FY2024 20-F says 130% (source-book discrepancy D5). Customer counts and ARR shares are point-in-time; ARR thresholds are nominal USD.
A14: Q1 2023 | B14: 162256 | C14: QA-0015 | D14: ER-2023Q1 | E14: =IF(OR(B14="",B10=""),"",B14/B10-1) -> 0.49548835 | F14: =IF(OR(B14="",B13=""),"",B14/B13-1) -> 0.082276666 | G14: 1.15 | H14: QA-1307 (floor) | I14: ER-2023Q1 | J14: 1.25 | K14: QA-1360 (floor) | L14: ER-2023Q1 | M14: 1.25 | N14: QA-1338 (floor) | O14: ER-2023Q1 | S14: 47228 | T14: QA-1460 | U14: ER-2024Q1 | V14: =IF(OR(S14="",S10=""),"",S14/S10-1) | W14: 1683 | X14: QA-1413 | Y14: ER-2023Q1 | Z14: =IF(OR(W14="",W10=""),"",W14/W10-1) -> 0.753125 | AA14: 588 | AB14: QA-1380 | AC14: ER-2024Q1 | AD14: =IF(OR(AA14="",AA10=""),"",AA14/AA10-1) | AH14: =IF(OR(AE14="",AE10=""),"",AE14/AE10-1) | AU14: NDR - all customers: floor only (over 115%). NDR - >10 users: floor only (over 125%). NDR - >$50k ARR: floor only (over 125%). Customer counts and ARR shares are point-in-time; ARR thresholds are nominal USD.
A15: Q2 2023 | B15: 175679 | C15: QA-0016 | D15: ER-2023Q2 | E15: =IF(OR(B15="",B11=""),"",B15/B11-1) -> 0.41999547 | F15: =IF(OR(B15="",B14=""),"",B15/B14-1) -> 0.082727295 | G15: 1.1 | H15: QA-1308 (floor) | I15: ER-2023Q2 | J15: 1.2 | K15: QA-1361 (floor) | L15: ER-2023Q2 | M15: 1.2 | N15: QA-1339 (floor) | O15: ER-2023Q2 | S15: 49936 | T15: QA-1461 | U15: ER-2024Q2 | V15: =IF(OR(S15="",S11=""),"",S15/S11-1) | W15: 1892 | X15: QA-1414 | Y15: ER-2023Q2 | Z15: =IF(OR(W15="",W11=""),"",W15/W11-1) -> 0.63103448 | AA15: 677 | AB15: QA-1381 | AC15: ER-2024Q2 | AD15: =IF(OR(AA15="",AA11=""),"",AA15/AA11-1) | AH15: =IF(OR(AE15="",AE11=""),"",AE15/AE11-1) | AU15: NDR - all customers: floor only (over 110%). NDR - >10 users: floor only (over 120%). NDR - >$50k ARR: floor only (over 120%). Customer counts and ARR shares are point-in-time; ARR thresholds are nominal USD.
A16: Q3 2023 | B16: 189190 | C16: QA-0018 | D16: ER-2023Q3 | E16: =IF(OR(B16="",B12=""),"",B16/B12-1) -> 0.3820283 | F16: =IF(OR(B16="",B15=""),"",B16/B15-1) -> 0.076907314 | G16: 1.1 | H16: QA-1309 (floor) | I16: ER-2023Q3 | J16: 1.15 | K16: QA-1362 (floor) | L16: ER-2023Q3 | M16: 1.15 | N16: QA-1340 (floor) | O16: ER-2023Q3 | S16: 52015 | T16: QA-1462 | U16: ER-2024Q3 | V16: =IF(OR(S16="",S12=""),"",S16/S12-1) | W16: 2077 | X16: QA-1415 | Y16: ER-2023Q3 | Z16: =IF(OR(W16="",W12=""),"",W16/W12-1) -> 0.56991686 | AA16: 749 | AB16: QA-1382 | AC16: ER-2024Q3 | AD16: =IF(OR(AA16="",AA12=""),"",AA16/AA12-1) | AH16: =IF(OR(AE16="",AE12=""),"",AE16/AE12-1) | AU16: NDR - all customers: floor only (over 110%). NDR - >10 users: floor only (over 115%). NDR - >$50k ARR: floor only (over 115%). Customer counts and ARR shares are point-in-time; ARR thresholds are nominal USD.
A17: Q4 2023 | B17: 202570 | C17: QA-0020 | D17: ER-2023Q4 | E17: =IF(OR(B17="",B13=""),"",B17/B13-1) -> 0.35117829 | F17: =IF(OR(B17="",B16=""),"",B17/B16-1) -> 0.070722554 | G17: 1.1 | H17: QA-1310 | I17: ER-2023Q4 | J17: 1.15 | K17: QA-1363 | L17: ER-2023Q4 | M17: 1.15 | N17: QA-1341 | O17: ER-2023Q4 | P17: 1.14 | Q17: QA-1322 | R17: ER-2023Q4 | S17: 53688 | T17: QA-1463 | U17: ER-2024Q4 | V17: =IF(OR(S17="",S13=""),"",S17/S13-1) | W17: 2295 | X17: QA-1416 | Y17: ER-2023Q4 | Z17: =IF(OR(W17="",W13=""),"",W17/W13-1) -> 0.55698779 | AA17: 833 | AB17: QA-1383 | AC17: ER-2023Q4 | AD17: =IF(OR(AA17="",AA13=""),"",AA17/AA13-1) -> 0.58064516 | AH17: =IF(OR(AE17="",AE13=""),"",AE17/AE13-1) | AU17: First quarter with exact (not floor) NDR values; >$100k cohort added. Customer counts and ARR shares are point-in-time; ARR thresholds are nominal USD.
A18: Q1 2024 | B18: 216913 | C18: QA-0022 | D18: ER-2024Q1 | E18: =IF(OR(B18="",B14=""),"",B18/B14-1) -> 0.33685657 | F18: =IF(OR(B18="",B17=""),"",B18/B17-1) -> 0.070805154 | G18: 1.1 | H18: QA-1311 | I18: ER-2024Q1 | J18: 1.14 | K18: QA-1364 | L18: ER-2024Q1 | M18: 1.14 | N18: QA-1342 | O18: ER-2024Q1 | P18: 1.13 | Q18: QA-1323 | R18: ER-2024Q1 | S18: 55515 | T18: QA-1464 | U18: ER-2024Q1 | V18: =IF(OR(S18="",S14=""),"",S18/S14-1) -> 0.17546794 | W18: 2491 | X18: QA-1417 | Y18: ER-2024Q1 | Z18: =IF(OR(W18="",W14=""),"",W18/W14-1) -> 0.48009507 | AA18: 911 | AB18: QA-1384 | AC18: ER-2024Q1 | AD18: =IF(OR(AA18="",AA14=""),"",AA18/AA14-1) -> 0.54931973 | AH18: =IF(OR(AE18="",AE14=""),"",AE18/AE14-1) | AU18: Company (FY2025 20-F) says pricing adjustments in 2024 and H1 2025 positively affected NDR; comparability with other periods is limited. Customer counts and ARR shares are point-in-time; ARR thresholds are nominal USD.
A19: Q2 2024 | B19: 236106 | C19: QA-0023 | D19: ER-2024Q2 | E19: =IF(OR(B19="",B15=""),"",B19/B15-1) -> 0.34396257 | F19: =IF(OR(B19="",B18=""),"",B19/B18-1) -> 0.088482479 | G19: 1.1 | H19: QA-1312 | I19: ER-2024Q2 | J19: 1.14 | K19: QA-1365 | L19: ER-2024Q2 | M19: 1.14 | N19: QA-1343 | O19: ER-2024Q2 | P19: 1.14 | Q19: QA-1324 | R19: ER-2024Q2 | S19: 57203 | T19: QA-1465 | U19: ER-2024Q2 | V19: =IF(OR(S19="",S15=""),"",S19/S15-1) -> 0.14552627 | W19: 2713 | X19: QA-1418 | Y19: ER-2024Q2 | Z19: =IF(OR(W19="",W15=""),"",W19/W15-1) -> 0.43393235 | AA19: 1009 | AB19: QA-1385 | AC19: ER-2024Q2 | AD19: =IF(OR(AA19="",AA15=""),"",AA19/AA15-1) -> 0.49039882 | AH19: =IF(OR(AE19="",AE15=""),"",AE19/AE15-1) | AU19: Company (FY2025 20-F) says pricing adjustments in 2024 and H1 2025 positively affected NDR; comparability with other periods is limited. Customer counts and ARR shares are point-in-time; ARR thresholds are nominal USD.
A20: Q3 2024 | B20: 251000 | C20: QA-0025 | D20: ER-2024Q3 | E20: =IF(OR(B20="",B16=""),"",B20/B16-1) -> 0.3267086 | F20: =IF(OR(B20="",B19=""),"",B20/B19-1) -> 0.063081836 | G20: 1.11 | H20: QA-1313 | I20: ER-2024Q3 | J20: 1.14 | K20: QA-1366 | L20: ER-2024Q3 | M20: 1.15 | N20: QA-1344 | O20: ER-2024Q3 | P20: 1.15 | Q20: QA-1325 | R20: ER-2024Q3 | S20: 58760 | T20: QA-1466 | U20: ER-2024Q3 | V20: =IF(OR(S20="",S16=""),"",S20/S16-1) -> 0.12967413 | W20: 2907 | X20: QA-1419 | Y20: ER-2024Q3 | Z20: =IF(OR(W20="",W16=""),"",W20/W16-1) -> 0.39961483 | AA20: 1080 | AB20: QA-1386 | AC20: ER-2024Q3 | AD20: =IF(OR(AA20="",AA16=""),"",AA20/AA16-1) -> 0.44192256 | AE20: 45 | AF20: QA-1448 | AG20: ER-2025Q3 | AH20: =IF(OR(AE20="",AE16=""),"",AE20/AE16-1) | AI20: 0.79 | AJ20: QA-1511 | AK20: ER-2025Q3 | AL20: 0.34 | AM20: QA-1494 | AN20: ER-2025Q3 | AO20: 0.22 | AP20: QA-1484 | AQ20: ER-2025Q3 | AR20: 0.04 | AS20: QA-1502 | AT20: ER-2025Q3 | AU20: Company (FY2025 20-F) says pricing adjustments in 2024 and H1 2025 positively affected NDR; comparability with other periods is limited. Customer counts and ARR shares are point-in-time; ARR thresholds are nominal USD.
A21: Q4 2024 | B21: 267976 | C21: QA-0027 | D21: ER-2024Q4 | E21: =IF(OR(B21="",B17=""),"",B21/B17-1) -> 0.32288098 | F21: =IF(OR(B21="",B20=""),"",B21/B20-1) -> 0.067633466 | G21: 1.12 | H21: QA-1314 | I21: ER-2024Q4 | J21: 1.15 | K21: QA-1367 | L21: ER-2024Q4 | M21: 1.15 | N21: QA-1345 | O21: ER-2024Q4 | P21: 1.16 | Q21: QA-1326 | R21: ER-2024Q4 | S21: 59214 | T21: QA-1467 | U21: ER-2024Q4 | V21: =IF(OR(S21="",S17=""),"",S21/S17-1) -> 0.10292803 | W21: 3201 | X21: QA-1420 | Y21: ER-2024Q4 | Z21: =IF(OR(W21="",W17=""),"",W21/W17-1) -> 0.39477124 | AA21: 1207 | AB21: QA-1387 | AC21: ER-2024Q4 | AD21: =IF(OR(AA21="",AA17=""),"",AA21/AA17-1) -> 0.44897959 | AE21: 50 | AF21: QA-1449 | AG21: ER-2025Q4 | AH21: =IF(OR(AE21="",AE17=""),"",AE21/AE17-1) | AI21: 0.79 | AJ21: QA-1512 | AK21: ER-2025Q4 | AL21: 0.36 | AM21: QA-1495 | AN21: ER-2025Q4 | AO21: 0.24 | AP21: QA-1485 | AQ21: ER-2025Q4 | AR21: 0.04 | AS21: QA-1503 | AT21: ER-2025Q4 | AU21: Company (FY2025 20-F) says pricing adjustments in 2024 and H1 2025 positively affected NDR; comparability with other periods is limited. Customer counts and ARR shares are point-in-time; ARR thresholds are nominal USD.
A22: Q1 2025 | B22: 282250 | C22: QA-0029 | D22: ER-2025Q1 | E22: =IF(OR(B22="",B18=""),"",B22/B18-1) -> 0.30121293 | F22: =IF(OR(B22="",B21=""),"",B22/B21-1) -> 0.053265964 | G22: 1.12 | H22: QA-1315 | I22: ER-2025Q1 | J22: 1.15 | K22: QA-1368 | L22: ER-2025Q1 | M22: 1.16 | N22: QA-1346 | O22: ER-2025Q1 | P22: 1.17 | Q22: QA-1327 | R22: ER-2025Q1 | S22: 60566 | T22: QA-1468 | U22: ER-2025Q1 | V22: =IF(OR(S22="",S18=""),"",S22/S18-1) -> 0.090984419 | W22: 3444 | X22: QA-1421 | Y22: ER-2025Q1 | Z22: =IF(OR(W22="",W18=""),"",W22/W18-1) -> 0.38257728 | AA22: 1328 | AB22: QA-1388 | AC22: ER-2025Q1 | AD22: =IF(OR(AA22="",AA18=""),"",AA22/AA18-1) -> 0.45773875 | AE22: 57 | AF22: QA-1450 | AG22: ER-2026Q1 | AH22: =IF(OR(AE22="",AE18=""),"",AE22/AE18-1) | AI22: 0.8 | AJ22: QA-1513 | AK22: ER-2026Q1 | AL22: 0.37 | AM22: QA-1496 | AN22: ER-2026Q1 | AO22: 0.24 | AP22: QA-1486 | AQ22: ER-2026Q1 | AR22: 0.05 | AS22: QA-1504 | AT22: ER-2026Q1 | AU22: Company (FY2025 20-F) says pricing adjustments in 2024 and H1 2025 positively affected NDR; comparability with other periods is limited. Customer counts and ARR shares are point-in-time; ARR thresholds are nominal USD.
A23: Q2 2025 | B23: 299014 | C23: QA-0030 | D23: ER-2025Q2 | E23: =IF(OR(B23="",B19=""),"",B23/B19-1) -> 0.26643965 | F23: =IF(OR(B23="",B22=""),"",B23/B22-1) -> 0.059394154 | G23: 1.11 | H23: QA-1316 | I23: ER-2025Q2 | J23: 1.15 | K23: QA-1369 | L23: ER-2025Q2 | M23: 1.16 | N23: QA-1347 | O23: ER-2025Q2 | P23: 1.17 | Q23: QA-1328 | R23: ER-2025Q2 | S23: 61803 | T23: QA-1469 | U23: ER-2025Q2 | V23: =IF(OR(S23="",S19=""),"",S23/S19-1) -> 0.080415363 | W23: 3702 | X23: QA-1422 | Y23: ER-2025Q2 | Z23: =IF(OR(W23="",W19=""),"",W23/W19-1) -> 0.3645411 | AA23: 1472 | AB23: QA-1389 | AC23: ER-2025Q2 | AD23: =IF(OR(AA23="",AA19=""),"",AA23/AA19-1) -> 0.45887017 | AE23: 68 | AF23: QA-1451 | AG23: ER-2026Q2 | AH23: =IF(OR(AE23="",AE19=""),"",AE23/AE19-1) | AI23: 0.8 | AJ23: QA-1514 | AK23: ER-2026Q2 | AL23: 0.38 | AM23: QA-1497 | AN23: ER-2026Q2 | AO23: 0.26 | AP23: QA-1487 | AQ23: ER-2026Q2 | AR23: 0.05 | AS23: QA-1505 | AT23: ER-2026Q2 | AU23: Company (FY2025 20-F) says pricing adjustments in 2024 and H1 2025 positively affected NDR; comparability with other periods is limited. Customer counts and ARR shares are point-in-time; ARR thresholds are nominal USD.
A24: Q3 2025 | B24: 316855 | C24: QA-0032 | D24: ER-2025Q3 | E24: =IF(OR(B24="",B20=""),"",B24/B20-1) -> 0.26237052 | F24: =IF(OR(B24="",B23=""),"",B24/B23-1) -> 0.059666103 | G24: 1.11 | H24: QA-1317 | I24: ER-2025Q3 | J24: 1.15 | K24: QA-1370 | L24: ER-2025Q3 | M24: 1.17 | N24: QA-1348 | O24: ER-2025Q3 | P24: 1.17 | Q24: QA-1329 | R24: ER-2025Q3 | S24: 63075 | T24: QA-1470 | U24: ER-2025Q3 | V24: =IF(OR(S24="",S20=""),"",S24/S20-1) -> 0.073434309 | W24: 3993 | X24: QA-1423 | Y24: ER-2025Q3 | Z24: =IF(OR(W24="",W20=""),"",W24/W20-1) -> 0.37358101 | AA24: 1603 | AB24: QA-1390 | AC24: ER-2025Q3 | AD24: =IF(OR(AA24="",AA20=""),"",AA24/AA20-1) -> 0.48425926 | AE24: 78 | AF24: QA-1452 | AG24: ER-2025Q3 | AH24: =IF(OR(AE24="",AE20=""),"",AE24/AE20-1) -> 0.73333333 | AI24: 0.81 | AJ24: QA-1515 | AK24: ER-2025Q3 | AL24: 0.4 | AM24: QA-1498 | AN24: ER-2025Q3 | AO24: 0.27 | AP24: QA-1488 | AQ24: ER-2025Q3 | AR24: 0.06 | AS24: QA-1506 | AT24: ER-2025Q3 | AU24: Company says NDR reflects expansion partly offset by the anniversary of 2024-H1 2025 pricing adjustments. >$500k cohort and ARR-share-by-threshold disclosures begin (comparatives from Q3 2024). Customer counts and ARR shares are point-in-time; ARR thresholds are nominal USD.
A25: Q4 2025 | B25: 333878 | C25: QA-0034 | D25: ER-2025Q4 | E25: =IF(OR(B25="",B21=""),"",B25/B21-1) -> 0.24592501 | F25: =IF(OR(B25="",B24=""),"",B25/B24-1) -> 0.05372489 | G25: 1.1 | H25: QA-1318 | I25: ER-2025Q4 | J25: 1.14 | K25: QA-1371 | L25: ER-2025Q4 | M25: 1.16 | N25: QA-1349 | O25: ER-2025Q4 | P25: 1.16 | Q25: QA-1330 | R25: ER-2025Q4 | S25: 63914 | T25: QA-1471 | U25: ER-2025Q4 | V25: =IF(OR(S25="",S21=""),"",S25/S21-1) -> 0.079373121 | W25: 4281 | X25: QA-1424 | Y25: ER-2025Q4 | Z25: =IF(OR(W25="",W21=""),"",W25/W21-1) -> 0.33739456 | AA25: 1756 | AB25: QA-1391 | AC25: ER-2025Q4 | AD25: =IF(OR(AA25="",AA21=""),"",AA25/AA21-1) -> 0.45484673 | AE25: 87 | AF25: QA-1453 | AG25: ER-2025Q4 | AH25: =IF(OR(AE25="",AE21=""),"",AE25/AE21-1) -> 0.74 | AI25: 0.81 | AJ25: QA-1516 | AK25: ER-2025Q4 | AL25: 0.41 | AM25: QA-1499 | AN25: ER-2025Q4 | AO25: 0.28 | AP25: QA-1489 | AQ25: ER-2025Q4 | AR25: 0.06 | AS25: QA-1507 | AT25: ER-2025Q4 | AU25: Company says NDR reflects expansion partly offset by the anniversary of 2024-H1 2025 pricing adjustments. Customer counts and ARR shares are point-in-time; ARR thresholds are nominal USD.
A26: Q1 2026 | B26: 351265 | C26: QA-0036 | D26: ER-2026Q1 | E26: =IF(OR(B26="",B22=""),"",B26/B22-1) -> 0.24451727 | F26: =IF(OR(B26="",B25=""),"",B26/B25-1) -> 0.052075908 | G26: 1.1 | H26: QA-1319 | I26: ER-2026Q1 | J26: 1.14 | K26: QA-1372 | L26: ER-2026Q1 | M26: 1.16 | N26: QA-1350 | O26: ER-2026Q1 | P26: 1.15 | Q26: QA-1331 | R26: ER-2026Q1 | S26: 65016 | T26: QA-1472 | U26: ER-2026Q1 | V26: =IF(OR(S26="",S22=""),"",S26/S22-1) -> 0.073473566 | W26: 4547 | X26: QA-1425 | Y26: ER-2026Q1 | Z26: =IF(OR(W26="",W22=""),"",W26/W22-1) -> 0.32026713 | AA26: 1844 | AB26: QA-1392 | AC26: ER-2026Q1 | AD26: =IF(OR(AA26="",AA22=""),"",AA26/AA22-1) -> 0.38855422 | AE26: 99 | AF26: QA-1454 | AG26: ER-2026Q1 | AH26: =IF(OR(AE26="",AE22=""),"",AE26/AE22-1) -> 0.73684211 | AI26: 0.82 | AJ26: QA-1517 | AK26: ER-2026Q1 | AL26: 0.42 | AM26: QA-1500 | AN26: ER-2026Q1 | AO26: 0.29 | AP26: QA-1490 | AQ26: ER-2026Q1 | AR26: 0.06 | AS26: QA-1508 | AT26: ER-2026Q1 | AU26: Company says NDR reflects expansion partly offset by the anniversary of 2024-H1 2025 pricing adjustments. Q1 2026: AI Work Platform launched with seats-plus-credits pricing (source book Definitions / Not_Disclosed). Customer counts and ARR shares are point-in-time; ARR thresholds are nominal USD.
A27: Q2 2026 | B27: 364621 | C27: QA-0037 | D27: ER-2026Q2 | E27: =IF(OR(B27="",B23=""),"",B27/B23-1) -> 0.21941113 | F27: =IF(OR(B27="",B26=""),"",B27/B26-1) -> 0.038022576 | G27: 1.09 | H27: QA-1320 | I27: ER-2026Q2 | J27: 1.13 | K27: QA-1373 | L27: ER-2026Q2 | M27: 1.15 | N27: QA-1351 | O27: ER-2026Q2 | P27: 1.15 | Q27: QA-1332 | R27: ER-2026Q2 | S27: 65783 | T27: QA-1473 | U27: ER-2026Q2 | V27: =IF(OR(S27="",S23=""),"",S27/S23-1) -> 0.064398168 | W27: 4834 | X27: QA-1426 | Y27: ER-2026Q2 | Z27: =IF(OR(W27="",W23=""),"",W27/W23-1) -> 0.30578066 | AA27: 2019 | AB27: QA-1393 | AC27: ER-2026Q2 | AD27: =IF(OR(AA27="",AA23=""),"",AA27/AA23-1) -> 0.37160326 | AE27: 114 | AF27: QA-1455 | AG27: ER-2026Q2 | AH27: =IF(OR(AE27="",AE23=""),"",AE27/AE23-1) -> 0.67647059 | AI27: 0.82 | AJ27: QA-1518 | AK27: ER-2026Q2 | AL27: 0.43 | AM27: QA-1501 | AN27: ER-2026Q2 | AO27: 0.3 | AP27: QA-1491 | AQ27: ER-2026Q2 | AR27: 0.07 | AS27: QA-1509 | AT27: ER-2026Q2 | AU27: Company says NDR reflects expansion partly offset by the anniversary of 2024-H1 2025 pricing adjustments. Q1 2026: AI Work Platform launched with seats-plus-credits pricing (source book Definitions / Not_Disclosed). Customer counts and ARR shares are point-in-time; ARR thresholds are nominal USD.
A30: Chart data (Derived links to the table above; for plotting only)
A31: Quarter | B31: Revenue YoY growth | C31: NDR all (value or floor) | D31: NDR >$100k | E31: Customers >$100k YoY growth | F31: ARR share >$100k
A32: Text / label | B32: Derived (formula) | C32: Derived (formula) | D32: Derived (formula) | E32: Derived (formula) | F32: Derived (formula)
A33: =A6 -> Q1 2021 | B33: =IF(E6="","",E6) | C33: =IF(G6="","",G6) | D33: =IF(P6="","",P6) | E33: =IF(AD6="","",AD6) | F33: =IF(AO6="","",AO6)
A34: =A7 -> Q2 2021 | B34: =IF(E7="","",E7) | C34: =IF(G7="","",G7) | D34: =IF(P7="","",P7) | E34: =IF(AD7="","",AD7) | F34: =IF(AO7="","",AO7)
A35: =A8 -> Q3 2021 | B35: =IF(E8="","",E8) | C35: =IF(G8="","",G8) | D35: =IF(P8="","",P8) | E35: =IF(AD8="","",AD8) | F35: =IF(AO8="","",AO8)
A36: =A9 -> Q4 2021 | B36: =IF(E9="","",E9) | C36: =IF(G9="","",G9) -> 1.2 | D36: =IF(P9="","",P9) | E36: =IF(AD9="","",AD9) | F36: =IF(AO9="","",AO9)
A37: =A10 -> Q1 2022 | B37: =IF(E10="","",E10) -> 0.83980533 | C37: =IF(G10="","",G10) -> 1.25 | D37: =IF(P10="","",P10) | E37: =IF(AD10="","",AD10) | F37: =IF(AO10="","",AO10)
A38: =A11 -> Q2 2022 | B38: =IF(E11="","",E11) -> 0.75200736 | C38: =IF(G11="","",G11) -> 1.25 | D38: =IF(P11="","",P11) | E38: =IF(AD11="","",AD11) | F38: =IF(AO11="","",AO11)
A39: =A12 -> Q3 2022 | B39: =IF(E12="","",E12) -> 0.64895565 | C39: =IF(G12="","",G12) -> 1.2 | D39: =IF(P12="","",P12) | E39: =IF(AD12="","",AD12) | F39: =IF(AO12="","",AO12)
A40: =A13 -> Q4 2022 | B40: =IF(E13="","",E13) -> 0.56911403 | C40: =IF(G13="","",G13) -> 1.21 | D40: =IF(P13="","",P13) -> 1.35 | E40: =IF(AD13="","",AD13) | F40: =IF(AO13="","",AO13)
A41: =A14 -> Q1 2023 | B41: =IF(E14="","",E14) -> 0.49548835 | C41: =IF(G14="","",G14) -> 1.15 | D41: =IF(P14="","",P14) | E41: =IF(AD14="","",AD14) | F41: =IF(AO14="","",AO14)
A42: =A15 -> Q2 2023 | B42: =IF(E15="","",E15) -> 0.41999547 | C42: =IF(G15="","",G15) -> 1.1 | D42: =IF(P15="","",P15) | E42: =IF(AD15="","",AD15) | F42: =IF(AO15="","",AO15)
A43: =A16 -> Q3 2023 | B43: =IF(E16="","",E16) -> 0.3820283 | C43: =IF(G16="","",G16) -> 1.1 | D43: =IF(P16="","",P16) | E43: =IF(AD16="","",AD16) | F43: =IF(AO16="","",AO16)
A44: =A17 -> Q4 2023 | B44: =IF(E17="","",E17) -> 0.35117829 | C44: =IF(G17="","",G17) -> 1.1 | D44: =IF(P17="","",P17) -> 1.14 | E44: =IF(AD17="","",AD17) -> 0.58064516 | F44: =IF(AO17="","",AO17)
... A54: =A27 -> Q2 2026 | B54: =IF(E27="","",E27) -> 0.21941113 | C54: =IF(G27="","",G27) -> 1.09 | D54: =IF(P27="","",P27) -> 1.15 | E54: =IF(AD27="","",AD27) -> 0.37160326 | F54: =IF(AO27="","",AO27) -> 0.3

Sheet Margin_Structure
A1: Margin structure: gross margin and operating expense ratios (GAAP and non-GAAP)
A2: Inputs USD thousands from Quarterly_Actuals (3-month and fiscal-year rows). Ratios are Derived (line / revenue). No adjustment is made for the 2025 commission model change.
A4: Period | B4: Basis | C4: Fiscal year | D4: Fiscal quarter | E4: Revenue (USD k) | F4: Row ID | G4: Source ID | H4: Gross profit (GAAP) (USD k) | I4: Row ID | J4: Source ID | K4: Gross profit (non-GAAP) (USD k) | L4: Row ID | M4: Source ID | N4: R&D (GAAP) (USD k) | O4: Row ID | P4: Source ID | Q4: R&D (non-GAAP) (USD k) | R4: Row ID | S4: Source ID | T4: S&M (GAAP) (USD k) | U4: Row ID | V4: Source ID | W4: S&M (non-GAAP) (USD k) | X4: Row ID | Y4: Source ID | Z4: G&A (GAAP) (USD k) | AA4: Row ID | AB4: Source ID | AC4: G&A (non-GAAP) (USD k) | AD4: Row ID | AE4: Source ID | AF4: Operating income (GAAP) (USD k) | AG4: Row ID | AH4: Source ID | AI4: Operating income (non-GAAP) (USD k) | AJ4: Row ID | AK4: Source ID | AL4: Gross margin (GAAP) | AM4: Gross margin (non-GAAP) | AN4: R&D % rev (GAAP) | AO4: R&D % rev (non-GAAP) | AP4: S&M % rev (GAAP) | AQ4: S&M % rev (non-GAAP) | AR4: G&A % rev (GAAP) | AS4: G&A % rev (non-GAAP) | AT4: Operating margin (GAAP) | AU4: Operating margin (non-GAAP) | AV4: Gross margin (non-GAAP): quarter minus same-year FY ratio | AW4: R&D % rev (non-GAAP): quarter minus same-year FY ratio | AX4: S&M % rev (non-GAAP): quarter minus same-year FY ratio | AY4: G&A % rev (non-GAAP): quarter minus same-year FY ratio | AZ4: Operating margin (non-GAAP): quarter minus same-year FY ratio
A5: Text / label | B5: Text / label | C5: Text / label | D5: Text / label | E5: Sourced (copied from source book) | F5: Source-book Row ID | G5: Source ID | H5: Sourced (copied from source book) | I5: Source-book Row ID | J5: Source ID | K5: Sourced (copied from source book) | L5: Source-book Row ID | M5: Source ID | N5: Sourced (copied from source book) | O5: Source-book Row ID | P5: Source ID | Q5: Sourced (copied from source book) | R5: Source-book Row ID | S5: Source ID | T5: Sourced (copied from source book) | U5: Source-book Row ID | V5: Source ID | W5: Sourced (copied from source book) | X5: Source-book Row ID | Y5: Source ID | Z5: Sourced (copied from source book) | AA5: Source-book Row ID | AB5: Source ID | AC5: Sourced (copied from source book) | AD5: Source-book Row ID | AE5: Source ID | AF5: Sourced (copied from source book) | AG5: Source-book Row ID | AH5: Source ID | AI5: Sourced (copied from source book) | AJ5: Source-book Row ID | AK5: Source ID | AL5: Derived (formula) | AM5: Derived (formula) | AN5: Derived (formula) | AO5: Derived (formula) | AP5: Derived (formula) | AQ5: Derived (formula) | AR5: Derived (formula) | AS5: Derived (formula) | AT5: Derived (formula) | AU5: Derived (formula) | AV5: Derived (formula) | AW5: Derived (formula) | AX5: Derived (formula) | AY5: Derived (formula) | AZ5: Derived (formula)
A6: Q1 2021 | B6: Quarter | C6: 2021 | D6: 1 | E6: 58972 | F6: QA-0001 | G6: ER-2022Q1 | H6: 51048 | I6: QA-0077 | J6: ER-2022Q1 | K6: 52579 | L6: QA-0475 | M6: ER-2022Q1 | N6: 15581 | O6: QA-0153 | P6: ER-2022Q1 | Q6: 11044 | R6: QA-0551 | S6: ER-2022Q1 | T6: 63048 | U6: QA-0191 | V6: ER-2022Q1 | W6: 59014 | X6: QA-0589 | Y6: ER-2022Q1 | Z6: 10266 | AA6: QA-0229 | AB6: ER-2022Q1 | AC6: 5828 | AD6: QA-0627 | AE6: ER-2022Q1 | AF6: -37847 | AG6: QA-0307 | AH6: ER-2022Q1 | AI6: -23307 | AJ6: QA-0665 | AK6: ER-2022Q1 | AL6: =H6/E6 -> 0.86563115 | AM6: =K6/E6 -> 0.89159262 | AN6: =N6/E6 -> 0.26421013 | AO6: =Q6/E6 -> 0.18727532 | AP6: =T6/E6 -> 1.0691175 | AQ6: =W6/E6 -> 1.0007122 | AR6: =Z6/E6 -> 0.17408262 | AS6: =AC6/E6 -> 0.098826562 | AT6: =AF6/E6 -> -0.64177915 | AU6: =AI6/E6 -> -0.39522146 | AV6: =AM6-AM28 -> -0.0067296254 | AW6: =AO6-AO28 -> 0.018828132 | AX6: =AQ6-AQ28 -> 0.20581361 | AY6: =AS6-AS28 -> -0.0068330196 | AZ6: =AU6-AU28 -> -0.22453835
A7: Q2 2021 | B7: Quarter | C7: 2021 | D7: 2 | E7: 70615 | F7: QA-0002 | G7: ER-2021Q2 | H7: 61507 | I7: QA-0078 | J7: ER-2021Q2 | K7: 63340 | L7: QA-0476 | M7: ER-2021Q2 | N7: 16271 | O7: QA-0154 | P7: ER-2021Q2 | Q7: 11203 | R7: QA-0552 | S7: ER-2021Q2 | T7: 61057 | U7: QA-0192 | V7: ER-2021Q2 | W7: 55521 | X7: QA-0590 | Y7: ER-2021Q2 | Z7: 11648 | AA7: QA-0230 | AB7: ER-2021Q2 | AC7: 6527 | AD7: QA-0628 | AE7: ER-2021Q2 | AF7: -27469 | AG7: QA-0308 | AH7: ER-2021Q2 | AI7: -9911 | AJ7: QA-0666 | AK7: ER-2021Q2 | AL7: =H7/E7 -> 0.87101891 | AM7: =K7/E7 -> 0.89697656 | AN7: =N7/E7 -> 0.23041847 | AO7: =Q7/E7 -> 0.15864901 | AP7: =T7/E7 -> 0.86464632 | AQ7: =W7/E7 -> 0.78624938 | AR7: =Z7/E7 -> 0.16495079 | AS7: =AC7/E7 -> 0.092430787 | AT7: =AF7/E7 -> -0.38899667 | AU7: =AI7/E7 -> -0.14035262 | AV7: =AM7-AM28 -> -0.0013456826 | AW7: =AO7-AO28 -> -0.0097981726 | AX7: =AQ7-AQ28 -> -0.0086492079 | AY7: =AS7-AS28 -> -0.013228795 | AZ7: =AU7-AU28 -> 0.030330493
A8: Q3 2021 | B8: Quarter | C8: 2021 | D8: 3 | E8: 83018 | F8: QA-0004 | G8: ER-2021Q3 | H8: 72805 | I8: QA-0080 | J8: ER-2021Q3 | K8: 74912 | L8: QA-0478 | M8: ER-2021Q3 | N8: 19875 | O8: QA-0156 | P8: ER-2021Q3 | Q8: 14255 | R8: QA-0554 | S8: ER-2021Q3 | T8: 67443 | U8: QA-0194 | V8: ER-2021Q3 | W8: 60995 | X8: QA-0592 | Y8: ER-2021Q3 | Z8: 14698 | AA8: QA-0232 | AB8: ER-2021Q3 | AC8: 9111 | AD8: QA-0630 | AE8: ER-2021Q3 | AF8: -29211 | AG8: QA-0310 | AH8: ER-2021Q3 | AI8: -9449 | AJ8: QA-0668 | AK8: ER-2021Q3 | AL8: =H8/E8 -> 0.87697849 | AM8: =K8/E8 -> 0.90235852 | AN8: =N8/E8 -> 0.23940591 | AO8: =Q8/E8 -> 0.17170975 | AP8: =T8/E8 -> 0.81239008 | AQ8: =W8/E8 -> 0.73472018 | AR8: =Z8/E8 -> 0.17704594 | AS8: =AC8/E8 -> 0.10974728 | AT8: =AF8/E8 -> -0.35186345 | AU8: =AI8/E8 -> -0.11381869 | AV8: =AM8-AM28 -> 0.004036279 | AW8: =AO8-AO28 -> 0.0032625649 | AX8: =AQ8-AQ28 -> -0.060178407 | AY8: =AS8-AS28 -> 0.0040877023 | AZ8: =AU8-AU28 -> 0.056864419
A9: Q4 2021 | B9: Quarter | C9: 2021 | D9: 4 | E9: 95545 | F9: QA-0006 | G9: ER-2021Q4 | H9: 83777 | I9: QA-0082 | J9: ER-2021Q4 | K9: 85987 | L9: QA-0480 | M9: ER-2021Q4 | N9: 21959 | O9: QA-0158 | P9: ER-2021Q4 | Q9: 15405 | R9: QA-0556 | S9: ER-2021Q4 | T9: 76535 | U9: QA-0196 | V9: ER-2021Q4 | W9: 69418 | X9: QA-0594 | Y9: ER-2021Q4 | Z9: 16881 | AA9: QA-0234 | AB9: ER-2021Q4 | AC9: 11093 | AD9: QA-0632 | AE9: ER-2021Q4 | AF9: -31598 | AG9: QA-0312 | AH9: ER-2021Q4 | AI9: -9929 | AJ9: QA-0670 | AK9: ER-2021Q4 | AL9: =H9/E9 -> 0.87683291 | AM9: =K9/E9 -> 0.89996337 | AN9: =N9/E9 -> 0.22982888 | AO9: =Q9/E9 -> 0.16123293 | AP9: =T9/E9 -> 0.80103616 | AQ9: =W9/E9 -> 0.7265477 | AR9: =Z9/E9 -> 0.17668115 | AS9: =AC9/E9 -> 0.11610236 | AT9: =AF9/E9 -> -0.33071328 | AU9: =AI9/E9 -> -0.10391962 | AV9: =AM9-AM28 -> 0.0016411224 | AW9: =AO9-AO28 -> -0.0072142579 | AX9: =AQ9-AQ28 -> -0.068350888 | AY9: =AS9-AS28 -> 0.010442779 | AZ9: =AU9-AU28 -> 0.06676349
A10: Q1 2022 | B10: Quarter | C10: 2022 | D10: 1 | E10: 108497 | F10: QA-0008 | G10: ER-2022Q1 | H10: 93888 | I10: QA-0084 | J10: ER-2022Q1 | K10: 96329 | L10: QA-0482 | M10: ER-2022Q1 | N10: 26541 | O10: QA-0160 | P10: ER-2022Q1 | Q10: 19153 | R10: QA-0558 | S10: ER-2022Q1 | T10: 115973 | U10: QA-0198 | V10: ER-2022Q1 | W10: 108595 | X10: QA-0596 | Y10: ER-2022Q1 | Z10: 18870 | AA10: QA-0236 | AB10: ER-2022Q1 | AC10: 12411 | AD10: QA-0634 | AE10: ER-2022Q1 | AF10: -67496 | AG10: QA-0314 | AH10: ER-2022Q1 | AI10: -43830 | AJ10: QA-0672 | AK10: ER-2022Q1 | AL10: =H10/E10 -> 0.86535112 | AM10: =K10/E10 -> 0.88784943 | AN10: =N10/E10 -> 0.24462428 | AO10: =Q10/E10 -> 0.17653023 | AP10: =T10/E10 -> 1.0689051 | AQ10: =W10/E10 -> 1.0009033 | AR10: =Z10/E10 -> 0.17392186 | AS10: =AC10/E10 -> 0.11439026 | AT10: =AF10/E10 -> -0.62210015 | AU10: =AI10/E10 -> -0.4039743 | AV10: =AM10-AM29 -> -0.0040217335 | AW10: =AO10-AO29 -> -0.0047505881 | AX10: =AQ10-AQ29 -> 0.30997654 | AY10: =AS10-AS29 -> 0.0039898774 | AZ10: =AU10-AU29 -> -0.31323756
A11: Q2 2022 | B11: Quarter | C11: 2022 | D11: 2 | E11: 123718 | F11: QA-0009 | G11: ER-2022Q2 | H11: 106988 | I11: QA-0085 | J11: ER-2022Q2 | K11: 109903 | L11: QA-0483 | M11: ER-2022Q2 | N11: 33962 | O11: QA-0161 | P11: ER-2022Q2 | Q11: 23963 | R11: QA-0559 | S11: ER-2022Q2 | T11: 96740 | U11: QA-0199 | V11: ER-2022Q2 | W11: 86665 | X11: QA-0597 | Y11: ER-2022Q2 | Z11: 22466 | AA11: QA-0237 | AB11: ER-2022Q2 | AC11: 14633 | AD11: QA-0635 | AE11: ER-2022Q2 | AF11: -46180 | AG11: QA-0315 | AH11: ER-2022Q2 | AI11: -15358 | AJ11: QA-0673 | AK11: ER-2022Q2 | AL11: =H11/E11 -> 0.86477311 | AM11: =K11/E11 -> 0.88833476 | AN11: =N11/E11 -> 0.27451139 | AO11: =Q11/E11 -> 0.19369049 | AP11: =T11/E11 -> 0.78193957 | AQ11: =W11/E11 -> 0.70050437 | AR11: =Z11/E11 -> 0.18159039 | AS11: =AC11/E11 -> 0.11827705 | AT11: =AF11/E11 -> -0.37326824 | AU11: =AI11/E11 -> -0.12413715 | AV11: =AM11-AM29 -> -0.0035364058 | AW11: =AO11-AO29 -> 0.012409675 | AX11: =AQ11-AQ29 -> 0.0095776616 | AY11: =AS11-AS29 -> 0.0078766672 | AZ11: =AU11-AU29 -> -0.03340041
A12: Q3 2022 | B12: Quarter | C12: 2022 | D12: 3 | E12: 136893 | F12: QA-0011 | G12: ER-2022Q3 | H12: 119063 | I12: QA-0087 | J12: ER-2022Q3 | K12: 121746 | L12: QA-0485 | M12: ER-2022Q3 | N12: 33984 | O12: QA-0163 | P12: ER-2022Q3 | Q12: 26259 | R12: QA-0561 | S12: ER-2022Q3 | T12: 90970 | U12: QA-0201 | V12: ER-2022Q3 | W12: 82432 | X12: QA-0599 | Y12: ER-2022Q3 | Z12: 22348 | AA12: QA-0239 | AB12: ER-2022Q3 | AC12: 15240 | AD12: QA-0637 | AE12: ER-2022Q3 | AF12: -28239 | AG12: QA-0317 | AH12: ER-2022Q3 | AI12: -2185 | AJ12: QA-0675 | AK12: ER-2022Q3 | AL12: =H12/E12 -> 0.86975229 | AM12: =K12/E12 -> 0.88935154 | AN12: =N12/E12 -> 0.24825228 | AO12: =Q12/E12 -> 0.19182135 | AP12: =T12/E12 -> 0.66453361 | AQ12: =W12/E12 -> 0.60216373 | AR12: =Z12/E12 -> 0.16325159 | AS12: =AC12/E12 -> 0.11132783 | AT12: =AF12/E12 -> -0.2062852 | AU12: =AI12/E12 -> -0.015961371 | AV12: =AM12-AM29 -> -0.0025196298 | AW12: =AO12-AO29 -> 0.010540535 | AX12: =AQ12-AQ29 -> -0.088762978 | AY12: =AS12-AS29 -> 0.00092744313 | AZ12: =AU12-AU29 -> 0.07477537
A13: Q4 2022 | B13: Quarter | C13: 2022 | D13: 4 | E13: 149921 | F13: QA-0013 | G13: ER-2022Q4 | H13: 132562 | I13: QA-0089 | J13: ER-2022Q4 | K13: 134929 | L13: QA-0487 | M13: ER-2022Q4 | N13: 32560 | O13: QA-0165 | P13: ER-2022Q4 | Q13: 24715 | R13: QA-0563 | S13: ER-2022Q4 | T13: 88385 | U13: QA-0203 | V13: ER-2022Q4 | W13: 80919 | X13: QA-0601 | Y13: ER-2022Q4 | Z13: 21717 | AA13: QA-0241 | AB13: ER-2022Q4 | AC13: 15017 | AD13: QA-0639 | AE13: ER-2022Q4 | AF13: -10100 | AG13: QA-0319 | AH13: ER-2022Q4 | AI13: 14278 | AJ13: QA-0677 | AK13: ER-2022Q4 | AL13: =H13/E13 -> 0.88421235 | AM13: =K13/E13 -> 0.90000067 | AN13: =N13/E13 -> 0.21718105 | AO13: =Q13/E13 -> 0.16485349 | AP13: =T13/E13 -> 0.58954383 | AQ13: =W13/E13 -> 0.53974427 | AR13: =Z13/E13 -> 0.14485629 | AS13: =AC13/E13 -> 0.10016609 | AT13: =AF13/E13 -> -0.067368814 | AU13: =AI13/E13 -> 0.095236825 | AV13: =AM13-AM29 -> 0.0081294999 | AW13: =AO13-AO29 -> -0.016427325 | AX13: =AQ13-AQ29 -> -0.15118245 | AY13: =AS13-AS29 -> -0.010234295 | AZ13: =AU13-AU29 -> 0.18597357
A14: Q1 2023 | B14: Quarter | C14: 2023 | D14: 1 | E14: 162256 | F14: QA-0015 | G14: ER-2023Q1 | H14: 145242 | I14: QA-0091 | J14: ER-2023Q1 | K14: 146719 | L14: QA-0489 | M14: ER-2023Q1 | N14: 37063 | O14: QA-0167 | P14: ER-2023Q1 | Q14: 28519 | R14: QA-0565 | S14: ER-2023Q1 | T14: 107680 | U14: QA-0205 | V14: ER-2023Q1 | W14: 102652 | X14: QA-0603 | Y14: ER-2023Q1 | Z14: 23251 | AA14: QA-0243 | AB14: ER-2023Q1 | AC14: 15841 | AD14: QA-0641 | AE14: ER-2023Q1 | AF14: -22752 | AG14: QA-0321 | AH14: ER-2023Q1 | AI14: -293 | AJ14: QA-0679 | AK14: ER-2023Q1 | AL14: =H14/E14 -> 0.89514101 | AM14: =K14/E14 -> 0.90424391 | AN14: =N14/E14 -> 0.22842299 | AO14: =Q14/E14 -> 0.17576546 | AP14: =T14/E14 -> 0.66364264 | AQ14: =W14/E14 -> 0.63265457 | AR14: =Z14/E14 -> 0.14329824 | AS14: =AC14/E14 -> 0.097629672 | AT14: =AF14/E14 -> -0.14022286 | AU14: =AI14/E14 -> -0.0018057884 | AV14: =AM14-AM30 -> 0.006119352 | AW14: =AO14-AO30 -> 0.01437885 | AX14: =AQ14-AQ30 -> 0.066655078 | AY14: =AS14-AS30 -> 0.011311415 | AZ14: =AU14-AU30 -> -0.086225991
A15: Q2 2023 | B15: Quarter | C15: 2023 | D15: 2 | E15: 175679 | F15: QA-0016 | G15: ER-2023Q2 | H15: 156163 | I15: QA-0092 | J15: ER-2023Q2 | K15: 158008 | L15: QA-0490 | M15: ER-2023Q2 | N15: 39106 | O15: QA-0168 | P15: ER-2023Q2 | Q15: 27908 | R15: QA-0566 | S15: ER-2023Q2 | T15: 107443 | U15: QA-0206 | V15: ER-2023Q2 | W15: 98831 | X15: QA-0604 | Y15: ER-2023Q2 | Z15: 21781 | AA15: QA-0244 | AB15: ER-2023Q2 | AC15: 14652 | AD15: QA-0642 | AE15: ER-2023Q2 | AF15: -12167 | AG15: QA-0322 | AH15: ER-2023Q2 | AI15: 16617 | AJ15: QA-0680 | AK15: ER-2023Q2 | AL15: =H15/E15 -> 0.88891103 | AM15: =K15/E15 -> 0.89941313 | AN15: =N15/E15 -> 0.22259917 | AO15: =Q15/E15 -> 0.15885792 | AP15: =T15/E15 -> 0.61158704 | AQ15: =W15/E15 -> 0.56256582 | AR15: =Z15/E15 -> 0.12398181 | AS15: =AC15/E15 -> 0.083402114 | AT15: =AF15/E15 -> -0.069256997 | AU15: =AI15/E15 -> 0.094587287 | AV15: =AM15-AM30 -> 0.0012885753 | AW15: =AO15-AO30 -> -0.0025286897 | AX15: =AQ15-AQ30 -> -0.0034336769 | AY15: =AS15-AS30 -> -0.0029161422 | AZ15: =AU15-AU30 -> 0.010167084
A16: Q3 2023 | B16: Quarter | C16: 2023 | D16: 3 | E16: 189190 | F16: QA-0018 | G16: ER-2023Q3 | H16: 167483 | I16: QA-0094 | J16: ER-2023Q3 | K16: 168866 | L16: QA-0492 | M16: ER-2023Q3 | N16: 38433 | O16: QA-0170 | P16: ER-2023Q3 | Q16: 28051 | R16: QA-0568 | S16: ER-2023Q3 | T16: 108360 | U16: QA-0208 | V16: ER-2023Q3 | W16: 101504 | X16: QA-0606 | Y16: ER-2023Q3 | Z16: 23211 | AA16: QA-0246 | AB16: ER-2023Q3 | AC16: 15234 | AD16: QA-0644 | AE16: ER-2023Q3 | AF16: -2521 | AG16: QA-0324 | AH16: ER-2023Q3 | AI16: 24077 | AJ16: QA-0682 | AK16: ER-2023Q3 | AL16: =H16/E16 -> 0.88526349 | AM16: =K16/E16 -> 0.8925736 | AN16: =N16/E16 -> 0.20314499 | AO16: =Q16/E16 -> 0.14826894 | AP16: =T16/E16 -> 0.57275755 | AQ16: =W16/E16 -> 0.53651884 | AR16: =Z16/E16 -> 0.12268619 | AS16: =AC16/E16 -> 0.080522226 | AT16: =AF16/E16 -> -0.013325229 | AU16: =AI16/E16 -> 0.1272636 | AV16: =AM16-AM30 -> -0.0055509556 | AW16: =AO16-AO30 -> -0.013117671 | AX16: =AQ16-AQ30 -> -0.029480649 | AY16: =AS16-AS30 -> -0.0057960299 | AZ16: =AU16-AU30 -> 0.042843394
A17: Q4 2023 | B17: Quarter | C17: 2023 | D17: 4 | E17: 202570 | F17: QA-0020 | G17: ER-2023Q4 | H17: 180162 | I17: QA-0096 | J17: ER-2023Q4 | K17: 181764 | L17: QA-0494 | M17: ER-2023Q4 | N17: 41898 | O17: QA-0172 | P17: ER-2023Q4 | Q17: 33285 | R17: QA-0570 | S17: ER-2023Q4 | T17: 114919 | U17: QA-0210 | V17: ER-2023Q4 | W17: 110020 | X17: QA-0608 | Y17: ER-2023Q4 | Z17: 24490 | AA17: QA-0248 | AB17: ER-2023Q4 | AC17: 17259 | AD17: QA-0646 | AE17: ER-2023Q4 | AF17: -1145 | AG17: QA-0326 | AH17: ER-2023Q4 | AI17: 21200 | AJ17: QA-0684 | AK17: ER-2023Q4 | AL17: =H17/E17 -> 0.88938145 | AM17: =K17/E17 -> 0.89728983 | AN17: =N17/E17 -> 0.20683221 | AO17: =Q17/E17 -> 0.16431357 | AP17: =T17/E17 -> 0.56730513 | AQ17: =W17/E17 -> 0.5431209 | AR17: =Z17/E17 -> 0.12089648 | AS17: =AC17/E17 -> 0.085200178 | AT17: =AF17/E17 -> -0.0056523671 | AU17: =AI17/E17 -> 0.10465518 | AV17: =AM17-AM30 -> -0.00083473315 | AW17: =AO17-AO30 -> 0.0029269639 | AX17: =AQ17-AQ30 -> -0.022878596 | AY17: =AS17-AS30 -> -0.0011180785 | AZ17: =AU17-AU30 -> 0.020234978
A18: Q1 2024 | B18: Quarter | C18: 2024 | D18: 1 | E18: 216913 | F18: QA-0022 | G18: ER-2024Q1 | H18: 193459 | I18: QA-0098 | J18: ER-2024Q1 | K18: 194703 | L18: QA-0496 | M18: ER-2024Q1 | N18: 44423 | O18: QA-0174 | P18: ER-2024Q1 | Q18: 34797 | R18: QA-0572 | S18: ER-2024Q1 | T18: 128141 | U18: QA-0212 | V18: ER-2024Q1 | W18: 120806 | X18: QA-0610 | Y18: ER-2024Q1 | Z18: 25917 | AA18: QA-0250 | AB18: ER-2024Q1 | AC18: 17579 | AD18: QA-0648 | AE18: ER-2024Q1 | AF18: -5022 | AG18: QA-0328 | AH18: ER-2024Q1 | AI18: 21521 | AJ18: QA-0686 | AK18: ER-2024Q1 | AL18: =H18/E18 -> 0.8918737 | AM18: =K18/E18 -> 0.89760872 | AN18: =N18/E18 -> 0.20479639 | AO18: =Q18/E18 -> 0.16041915 | AP18: =T18/E18 -> 0.59074836 | AQ18: =W18/E18 -> 0.55693296 | AR18: =Z18/E18 -> 0.11948108 | AS18: =AC18/E18 -> 0.081041708 | AT18: =AF18/E18 -> -0.023152139 | AU18: =AI18/E18 -> 0.099214893 | AV18: =AM18-AM31 -> -0.0025059938 | AW18: =AO18-AO31 -> -0.0069829415 | AX18: =AQ18-AQ31 -> 0.042862418 | AY18: =AS18-AS31 -> -0.0014031606 | AZ18: =AU18-AU31 -> -0.03698231
A19: Q2 2024 | B19: Quarter | C19: 2024 | D19: 2 | E19: 236106 | F19: QA-0023 | G19: ER-2024Q2 | H19: 212343 | I19: QA-0099 | J19: ER-2024Q2 | K19: 214215 | L19: QA-0497 | M19: ER-2024Q2 | N19: 50445 | O19: QA-0175 | P19: ER-2024Q2 | Q19: 36878 | R19: QA-0573 | S19: ER-2024Q2 | T19: 131471 | U19: QA-0213 | V19: ER-2024Q2 | W19: 120738 | X19: QA-0611 | Y19: ER-2024Q2 | Z19: 28633 | AA19: QA-0251 | AB19: ER-2024Q2 | AC19: 18182 | AD19: QA-0649 | AE19: ER-2024Q2 | AF19: 1794 | AG19: QA-0329 | AH19: ER-2024Q2 | AI19: 38417 | AJ19: QA-0687 | AK19: ER-2024Q2 | AL19: =H19/E19 -> 0.89935453 | AM19: =K19/E19 -> 0.90728317 | AN19: =N19/E19 -> 0.21365404 | AO19: =Q19/E19 -> 0.15619256 | AP19: =T19/E19 -> 0.55683041 | AQ19: =W19/E19 -> 0.51137201 | AR19: =Z19/E19 -> 0.1212718 | AS19: =AC19/E19 -> 0.077007785 | AT19: =AF19/E19 -> 0.0075982821 | AU19: =AI19/E19 -> 0.16271082 | AV19: =AM19-AM31 -> 0.0071684569 | AW19: =AO19-AO31 -> -0.011209538 | AX19: =AQ19-AQ31 -> -0.0026985348 | AY19: =AS19-AS31 -> -0.0054370839 | AZ19: =AU19-AU31 -> 0.026513614
A20: Q3 2024 | B20: Quarter | C20: 2024 | D20: 3 | E20: 251000 | F20: QA-0025 | G20: ER-2024Q3 | H20: 225028 | I20: QA-0101 | J20: ER-2024Q3 | K20: 226909 | L20: QA-0499 | M20: ER-2024Q3 | N20: 56509 | O20: QA-0177 | P20: ER-2024Q3 | Q20: 42973 | R20: QA-0575 | S20: ER-2024Q3 | T20: 140284 | U20: QA-0215 | V20: ER-2024Q3 | W20: 130339 | X20: QA-0613 | Y20: ER-2024Q3 | Z20: 55637 | AA20: QA-0253 | AB20: ER-2024Q3 | AC20: 21417 | AD20: QA-0651 | AE20: ER-2024Q3 | AF20: -27402 | AG20: QA-0331 | AH20: ER-2024Q3 | AI20: 32180 | AJ20: QA-0689 | AK20: ER-2024Q3 | AL20: =H20/E20 -> 0.8965259 | AM20: =K20/E20 -> 0.90401992 | AN20: =N20/E20 -> 0.22513546 | AO20: =Q20/E20 -> 0.17120717 | AP20: =T20/E20 -> 0.5589004 | AQ20: =W20/E20 -> 0.51927888 | AR20: =Z20/E20 -> 0.22166135 | AS20: =AC20/E20 -> 0.085326693 | AT20: =AF20/E20 -> -0.10917131 | AU20: =AI20/E20 -> 0.12820717 | AV20: =AM20-AM31 -> 0.0039052078 | AW20: =AO20-AO31 -> 0.0038050756 | AX20: =AQ20-AQ31 -> 0.0052083388 | AY20: =AS20-AS31 -> 0.0028818247 | AZ20: =AU20-AU31 -> -0.0079900313
A21: Q4 2024 | B21: Quarter | C21: 2024 | D21: 4 | E21: 267976 | F21: QA-0027 | G21: ER-2024Q4 | H21: 237474 | I21: QA-0103 | J21: ER-2024Q4 | K21: 239080 | L21: QA-0501 | M21: ER-2024Q4 | N21: 62332 | O21: QA-0179 | P21: ER-2024Q4 | Q21: 48066 | R21: QA-0577 | S21: ER-2024Q4 | T21: 133643 | U21: QA-0217 | V21: ER-2024Q4 | W21: 127791 | X21: QA-0615 | Y21: ER-2024Q4 | Z21: 31903 | AA21: QA-0255 | AB21: ER-2024Q4 | AC21: 22958 | AD21: QA-0653 | AE21: ER-2024Q4 | AF21: 9596 | AG21: QA-0333 | AH21: ER-2024Q4 | AI21: 40265 | AJ21: QA-0691 | AK21: ER-2024Q4 | AL21: =H21/E21 -> 0.88617637 | AM21: =K21/E21 -> 0.89216945 | AN21: =N21/E21 -> 0.23260292 | AO21: =Q21/E21 -> 0.17936681 | AP21: =T21/E21 -> 0.49871257 | AQ21: =W21/E21 -> 0.47687479 | AR21: =Z21/E21 -> 0.11905171 | AS21: =AC21/E21 -> 0.085671851 | AT21: =AF21/E21 -> 0.035809177 | AU21: =AI21/E21 -> 0.15025599 | AV21: =AM21-AM31 -> -0.0079452645 | AW21: =AO21-AO31 -> 0.011964713 | AX21: =AQ21-AQ31 -> -0.037195751 | AY21: =AS21-AS31 -> 0.0032269827 | AZ21: =AU21-AU31 -> 0.01405879
A22: Q1 2025 | B22: Quarter | C22: 2025 | D22: 1 | E22: 282250 | F22: QA-0029 | G22: ER-2025Q1 | H22: 253445 | I22: QA-0105 | J22: ER-2025Q1 | K22: 254579 | L22: QA-0503 | M22: ER-2025Q1 | N22: 69385 | O22: QA-0181 | P22: ER-2025Q1 | Q22: 53844 | R22: QA-0579 | S22: ER-2025Q1 | T22: 141720 | U22: QA-0219 | V22: ER-2025Q1 | W22: 135882 | X22: QA-0617 | Y22: ER-2025Q1 | Z22: 32544 | AA22: QA-0257 | AB22: ER-2025Q1 | AC22: 24099 | AD22: QA-0655 | AE22: ER-2025Q1 | AF22: 9796 | AG22: QA-0335 | AH22: ER-2025Q1 | AI22: 40754 | AJ22: QA-0693 | AK22: ER-2025Q1 | AL22: =H22/E22 -> 0.89794508 | AM22: =K22/E22 -> 0.9019628 | AN22: =N22/E22 -> 0.24582817 | AO22: =Q22/E22 -> 0.19076705 | AP22: =T22/E22 -> 0.50210806 | AQ22: =W22/E22 -> 0.48142427 | AR22: =Z22/E22 -> 0.11530204 | AS22: =AC22/E22 -> 0.085381754 | AT22: =AF22/E22 -> 0.03470682 | AU22: =AI22/E22 -> 0.14438973 | AV22: =AM22-AM32 -> 0.003049084 | AW22: =AO22-AO32 -> -0.0028608561 | AX22: =AQ22-AQ32 -> 0.0051511939 | AY22: =AS22-AS32 -> -0.0013717042 | AZ22: =AU22-AU32 -> 0.0021304504
A23: Q2 2025 | B23: Quarter | C23: 2025 | D23: 2 | E23: 299014 | F23: QA-0030 | G23: ER-2025Q2 | H23: 267841 | I23: QA-0106 | J23: ER-2025Q2 | K23: 270113 | L23: QA-0504 | M23: ER-2025Q2 | N23: 87039 | O23: QA-0182 | P23: ER-2025Q2 | Q23: 59233 | R23: QA-0580 | S23: ER-2025Q2 | T23: 152590 | U23: QA-0220 | V23: ER-2025Q2 | W23: 139223 | X23: QA-0618 | Y23: ER-2025Q2 | Z23: 39763 | AA23: QA-0258 | AB23: ER-2025Q2 | AC23: 26563 | AD23: QA-0656 | AE23: ER-2025Q2 | AF23: -11551 | AG23: QA-0336 | AH23: ER-2025Q2 | AI23: 45094 | AJ23: QA-0694 | AK23: ER-2025Q2 | AL23: =H23/E23 -> 0.89574736 | AM23: =K23/E23 -> 0.90334566 | AN23: =N23/E23 -> 0.2910867 | AO23: =Q23/E23 -> 0.1980944 | AP23: =T23/E23 -> 0.51031055 | AQ23: =W23/E23 -> 0.46560696 | AR23: =Z23/E23 -> 0.1329804 | AS23: =AC23/E23 -> 0.088835305 | AT23: =AF23/E23 -> -0.038630298 | AU23: =AI23/E23 -> 0.15080899 | AV23: =AM23-AM32 -> 0.0044319479 | AW23: =AO23-AO32 -> 0.004466497 | AX23: =AQ23-AQ32 -> -0.010666114 | AY23: =AS23-AS32 -> 0.0020818474 | AZ23: =AU23-AU32 -> 0.0085497172
A24: Q3 2025 | B24: Quarter | C24: 2025 | D24: 3 | E24: 316855 | F24: QA-0032 | G24: ER-2025Q3 | H24: 281067 | I24: QA-0108 | J24: ER-2025Q3 | K24: 284031 | L24: QA-0506 | M24: ER-2025Q3 | N24: 79453 | O24: QA-0184 | P24: ER-2025Q3 | Q24: 57772 | R24: QA-0582 | S24: ER-2025Q3 | T24: 165808 | U24: QA-0222 | V24: ER-2025Q3 | W24: 151804 | X24: QA-0620 | Y24: ER-2025Q3 | Z24: 38184 | AA24: QA-0260 | AB24: ER-2025Q3 | AC24: 26971 | AD24: QA-0658 | AE24: ER-2025Q3 | AF24: -2378 | AG24: QA-0338 | AH24: ER-2025Q3 | AI24: 47484 | AJ24: QA-0696 | AK24: ER-2025Q3 | AL24: =H24/E24 -> 0.88705244 | AM24: =K24/E24 -> 0.89640687 | AN24: =N24/E24 -> 0.25075508 | AO24: =Q24/E24 -> 0.18232946 | AP24: =T24/E24 -> 0.52329299 | AQ24: =W24/E24 -> 0.47909612 | AR24: =Z24/E24 -> 0.12050938 | AS24: =AC24/E24 -> 0.085120954 | AT24: =AF24/E24 -> -0.0075050102 | AU24: =AI24/E24 -> 0.14986035 | AV24: =AM24-AM32 -> -0.0025068411 | AW24: =AO24-AO32 -> -0.01129845 | AX24: =AQ24-AQ32 -> 0.0028230412 | AY24: =AS24-AS32 -> -0.0016325036 | AZ24: =AU24-AU32 -> 0.0076010712
A25: Q4 2025 | B25: Quarter | C25: 2025 | D25: 4 | E25: 333878 | F25: QA-0034 | G25: ER-2025Q4 | H25: 296545 | I25: QA-0110 | J25: ER-2025Q4 | K25: 298736 | L25: QA-0508 | M25: ER-2025Q4 | N25: 84922 | O25: QA-0186 | P25: ER-2025Q4 | Q25: 67700 | R25: QA-0584 | S25: ER-2025Q4 | T25: 170733 | U25: QA-0224 | V25: ER-2025Q4 | W25: 159858 | X25: QA-0622 | Y25: ER-2025Q4 | Z25: 38505 | AA25: QA-0262 | AB25: ER-2025Q4 | AC25: 29247 | AD25: QA-0660 | AE25: ER-2025Q4 | AF25: 2385 | AG25: QA-0340 | AH25: ER-2025Q4 | AI25: 41931 | AJ25: QA-0698 | AK25: ER-2025Q4 | AL25: =H25/E25 -> 0.88818371 | AM25: =K25/E25 -> 0.89474599 | AN25: =N25/E25 -> 0.25435039 | AO25: =Q25/E25 -> 0.20276868 | AP25: =T25/E25 -> 0.51136343 | AQ25: =W25/E25 -> 0.47879165 | AR25: =Z25/E25 -> 0.11532656 | AS25: =AC25/E25 -> 0.087597865 | AT25: =AF25/E25 -> 0.0071433278 | AU25: =AI25/E25 -> 0.12558779 | AV25: =AM25-AM32 -> -0.0041677298 | AW25: =AO25-AO32 -> 0.0091407694 | AX25: =AQ25-AQ32 -> 0.0025185791 | AY25: =AS25-AS32 -> 0.00084440708 | AZ25: =AU25-AU32 -> -0.016671485
A26: Q1 2026 | B26: Quarter | C26: 2026 | D26: 1 | E26: 351265 | F26: QA-0036 | G26: ER-2026Q1 | H26: 313141 | I26: QA-0112 | J26: ER-2026Q1 | K26: 314190 | L26: QA-0510 | M26: ER-2026Q1 | N26: 92020 | O26: QA-0188 | P26: ER-2026Q1 | Q26: 78413 | R26: QA-0586 | S26: ER-2026Q1 | T26: 165395 | U26: QA-0226 | V26: ER-2026Q1 | W26: 158181 | X26: QA-0624 | Y26: ER-2026Q1 | Z26: 35972 | AA26: QA-0264 | AB26: ER-2026Q1 | AC26: 28559 | AD26: QA-0662 | AE26: ER-2026Q1 | AF26: 19754 | AG26: QA-0342 | AH26: ER-2026Q1 | AI26: 49037 | AJ26: QA-0700 | AK26: ER-2026Q1 | AL26: =H26/E26 -> 0.89146656 | AM26: =K26/E26 -> 0.89445291 | AN26: =N26/E26 -> 0.26196746 | AO26: =Q26/E26 -> 0.22323032 | AP26: =T26/E26 -> 0.47085534 | AQ26: =W26/E26 -> 0.45031814 | AR26: =Z26/E26 -> 0.10240701 | AS26: =AC26/E26 -> 0.08130329 | AT26: =AF26/E26 -> 0.056236744 | AU26: =AI26/E26 -> 0.13960116
A27: Q2 2026 | B27: Quarter | C27: 2026 | D27: 2 | E27: 364621 | F27: QA-0037 | G27: ER-2026Q2 | H27: 321960 | I27: QA-0113 | J27: ER-2026Q2 | K27: 324222 | L27: QA-0511 | M27: ER-2026Q2 | N27: 99307 | O27: QA-0189 | P27: ER-2026Q2 | Q27: 83003 | R27: QA-0587 | S27: ER-2026Q2 | T27: 162402 | U27: QA-0227 | V27: ER-2026Q2 | W27: 149444 | X27: QA-0625 | Y27: ER-2026Q2 | Z27: 40359 | AA27: QA-0265 | AB27: ER-2026Q2 | AC27: 30665 | AD27: QA-0663 | AE27: ER-2026Q2 | AF27: -1544 | AG27: QA-0343 | AH27: ER-2026Q2 | AI27: 61110 | AJ27: QA-0701 | AK27: ER-2026Q2 | AL27: =H27/E27 -> 0.88299906 | AM27: =K27/E27 -> 0.88920276 | AN27: =N27/E27 -> 0.27235678 | AO27: =Q27/E27 -> 0.22764185 | AP27: =T27/E27 -> 0.44539947 | AQ27: =W27/E27 -> 0.4098612 | AR27: =Z27/E27 -> 0.11068754 | AS27: =AC27/E27 -> 0.084101025 | AT27: =AF27/E27 -> -0.0042345339 | AU27: =AI27/E27 -> 0.16759868
A28: FY 2021 | B28: Fiscal year | C28: 2021 | D28: FY | E28: 308150 | F28: QA-0007 | G28: ER-2021Q4 | H28: 269137 | I28: QA-0083 | J28: ER-2021Q4 | K28: 276818 | L28: QA-0481 | M28: ER-2021Q4 | N28: 73686 | O28: QA-0159 | P28: ER-2021Q4 | Q28: 51907 | R28: QA-0557 | S28: ER-2021Q4 | T28: 268083 | U28: QA-0197 | V28: ER-2021Q4 | W28: 244948 | X28: QA-0595 | Y28: ER-2021Q4 | Z28: 53493 | AA28: QA-0235 | AB28: ER-2021Q4 | AC28: 32559 | AD28: QA-0633 | AE28: ER-2021Q4 | AF28: -126125 | AG28: QA-0313 | AH28: ER-2021Q4 | AI28: -52596 | AJ28: QA-0671 | AK28: ER-2021Q4 | AL28: =H28/E28 -> 0.87339607 | AM28: =K28/E28 -> 0.89832225 | AN28: =N28/E28 -> 0.2391238 | AO28: =Q28/E28 -> 0.16844718 | AP28: =T28/E28 -> 0.86997566 | AQ28: =W28/E28 -> 0.79489859 | AR28: =Z28/E28 -> 0.17359403 | AS28: =AC28/E28 -> 0.10565958 | AT28: =AF28/E28 -> -0.40929742 | AU28: =AI28/E28 -> -0.17068311
A29: FY 2022 | B29: Fiscal year | C29: 2022 | D29: FY | E29: 519029 | F29: QA-0014 | G29: ER-2022Q4 | H29: 452501 | I29: QA-0090 | J29: ER-2022Q4 | K29: 462907 | L29: QA-0488 | M29: ER-2022Q4 | N29: 127047 | O29: QA-0166 | P29: ER-2022Q4 | Q29: 94090 | R29: QA-0564 | S29: ER-2022Q4 | T29: 392068 | U29: QA-0204 | V29: ER-2022Q4 | W29: 358611 | X29: QA-0602 | Y29: ER-2022Q4 | Z29: 85401 | AA29: QA-0242 | AB29: ER-2022Q4 | AC29: 57301 | AD29: QA-0640 | AE29: ER-2022Q4 | AF29: -152015 | AG29: QA-0320 | AH29: ER-2022Q4 | AI29: -47095 | AJ29: QA-0678 | AK29: ER-2022Q4 | AL29: =H29/E29 -> 0.87182219 | AM29: =K29/E29 -> 0.89187117 | AN29: =N29/E29 -> 0.24477823 | AO29: =Q29/E29 -> 0.18128081 | AP29: =T29/E29 -> 0.75538746 | AQ29: =W29/E29 -> 0.69092671 | AR29: =Z29/E29 -> 0.16453994 | AS29: =AC29/E29 -> 0.11040038 | AT29: =AF29/E29 -> -0.29288344 | AU29: =AI29/E29 -> -0.090736741
A30: FY 2023 | B30: Fiscal year | C30: 2023 | D30: FY | E30: 729695 | F30: QA-0021 | G30: ER-2023Q4 | H30: 649050 | I30: QA-0097 | J30: ER-2023Q4 | K30: 655357 | L30: QA-0495 | M30: ER-2023Q4 | N30: 156500 | O30: QA-0173 | P30: ER-2023Q4 | Q30: 117763 | R30: QA-0571 | S30: ER-2023Q4 | T30: 438402 | U30: QA-0211 | V30: ER-2023Q4 | W30: 413007 | X30: QA-0609 | Y30: ER-2023Q4 | Z30: 92733 | AA30: QA-0249 | AB30: ER-2023Q4 | AC30: 62986 | AD30: QA-0647 | AE30: ER-2023Q4 | AF30: -38585 | AG30: QA-0327 | AH30: ER-2023Q4 | AI30: 61601 | AJ30: QA-0685 | AK30: ER-2023Q4 | AL30: =H30/E30 -> 0.88948122 | AM30: =K30/E30 -> 0.89812456 | AN30: =N30/E30 -> 0.21447317 | AO30: =Q30/E30 -> 0.16138661 | AP30: =T30/E30 -> 0.6008017 | AQ30: =W30/E30 -> 0.56599949 | AR30: =Z30/E30 -> 0.1270846 | AS30: =AC30/E30 -> 0.086318256 | AT30: =AF30/E30 -> -0.052878257 | AU30: =AI30/E30 -> 0.084420203
A31: FY 2024 | B31: Fiscal year | C31: 2024 | D31: FY | E31: 971995 | F31: QA-0028 | G31: ER-2024Q4 | H31: 868304 | I31: QA-0104 | J31: ER-2024Q4 | K31: 874907 | L31: QA-0502 | M31: ER-2024Q4 | N31: 213709 | O31: QA-0180 | P31: ER-2024Q4 | Q31: 162714 | R31: QA-0578 | S31: ER-2024Q4 | T31: 533539 | U31: QA-0218 | V31: ER-2024Q4 | W31: 499674 | X31: QA-0616 | Y31: ER-2024Q4 | Z31: 142090 | AA31: QA-0256 | AB31: ER-2024Q4 | AC31: 80136 | AD31: QA-0654 | AE31: ER-2024Q4 | AF31: -21034 | AG31: QA-0334 | AH31: ER-2024Q4 | AI31: 132383 | AJ31: QA-0692 | AK31: ER-2024Q4 | AL31: =H31/E31 -> 0.89332147 | AM31: =K31/E31 -> 0.90011471 | AN31: =N31/E31 -> 0.21986636 | AO31: =Q31/E31 -> 0.1674021 | AP31: =T31/E31 -> 0.54891126 | AQ31: =W31/E31 -> 0.51407055 | AR31: =Z31/E31 -> 0.14618388 | AS31: =AC31/E31 -> 0.082444869 | AT31: =AF31/E31 -> -0.021640029 | AU31: =AI31/E31 -> 0.1361972
A32: FY 2025 | B32: Fiscal year | C32: 2025 | D32: FY | E32: 1231997 | F32: QA-0035 | G32: ER-2025Q4 | H32: 1098898 | I32: QA-0111 | J32: ER-2025Q4 | K32: 1107459 | L32: QA-0509 | M32: ER-2025Q4 | N32: 320799 | O32: QA-0187 | P32: ER-2025Q4 | Q32: 238549 | R32: QA-0585 | S32: ER-2025Q4 | T32: 630851 | U32: QA-0225 | V32: ER-2025Q4 | W32: 586767 | X32: QA-0623 | Y32: ER-2025Q4 | Z32: 148996 | AA32: QA-0263 | AB32: ER-2025Q4 | AC32: 106880 | AD32: QA-0661 | AE32: ER-2025Q4 | AF32: -1748 | AG32: QA-0341 | AH32: ER-2025Q4 | AI32: 175263 | AJ32: QA-0699 | AK32: ER-2025Q4 | AL32: =H32/E32 -> 0.89196483 | AM32: =K32/E32 -> 0.89891371 | AN32: =N32/E32 -> 0.26038943 | AO32: =Q32/E32 -> 0.19362791 | AP32: =T32/E32 -> 0.51205563 | AQ32: =W32/E32 -> 0.47627308 | AR32: =Z32/E32 -> 0.12093861 | AS32: =AC32/E32 -> 0.086753458 | AT32: =AF32/E32 -> -0.0014188346 | AU32: =AI32/E32 -> 0.14225927
A35: Seasonality (Derived): average by fiscal quarter, complete years 2022-2025 (2021 excluded: IPO year, operating losses; 2026 incomplete)
A36: Ratio | B36: Q1 avg | C36: Q2 avg | D36: Q3 avg | E36: Q4 avg | F36: Q1 avg deviation vs FY | G36: Q2 avg deviation vs FY | H36: Q3 avg deviation vs FY | I36: Q4 avg deviation vs FY
A37: Text / label | B37: Derived (formula) | C37: Derived (formula) | D37: Derived (formula) | E37: Derived (formula) | F37: Derived (formula) | G37: Derived (formula) | H37: Derived (formula) | I37: Derived (formula)
A38: Gross margin (GAAP) | B38: =AVERAGEIFS($AL$6:$AL$32,$B$6:$B$32,"Quarter",$D$6:$D$32,1,$C$6:$C$32,">=2022",$C$6:$C$32,"<=2025") -> 0.88757773 | C38: =AVERAGEIFS($AL$6:$AL$32,$B$6:$B$32,"Quarter",$D$6:$D$32,2,$C$6:$C$32,">=2022",$C$6:$C$32,"<=2025") -> 0.88719651 | D38: =AVERAGEIFS($AL$6:$AL$32,$B$6:$B$32,"Quarter",$D$6:$D$32,3,$C$6:$C$32,">=2022",$C$6:$C$32,"<=2025") -> 0.88464853 | E38: =AVERAGEIFS($AL$6:$AL$32,$B$6:$B$32,"Quarter",$D$6:$D$32,4,$C$6:$C$32,">=2022",$C$6:$C$32,"<=2025") -> 0.88698847
A39: Gross margin (non-GAAP) | B39: =AVERAGEIFS($AM$6:$AM$32,$B$6:$B$32,"Quarter",$D$6:$D$32,1,$C$6:$C$32,">=2022",$C$6:$C$32,"<=2025") -> 0.89791622 | C39: =AVERAGEIFS($AM$6:$AM$32,$B$6:$B$32,"Quarter",$D$6:$D$32,2,$C$6:$C$32,">=2022",$C$6:$C$32,"<=2025") -> 0.89959418 | D39: =AVERAGEIFS($AM$6:$AM$32,$B$6:$B$32,"Quarter",$D$6:$D$32,3,$C$6:$C$32,">=2022",$C$6:$C$32,"<=2025") -> 0.89558798 | E39: =AVERAGEIFS($AM$6:$AM$32,$B$6:$B$32,"Quarter",$D$6:$D$32,4,$C$6:$C$32,">=2022",$C$6:$C$32,"<=2025") -> 0.89605148 | F39: =AVERAGEIFS($AV$6:$AV$32,$B$6:$B$32,"Quarter",$D$6:$D$32,1,$C$6:$C$32,">=2022",$C$6:$C$32,"<=2025") -> 0.00066017717 | G39: =AVERAGEIFS($AV$6:$AV$32,$B$6:$B$32,"Quarter",$D$6:$D$32,2,$C$6:$C$32,">=2022",$C$6:$C$32,"<=2025") -> 0.0023381436 | H39: =AVERAGEIFS($AV$6:$AV$32,$B$6:$B$32,"Quarter",$D$6:$D$32,3,$C$6:$C$32,">=2022",$C$6:$C$32,"<=2025") -> -0.0016680547 | I39: =AVERAGEIFS($AV$6:$AV$32,$B$6:$B$32,"Quarter",$D$6:$D$32,4,$C$6:$C$32,">=2022",$C$6:$C$32,"<=2025") -> -0.0012045569
A40: R&D % rev (GAAP) | B40: =AVERAGEIFS($AN$6:$AN$32,$B$6:$B$32,"Quarter",$D$6:$D$32,1,$C$6:$C$32,">=2022",$C$6:$C$32,"<=2025") -> 0.23091796 | C40: =AVERAGEIFS($AN$6:$AN$32,$B$6:$B$32,"Quarter",$D$6:$D$32,2,$C$6:$C$32,">=2022",$C$6:$C$32,"<=2025") -> 0.25046283 | D40: =AVERAGEIFS($AN$6:$AN$32,$B$6:$B$32,"Quarter",$D$6:$D$32,3,$C$6:$C$32,">=2022",$C$6:$C$32,"<=2025") -> 0.23182195 | E40: =AVERAGEIFS($AN$6:$AN$32,$B$6:$B$32,"Quarter",$D$6:$D$32,4,$C$6:$C$32,">=2022",$C$6:$C$32,"<=2025") -> 0.22774164
A41: R&D % rev (non-GAAP) | B41: =AVERAGEIFS($AO$6:$AO$32,$B$6:$B$32,"Quarter",$D$6:$D$32,1,$C$6:$C$32,">=2022",$C$6:$C$32,"<=2025") -> 0.17587047 | C41: =AVERAGEIFS($AO$6:$AO$32,$B$6:$B$32,"Quarter",$D$6:$D$32,2,$C$6:$C$32,">=2022",$C$6:$C$32,"<=2025") -> 0.17670884 | D41: =AVERAGEIFS($AO$6:$AO$32,$B$6:$B$32,"Quarter",$D$6:$D$32,3,$C$6:$C$32,">=2022",$C$6:$C$32,"<=2025") -> 0.17340673 | E41: =AVERAGEIFS($AO$6:$AO$32,$B$6:$B$32,"Quarter",$D$6:$D$32,4,$C$6:$C$32,">=2022",$C$6:$C$32,"<=2025") -> 0.17782564 | F41: =AVERAGEIFS($AW$6:$AW$32,$B$6:$B$32,"Quarter",$D$6:$D$32,1,$C$6:$C$32,">=2022",$C$6:$C$32,"<=2025") -> -5.3883832e-05 | G41: =AVERAGEIFS($AW$6:$AW$32,$B$6:$B$32,"Quarter",$D$6:$D$32,2,$C$6:$C$32,">=2022",$C$6:$C$32,"<=2025") -> 0.00078448603 | H41: =AVERAGEIFS($AW$6:$AW$32,$B$6:$B$32,"Quarter",$D$6:$D$32,3,$C$6:$C$32,">=2022",$C$6:$C$32,"<=2025") -> -0.0025176276 | I41: =AVERAGEIFS($AW$6:$AW$32,$B$6:$B$32,"Quarter",$D$6:$D$32,4,$C$6:$C$32,">=2022",$C$6:$C$32,"<=2025") -> 0.0019012803
A42: S&M % rev (GAAP) | B42: =AVERAGEIFS($AP$6:$AP$32,$B$6:$B$32,"Quarter",$D$6:$D$32,1,$C$6:$C$32,">=2022",$C$6:$C$32,"<=2025") -> 0.70635105 | C42: =AVERAGEIFS($AP$6:$AP$32,$B$6:$B$32,"Quarter",$D$6:$D$32,2,$C$6:$C$32,">=2022",$C$6:$C$32,"<=2025") -> 0.61516689 | D42: =AVERAGEIFS($AP$6:$AP$32,$B$6:$B$32,"Quarter",$D$6:$D$32,3,$C$6:$C$32,">=2022",$C$6:$C$32,"<=2025") -> 0.57987114 | E42: =AVERAGEIFS($AP$6:$AP$32,$B$6:$B$32,"Quarter",$D$6:$D$32,4,$C$6:$C$32,">=2022",$C$6:$C$32,"<=2025") -> 0.54173124
A43: S&M % rev (non-GAAP) | B43: =AVERAGEIFS($AQ$6:$AQ$32,$B$6:$B$32,"Quarter",$D$6:$D$32,1,$C$6:$C$32,">=2022",$C$6:$C$32,"<=2025") -> 0.66797876 | C43: =AVERAGEIFS($AQ$6:$AQ$32,$B$6:$B$32,"Quarter",$D$6:$D$32,2,$C$6:$C$32,">=2022",$C$6:$C$32,"<=2025") -> 0.56001229 | D43: =AVERAGEIFS($AQ$6:$AQ$32,$B$6:$B$32,"Quarter",$D$6:$D$32,3,$C$6:$C$32,">=2022",$C$6:$C$32,"<=2025") -> 0.53426439 | E43: =AVERAGEIFS($AQ$6:$AQ$32,$B$6:$B$32,"Quarter",$D$6:$D$32,4,$C$6:$C$32,">=2022",$C$6:$C$32,"<=2025") -> 0.5096329 | F43: =AVERAGEIFS($AX$6:$AX$32,$B$6:$B$32,"Quarter",$D$6:$D$32,1,$C$6:$C$32,">=2022",$C$6:$C$32,"<=2025") -> 0.10616131 | G43: =AVERAGEIFS($AX$6:$AX$32,$B$6:$B$32,"Quarter",$D$6:$D$32,2,$C$6:$C$32,">=2022",$C$6:$C$32,"<=2025") -> -0.001805166 | H43: =AVERAGEIFS($AX$6:$AX$32,$B$6:$B$32,"Quarter",$D$6:$D$32,3,$C$6:$C$32,">=2022",$C$6:$C$32,"<=2025") -> -0.027553062 | I43: =AVERAGEIFS($AX$6:$AX$32,$B$6:$B$32,"Quarter",$D$6:$D$32,4,$C$6:$C$32,">=2022",$C$6:$C$32,"<=2025") -> -0.052184554
A44: G&A % rev (GAAP) | B44: =AVERAGEIFS($AR$6:$AR$32,$B$6:$B$32,"Quarter",$D$6:$D$32,1,$C$6:$C$32,">=2022",$C$6:$C$32,"<=2025") -> 0.13800081 | C44: =AVERAGEIFS($AR$6:$AR$32,$B$6:$B$32,"Quarter",$D$6:$D$32,2,$C$6:$C$32,">=2022",$C$6:$C$32,"<=2025") -> 0.1399561 | D44: =AVERAGEIFS($AR$6:$AR$32,$B$6:$B$32,"Quarter",$D$6:$D$32,3,$C$6:$C$32,">=2022",$C$6:$C$32,"<=2025") -> 0.15702713 | E44: =AVERAGEIFS($AR$6:$AR$32,$B$6:$B$32,"Quarter",$D$6:$D$32,4,$C$6:$C$32,">=2022",$C$6:$C$32,"<=2025") -> 0.12503276
A45: G&A % rev (non-GAAP) | B45: =AVERAGEIFS($AS$6:$AS$32,$B$6:$B$32,"Quarter",$D$6:$D$32,1,$C$6:$C$32,">=2022",$C$6:$C$32,"<=2025") -> 0.094610848 | C45: =AVERAGEIFS($AS$6:$AS$32,$B$6:$B$32,"Quarter",$D$6:$D$32,2,$C$6:$C$32,">=2022",$C$6:$C$32,"<=2025") -> 0.091880563 | D45: =AVERAGEIFS($AS$6:$AS$32,$B$6:$B$32,"Quarter",$D$6:$D$32,3,$C$6:$C$32,">=2022",$C$6:$C$32,"<=2025") -> 0.090574425 | E45: =AVERAGEIFS($AS$6:$AS$32,$B$6:$B$32,"Quarter",$D$6:$D$32,4,$C$6:$C$32,">=2022",$C$6:$C$32,"<=2025") -> 0.089658995 | F45: =AVERAGEIFS($AY$6:$AY$32,$B$6:$B$32,"Quarter",$D$6:$D$32,1,$C$6:$C$32,">=2022",$C$6:$C$32,"<=2025") -> 0.003131607 | G45: =AVERAGEIFS($AY$6:$AY$32,$B$6:$B$32,"Quarter",$D$6:$D$32,2,$C$6:$C$32,">=2022",$C$6:$C$32,"<=2025") -> 0.00040132211 | H45: =AVERAGEIFS($AY$6:$AY$32,$B$6:$B$32,"Quarter",$D$6:$D$32,3,$C$6:$C$32,">=2022",$C$6:$C$32,"<=2025") -> -0.00090481643 | I45: =AVERAGEIFS($AY$6:$AY$32,$B$6:$B$32,"Quarter",$D$6:$D$32,4,$C$6:$C$32,">=2022",$C$6:$C$32,"<=2025") -> -0.0018202459
A46: Operating margin (GAAP) | B46: =AVERAGEIFS($AT$6:$AT$32,$B$6:$B$32,"Quarter",$D$6:$D$32,1,$C$6:$C$32,">=2022",$C$6:$C$32,"<=2025") -> -0.18769208 | C46: =AVERAGEIFS($AT$6:$AT$32,$B$6:$B$32,"Quarter",$D$6:$D$32,2,$C$6:$C$32,">=2022",$C$6:$C$32,"<=2025") -> -0.11838931 | D46: =AVERAGEIFS($AT$6:$AT$32,$B$6:$B$32,"Quarter",$D$6:$D$32,3,$C$6:$C$32,">=2022",$C$6:$C$32,"<=2025") -> -0.084071689 | E46: =AVERAGEIFS($AT$6:$AT$32,$B$6:$B$32,"Quarter",$D$6:$D$32,4,$C$6:$C$32,">=2022",$C$6:$C$32,"<=2025") -> -0.0075171691
A47: Operating margin (non-GAAP) | B47: =AVERAGEIFS($AU$6:$AU$32,$B$6:$B$32,"Quarter",$D$6:$D$32,1,$C$6:$C$32,">=2022",$C$6:$C$32,"<=2025") -> -0.040543868 | C47: =AVERAGEIFS($AU$6:$AU$32,$B$6:$B$32,"Quarter",$D$6:$D$32,2,$C$6:$C$32,">=2022",$C$6:$C$32,"<=2025") -> 0.070992486 | D47: =AVERAGEIFS($AU$6:$AU$32,$B$6:$B$32,"Quarter",$D$6:$D$32,3,$C$6:$C$32,">=2022",$C$6:$C$32,"<=2025") -> 0.097342436 | E47: =AVERAGEIFS($AU$6:$AU$32,$B$6:$B$32,"Quarter",$D$6:$D$32,4,$C$6:$C$32,">=2022",$C$6:$C$32,"<=2025") -> 0.11893395 | F47: =AVERAGEIFS($AZ$6:$AZ$32,$B$6:$B$32,"Quarter",$D$6:$D$32,1,$C$6:$C$32,">=2022",$C$6:$C$32,"<=2025") -> -0.10857885 | G47: =AVERAGEIFS($AZ$6:$AZ$32,$B$6:$B$32,"Quarter",$D$6:$D$32,2,$C$6:$C$32,">=2022",$C$6:$C$32,"<=2025") -> 0.0029575014 | H47: =AVERAGEIFS($AZ$6:$AZ$32,$B$6:$B$32,"Quarter",$D$6:$D$32,3,$C$6:$C$32,">=2022",$C$6:$C$32,"<=2025") -> 0.029307451 | I47: =AVERAGEIFS($AZ$6:$AZ$32,$B$6:$B$32,"Quarter",$D$6:$D$32,4,$C$6:$C$32,">=2022",$C$6:$C$32,"<=2025") -> 0.050898962
A50: Sales & marketing and the 2025 commission model change (NOT comparable across the change; no adjustment made)
A51: Period | B51: S&M % rev (GAAP) | C51: S&M % rev (non-GAAP) | D51: Commissions % of revenue (as reported) | E51: Row ID | F51: Source ID | G51: Commission metric label in source
A52: Text / label | B52: Derived (formula) | C52: Derived (formula) | D52: Sourced (copied from source book) | E52: Source-book Row ID | F52: Source ID | G52: Text / label
A53: FY 2023 | B53: =AP30 -> 0.6008017 | C53: =AQ30 -> 0.56599949 | D53: 0.06 | E53: AN-0348 | F53: 20F-FY2025 | G53: Sales related commissions as % of revenue (FY2025 20-F)
A54: FY 2024 | B54: =AP31 -> 0.54891126 | C54: =AQ31 -> 0.51407055 | D54: 0.05 | E54: AN-0349 | F54: 20F-FY2025 | G54: Sales related commissions as % of revenue (FY2025 20-F)
A55: FY 2025 | B55: =AP32 -> 0.51205563 | C55: =AQ32 -> 0.47627308 | D55: 0.02 | E55: AN-0350 | F55: 20F-FY2025 | G55: Sales related commissions as % of revenue (FY2025 20-F)
A56: Q1 2024 | B56: =AP18 -> 0.59074836 | C56: =AQ18 -> 0.55693296
A57: Q2 2024 | B57: =AP19 -> 0.55683041 | C57: =AQ19 -> 0.51137201
A58: Q1 2025 | B58: =AP22 -> 0.50210806 | C58: =AQ22 -> 0.48142427
A59: Q2 2025 | B59: =AP23 -> 0.51031055 | C59: =AQ23 -> 0.46560696
A60: Q1 2026 | B60: =AP26 -> 0.47085534 | C60: =AQ26 -> 0.45031814
A61: Q2 2026 | B61: =AP27 -> 0.44539947 | C61: =AQ27 -> 0.4098612
A62: H1 2024 | D62: 0.05 | E62: AN-2041 | F62: H1MDA-2024 | G62: H1 2024: Channel partners' commissions as % of revenue (H1 2024 MD&A)
A63: H1 2025 | D63: 0.02 | E63: AN-2042 | F63: H1MDA-2025 | G63: H1 2025: Channel partners' commissions as % of revenue (H1 2025 MD&A)
A64: H1 2026 | D64: 0.02 | E64: AN-2430 | F64: H1MDA-2026 | G64: H1 2026: Sales related commissions as % of revenue (H1 2026 MD&A)
A65: Partners commission expense decrease due to capitalization, FY2025 (USD millions): | D65: 25.2 | E65: AN-2085 | F65: 20F-FY2025
A67: READ THIS: The FY2025 20-F states that sales-related commissions fell to ~2% of revenue (from ~5% in 2024 and ~6% in 2023) because of a change in the commissions model, and that partner commission expense decreased $25.2M "due to capitalization".
A68: More commission cost is now capitalized and amortized over ~3 years, so S&M expense in 2025 and 2026 is NOT comparable with 2023-2024. The S&M ratios above are shown as reported; no restatement, normalization or pro-forma adjustment has been made.
A69: Commission percentages are rounded whole percentages as disclosed; the 2023-2024 basis ("channel partners' commissions" in earlier filings vs "sales related commissions" in later ones) is itself a wording change.

Sheet Cash_Conversion
A1: Cash conversion: adjusted FCF vs revenue and non-GAAP operating income; Q1-Q2 2026 cash bridge
A2: Adjusted FCF is the company-defined measure (label and add-back scope change over time: see source-book Definitions). USD thousands.
A4: Period | B4: Basis | C4: Fiscal year | D4: Fiscal quarter | E4: Revenue (USD k) | F4: Row ID | G4: Source ID | H4: Non-GAAP operating income (USD k) | I4: Row ID | J4: Source ID | K4: Operating cash flow (USD k) | L4: Row ID | M4: Source ID | N4: Adjusted FCF / FCF (USD k) | O4: Row ID | P4: Source ID | Q4: Adj. FCF % of revenue | R4: Adj. FCF / non-GAAP op. income (n/m if op. income <= 0) | S4: OCF % of revenue | T4: Quarter share of FY adj. FCF
A5: Text / label | B5: Text / label | C5: Text / label | D5: Text / label | E5: Sourced (copied from source book) | F5: Source-book Row ID | G5: Source ID | H5: Sourced (copied from source book) | I5: Source-book Row ID | J5: Source ID | K5: Sourced (copied from source book) | L5: Source-book Row ID | M5: Source ID | N5: Sourced (copied from source book) | O5: Source-book Row ID | P5: Source ID | Q5: Derived (formula) | R5: Derived (formula) | S5: Derived (formula) | T5: Derived (formula)
A6: Q1 2021 | B6: Quarter | C6: 2021 | D6: 1 | E6: 58972 | F6: QA-0001 | G6: ER-2022Q1 | H6: -23307 | I6: QA-0665 | J6: ER-2022Q1 | K6: -599 | L6: QA-0929 | M6: ER-2022Q1 | N6: -1595 | O6: QA-1067 | P6: ER-2022Q1 | Q6: =N6/E6 -> -0.027046734 | R6: =IF(H6<=0,"n/m",N6/H6) -> n/m | S6: =K6/E6 -> -0.010157363 | T6: =IF(N28<=0,"n/m",N6/N28) -> -0.16111111
A7: Q2 2021 | B7: Quarter | C7: 2021 | D7: 2 | E7: 70615 | F7: QA-0002 | G7: ER-2021Q2 | H7: -9911 | I7: QA-0666 | J7: ER-2021Q2 | K7: -355 | L7: QA-0930 | M7: ER-2021Q2 | N7: -1480 | O7: QA-1068 | P7: ER-2021Q2 | Q7: =N7/E7 -> -0.02095872 | R7: =IF(H7<=0,"n/m",N7/H7) -> n/m | S7: =K7/E7 -> -0.0050272605 | T7: =IF(N28<=0,"n/m",N7/N28) -> -0.14949495
A8: Q3 2021 | B8: Quarter | C8: 2021 | D8: 3 | E8: 83018 | F8: QA-0004 | G8: ER-2021Q3 | H8: -9449 | I8: QA-0668 | J8: ER-2021Q3 | K8: 3793 | L8: QA-0932 | M8: ER-2021Q3 | N8: 2865 | O8: QA-1070 | P8: ER-2021Q3 | Q8: =N8/E8 -> 0.034510588 | R8: =IF(H8<=0,"n/m",N8/H8) -> n/m | S8: =K8/E8 -> 0.045688887 | T8: =IF(N28<=0,"n/m",N8/N28) -> 0.28939394
A9: Q4 2021 | B9: Quarter | C9: 2021 | D9: 4 | E9: 95545 | F9: QA-0006 | G9: ER-2021Q4 | H9: -9929 | I9: QA-0670 | J9: ER-2021Q4 | K9: 13516 | L9: QA-0934 | M9: ER-2021Q4 | N9: 10110 | O9: QA-1072 | P9: ER-2021Q4 | Q9: =N9/E9 -> 0.10581401 | R9: =IF(H9<=0,"n/m",N9/H9) -> n/m | S9: =K9/E9 -> 0.14146214 | T9: =IF(N28<=0,"n/m",N9/N28) -> 1.0212121
A10: Q1 2022 | B10: Quarter | C10: 2022 | D10: 1 | E10: 108497 | F10: QA-0008 | G10: ER-2022Q1 | H10: -43830 | I10: QA-0672 | J10: ER-2022Q1 | K10: -12912 | L10: QA-0936 | M10: ER-2022Q1 | N10: -16192 | O10: QA-1074 | P10: ER-2022Q1 | Q10: =N10/E10 -> -0.14923915 | R10: =IF(H10<=0,"n/m",N10/H10) -> n/m | S10: =K10/E10 -> -0.1190079 | T10: =IF(N29<=0,"n/m",N10/N29) -> -1.9899226
A11: Q2 2022 | B11: Quarter | C11: 2022 | D11: 2 | E11: 123718 | F11: QA-0009 | G11: ER-2022Q2 | H11: -15358 | I11: QA-0673 | J11: ER-2022Q2 | K11: -14061 | L11: QA-0937 | M11: ER-2022Q2 | N11: -19295 | O11: QA-1075 | P11: ER-2022Q2 | Q11: =N11/E11 -> -0.15595952 | R11: =IF(H11<=0,"n/m",N11/H11) -> n/m | S11: =K11/E11 -> -0.11365363 | T11: =IF(N29<=0,"n/m",N11/N29) -> -2.3712671
A12: Q3 2022 | B12: Quarter | C12: 2022 | D12: 3 | E12: 136893 | F12: QA-0011 | G12: ER-2022Q3 | H12: -2185 | I12: QA-0675 | J12: ER-2022Q3 | K12: 20030 | L12: QA-0939 | M12: ER-2022Q3 | N12: 13959 | O12: QA-1077 | P12: ER-2022Q3 | Q12: =N12/E12 -> 0.10197015 | R12: =IF(H12<=0,"n/m",N12/H12) -> n/m | S12: =K12/E12 -> 0.14631866 | T12: =IF(N29<=0,"n/m",N12/N29) -> 1.7154971
A13: Q4 2022 | B13: Quarter | C13: 2022 | D13: 4 | E13: 149921 | F13: QA-0013 | G13: ER-2022Q4 | H13: 14278 | I13: QA-0677 | J13: ER-2022Q4 | K13: 34081 | L13: QA-0941 | M13: ER-2022Q4 | N13: 29665 | O13: QA-1079 | P13: ER-2022Q4 | Q13: =N13/E13 -> 0.19787088 | R13: =IF(H13<=0,"n/m",N13/H13) -> 2.0776719 | S13: =K13/E13 -> 0.22732639 | T13: =IF(N29<=0,"n/m",N13/N29) -> 3.6456925
A14: Q1 2023 | B14: Quarter | C14: 2023 | D14: 1 | E14: 162256 | F14: QA-0015 | G14: ER-2023Q1 | H14: -293 | I14: QA-0679 | J14: ER-2023Q1 | K14: 42728 | L14: QA-0943 | M14: ER-2023Q1 | N14: 38682 | O14: QA-1081 | P14: ER-2023Q1 | Q14: =N14/E14 -> 0.23840105 | R14: =IF(H14<=0,"n/m",N14/H14) -> n/m | S14: =K14/E14 -> 0.26333695 | T14: =IF(N30<=0,"n/m",N14/N30) -> 0.18874332
A15: Q2 2023 | B15: Quarter | C15: 2023 | D15: 2 | E15: 175679 | F15: QA-0016 | G15: ER-2023Q2 | H15: 16617 | I15: QA-0680 | J15: ER-2023Q2 | K15: 47589 | L15: QA-0944 | M15: ER-2023Q2 | N15: 45932 | O15: QA-1082 | P15: ER-2023Q2 | Q15: =N15/E15 -> 0.26145413 | R15: =IF(H15<=0,"n/m",N15/H15) -> 2.7641572 | S15: =K15/E15 -> 0.2708861 | T15: =IF(N30<=0,"n/m",N15/N30) -> 0.22411867
A16: Q3 2023 | B16: Quarter | C16: 2023 | D16: 3 | E16: 189190 | F16: QA-0018 | G16: ER-2023Q3 | H16: 24077 | I16: QA-0682 | J16: ER-2023Q3 | K16: 66579 | L16: QA-0946 | M16: ER-2023Q3 | N16: 64890 | O16: QA-1084 | P16: ER-2023Q3 | Q16: =N16/E16 -> 0.34298853 | R16: =IF(H16<=0,"n/m",N16/H16) -> 2.6951032 | S16: =K16/E16 -> 0.35191606 | T16: =IF(N30<=0,"n/m",N16/N30) -> 0.31662153
A17: Q4 2023 | B17: Quarter | C17: 2023 | D17: 4 | E17: 202570 | F17: QA-0020 | G17: ER-2023Q4 | H17: 21200 | I17: QA-0684 | J17: ER-2023Q4 | K17: 58508 | L17: QA-0948 | M17: ER-2023Q4 | N17: 55441 | O17: QA-1086 | P17: ER-2023Q4 | Q17: =N17/E17 -> 0.27368811 | R17: =IF(H17<=0,"n/m",N17/H17) -> 2.6151415 | S17: =K17/E17 -> 0.28882855 | T17: =IF(N30<=0,"n/m",N17/N30) -> 0.27051648
A18: Q1 2024 | B18: Quarter | C18: 2024 | D18: 1 | E18: 216913 | F18: QA-0022 | G18: ER-2024Q1 | H18: 21521 | I18: QA-0686 | J18: ER-2024Q1 | K18: 91955 | L18: QA-0950 | M18: ER-2024Q1 | N18: 89894 | O18: QA-1088 | P18: ER-2024Q1 | Q18: =N18/E18 -> 0.41442422 | R18: =IF(H18<=0,"n/m",N18/H18) -> 4.1770364 | S18: =K18/E18 -> 0.42392572 | T18: =IF(N31<=0,"n/m",N18/N31) -> 0.30387047
A19: Q2 2024 | B19: Quarter | C19: 2024 | D19: 2 | E19: 236106 | F19: QA-0023 | G19: ER-2024Q2 | H19: 38417 | I19: QA-0687 | J19: ER-2024Q2 | K19: 55794 | L19: QA-0951 | M19: ER-2024Q2 | N19: 50821 | O19: QA-1089 | P19: ER-2024Q2 | Q19: =N19/E19 -> 0.21524654 | R19: =IF(H19<=0,"n/m",N19/H19) -> 1.3228779 | S19: =K19/E19 -> 0.23630912 | T19: =IF(N31<=0,"n/m",N19/N31) -> 0.17179123
A20: Q3 2024 | B20: Quarter | C20: 2024 | D20: 3 | E20: 251000 | F20: QA-0025 | G20: ER-2024Q3 | H20: 32180 | I20: QA-0689 | J20: ER-2024Q3 | K20: 86605 | L20: QA-0953 | M20: ER-2024Q3 | N20: 82412 | O20: QA-1091 | P20: ER-2024Q3 | Q20: =N20/E20 -> 0.32833466 | R20: =IF(H20<=0,"n/m",N20/H20) -> 2.5609695 | S20: =K20/E20 -> 0.34503984 | T20: =IF(N31<=0,"n/m",N20/N31) -> 0.27857891
A21: Q4 2024 | B21: Quarter | C21: 2024 | D21: 4 | E21: 267976 | F21: QA-0027 | G21: ER-2024Q4 | H21: 40265 | I21: QA-0691 | J21: ER-2024Q4 | K21: 76711 | L21: QA-0955 | M21: ER-2024Q4 | N21: 72703 | O21: QA-1093 | P21: ER-2024Q4 | Q21: =N21/E21 -> 0.27130415 | R21: =IF(H21<=0,"n/m",N21/H21) -> 1.8056128 | S21: =K21/E21 -> 0.28626071 | T21: =IF(N31<=0,"n/m",N21/N31) -> 0.24575939
A22: Q1 2025 | B22: Quarter | C22: 2025 | D22: 1 | E22: 282250 | F22: QA-0029 | G22: ER-2025Q1 | H22: 40754 | I22: QA-0693 | J22: ER-2025Q1 | K22: 111970 | L22: QA-0957 | M22: ER-2025Q1 | N22: 109532 | O22: QA-1095 | P22: ER-2025Q1 | Q22: =N22/E22 -> 0.38806732 | R22: =IF(H22<=0,"n/m",N22/H22) -> 2.687638 | S22: =K22/E22 -> 0.39670505 | T22: =IF(N32<=0,"n/m",N22/N32) -> 0.33946569
A23: Q2 2025 | B23: Quarter | C23: 2025 | D23: 2 | E23: 299014 | F23: QA-0030 | G23: ER-2025Q2 | H23: 45094 | I23: QA-0694 | J23: ER-2025Q2 | K23: 66837 | L23: QA-0958 | M23: ER-2025Q2 | N23: 64093 | O23: QA-1096 | P23: ER-2025Q2 | Q23: =N23/E23 -> 0.21434782 | R23: =IF(H23<=0,"n/m",N23/H23) -> 1.4213199 | S23: =K23/E23 -> 0.22352465 | T23: =IF(N32<=0,"n/m",N23/N32) -> 0.19863943
A24: Q3 2025 | B24: Quarter | C24: 2025 | D24: 3 | E24: 316855 | F24: QA-0032 | G24: ER-2025Q3 | H24: 47484 | I24: QA-0696 | J24: ER-2025Q3 | K24: 95144 | L24: QA-0960 | M24: ER-2025Q3 | N24: 92301 | O24: QA-1098 | P24: ER-2025Q3 | Q24: =N24/E24 -> 0.29130359 | R24: =IF(H24<=0,"n/m",N24/H24) -> 1.9438337 | S24: =K24/E24 -> 0.30027615 | T24: =IF(N32<=0,"n/m",N24/N32) -> 0.28606273
A25: Q4 2025 | B25: Quarter | C25: 2025 | D25: 4 | E25: 333878 | F25: QA-0034 | G25: ER-2025Q4 | H25: 41931 | I25: QA-0698 | J25: ER-2025Q4 | K25: 59693 | L25: QA-0962 | M25: ER-2025Q4 | N25: 56734 | O25: QA-1100 | P25: ER-2025Q4 | Q25: =N25/E25 -> 0.16992434 | R25: =IF(H25<=0,"n/m",N25/H25) -> 1.3530324 | S25: =K25/E25 -> 0.17878686 | T25: =IF(N32<=0,"n/m",N25/N32) -> 0.17583215
A26: Q1 2026 | B26: Quarter | C26: 2026 | D26: 1 | E26: 351265 | F26: QA-0036 | G26: ER-2026Q1 | H26: 49037 | I26: QA-0700 | J26: ER-2026Q1 | K26: 104687 | L26: QA-0964 | M26: ER-2026Q1 | N26: 102778 | O26: QA-1102 | P26: ER-2026Q1 | Q26: =N26/E26 -> 0.29259391 | R26: =IF(H26<=0,"n/m",N26/H26) -> 2.0959276 | S26: =K26/E26 -> 0.29802855
A27: Q2 2026 | B27: Quarter | C27: 2026 | D27: 2 | E27: 364621 | F27: QA-0037 | G27: ER-2026Q2 | H27: 61110 | I27: QA-0701 | J27: ER-2026Q2 | K27: 55354 | L27: QA-0965 | M27: ER-2026Q2 | N27: 52344 | O27: QA-1103 | P27: ER-2026Q2 | Q27: =N27/E27 -> 0.14355728 | R27: =IF(H27<=0,"n/m",N27/H27) -> 0.85655376 | S27: =K27/E27 -> 0.15181243
A28: FY 2021 | B28: Fiscal year | C28: 2021 | D28: FY | E28: 308150 | F28: QA-0007 | G28: ER-2021Q4 | H28: -52596 | I28: QA-0671 | J28: ER-2021Q4 | K28: 16355 | L28: QA-0935 | M28: ER-2021Q4 | N28: 9900 | O28: QA-1073 | P28: ER-2021Q4 | Q28: =N28/E28 -> 0.032127211 | R28: =IF(H28<=0,"n/m",N28/H28) -> n/m | S28: =K28/E28 -> 0.053074801
A29: FY 2022 | B29: Fiscal year | C29: 2022 | D29: FY | E29: 519029 | F29: QA-0014 | G29: ER-2022Q4 | H29: -47095 | I29: QA-0678 | J29: ER-2022Q4 | K29: 27138 | L29: QA-0942 | M29: ER-2022Q4 | N29: 8137 | O29: QA-1080 | P29: ER-2022Q4 | Q29: =N29/E29 -> 0.015677351 | R29: =IF(H29<=0,"n/m",N29/H29) -> n/m | S29: =K29/E29 -> 0.052286096
A30: FY 2023 | B30: Fiscal year | C30: 2023 | D30: FY | E30: 729695 | F30: QA-0021 | G30: ER-2023Q4 | H30: 61601 | I30: QA-0685 | J30: ER-2023Q4 | K30: 215404 | L30: QA-0949 | M30: ER-2023Q4 | N30: 204945 | O30: QA-1087 | P30: ER-2023Q4 | Q30: =N30/E30 -> 0.28086392 | R30: =IF(H30<=0,"n/m",N30/H30) -> 3.3269752 | S30: =K30/E30 -> 0.29519731
A31: FY 2024 | B31: Fiscal year | C31: 2024 | D31: FY | E31: 971995 | F31: QA-0028 | G31: ER-2024Q4 | H31: 132383 | I31: QA-0692 | J31: ER-2024Q4 | K31: 311065 | L31: QA-0956 | M31: ER-2024Q4 | N31: 295830 | O31: QA-1094 | P31: ER-2024Q4 | Q31: =N31/E31 -> 0.30435342 | R31: =IF(H31<=0,"n/m",N31/H31) -> 2.2346525 | S31: =K31/E31 -> 0.32002737
A32: FY 2025 | B32: Fiscal year | C32: 2025 | D32: FY | E32: 1231997 | F32: QA-0035 | G32: ER-2025Q4 | H32: 175263 | I32: QA-0699 | J32: ER-2025Q4 | K32: 333644 | L32: QA-0963 | M32: ER-2025Q4 | N32: 322660 | O32: QA-1101 | P32: ER-2025Q4 | Q32: =N32/E32 -> 0.26189999 | R32: =IF(H32<=0,"n/m",N32/H32) -> 1.8410047 | S32: =K32/E32 -> 0.27081559
A35: Seasonality (Derived): averages by fiscal quarter
A36: Measure | B36: Years | C36: Q1 | D36: Q2 | E36: Q3 | F36: Q4
A37: Text / label | B37: Text / label | C37: Derived (formula) | D37: Derived (formula) | E37: Derived (formula) | F37: Derived (formula)
A38: Adj. FCF % of revenue | B38: 2022-2025 | C38: =AVERAGEIFS($Q$6:$Q$32,$B$6:$B$32,"Quarter",$D$6:$D$32,1,$C$6:$C$32,">=2022",$C$6:$C$32,"<=2025") -> 0.22291336 | D38: =AVERAGEIFS($Q$6:$Q$32,$B$6:$B$32,"Quarter",$D$6:$D$32,2,$C$6:$C$32,">=2022",$C$6:$C$32,"<=2025") -> 0.13377224 | E38: =AVERAGEIFS($Q$6:$Q$32,$B$6:$B$32,"Quarter",$D$6:$D$32,3,$C$6:$C$32,">=2022",$C$6:$C$32,"<=2025") -> 0.26614923 | F38: =AVERAGEIFS($Q$6:$Q$32,$B$6:$B$32,"Quarter",$D$6:$D$32,4,$C$6:$C$32,">=2022",$C$6:$C$32,"<=2025") -> 0.22819687
A39: Adj. FCF % of revenue | B39: 2023-2025 | C39: =AVERAGEIFS($Q$6:$Q$32,$B$6:$B$32,"Quarter",$D$6:$D$32,1,$C$6:$C$32,">=2023",$C$6:$C$32,"<=2025") -> 0.34696419 | D39: =AVERAGEIFS($Q$6:$Q$32,$B$6:$B$32,"Quarter",$D$6:$D$32,2,$C$6:$C$32,">=2023",$C$6:$C$32,"<=2025") -> 0.2303495 | E39: =AVERAGEIFS($Q$6:$Q$32,$B$6:$B$32,"Quarter",$D$6:$D$32,3,$C$6:$C$32,">=2023",$C$6:$C$32,"<=2025") -> 0.32087559 | F39: =AVERAGEIFS($Q$6:$Q$32,$B$6:$B$32,"Quarter",$D$6:$D$32,4,$C$6:$C$32,">=2023",$C$6:$C$32,"<=2025") -> 0.23830553
A40: OCF % of revenue | B40: 2023-2025 | C40: =AVERAGEIFS($S$6:$S$32,$B$6:$B$32,"Quarter",$D$6:$D$32,1,$C$6:$C$32,">=2023",$C$6:$C$32,"<=2025") -> 0.36132257 | D40: =AVERAGEIFS($S$6:$S$32,$B$6:$B$32,"Quarter",$D$6:$D$32,2,$C$6:$C$32,">=2023",$C$6:$C$32,"<=2025") -> 0.24357329 | E40: =AVERAGEIFS($S$6:$S$32,$B$6:$B$32,"Quarter",$D$6:$D$32,3,$C$6:$C$32,">=2023",$C$6:$C$32,"<=2025") -> 0.33241069 | F40: =AVERAGEIFS($S$6:$S$32,$B$6:$B$32,"Quarter",$D$6:$D$32,4,$C$6:$C$32,">=2023",$C$6:$C$32,"<=2025") -> 0.25129204
A41: Quarter share of FY adj. FCF | B41: 2023-2025 | C41: =AVERAGEIFS($T$6:$T$32,$B$6:$B$32,"Quarter",$D$6:$D$32,1,$C$6:$C$32,">=2023",$C$6:$C$32,"<=2025") -> 0.27735983 | D41: =AVERAGEIFS($T$6:$T$32,$B$6:$B$32,"Quarter",$D$6:$D$32,2,$C$6:$C$32,">=2023",$C$6:$C$32,"<=2025") -> 0.19818311 | E41: =AVERAGEIFS($T$6:$T$32,$B$6:$B$32,"Quarter",$D$6:$D$32,3,$C$6:$C$32,">=2023",$C$6:$C$32,"<=2025") -> 0.29375439 | F41: =AVERAGEIFS($T$6:$T$32,$B$6:$B$32,"Quarter",$D$6:$D$32,4,$C$6:$C$32,">=2023",$C$6:$C$32,"<=2025") -> 0.23070267
A42: 2023-2025 = years with positive non-GAAP operating income and positive FCF in every quarter; 2022 includes negative-FCF quarters. "Quarter share of FY" uses each year's FY adjusted FCF.
A45: Cash and cash equivalents bridge, Q1-Q2 2026 (disclosed items only; "other" is the Derived residual)
A46: Line | B46: Q1 2026 (USD k) | C46: Row ID | D46: Source ID | E46: Q2 2026 (USD k) | F46: Row ID | G46: Source ID | H46: H1 2026 (USD k) | I46: Label
A47: Text / label | B47: Sourced / Derived | C47: Source-book Row ID | D47: Source ID | E47: Sourced / Derived | F47: Source-book Row ID | G47: Source ID | H47: Derived (formula) | I47: Text / label
A48: Opening cash and cash equivalents | B48: 1503149 | C48: QA-1231 | D48: ER-2025Q4 | E48: 997135 | F48: QA-1232 | G48: ER-2026Q1 | H48: =B48 -> 1503149 | I48: Sourced
A49: Net cash provided by operating activities | B49: 104687 | C49: QA-0964 | D49: ER-2026Q1 | E49: 55354 | F49: QA-0965 | G49: ER-2026Q2 | H49: =B49+E49 -> 160041 | I49: Sourced
A50: Purchase of property and equipment | B50: -2447 | C50: QA-1002 | D50: ER-2026Q1 | E50: -3790 | F50: QA-1003 | G50: ER-2026Q2 | H50: =B50+E50 -> -6237 | I50: Sourced
A51: Capitalized software development costs | B51: -484 | C51: QA-1040 | D51: ER-2026Q1 | E51: -1106 | F51: QA-1041 | G51: ER-2026Q2 | H51: =B51+E51 -> -1590 | I51: Sourced
A52: Repurchase of ordinary shares | B52: -552612 | C52: QA-1200 | D52: ER-2026Q1 | E52: -182359 | F52: QA-1201 | G52: ER-2026Q2 | H52: =B52+E52 -> -734971 | I52: Sourced
A53: Other (residual: all other investing and financing flows, e.g. marketable-securities purchases/maturities, OneAI acquisition, private investments, option exercises, tax advances; not itemized in the source book quarterly) | B53: =B54-B48-SUM(B49:B52) -> -55158 | E53: =E54-E48-SUM(E49:E52) -> -11832 | H53: =B53+E53 -> -66990 | I53: Derived (residual)
A54: Closing cash and cash equivalents | B54: 997135 | C54: QA-1232 | D54: ER-2026Q1 | E54: 853402 | F54: QA-1233 | G54: ER-2026Q2 | H54: =E54 -> 853402 | I54: Sourced
A56: Memo: marketable securities (point-in-time)
A57: Marketable securities, Dec 31, 2025 | B57: 162308 | C57: QA-1242 | D57: ER-2025Q4
A58: Marketable securities, Mar 31, 2026 | B58: 215141 | C58: QA-1243 | D58: ER-2026Q1
A59: Marketable securities, Jun 30, 2026 | B59: 219353 | C59: QA-1244 | D59: ER-2026Q2
A60: Cash, equivalents and marketable securities: change Dec 31, 2025 to Jun 30, 2026 | H60: =(E54+B59)-(B48+B57) -> -592702 | I60: Derived
A61: Memo: H1 2026 operating cash flow and repurchases per the 6M rows (for tie-out in Checks)
A62: OCF 6M 2026 | B62: 160041 | C62: QA-0966 | D62: ER-2026Q2
A63: Repurchases 6M 2026 | B63: -734971 | C63: QA-1202 | D63: ER-2026Q2

Sheet Deceleration
A1: Revenue growth, FX-adjusted view where disclosed, and what Q3 / FY2026 guidance implies for H2 2026
A2: All growth rates and implied values are Derived from copied inputs. Implied figures are arithmetic on company guidance, not a forecast.
A4: Quarter | B4: Revenue (USD k) | C4: Row ID | D4: Source ID | E4: Prior-year quarter revenue (USD k) | F4: Reported YoY growth | G4: Change vs prior quarter (pp) | H4: Disclosed FX impact on revenue growth (bps; negative = unfavorable) | I4: FX Row ID | J4: FX Source ID | K4: FX-adjusted YoY growth = reported - FX impact | L4: Note
A5: Text / label | B5: Sourced (copied from source book) | C5: Source-book Row ID | D5: Source ID | E5: Derived (formula) | F5: Derived (formula) | G5: Derived (formula) | H5: Sourced (copied from source book) | I5: Source-book Row ID | J5: Source ID | K5: Derived (formula) | L5: Text / label
A6: Q1 2021 | B6: 58972 | C6: QA-0001 | D6: ER-2022Q1 | L6: Prior-year quarter not in source book (history starts Q1 2021).
A7: Q2 2021 | B7: 70615 | C7: QA-0002 | D7: ER-2021Q2 | L7: Prior-year quarter not in source book (history starts Q1 2021).
A8: Q3 2021 | B8: 83018 | C8: QA-0004 | D8: ER-2021Q3 | L8: Prior-year quarter not in source book (history starts Q1 2021).
A9: Q4 2021 | B9: 95545 | C9: QA-0006 | D9: ER-2021Q4 | L9: Prior-year quarter not in source book (history starts Q1 2021).
A10: Q1 2022 | B10: 108497 | C10: QA-0008 | D10: ER-2022Q1 | E10: =B6 -> 58972 | F10: =B10/E10-1 -> 0.83980533 | H10: -100 | I10: QA-1546 | J10: ER-2022Q3 | K10: =F10-H10/10000 -> 0.84980533 | L10: FX table precision is whole percentage points (+/-50 bps).
A11: Q2 2022 | B11: 123718 | C11: QA-0009 | D11: ER-2022Q2 | E11: =B7 -> 70615 | F11: =B11/E11-1 -> 0.75200736 | G11: =(F11-F10)*100 -> -8.7797967 | H11: -200 | I11: QA-1547 | J11: ER-2022Q3 | K11: =F11-H11/10000 -> 0.77200736 | L11: FX table precision is whole percentage points (+/-50 bps).
A12: Q3 2022 | B12: 136893 | C12: QA-0011 | D12: ER-2022Q3 | E12: =B8 -> 83018 | F12: =B12/E12-1 -> 0.64895565 | G12: =(F12-F11)*100 -> -10.305172 | H12: -300 | I12: QA-1548 | J12: ER-2022Q3 | K12: =F12-H12/10000 -> 0.67895565 | L12: FX table precision is whole percentage points (+/-50 bps).
A13: Q4 2022 | B13: 149921 | C13: QA-0013 | D13: ER-2022Q4 | E13: =B9 -> 95545 | F13: =B13/E13-1 -> 0.56911403 | G13: =(F13-F12)*100 -> -7.9841618 | H13: -300 | I13: QA-1549 | J13: ER-2022Q4 | K13: =F13-H13/10000 -> 0.59911403 | L13: FX table precision is whole percentage points (+/-50 bps).
A14: Q1 2023 | B14: 162256 | C14: QA-0015 | D14: ER-2023Q1 | E14: =B10 -> 108497 | F14: =B14/E14-1 -> 0.49548835 | G14: =(F14-F13)*100 -> -7.3625676 | H14: -100 | I14: QA-1551 | J14: ER-2023Q1 | K14: =F14-H14/10000 -> 0.50548835 | L14: FX table precision is whole percentage points (+/-50 bps).
A15: Q2 2023 | B15: 175679 | C15: QA-0016 | D15: ER-2023Q2 | E15: =B11 -> 123718 | F15: =B15/E15-1 -> 0.41999547 | G15: =(F15-F14)*100 -> -7.5492881 | H15: -100 | I15: QA-1552 | J15: ER-2023Q2 | K15: =F15-H15/10000 -> 0.42999547 | L15: FX table precision is whole percentage points (+/-50 bps).
A16: Q3 2023 | B16: 189190 | C16: QA-0018 | D16: ER-2023Q3 | E16: =B12 -> 136893 | F16: =B16/E16-1 -> 0.3820283 | G16: =(F16-F15)*100 -> -3.7967174 | H16: 0 | I16: QA-1553 | J16: ER-2023Q3 | K16: =F16-H16/10000 -> 0.3820283 | L16: FX table precision is whole percentage points (+/-50 bps).
A17: Q4 2023 | B17: 202570 | C17: QA-0020 | D17: ER-2023Q4 | E17: =B13 -> 149921 | F17: =B17/E17-1 -> 0.35117829 | G17: =(F17-F16)*100 -> -3.0850012 | H17: 0 | I17: QA-1554 | J17: ER-2023Q4 | K17: =F17-H17/10000 -> 0.35117829 | L17: FX table precision is whole percentage points (+/-50 bps).
A18: Q1 2024 | B18: 216913 | C18: QA-0022 | D18: ER-2024Q1 | E18: =B14 -> 162256 | F18: =B18/E18-1 -> 0.33685657 | G18: =(F18-F17)*100 -> -1.4321715 | H18: 0 | I18: QA-1556 | J18: ER-2024Q1 | K18: =F18-H18/10000 -> 0.33685657 | L18: FX table precision is whole percentage points (+/-50 bps).
A19: Q2 2024 | B19: 236106 | C19: QA-0023 | D19: ER-2024Q2 | E19: =B15 -> 175679 | F19: =B19/E19-1 -> 0.34396257 | G19: =(F19-F18)*100 -> 0.71059958 | H19: 0 | I19: QA-1557 | J19: ER-2024Q2 | K19: =F19-H19/10000 -> 0.34396257 | L19: FX table precision is whole percentage points (+/-50 bps).
A20: Q3 2024 | B20: 251000 | C20: QA-0025 | D20: ER-2024Q3 | E20: =B16 -> 189190 | F20: =B20/E20-1 -> 0.3267086 | G20: =(F20-F19)*100 -> -1.7253968 | L20: No revenue FX impact disclosed for this quarter.
A21: Q4 2024 | B21: 267976 | C21: QA-0027 | D21: ER-2024Q4 | E21: =B17 -> 202570 | F21: =B21/E21-1 -> 0.32288098 | G21: =(F21-F20)*100 -> -0.38276204 | L21: No revenue FX impact disclosed for this quarter.
A22: Q1 2025 | B22: 282250 | C22: QA-0029 | D22: ER-2025Q1 | E22: =B18 -> 216913 | F22: =B22/E22-1 -> 0.30121293 | G22: =(F22-F21)*100 -> -2.1668051 | L22: No revenue FX impact disclosed for this quarter.
A23: Q2 2025 | B23: 299014 | C23: QA-0030 | D23: ER-2025Q2 | E23: =B19 -> 236106 | F23: =B23/E23-1 -> 0.26643965 | G23: =(F23-F22)*100 -> -3.4773279 | L23: No revenue FX impact disclosed for this quarter.
A24: Q3 2025 | B24: 316855 | C24: QA-0032 | D24: ER-2025Q3 | E24: =B20 -> 251000 | F24: =B24/E24-1 -> 0.26237052 | G24: =(F24-F23)*100 -> -0.40691321 | L24: No revenue FX impact disclosed for this quarter.
A25: Q4 2025 | B25: 333878 | C25: QA-0034 | D25: ER-2025Q4 | E25: =B21 -> 267976 | F25: =B25/E25-1 -> 0.24592501 | G25: =(F25-F24)*100 -> -1.644551 | L25: No revenue FX impact disclosed for this quarter.
A26: Q1 2026 | B26: 351265 | C26: QA-0036 | D26: ER-2026Q1 | E26: =B22 -> 282250 | F26: =B26/E26-1 -> 0.24451727 | G26: =(F26-F25)*100 -> -0.14077363 | L26: No revenue FX impact disclosed for this quarter.
A27: Q2 2026 | B27: 364621 | C27: QA-0037 | D27: ER-2026Q2 | E27: =B23 -> 299014 | F27: =B27/E27-1 -> 0.21941113 | G27: =(F27-F26)*100 -> -2.5106141 | H27: 110 | I27: QA-1558 | J27: ER-2026Q2 | K27: =F27-H27/10000 -> 0.20841113 | L27: FX impact stated as "approximately 110 basis point favorable".
A30: What the guidance implies for H2 2026 (Derived arithmetic; range ends paired low-with-low and high-with-high; not a forecast)
A31: Item | B31: Low | C31: Midpoint | D31: High | E31: Unit | F31: ID(s) | G31: Formula / note
A32: Text / label | B32: Sourced / Derived | C32: Sourced / Derived | D32: Sourced / Derived | E32: Text / label | F32: Source-book Row ID | G32: Text / label
A33: Q3 2026 revenue guidance | B33: 368 | C33: =(B33+D33)/2 -> 369 | D33: 370 | E33: USD m | F33: GH-0102 / ER-2026Q2 | G33: Guidance (copied); midpoint = average
A34: Q3 2025 revenue (actual) | C34: 316855 | E34: USD k | F34: QA-0032 / ER-2025Q3 | G34: Actual (copied)
A35: Implied Q3 2026 YoY revenue growth | B35: =B33*1000/C34-1 -> 0.16141453 | C35: =C33*1000/C34-1 -> 0.16457054 | D35: =D33*1000/C34-1 -> 0.16772656 | E35: % | G35: guidance x 1000 / Q3 2025 revenue - 1 (company text: "16% to 17%")
A36: FY2026 revenue guidance (Aug 10, 2026 vintage) | B36: 1466 | C36: =(B36+D36)/2 -> 1470 | D36: 1474 | E36: USD m | F36: GH-0100 / ER-2026Q2 | G36: Guidance (copied); midpoint = average
A37: FY2025 revenue (actual) | C37: 1231997 | E37: USD k | F37: QA-0035 / ER-2025Q4 | G37: Actual (copied)
A38: Implied FY2026 YoY revenue growth | B38: =B36*1000/C37-1 -> 0.18993796 | C38: =C36*1000/C37-1 -> 0.19318472 | D38: =D36*1000/C37-1 -> 0.19643148 | E38: % | G38: guidance x 1000 / FY2025 revenue - 1 (company text: "19% to 20%")
A39: H1 2026 revenue (actual, 6M) | C39: 715886 | E39: USD k | F39: QA-0038 / ER-2026Q2 | G39: Actual (copied)
A40: H1 2025 revenue (actual, 6M) | C40: 581264 | E40: USD k | F40: QA-0031 / ER-2025Q2 | G40: Actual (copied)
A41: H1 2026 YoY revenue growth (actual) | C41: =C39/C40-1 -> 0.23160216 | E41: % | G41: H1 2026 / H1 2025 - 1
A42: Implied H2 2026 revenue = FY guide - H1 actual | B42: =B36*1000-C39 -> 750114 | C42: =C36*1000-C39 -> 754114 | D42: =D36*1000-C39 -> 758114 | E42: USD k | G42: FY guidance x 1000 - H1 2026 actual
A43: H2 2025 revenue (actual) = FY2025 - H1 2025 | C43: =C37-C40 -> 650733 | E43: USD k | G43: FY2025 - 6M 2025
A44: Implied H2 2026 YoY revenue growth | B44: =B42/C43-1 -> 0.15272162 | C44: =C42/C43-1 -> 0.15886854 | D44: =D42/C43-1 -> 0.16501545 | E44: % | G44: implied H2 2026 / H2 2025 - 1
A45: Implied Q4 2026 revenue = FY guide - H1 actual - Q3 guide | B45: =B42-B33*1000 -> 382114 | C45: =C42-C33*1000 -> 385114 | D45: =D42-D33*1000 -> 388114 | E45: USD k | G45: Paired ends: (FY low - Q3 low), (mid - mid), (FY high - Q3 high). Other pairings give a wider range.
A46: Q4 2025 revenue (actual) | C46: 333878 | E46: USD k | F46: QA-0034 / ER-2025Q4 | G46: Actual (copied)
A47: Implied Q4 2026 YoY revenue growth | B47: =B45/C46-1 -> 0.14447193 | C47: =C45/C46-1 -> 0.15345725 | D47: =D45/C46-1 -> 0.16244257 | E47: % | G47: implied Q4 2026 / Q4 2025 - 1
A48: Implied Q4 2026 vs Q3 2026 guide (sequential change) | B48: =B45/(B33*1000)-1 -> 0.038353261 | C48: =C45/(C33*1000)-1 -> 0.043669377 | D48: =D45/(D33*1000)-1 -> 0.048956757 | E48: % | G48: implied Q4 / Q3 guide - 1
A50: FY2026 non-GAAP operating income guidance (Aug 10, 2026) | B50: 230 | C50: =(B50+D50)/2 -> 232 | D50: 234 | E50: USD m | F50: GH-0099 / ER-2026Q2 | G50: Guidance (copied); midpoint = average
A51: H1 2026 non-GAAP operating income (actual, 6M) | C51: 110147 | E51: USD k | F51: QA-0702 / ER-2026Q2 | G51: Actual (copied)
A52: Implied H2 2026 non-GAAP operating income | B52: =B50*1000-C51 -> 119853 | C52: =C50*1000-C51 -> 121853 | D52: =D50*1000-C51 -> 123853 | E52: USD k | G52: FY guide x 1000 - H1 actual
A53: Implied H2 2026 non-GAAP operating margin | B53: =B52/B42 -> 0.15977971 | C53: =C52/C42 -> 0.16158432 | D53: =D52/D42 -> 0.16336989 | E53: % | G53: implied H2 op. income / implied H2 revenue (paired ends)
A54: Q3 2026 non-GAAP operating income guidance | B54: 57 | C54: =(B54+D54)/2 -> 58 | D54: 59 | E54: USD m | F54: GH-0101 / ER-2026Q2 | G54: Guidance (copied); midpoint = average
A55: Implied Q4 2026 non-GAAP operating income | B55: =B52-B54*1000 -> 62853 | C55: =C52-C54*1000 -> 63853 | D55: =D52-D54*1000 -> 64853 | E55: USD k | G55: implied H2 - Q3 guide (paired ends)
A56: Implied Q4 2026 non-GAAP operating margin | B56: =B55/B45 -> 0.16448756 | C56: =C55/C45 -> 0.16580285 | D56: =D55/D45 -> 0.16709781 | E56: % | G56: implied Q4 op. income / implied Q4 revenue
A57: FY2026 adjusted FCF guidance (Aug 10, 2026) | B57: 280 | C57: =(B57+D57)/2 -> 285 | D57: 290 | E57: USD m | F57: GH-0098 / ER-2026Q2 | G57: Guidance (copied); midpoint = average
A58: H1 2026 adjusted FCF (actual, 6M) | C58: 155122 | E58: USD k | F58: QA-1104 / ER-2026Q2 | G58: Actual (copied)
A59: Implied H2 2026 adjusted FCF | B59: =B57*1000-C58 -> 124878 | C59: =C57*1000-C58 -> 129878 | D59: =D57*1000-C58 -> 134878 | E59: USD k | G59: FY guide x 1000 - H1 actual
A60: Implied H2 2026 adjusted FCF margin | B60: =B59/B42 -> 0.1664787 | C60: =C59/C42 -> 0.17222595 | D60: =D59/D42 -> 0.17791256 | E60: % | G60: implied H2 FCF / implied H2 revenue
A61: FY2025 adjusted FCF (actual) | C61: 322660 | E61: USD k | F61: QA-1101 / ER-2025Q4 | G61: Actual (copied)
A62: H1 2025 adjusted FCF (actual, 6M) | C62: 173625 | E62: USD k | F62: QA-1097 / ER-2025Q2 | G62: Actual (copied)
A63: H2 2025 adjusted FCF (actual) = FY2025 - H1 2025 | C63: =C61-C62 -> 149035 | E63: USD k | G63: FY2025 - 6M 2025
A64: H2 2025 adjusted FCF margin (actual) | C64: =C63/C43 -> 0.22902634 | E64: % | G64: H2 2025 adj. FCF / H2 2025 revenue
A66: How the H2 2026 implied by guidance changed between the May 11 and Aug 10, 2026 vintages (Derived; paired range ends)
A67: FY2026 revenue guidance (May 11, 2026 vintage) | B67: 1466 | C67: =(B67+D67)/2 -> 1470 | D67: 1474 | E67: USD m | F67: GH-0092 / ER-2026Q1 | G67: Guidance (copied); midpoint = average
A68: Q1 2026 revenue (actual) | C68: 351265 | E68: USD k | F68: QA-0036 / ER-2026Q1 | G68: Actual (copied)
A69: Q2 2026 revenue guidance (May 11, 2026) | B69: 354 | C69: =(B69+D69)/2 -> 355 | D69: 356 | E69: USD m | F69: GH-0094 / ER-2026Q1 | G69: Guidance (copied); midpoint = average
A70: H2 2026 revenue implied at May vintage = FY guide - Q1 actual - Q2 guide | B70: =B67*1000-C68-B69*1000 -> 760735 | C70: =C67*1000-C68-C69*1000 -> 763735 | D70: =D67*1000-C68-D69*1000 -> 766735 | E70: USD k | G70: May FY guide - Q1 actual - Q2 guide (paired ends)
A71: Change in implied H2 2026 revenue, Aug vs May vintage | B71: =B42-B70 -> -10621 | C71: =C42-C70 -> -9621 | D71: =D42-D70 -> -8621 | E71: USD k | G71: Aug implied H2 - May implied H2
A72: FY2026 non-GAAP operating income guidance (May 11, 2026 vintage) | B72: 185 | C72: =(B72+D72)/2 -> 188 | D72: 191 | E72: USD m | F72: GH-0091 / ER-2026Q1 | G72: Guidance (copied); midpoint = average
A73: Q1 2026 non-GAAP operating income (actual) | C73: 49037 | E73: USD k | F73: QA-0700 / ER-2026Q1 | G73: Actual (copied)
A74: Q2 2026 non-GAAP operating income guidance (May 11, 2026) | B74: 46 | C74: =(B74+D74)/2 -> 47 | D74: 48 | E74: USD m | F74: GH-0093 / ER-2026Q1 | G74: Guidance (copied); midpoint = average
A75: H2 2026 non-GAAP op. income implied at May vintage | B75: =B72*1000-C73-B74*1000 -> 89963 | C75: =C72*1000-C73-C74*1000 -> 91963 | D75: =D72*1000-C73-D74*1000 -> 93963 | E75: USD k | G75: May FY guide - Q1 actual - Q2 guide (paired ends)
A76: Change in implied H2 2026 non-GAAP op. income, Aug vs May vintage | B76: =B52-B75 -> 29890 | C76: =C52-C75 -> 29890 | D76: =D52-D75 -> 29890 | E76: USD k | G76: Aug implied H2 - May implied H2
A78: July 22, 2026 interim outlook (restructuring 6-K): FY2026 margins
A79: FY2026 non-GAAP operating margin, July 22 "Current" (~15%) | B79: 0.15 | C79: =(B79+D79)/2 -> 0.15 | D79: 0.15 | E79: % | F79: GH-0096 / 6K-20260722-RESTR | G79: Guidance (copied); midpoint = average
A80: FY2026 non-GAAP operating margin implied by Aug 10 USD guidance | B80: =B50/B36 -> 0.1568895 | C80: =C50/C36 -> 0.15782313 | D80: =D50/D36 -> 0.1587517 | E80: % | G80: FY op. income guide / FY revenue guide (company text: "approximately 16%")
A82: Restructuring: the July 22 plan expects ~$45-55M net charges mostly in H2 2026; the FY2026 non-GAAP outlook excludes them (source book Annual / Definitions). GAAP implications are not modeled here.

Sheet Findings
A1: Findings (historical analysis only; no forecast)
A2: Each finding cites the cells that support it. Numbers quoted in the text are rounded versions of those cells.
A4: # | B4: Finding | C4: Supporting cells
A5: Text / label | B5: Text / label | C5: Text / label
A6: 1 | B6: Revenue guidance has been conservative in every evaluated quarter: actual revenue beat the TOP of the next-quarter range in 20 of 20 quarters (Q3 2021-Q2 2026). The beat versus the midpoint averaged 4.3% over all history but has narrowed to 2.4% on average in the last 8 quarters (range 1.5% to 3.6%; sample std. dev. 0.7%). | C6: Guidance_Accuracy!C67:M67, C68:M68; detail rows 7-26
A7: 2 | B7: Non-GAAP operating income beat the top of the next-quarter range in all 20 quarters. In the last 8 quarters the beat versus the midpoint averaged 36% (median 35%); the smallest was Q4 2025 at 13%, the quarter the company first quantified an FX headwind on non-GAAP operating margin (-180 bps). Quarterly FCF guidance existed only in 2024: 3 beats above the range and 1 in range. | C7: Guidance_Accuracy!C69:M70, N49, V49; C71:M71
A8: 3 | B8: Reported year-over-year revenue growth fell from 84.0% in Q1 2022 to 21.9% in Q2 2026. Q2 2026 included an approximately +110 bps FX benefit, so the FX-adjusted rate was about 20.8%. Sequential growth in Q2 2026 was 3.8%, the lowest quarter-on-quarter rate in the series. Revenue FX impact was not disclosed for Q3 2024-Q1 2026. | C8: Deceleration!F10, F27, H27, K27; Growth_Decomposition!F27
A9: 4 | B9: Guidance implies a further step-down: H1 2026 revenue grew 23.2%, while the Q3 2026 guide implies 16.1%-16.8% and the FY guide implies 15.3%-16.5% for H2 and 14.4%-16.2% for Q4 (paired range ends; arithmetic on guidance, not a forecast). | C9: Deceleration!C41, B35:D35, B44:D44, B47:D47
A10: 5 | B10: In August the company kept FY2026 revenue guidance unchanged ($1,466-1,474M) after a Q2 beat, which lowered the H2 revenue implied by guidance by about $9.6M versus the May vintage. At the same time it raised FY non-GAAP operating income guidance from $185-191M to $230-234M, lifting implied H2 operating income by about $29.9M. This followed the July 22 restructuring 6-K, which raised the FY non-GAAP margin outlook from ~13% to ~15% and excludes restructuring charges. | C10: Deceleration!B71:D71, B76:D76, B79:D80; Guidance_Accuracy FY2026 vintage list
A11: 6 | B11: All-customer net dollar retention was 109% in Q2 2026, the lowest exact value since exact disclosure began in Q4 2023 (110%-112% in between); the >$100k cohort was 115% and >10 users 113%. The company attributes part of the 2024-H1 2025 NDR to pricing adjustments that have since anniversaried. NDR before Q4 2023 was disclosed only as floors and is not comparable; the measurement basis (point-in-time vs trailing) is not stated. | C11: Growth_Decomposition!G17:G27, P27, J27; flags column
A12: 7 | B12: Disclosed customer KPIs show the base shifting toward larger accounts (descriptive, not causal): customers above $100k ARR grew 37% year over year to 2,019 in Q2 2026, and their share of ARR rose from 22% (Q3 2024) to 30%. Customers with more than 10 users grew only 6.4%. | C12: Growth_Decomposition!AA27, AD27, AO20:AO27, V27
A13: 8 | B13: The non-GAAP operating margin reached 16.8% in Q2 2026, the highest in the series, as non-GAAP S&M fell to 41.0% of revenue (FY2024: 51.4%). Most of that S&M decline is NOT comparable: commissions fell from ~5% to ~2% of revenue in 2025 when the commission model changed and more cost was capitalized. Meanwhile non-GAAP R&D rose to 22.8% of revenue (FY2024: 16.7%) and non-GAAP gross margin was 88.9%, its lowest since 2022. | C13: Margin_Structure!AU27, AQ27, AQ31, AO27, AO31, AM27; commission block D53:D55
A14: 9 | B14: Cash conversion is seasonal and has weakened: over 2023-2025 the adjusted FCF margin averaged 34.7% in Q1 against 23.0% in Q2. Q2 2026 came in at 14.4%, with FCF at 0.86x non-GAAP operating income, the lowest ratio in any positive-income quarter. FY guidance implies an H2 2026 adjusted FCF margin of about 17.2%, against 22.9% actual in H2 2025. | C14: Cash_Conversion!C39:F39, Q27, R27; Deceleration!B60:D60, C64
A15: 10 | B15: Cash and cash equivalents fell from $1,503M to $853M in H1 2026. Share repurchases of $735M (which used up the $870M authorization) far exceeded operating cash flow of $160M; other items not itemized in the source book were a net outflow of $67M. Including marketable securities, liquidity fell $593M. | C15: Cash_Conversion!B48:H54, H60
A18: Open questions for the Q3 2026 forecast design
A19: 1 | B19: Guidance conservatism: should the Q3 2026 design anchor on the guidance midpoint, the top of the range, or a historical beat distribution? Revenue beats have narrowed (last 8 quarters avg ~2.4% vs midpoint) and the non-GAAP operating income beat pattern is large but volatile.
A20: 2 | B20: FX: revenue guidance carries no stated FX assumption, while operating income guidance assumes a 100-200 bps negative FX impact; Q2 2026 revenue had a ~110 bps FX tailwind. How should FX be treated, given that no revenue FX impact was disclosed for Q3 2024-Q1 2026?
A21: 3 | B21: Restructuring (July 22, 2026; ~20% of the workforce; ~$45-55M net charges mostly in H2 2026; severance cash timing not disclosed): how should the opex run-rate, the GAAP charges, the ~$15M SBC credit and the cash payments be phased into Q3 without assuming undisclosed details?
A22: 4 | B22: S&M comparability: with commission capitalization since 2025, should S&M be modeled on the post-change basis only (2025 onward)? Any cross-period comparison would need a labeled adjustment.
A23: 5 | B23: Revenue drivers: total ARR, new ARR, churn and seat or pricing data are not disclosed. Which disclosed series (customer cohorts, NDR, RPO/cRPO) can serve as cross-checks, given the floor-only NDR before Q4 2023, the unstated NDR basis and the June 2025 RPO recast?
A24: 6 | B24: AI pricing: AI products were 17% of net new ARR in Q2 2026, and seats-plus-credits pricing launched in Q1 2026, but there is no base or revenue split. Should AI monetization be an explicit (Assumed) driver or left inside the revenue trend?
A25: 7 | B25: Gross margin: the company expects AI compute costs to reduce gross margin modestly over the medium term. Should Q3 gross margin follow the recent trend (88.9% non-GAAP in Q2 2026) or a stated assumption?
A26: 8 | B26: Cash: the buyback authorization is fully used and no new program has been disclosed. How should financial income (lower cash balance) and FCF seasonality (Q3 has historically been strong) be handled for Q3?
A27: 9 | B27: Implied H2: the FY guidance implies Q4 revenue growth of ~14-16% and a Q4 non-GAAP margin of ~16.5%. Should the Q3 call be reconciled to the FY guide, or treated independently?

Sheet Checks
A1: Checks: every copied input tied back to the source book by Row ID, plus internal arithmetic checks
A2: Tie-back: "Source-book value" is re-read by Row ID (independent lookup) from monday_sourcebook.xlsx at build time; Difference = analysis cell - source-book value.
A4: Summary by input family
B5: Family | C5: Checks | D5: PASS | E5: FAIL
B6: Text / label | C6: Derived (formula) | D6: Derived (formula) | E6: Derived (formula)
B7: Guidance_Accuracy: guidance inputs | C7: =COUNTIF($B$26:$B$1394,B7) -> 478 | D7: =COUNTIFS($B$26:$B$1394,B7,$I$26:$I$1394,"PASS") -> 478 | E7: =COUNTIFS($B$26:$B$1394,B7,$I$26:$I$1394,"FAIL") -> 0
B8: Guidance_Accuracy: financial inputs | C8: =COUNTIF($B$26:$B$1394,B8) -> 88 | D8: =COUNTIFS($B$26:$B$1394,B8,$I$26:$I$1394,"PASS") -> 88 | E8: =COUNTIFS($B$26:$B$1394,B8,$I$26:$I$1394,"FAIL") -> 0
B9: Guidance_Accuracy: FX inputs | C9: =COUNTIF($B$26:$B$1394,B9) -> 30 | D9: =COUNTIFS($B$26:$B$1394,B9,$I$26:$I$1394,"PASS") -> 30 | E9: =COUNTIFS($B$26:$B$1394,B9,$I$26:$I$1394,"FAIL") -> 0
B10: Growth_Decomposition: financial inputs | C10: =COUNTIF($B$26:$B$1394,B10) -> 22 | D10: =COUNTIFS($B$26:$B$1394,B10,$I$26:$I$1394,"PASS") -> 22 | E10: =COUNTIFS($B$26:$B$1394,B10,$I$26:$I$1394,"FAIL") -> 0
B11: Growth_Decomposition: KPI inputs | C11: =COUNTIF($B$26:$B$1394,B11) -> 164 | D11: =COUNTIFS($B$26:$B$1394,B11,$I$26:$I$1394,"PASS") -> 164 | E11: =COUNTIFS($B$26:$B$1394,B11,$I$26:$I$1394,"FAIL") -> 0
B12: Margin_Structure: financial inputs | C12: =COUNTIF($B$26:$B$1394,B12) -> 297 | D12: =COUNTIFS($B$26:$B$1394,B12,$I$26:$I$1394,"PASS") -> 297 | E12: =COUNTIFS($B$26:$B$1394,B12,$I$26:$I$1394,"FAIL") -> 0
B13: Margin_Structure: commission inputs | C13: =COUNTIF($B$26:$B$1394,B13) -> 7 | D13: =COUNTIFS($B$26:$B$1394,B13,$I$26:$I$1394,"PASS") -> 7 | E13: =COUNTIFS($B$26:$B$1394,B13,$I$26:$I$1394,"FAIL") -> 0
B14: Cash_Conversion: financial inputs | C14: =COUNTIF($B$26:$B$1394,B14) -> 108 | D14: =COUNTIFS($B$26:$B$1394,B14,$I$26:$I$1394,"PASS") -> 108 | E14: =COUNTIFS($B$26:$B$1394,B14,$I$26:$I$1394,"FAIL") -> 0
B15: Cash_Conversion: cash bridge inputs | C15: =COUNTIF($B$26:$B$1394,B15) -> 17 | D15: =COUNTIFS($B$26:$B$1394,B15,$I$26:$I$1394,"PASS") -> 17 | E15: =COUNTIFS($B$26:$B$1394,B15,$I$26:$I$1394,"FAIL") -> 0
B16: Deceleration: financial inputs | C16: =COUNTIF($B$26:$B$1394,B16) -> 53 | D16: =COUNTIFS($B$26:$B$1394,B16,$I$26:$I$1394,"PASS") -> 53 | E16: =COUNTIFS($B$26:$B$1394,B16,$I$26:$I$1394,"FAIL") -> 0
B17: Deceleration: FX inputs | C17: =COUNTIF($B$26:$B$1394,B17) -> 11 | D17: =COUNTIFS($B$26:$B$1394,B17,$I$26:$I$1394,"PASS") -> 11 | E17: =COUNTIFS($B$26:$B$1394,B17,$I$26:$I$1394,"FAIL") -> 0
B18: Internal: guidance arithmetic | C18: =COUNTIF($B$26:$B$1394,B18) -> 88 | D18: =COUNTIFS($B$26:$B$1394,B18,$I$26:$I$1394,"PASS") -> 88 | E18: =COUNTIFS($B$26:$B$1394,B18,$I$26:$I$1394,"FAIL") -> 0
... B20: Internal: H1 additivity | C20: =COUNTIF($B$26:$B$1394,B20) -> 2 | D20: =COUNTIFS($B$26:$B$1394,B20,$I$26:$I$1394,"PASS") -> 2 | E20: =COUNTIFS($B$26:$B$1394,B20,$I$26:$I$1394,"FAIL") -> 0
B21: TOTAL | C21: =SUM(C7:C20) -> 1369 | D21: =SUM(D7:D20) -> 1369 | E21: =SUM(E7:E20) -> 0
A24: Check ID | B24: Family | C24: Analysis cell | D24: Source-book sheet | E24: Source-book Row ID | F24: Analysis value | G24: Source-book value (re-read by Row ID) | H24: Difference | I24: Status | J24: Context
A25: Text / label | B25: Text / label | C25: Text / label | D25: Text / label | E25: Source-book Row ID | F25: Derived (formula) | G25: Sourced (copied from source book) | H25: Derived (formula) | I25: Derived (formula) | J25: Text / label
A26: P1-0001 | B26: Guidance_Accuracy: guidance inputs | C26: Guidance_Accuracy!D7 | D26: Guidance_History | E26: GH-0004 | F26: =Guidance_Accuracy!D7 -> 44425 | G26: 44425 | H26: =F26-G26 -> 0 | I26: =IF(ABS(H26)<=0.000001,"PASS","FAIL") -> PASS | J26: Guidance issued date
A27: P1-0002 | B27: Guidance_Accuracy: guidance inputs | C27: Guidance_Accuracy!E7 | D27: Guidance_History | E27: GH-0004 | F27: =Guidance_Accuracy!E7 -> Revenue | G27: Revenue | H27: =IF(EXACT(F27,G27),0,1) -> 0 | I27: =IF(ABS(H27)<=0.000001,"PASS","FAIL") -> PASS | J27: Guidance metric label
A28: P1-0003 | B28: Guidance_Accuracy: guidance inputs | C28: Guidance_Accuracy!F7 | D28: Guidance_History | E28: GH-0004 | F28: =Guidance_Accuracy!F7 -> 74 | G28: 74 | H28: =F28-G28 -> 0 | I28: =IF(ABS(H28)<=0.000001,"PASS","FAIL") -> PASS | J28: Guidance low
A29: P1-0004 | B29: Guidance_Accuracy: guidance inputs | C29: Guidance_Accuracy!G7 | D29: Guidance_History | E29: GH-0004 | F29: =Guidance_Accuracy!G7 -> 75 | G29: 75 | H29: =F29-G29 -> 0 | I29: =IF(ABS(H29)<=0.000001,"PASS","FAIL") -> PASS | J29: Guidance high
A30: P1-0005 | B30: Guidance_Accuracy: financial inputs | C30: Guidance_Accuracy!I7 | D30: Quarterly_Actuals | E30: QA-0004 | F30: =Guidance_Accuracy!I7 -> 83018 | G30: 83018 | H30: =F30-G30 -> 0 | I30: =IF(ABS(H30)<=0.000001,"PASS","FAIL") -> PASS | J30: Actual Revenue Q3 2021
A31: P1-0006 | B31: Guidance_Accuracy: guidance inputs | C31: Guidance_Accuracy!D8 | D31: Guidance_History | E31: GH-0008 | F31: =Guidance_Accuracy!D8 -> 44510 | G31: 44510 | H31: =F31-G31 -> 0 | I31: =IF(ABS(H31)<=0.000001,"PASS","FAIL") -> PASS | J31: Guidance issued date
A32: P1-0007 | B32: Guidance_Accuracy: guidance inputs | C32: Guidance_Accuracy!E8 | D32: Guidance_History | E32: GH-0008 | F32: =Guidance_Accuracy!E8 -> Revenue | G32: Revenue | H32: =IF(EXACT(F32,G32),0,1) -> 0 | I32: =IF(ABS(H32)<=0.000001,"PASS","FAIL") -> PASS | J32: Guidance metric label
A33: P1-0008 | B33: Guidance_Accuracy: guidance inputs | C33: Guidance_Accuracy!F8 | D33: Guidance_History | E33: GH-0008 | F33: =Guidance_Accuracy!F8 -> 87 | G33: 87 | H33: =F33-G33 -> 0 | I33: =IF(ABS(H33)<=0.000001,"PASS","FAIL") -> PASS | J33: Guidance low
A34: P1-0009 | B34: Guidance_Accuracy: guidance inputs | C34: Guidance_Accuracy!G8 | D34: Guidance_History | E34: GH-0008 | F34: =Guidance_Accuracy!G8 -> 88 | G34: 88 | H34: =F34-G34 -> 0 | I34: =IF(ABS(H34)<=0.000001,"PASS","FAIL") -> PASS | J34: Guidance high
A35: P1-0010 | B35: Guidance_Accuracy: financial inputs | C35: Guidance_Accuracy!I8 | D35: Quarterly_Actuals | E35: QA-0006 | F35: =Guidance_Accuracy!I8 -> 95545 | G35: 95545 | H35: =F35-G35 -> 0 | I35: =IF(ABS(H35)<=0.000001,"PASS","FAIL") -> PASS | J35: Actual Revenue Q4 2021
A36: P1-0011 | B36: Guidance_Accuracy: guidance inputs | C36: Guidance_Accuracy!D9 | D36: Guidance_History | E36: GH-0012 | F36: =Guidance_Accuracy!D9 -> 44615 | G36: 44615 | H36: =F36-G36 -> 0 | I36: =IF(ABS(H36)<=0.000001,"PASS","FAIL") -> PASS | J36: Guidance issued date
A37: P1-0012 | B37: Guidance_Accuracy: guidance inputs | C37: Guidance_Accuracy!E9 | D37: Guidance_History | E37: GH-0012 | F37: =Guidance_Accuracy!E9 -> Revenue | G37: Revenue | H37: =IF(EXACT(F37,G37),0,1) -> 0 | I37: =IF(ABS(H37)<=0.000001,"PASS","FAIL") -> PASS | J37: Guidance metric label
A38: P1-0013 | B38: Guidance_Accuracy: guidance inputs | C38: Guidance_Accuracy!F9 | D38: Guidance_History | E38: GH-0012 | F38: =Guidance_Accuracy!F9 -> 100 | G38: 100 | H38: =F38-G38 -> 0 | I38: =IF(ABS(H38)<=0.000001,"PASS","FAIL") -> PASS | J38: Guidance low
A39: P1-0014 | B39: Guidance_Accuracy: guidance inputs | C39: Guidance_Accuracy!G9 | D39: Guidance_History | E39: GH-0012 | F39: =Guidance_Accuracy!G9 -> 102 | G39: 102 | H39: =F39-G39 -> 0 | I39: =IF(ABS(H39)<=0.000001,"PASS","FAIL") -> PASS | J39: Guidance high
A40: P1-0015 | B40: Guidance_Accuracy: financial inputs | C40: Guidance_Accuracy!I9 | D40: Quarterly_Actuals | E40: QA-0008 | F40: =Guidance_Accuracy!I9 -> 108497 | G40: 108497 | H40: =F40-G40 -> 0 | I40: =IF(ABS(H40)<=0.000001,"PASS","FAIL") -> PASS | J40: Actual Revenue Q1 2022
A41: P1-0016 | B41: Guidance_Accuracy: FX inputs | C41: Guidance_Accuracy!S9 | D41: Quarterly_Actuals | E41: QA-1546 | F41: =Guidance_Accuracy!S9 -> -100 | G41: -100 | H41: =F41-G41 -> 0 | I41: =IF(ABS(H41)<=0.000001,"PASS","FAIL") -> PASS | J41: FX revenue Q1 2022
A42: P1-0017 | B42: Guidance_Accuracy: guidance inputs | C42: Guidance_Accuracy!D10 | D42: Guidance_History | E42: GH-0016 | F42: =Guidance_Accuracy!D10 -> 44697 | G42: 44697 | H42: =F42-G42 -> 0 | I42: =IF(ABS(H42)<=0.000001,"PASS","FAIL") -> PASS | J42: Guidance issued date
A43: P1-0018 | B43: Guidance_Accuracy: guidance inputs | C43: Guidance_Accuracy!E10 | D43: Guidance_History | E43: GH-0016 | F43: =Guidance_Accuracy!E10 -> Revenue | G43: Revenue | H43: =IF(EXACT(F43,G43),0,1) -> 0 | I43: =IF(ABS(H43)<=0.000001,"PASS","FAIL") -> PASS | J43: Guidance metric label
A44: P1-0019 | B44: Guidance_Accuracy: guidance inputs | C44: Guidance_Accuracy!F10 | D44: Guidance_History | E44: GH-0016 | F44: =Guidance_Accuracy!F10 -> 117 | G44: 117 | H44: =F44-G44 -> 0 | I44: =IF(ABS(H44)<=0.000001,"PASS","FAIL") -> PASS | J44: Guidance low
A45: P1-0020 | B45: Guidance_Accuracy: guidance inputs | C45: Guidance_Accuracy!G10 | D45: Guidance_History | E45: GH-0016 | F45: =Guidance_Accuracy!G10 -> 119 | G45: 119 | H45: =F45-G45 -> 0 | I45: =IF(ABS(H45)<=0.000001,"PASS","FAIL") -> PASS | J45: Guidance high
A46: P1-0021 | B46: Guidance_Accuracy: financial inputs | C46: Guidance_Accuracy!I10 | D46: Quarterly_Actuals | E46: QA-0009 | F46: =Guidance_Accuracy!I10 -> 123718 | G46: 123718 | H46: =F46-G46 -> 0 | I46: =IF(ABS(H46)<=0.000001,"PASS","FAIL") -> PASS | J46: Actual Revenue Q2 2022
A47: P1-0022 | B47: Guidance_Accuracy: FX inputs | C47: Guidance_Accuracy!S10 | D47: Quarterly_Actuals | E47: QA-1547 | F47: =Guidance_Accuracy!S10 -> -200 | G47: -200 | H47: =F47-G47 -> 0 | I47: =IF(ABS(H47)<=0.000001,"PASS","FAIL") -> PASS | J47: FX revenue Q2 2022
A48: P1-0023 | B48: Guidance_Accuracy: guidance inputs | C48: Guidance_Accuracy!D11 | D48: Guidance_History | E48: GH-0020 | F48: =Guidance_Accuracy!D11 -> 44781 | G48: 44781 | H48: =F48-G48 -> 0 | I48: =IF(ABS(H48)<=0.000001,"PASS","FAIL") -> PASS | J48: Guidance issued date
A49: P1-0024 | B49: Guidance_Accuracy: guidance inputs | C49: Guidance_Accuracy!E11 | D49: Guidance_History | E49: GH-0020 | F49: =Guidance_Accuracy!E11 -> Revenue | G49: Revenue | H49: =IF(EXACT(F49,G49),0,1) -> 0 | I49: =IF(ABS(H49)<=0.000001,"PASS","FAIL") -> PASS | J49: Guidance metric label
A50: P1-0025 | B50: Guidance_Accuracy: guidance inputs | C50: Guidance_Accuracy!F11 | D50: Guidance_History | E50: GH-0020 | F50: =Guidance_Accuracy!F11 -> 130 | G50: 130 | H50: =F50-G50 -> 0 | I50: =IF(ABS(H50)<=0.000001,"PASS","FAIL") -> PASS | J50: Guidance low
A51: P1-0026 | B51: Guidance_Accuracy: guidance inputs | C51: Guidance_Accuracy!G11 | D51: Guidance_History | E51: GH-0020 | F51: =Guidance_Accuracy!G11 -> 131 | G51: 131 | H51: =F51-G51 -> 0 | I51: =IF(ABS(H51)<=0.000001,"PASS","FAIL") -> PASS | J51: Guidance high
A52: P1-0027 | B52: Guidance_Accuracy: financial inputs | C52: Guidance_Accuracy!I11 | D52: Quarterly_Actuals | E52: QA-0011 | F52: =Guidance_Accuracy!I11 -> 136893 | G52: 136893 | H52: =F52-G52 -> 0 | I52: =IF(ABS(H52)<=0.000001,"PASS","FAIL") -> PASS | J52: Actual Revenue Q3 2022
A53: P1-0028 | B53: Guidance_Accuracy: FX inputs | C53: Guidance_Accuracy!S11 | D53: Quarterly_Actuals | E53: QA-1548 | F53: =Guidance_Accuracy!S11 -> -300 | G53: -300 | H53: =F53-G53 -> 0 | I53: =IF(ABS(H53)<=0.000001,"PASS","FAIL") -> PASS | J53: FX revenue Q3 2022
A54: P1-0029 | B54: Guidance_Accuracy: guidance inputs | C54: Guidance_Accuracy!D12 | D54: Guidance_History | E54: GH-0024 | F54: =Guidance_Accuracy!D12 -> 44879 | G54: 44879 | H54: =F54-G54 -> 0 | I54: =IF(ABS(H54)<=0.000001,"PASS","FAIL") -> PASS | J54: Guidance issued date
A55: P1-0030 | B55: Guidance_Accuracy: guidance inputs | C55: Guidance_Accuracy!E12 | D55: Guidance_History | E55: GH-0024 | F55: =Guidance_Accuracy!E12 -> Revenue | G55: Revenue | H55: =IF(EXACT(F55,G55),0,1) -> 0 | I55: =IF(ABS(H55)<=0.000001,"PASS","FAIL") -> PASS | J55: Guidance metric label
A56: P1-0031 | B56: Guidance_Accuracy: guidance inputs | C56: Guidance_Accuracy!F12 | D56: Guidance_History | E56: GH-0024 | F56: =Guidance_Accuracy!F12 -> 140 | G56: 140 | H56: =F56-G56 -> 0 | I56: =IF(ABS(H56)<=0.000001,"PASS","FAIL") -> PASS | J56: Guidance low
A57: P1-0032 | B57: Guidance_Accuracy: guidance inputs | C57: Guidance_Accuracy!G12 | D57: Guidance_History | E57: GH-0024 | F57: =Guidance_Accuracy!G12 -> 142 | G57: 142 | H57: =F57-G57 -> 0 | I57: =IF(ABS(H57)<=0.000001,"PASS","FAIL") -> PASS | J57: Guidance high
A58: P1-0033 | B58: Guidance_Accuracy: financial inputs | C58: Guidance_Accuracy!I12 | D58: Quarterly_Actuals | E58: QA-0013 | F58: =Guidance_Accuracy!I12 -> 149921 | G58: 149921 | H58: =F58-G58 -> 0 | I58: =IF(ABS(H58)<=0.000001,"PASS","FAIL") -> PASS | J58: Actual Revenue Q4 2022
A59: P1-0034 | B59: Guidance_Accuracy: FX inputs | C59: Guidance_Accuracy!S12 | D59: Quarterly_Actuals | E59: QA-1549 | F59: =Guidance_Accuracy!S12 -> -300 | G59: -300 | H59: =F59-G59 -> 0 | I59: =IF(ABS(H59)<=0.000001,"PASS","FAIL") -> PASS | J59: FX revenue Q4 2022
A60: P1-0035 | B60: Guidance_Accuracy: guidance inputs | C60: Guidance_Accuracy!D13 | D60: Guidance_History | E60: GH-0028 | F60: =Guidance_Accuracy!D13 -> 44970 | G60: 44970 | H60: =F60-G60 -> 0 | I60: =IF(ABS(H60)<=0.000001,"PASS","FAIL") -> PASS | J60: Guidance issued date
A61: P1-0036 | B61: Guidance_Accuracy: guidance inputs | C61: Guidance_Accuracy!E13 | D61: Guidance_History | E61: GH-0028 | F61: =Guidance_Accuracy!E13 -> Revenue | G61: Revenue | H61: =IF(EXACT(F61,G61),0,1) -> 0 | I61: =IF(ABS(H61)<=0.000001,"PASS","FAIL") -> PASS | J61: Guidance metric label
A62: P1-0037 | B62: Guidance_Accuracy: guidance inputs | C62: Guidance_Accuracy!F13 | D62: Guidance_History | E62: GH-0028 | F62: =Guidance_Accuracy!F13 -> 154 | G62: 154 | H62: =F62-G62 -> 0 | I62: =IF(ABS(H62)<=0.000001,"PASS","FAIL") -> PASS | J62: Guidance low
A63: P1-0038 | B63: Guidance_Accuracy: guidance inputs | C63: Guidance_Accuracy!G13 | D63: Guidance_History | E63: GH-0028 | F63: =Guidance_Accuracy!G13 -> 156 | G63: 156 | H63: =F63-G63 -> 0 | I63: =IF(ABS(H63)<=0.000001,"PASS","FAIL") -> PASS | J63: Guidance high
A64: P1-0039 | B64: Guidance_Accuracy: financial inputs | C64: Guidance_Accuracy!I13 | D64: Quarterly_Actuals | E64: QA-0015 | F64: =Guidance_Accuracy!I13 -> 162256 | G64: 162256 | H64: =F64-G64 -> 0 | I64: =IF(ABS(H64)<=0.000001,"PASS","FAIL") -> PASS | J64: Actual Revenue Q1 2023
A65: P1-0040 | B65: Guidance_Accuracy: FX inputs | C65: Guidance_Accuracy!S13 | D65: Quarterly_Actuals | E65: QA-1551 | F65: =Guidance_Accuracy!S13 -> -100 | G65: -100 | H65: =F65-G65 -> 0 | I65: =IF(ABS(H65)<=0.000001,"PASS","FAIL") -> PASS | J65: FX revenue Q1 2023
A66: P1-0041 | B66: Guidance_Accuracy: guidance inputs | C66: Guidance_Accuracy!D14 | D66: Guidance_History | E66: GH-0032 | F66: =Guidance_Accuracy!D14 -> 45061 | G66: 45061 | H66: =F66-G66 -> 0 | I66: =IF(ABS(H66)<=0.000001,"PASS","FAIL") -> PASS | J66: Guidance issued date
A67: P1-0042 | B67: Guidance_Accuracy: guidance inputs | C67: Guidance_Accuracy!E14 | D67: Guidance_History | E67: GH-0032 | F67: =Guidance_Accuracy!E14 -> Revenue | G67: Revenue | H67: =IF(EXACT(F67,G67),0,1) -> 0 | I67: =IF(ABS(H67)<=0.000001,"PASS","FAIL") -> PASS | J67: Guidance metric label
A68: P1-0043 | B68: Guidance_Accuracy: guidance inputs | C68: Guidance_Accuracy!F14 | D68: Guidance_History | E68: GH-0032 | F68: =Guidance_Accuracy!F14 -> 168 | G68: 168 | H68: =F68-G68 -> 0 | I68: =IF(ABS(H68)<=0.000001,"PASS","FAIL") -> PASS | J68: Guidance low
A69: P1-0044 | B69: Guidance_Accuracy: guidance inputs | C69: Guidance_Accuracy!G14 | D69: Guidance_History | E69: GH-0032 | F69: =Guidance_Accuracy!G14 -> 170 | G69: 170 | H69: =F69-G69 -> 0 | I69: =IF(ABS(H69)<=0.000001,"PASS","FAIL") -> PASS | J69: Guidance high
A70: P1-0045 | B70: Guidance_Accuracy: financial inputs | C70: Guidance_Accuracy!I14 | D70: Quarterly_Actuals | E70: QA-0016 | F70: =Guidance_Accuracy!I14 -> 175679 | G70: 175679 | H70: =F70-G70 -> 0 | I70: =IF(ABS(H70)<=0.000001,"PASS","FAIL") -> PASS | J70: Actual Revenue Q2 2023
A71: P1-0046 | B71: Guidance_Accuracy: FX inputs | C71: Guidance_Accuracy!S14 | D71: Quarterly_Actuals | E71: QA-1552 | F71: =Guidance_Accuracy!S14 -> -100 | G71: -100 | H71: =F71-G71 -> 0 | I71: =IF(ABS(H71)<=0.000001,"PASS","FAIL") -> PASS | J71: FX revenue Q2 2023
A72: P1-0047 | B72: Guidance_Accuracy: guidance inputs | C72: Guidance_Accuracy!D15 | D72: Guidance_History | E72: GH-0036 | F72: =Guidance_Accuracy!D15 -> 45152 | G72: 45152 | H72: =F72-G72 -> 0 | I72: =IF(ABS(H72)<=0.000001,"PASS","FAIL") -> PASS | J72: Guidance issued date
A73: P1-0048 | B73: Guidance_Accuracy: guidance inputs | C73: Guidance_Accuracy!E15 | D73: Guidance_History | E73: GH-0036 | F73: =Guidance_Accuracy!E15 -> Revenue | G73: Revenue | H73: =IF(EXACT(F73,G73),0,1) -> 0 | I73: =IF(ABS(H73)<=0.000001,"PASS","FAIL") -> PASS | J73: Guidance metric label
A74: P1-0049 | B74: Guidance_Accuracy: guidance inputs | C74: Guidance_Accuracy!F15 | D74: Guidance_History | E74: GH-0036 | F74: =Guidance_Accuracy!F15 -> 181 | G74: 181 | H74: =F74-G74 -> 0 | I74: =IF(ABS(H74)<=0.000001,"PASS","FAIL") -> PASS | J74: Guidance low
A75: P1-0050 | B75: Guidance_Accuracy: guidance inputs | C75: Guidance_Accuracy!G15 | D75: Guidance_History | E75: GH-0036 | F75: =Guidance_Accuracy!G15 -> 183 | G75: 183 | H75: =F75-G75 -> 0 | I75: =IF(ABS(H75)<=0.000001,"PASS","FAIL") -> PASS | J75: Guidance high
A76: P1-0051 | B76: Guidance_Accuracy: financial inputs | C76: Guidance_Accuracy!I15 | D76: Quarterly_Actuals | E76: QA-0018 | F76: =Guidance_Accuracy!I15 -> 189190 | G76: 189190 | H76: =F76-G76 -> 0 | I76: =IF(ABS(H76)<=0.000001,"PASS","FAIL") -> PASS | J76: Actual Revenue Q3 2023
A77: P1-0052 | B77: Guidance_Accuracy: FX inputs | C77: Guidance_Accuracy!S15 | D77: Quarterly_Actuals | E77: QA-1553 | F77: =Guidance_Accuracy!S15 -> 0 | G77: 0 | H77: =F77-G77 -> 0 | I77: =IF(ABS(H77)<=0.000001,"PASS","FAIL") -> PASS | J77: FX revenue Q3 2023
A78: P1-0053 | B78: Guidance_Accuracy: guidance inputs | C78: Guidance_Accuracy!D16 | D78: Guidance_History | E78: GH-0040 | F78: =Guidance_Accuracy!D16 -> 45243 | G78: 45243 | H78: =F78-G78 -> 0 | I78: =IF(ABS(H78)<=0.000001,"PASS","FAIL") -> PASS | J78: Guidance issued date
A79: P1-0054 | B79: Guidance_Accuracy: guidance inputs | C79: Guidance_Accuracy!E16 | D79: Guidance_History | E79: GH-0040 | F79: =Guidance_Accuracy!E16 -> Revenue | G79: Revenue | H79: =IF(EXACT(F79,G79),0,1) -> 0 | I79: =IF(ABS(H79)<=0.000001,"PASS","FAIL") -> PASS | J79: Guidance metric label
A80: P1-0055 | B80: Guidance_Accuracy: guidance inputs | C80: Guidance_Accuracy!F16 | D80: Guidance_History | E80: GH-0040 | F80: =Guidance_Accuracy!F16 -> 196 | G80: 196 | H80: =F80-G80 -> 0 | I80: =IF(ABS(H80)<=0.000001,"PASS","FAIL") -> PASS | J80: Guidance low
A81: P1-0056 | B81: Guidance_Accuracy: guidance inputs | C81: Guidance_Accuracy!G16 | D81: Guidance_History | E81: GH-0040 | F81: =Guidance_Accuracy!G16 -> 198 | G81: 198 | H81: =F81-G81 -> 0 | I81: =IF(ABS(H81)<=0.000001,"PASS","FAIL") -> PASS | J81: Guidance high
A82: P1-0057 | B82: Guidance_Accuracy: financial inputs | C82: Guidance_Accuracy!I16 | D82: Quarterly_Actuals | E82: QA-0020 | F82: =Guidance_Accuracy!I16 -> 202570 | G82: 202570 | H82: =F82-G82 -> 0 | I82: =IF(ABS(H82)<=0.000001,"PASS","FAIL") -> PASS | J82: Actual Revenue Q4 2023
A83: P1-0058 | B83: Guidance_Accuracy: FX inputs | C83: Guidance_Accuracy!S16 | D83: Quarterly_Actuals | E83: QA-1554 | F83: =Guidance_Accuracy!S16 -> 0 | G83: 0 | H83: =F83-G83 -> 0 | I83: =IF(ABS(H83)<=0.000001,"PASS","FAIL") -> PASS | J83: FX revenue Q4 2023
A84: P1-0059 | B84: Guidance_Accuracy: guidance inputs | C84: Guidance_Accuracy!D17 | D84: Guidance_History | E84: GH-0046 | F84: =Guidance_Accuracy!D17 -> 45334 | G84: 45334 | H84: =F84-G84 -> 0 | I84: =IF(ABS(H84)<=0.000001,"PASS","FAIL") -> PASS | J84: Guidance issued date
A85: P1-0060 | B85: Guidance_Accuracy: guidance inputs | C85: Guidance_Accuracy!E17 | D85: Guidance_History | E85: GH-0046 | F85: =Guidance_Accuracy!E17 -> Revenue | G85: Revenue | H85: =IF(EXACT(F85,G85),0,1) -> 0 | I85: =IF(ABS(H85)<=0.000001,"PASS","FAIL") -> PASS | J85: Guidance metric label
A86: P1-0061 | B86: Guidance_Accuracy: guidance inputs | C86: Guidance_Accuracy!F17 | D86: Guidance_History | E86: GH-0046 | F86: =Guidance_Accuracy!F17 -> 207 | G86: 207 | H86: =F86-G86 -> 0 | I86: =IF(ABS(H86)<=0.000001,"PASS","FAIL") -> PASS | J86: Guidance low
A87: P1-0062 | B87: Guidance_Accuracy: guidance inputs | C87: Guidance_Accuracy!G17 | D87: Guidance_History | E87: GH-0046 | F87: =Guidance_Accuracy!G17 -> 211 | G87: 211 | H87: =F87-G87 -> 0 | I87: =IF(ABS(H87)<=0.000001,"PASS","FAIL") -> PASS | J87: Guidance high
A88: P1-0063 | B88: Guidance_Accuracy: financial inputs | C88: Guidance_Accuracy!I17 | D88: Quarterly_Actuals | E88: QA-0022 | F88: =Guidance_Accuracy!I17 -> 216913 | G88: 216913 | H88: =F88-G88 -> 0 | I88: =IF(ABS(H88)<=0.000001,"PASS","FAIL") -> PASS | J88: Actual Revenue Q1 2024
A89: P1-0064 | B89: Guidance_Accuracy: FX inputs | C89: Guidance_Accuracy!S17 | D89: Quarterly_Actuals | E89: QA-1556 | F89: =Guidance_Accuracy!S17 -> 0 | G89: 0 | H89: =F89-G89 -> 0 | I89: =IF(ABS(H89)<=0.000001,"PASS","FAIL") -> PASS | J89: FX revenue Q1 2024
A90: P1-0065 | B90: Guidance_Accuracy: guidance inputs | C90: Guidance_Accuracy!D18 | D90: Guidance_History | E90: GH-0052 | F90: =Guidance_Accuracy!D18 -> 45427 | G90: 45427 | H90: =F90-G90 -> 0 | I90: =IF(ABS(H90)<=0.000001,"PASS","FAIL") -> PASS | J90: Guidance issued date
A91: P1-0066 | B91: Guidance_Accuracy: guidance inputs | C91: Guidance_Accuracy!E18 | D91: Guidance_History | E91: GH-0052 | F91: =Guidance_Accuracy!E18 -> Revenue | G91: Revenue | H91: =IF(EXACT(F91,G91),0,1) -> 0 | I91: =IF(ABS(H91)<=0.000001,"PASS","FAIL") -> PASS | J91: Guidance metric label
A92: P1-0067 | B92: Guidance_Accuracy: guidance inputs | C92: Guidance_Accuracy!F18 | D92: Guidance_History | E92: GH-0052 | F92: =Guidance_Accuracy!F18 -> 226 | G92: 226 | H92: =F92-G92 -> 0 | I92: =IF(ABS(H92)<=0.000001,"PASS","FAIL") -> PASS | J92: Guidance low
A93: P1-0068 | B93: Guidance_Accuracy: guidance inputs | C93: Guidance_Accuracy!G18 | D93: Guidance_History | E93: GH-0052 | F93: =Guidance_Accuracy!G18 -> 230 | G93: 230 | H93: =F93-G93 -> 0 | I93: =IF(ABS(H93)<=0.000001,"PASS","FAIL") -> PASS | J93: Guidance high
A94: P1-0069 | B94: Guidance_Accuracy: financial inputs | C94: Guidance_Accuracy!I18 | D94: Quarterly_Actuals | E94: QA-0023 | F94: =Guidance_Accuracy!I18 -> 236106 | G94: 236106 | H94: =F94-G94 -> 0 | I94: =IF(ABS(H94)<=0.000001,"PASS","FAIL") -> PASS | J94: Actual Revenue Q2 2024
A95: P1-0070 | B95: Guidance_Accuracy: FX inputs | C95: Guidance_Accuracy!S18 | D95: Quarterly_Actuals | E95: QA-1557 | F95: =Guidance_Accuracy!S18 -> 0 | G95: 0 | H95: =F95-G95 -> 0 | I95: =IF(ABS(H95)<=0.000001,"PASS","FAIL") -> PASS | J95: FX revenue Q2 2024
A96: P1-0071 | B96: Guidance_Accuracy: guidance inputs | C96: Guidance_Accuracy!D19 | D96: Guidance_History | E96: GH-0058 | F96: =Guidance_Accuracy!D19 -> 45516 | G96: 45516 | H96: =F96-G96 -> 0 | I96: =IF(ABS(H96)<=0.000001,"PASS","FAIL") -> PASS | J96: Guidance issued date
A97: P1-0072 | B97: Guidance_Accuracy: guidance inputs | C97: Guidance_Accuracy!E19 | D97: Guidance_History | E97: GH-0058 | F97: =Guidance_Accuracy!E19 -> Revenue | G97: Revenue | H97: =IF(EXACT(F97,G97),0,1) -> 0 | I97: =IF(ABS(H97)<=0.000001,"PASS","FAIL") -> PASS | J97: Guidance metric label
A98: P1-0073 | B98: Guidance_Accuracy: guidance inputs | C98: Guidance_Accuracy!F19 | D98: Guidance_History | E98: GH-0058 | F98: =Guidance_Accuracy!F19 -> 243 | G98: 243 | H98: =F98-G98 -> 0 | I98: =IF(ABS(H98)<=0.000001,"PASS","FAIL") -> PASS | J98: Guidance low
A99: P1-0074 | B99: Guidance_Accuracy: guidance inputs | C99: Guidance_Accuracy!G19 | D99: Guidance_History | E99: GH-0058 | F99: =Guidance_Accuracy!G19 -> 247 | G99: 247 | H99: =F99-G99 -> 0 | I99: =IF(ABS(H99)<=0.000001,"PASS","FAIL") -> PASS | J99: Guidance high
A100: P1-0075 | B100: Guidance_Accuracy: financial inputs | C100: Guidance_Accuracy!I19 | D100: Quarterly_Actuals | E100: QA-0025 | F100: =Guidance_Accuracy!I19 -> 251000 | G100: 251000 | H100: =F100-G100 -> 0 | I100: =IF(ABS(H100)<=0.000001,"PASS","FAIL") -> PASS | J100: Actual Revenue Q3 2024
A101: P1-0076 | B101: Guidance_Accuracy: guidance inputs | C101: Guidance_Accuracy!D20 | D101: Guidance_History | E101: GH-0064 | F101: =Guidance_Accuracy!D20 -> 45608 | G101: 45608 | H101: =F101-G101 -> 0 | I101: =IF(ABS(H101)<=0.000001,"PASS","FAIL") -> PASS | J101: Guidance issued date
A102: P1-0077 | B102: Guidance_Accuracy: guidance inputs | C102: Guidance_Accuracy!E20 | D102: Guidance_History | E102: GH-0064 | F102: =Guidance_Accuracy!E20 -> Revenue | G102: Revenue | H102: =IF(EXACT(F102,G102),0,1) -> 0 | I102: =IF(ABS(H102)<=0.000001,"PASS","FAIL") -> PASS | J102: Guidance metric label
A103: P1-0078 | B103: Guidance_Accuracy: guidance inputs | C103: Guidance_Accuracy!F20 | D103: Guidance_History | E103: GH-0064 | F103: =Guidance_Accuracy!F20 -> 260 | G103: 260 | H103: =F103-G103 -> 0 | I103: =IF(ABS(H103)<=0.000001,"PASS","FAIL") -> PASS | J103: Guidance low
A104: P1-0079 | B104: Guidance_Accuracy: guidance inputs | C104: Guidance_Accuracy!G20 | D104: Guidance_History | E104: GH-0064 | F104: =Guidance_Accuracy!G20 -> 262 | G104: 262 | H104: =F104-G104 -> 0 | I104: =IF(ABS(H104)<=0.000001,"PASS","FAIL") -> PASS | J104: Guidance high
...
